Workbook
Name ailxcfjb: '[1]#REF'!$A$1
Name apyfcyhw: '[1]#REF'!$A$1
Name aujzarkj: '[2]#REF'!$A$1
Name avmpmedq: '[3]#REF'!$A$1
Name bdairnqd: '[4]#REF'!$A$1
Name bitfxntp: '[5]#REF'!$A$1
Name biukkekl: 本年累计!$A$1
Name biukkekl: Sheet54!$A$1
Name bknrcbtm: '[6]#REF'!$A$1
Name bmygeinz: '[1]#REF'!$A$1
Name boxvdrvn: '[7]#REF'!$A$1
Name bquckijz: '[2]#REF'!$A$1
Name buvomlnr: '[8]#REF'!$A$1
Name bvdepspo: '[2]#REF'!$A$1
Name bwqsqjza: '[2]#REF'!$E$3
Name bxrfmpue: '[7]#REF'!$A$1
Name byndfpoi: '[9]#REF'!$A$1
Name bzartlsc: '[8]#REF'!$A$1
Name caedeslv: '[7]#REF'!$A$1
Name cdcwryey: '[10]#REF'!$A$1
Name cpnllhur: '[1]#REF'!$A$1
Name cuyosutd: '[2]#REF'!$A$1
Name cvuklgsj: '[11]#REF'!$B$2
Name deqkwkzi: '[2]#REF'!$A$1
Name dftrqaiy: '[5]#REF'!$A$1
Name dmesnbje: '[12]#REF'!$A$1
Name dmfezyqy: '[13]#REF'!$A$1
Name dvqalzwz: '[6]#REF'!$A$1
Name dvutfafg: '[6]#REF'!$A$1
Name dxvlhjnw: '[14]#REF'!$A$1
Name dzcclxak: '[7]#REF'!$A$1
Name ebeqqinm: '[15]#REF'!$A$1
Name eizqawwj: '[2]#REF'!$A$1
Name envbgpbp: '[6]#REF'!$A$1
Name etthwfcb: '[12]#REF'!$A$1
Name feucnzqk: '[16]#REF'!$A$1
Name fftruyvd: '[2]#REF'!$A$1
Name fnlzvoxv: '[6]#REF'!$A$1
Name fnqdbnof: '[17]#REF'!$A$1
Name fufmbntk: '[18]#REF'!$A$1
Name fvgavnsv: '[19]#REF'!$A$1
Name fvwexuqp: '[8]#REF'!$A$1
Name fytaxufy: '[11]#REF'!$A$1
Name fzafntic: 本年累计!$A$1
Name fzafntic: Sheet54!$A$1
Name gaanfxcg: '[12]#REF'!$A$1
Name gjeooxbo: '[20]#REF'!$A$1
Name gmjryrwu: '[21]#REF'!$A$1
Name gnkvapru: '[22]#REF'!$A$1
Name gpbxymfw: '[6]#REF'!$A$1
Name gtyxyotn: '[6]#REF'!$A$1
Name guoaukrd: '[4]#REF'!$A$1
Name gzlmsitz: '[20]#REF'!$A$1
Name hgxswcaz: '[2]#REF'!$A$1
Name hhqfyrcr: '[3]#REF'!$A$1
Name hifqhofn: '[13]#REF'!$A$1
Name hkkjzqai: 本年累计!$A$1
Name hkkjzqai: Sheet54!$A$1
Name hliogioo: '[1]#REF'!$A$1
Name hlohimar: 本年累计!$A$1

Sheet Sheet54
A1: 绩效归因产品口径一级分类 | B1: 绩效归因产品口径二级分类 | C1: 六级科目名称 | D1: 绩效归因科目口径 | E1: 2026年初 | F1: 2026-01-01 | G1: 2026-01-02 | H1: 2026-01-03 | I1: 2026-01-04 | J1: 2026-01-05 | K1: 2026-01-06 | L1: 2026-01-07 | M1: 2026-01-08 | N1: 2026-01-09 | O1: 2026-01-10 | P1: 2026-01-11 | Q1: 2026-01-12 | R1: 2026-01-13 | S1: 2026-01-14 | T1: 2026-01-15 | U1: 2026-01-16 | V1: 2026-01-17 | W1: 2026-01-18 | X1: 2026-01-19 | Y1: 2026-01-20 | Z1: 2026-01-21 | AA1: 2026-01-22 | AB1: 2026-01-23 | AC1: 2026-01-24 | AD1: 2026-01-25 | AE1: 2026-01-26 | AF1: 2026-01-27 | AG1: 2026-01-28 | AH1: 2026-01-29 | AI1: 2026-01-30 | AJ1: 2026-01-31
A2: 权益类产品 | B2: 股票 | C2: 安徽皖通高速公路 | D2: 持仓成本 | E2: 12.061917 | F2: 0 | G2: 0 | H2: 0 | I2: 0 | J2: 0 | K2: 0 | L2: 0 | M2: 0 | N2: 0 | O2: 0 | P2: 0 | Q2: 0 | R2: 0 | S2: 0 | T2: 0 | U2: 0 | V2: 0 | W2: 0 | X2: 0 | Y2: 0 | Z2: 0 | AA2: 0 | AB2: 0 | AC2: 0 | AD2: 0 | AE2: 0 | AF2: 0 | AG2: 0 | AH2: 0 | AI2: 0 | AJ2: 0 | AK2: =ROUND(ABS(E2)+ABS(F2)+ABS(G2)+ABS(H2)+ABS(I2)+ABS(J2)+ABS(K2)+ABS(L2)+ABS(M2)+ABS(N2)+ABS(O2)+ABS(P2)+ABS(Q2)+ABS(R2)+ABS(S2)+ABS(T2)+ABS(U2)+ABS(V2)+ABS(W2)+ABS(X2)+ABS(Y2)+ABS(Z2)+ABS(AA2)+ABS(AB2)+ABS(AC2)+ABS(AD2)+ABS(AE2)+ABS(AF2)+ABS(AG2)+ABS(AH2)+ABS(AI2)+ABS(AJ2),6) -> 12.061917
D3: 持仓公允 | E3: -0.323925 | F3: 0 | G3: 0 | H3: 0 | I3: 0 | J3: -0.181052 | K3: -0.04591 | L3: 0.021777 | M3: -0.035832 | N3: 0.148425 | O3: 0 | P3: 0 | Q3: -0.056336 | R3: 0.007413 | S3: -0.151997 | T3: -0.070256 | U3: 0.116186 | V3: 0 | W3: 0 | X3: -0.111042 | Y3: 0.187432 | Z3: 0.015084 | AA3: -0.12726 | AB3: 0.077768 | AC3: 0 | AD3: 0 | AE3: -0.05227 | AF3: 0.142638 | AG3: 0.041984 | AH3: 0.299031 | AI3: 0.40917 | AJ3: 0 | AK3: =ROUND(ABS(E3)+ABS(F3)+ABS(G3)+ABS(H3)+ABS(I3)+ABS(J3)+ABS(K3)+ABS(L3)+ABS(M3)+ABS(N3)+ABS(O3)+ABS(P3)+ABS(Q3)+ABS(R3)+ABS(S3)+ABS(T3)+ABS(U3)+ABS(V3)+ABS(W3)+ABS(X3)+ABS(Y3)+ABS(Z3)+ABS(AA3)+ABS(AB3)+ABS(AC3)+ABS(AD3)+ABS(AE3)+ABS(AF3)+ABS(AG3)+ABS(AH3)+ABS(AI3)+ABS(AJ3),6) -> 2.622788
D4: OCI公允 | E4: 0 | F4: 0 | G4: 0 | H4: 0 | I4: 0 | J4: -0.181052 | K4: -0.04591 | L4: 0.021777 | M4: -0.035832 | N4: 0.148425 | O4: 0 | P4: 0 | Q4: -0.056336 | R4: 0.007413 | S4: -0.151997 | T4: -0.070256 | U4: 0.116186 | V4: 0 | W4: 0 | X4: -0.111042 | Y4: 0.187432 | Z4: 0.015084 | AA4: -0.12726 | AB4: 0.077768 | AC4: 0 | AD4: 0 | AE4: -0.05227 | AF4: 0.142638 | AG4: 0.041984 | AH4: 0.299031 | AI4: 0.40917 | AJ4: 0 | AK4: =ROUND(ABS(E4)+ABS(F4)+ABS(G4)+ABS(H4)+ABS(I4)+ABS(J4)+ABS(K4)+ABS(L4)+ABS(M4)+ABS(N4)+ABS(O4)+ABS(P4)+ABS(Q4)+ABS(R4)+ABS(S4)+ABS(T4)+ABS(U4)+ABS(V4)+ABS(W4)+ABS(X4)+ABS(Y4)+ABS(Z4)+ABS(AA4)+ABS(AB4)+ABS(AC4)+ABS(AD4)+ABS(AE4)+ABS(AF4)+ABS(AG4)+ABS(AH4)+ABS(AI4)+ABS(AJ4),6) -> 2.298863
C5: 安踏体育 | D5: 持仓成本 | E5: 758.75399 | F5: 0 | G5: 0 | H5: 0 | I5: 0 | J5: 0 | K5: 0 | L5: 0 | M5: 0 | N5: 0 | O5: 0 | P5: 0 | Q5: 0 | R5: 0 | S5: 0 | T5: 0 | U5: 0 | V5: 0 | W5: 0 | X5: 0 | Y5: 0 | Z5: 0 | AA5: 0 | AB5: 0 | AC5: 0 | AD5: 0 | AE5: 0 | AF5: 0 | AG5: 0 | AH5: 0 | AI5: 0 | AJ5: 0 | AK5: =ROUND(ABS(E5)+ABS(F5)+ABS(G5)+ABS(H5)+ABS(I5)+ABS(J5)+ABS(K5)+ABS(L5)+ABS(M5)+ABS(N5)+ABS(O5)+ABS(P5)+ABS(Q5)+ABS(R5)+ABS(S5)+ABS(T5)+ABS(U5)+ABS(V5)+ABS(W5)+ABS(X5)+ABS(Y5)+ABS(Z5)+ABS(AA5)+ABS(AB5)+ABS(AC5)+ABS(AD5)+ABS(AE5)+ABS(AF5)+ABS(AG5)+ABS(AH5)+ABS(AI5)+ABS(AJ5),6) -> 758.75399
D6: 持仓公允 | E6: -35.898292 | F6: 0 | G6: 0 | H6: 0 | I6: 0 | J6: -4.12495 | K6: 21.64795 | L6: -10.0572 | M6: 1.141 | N6: -12.1351 | O6: 0 | P6: 0 | Q6: -8.221 | R6: 5.9618 | S6: 8.49395 | T6: 5.44635 | U6: 2.10825 | V6: 0 | W6: 0 | X6: -2.47915 | Y6: 6.12115 | Z6: -31.50315 | AA6: -13.3356 | AB6: -4.1717 | AC6: 0 | AD6: 0 | AE6: -6.17185 | AF6: 13.29155 | AG6: -8.182 | AH6: 31.1405 | AI6: -21.79275 | AJ6: 0 | AK6: =ROUND(ABS(E6)+ABS(F6)+ABS(G6)+ABS(H6)+ABS(I6)+ABS(J6)+ABS(K6)+ABS(L6)+ABS(M6)+ABS(N6)+ABS(O6)+ABS(P6)+ABS(Q6)+ABS(R6)+ABS(S6)+ABS(T6)+ABS(U6)+ABS(V6)+ABS(W6)+ABS(X6)+ABS(Y6)+ABS(Z6)+ABS(AA6)+ABS(AB6)+ABS(AC6)+ABS(AD6)+ABS(AE6)+ABS(AF6)+ABS(AG6)+ABS(AH6)+ABS(AI6)+ABS(AJ6),6) -> 253.42524
D7: OCI公允 | E7: 0 | F7: 0 | G7: 0 | H7: 0 | I7: 0 | J7: -4.12495 | K7: 21.64795 | L7: -10.0572 | M7: 1.141 | N7: -12.1351 | O7: 0 | P7: 0 | Q7: -8.221 | R7: 5.9618 | S7: 8.49395 | T7: 5.44635 | U7: 2.10825 | V7: 0 | W7: 0 | X7: -2.47915 | Y7: 6.12115 | Z7: -31.50315 | AA7: -13.3356 | AB7: -4.1717 | AC7: 0 | AD7: 0 | AE7: -6.17185 | AF7: 13.29155 | AG7: -8.182 | AH7: 31.1405 | AI7: -21.79275 | AJ7: 0 | AK7: =ROUND(ABS(E7)+ABS(F7)+ABS(G7)+ABS(H7)+ABS(I7)+ABS(J7)+ABS(K7)+ABS(L7)+ABS(M7)+ABS(N7)+ABS(O7)+ABS(P7)+ABS(Q7)+ABS(R7)+ABS(S7)+ABS(T7)+ABS(U7)+ABS(V7)+ABS(W7)+ABS(X7)+ABS(Y7)+ABS(Z7)+ABS(AA7)+ABS(AB7)+ABS(AC7)+ABS(AD7)+ABS(AE7)+ABS(AF7)+ABS(AG7)+ABS(AH7)+ABS(AI7)+ABS(AJ7),6) -> 217.52695
C8: 北京银行 | D8: 持仓成本 | E8: 879.18426 | F8: 0 | G8: 0 | H8: 0 | I8: 0 | J8: 0 | K8: 0 | L8: 0 | M8: 0 | N8: 0 | O8: 0 | P8: 0 | Q8: 0 | R8: 0 | S8: 0 | T8: 0 | U8: 0 | V8: 0 | W8: 0 | X8: 0 | Y8: 0 | Z8: 0 | AA8: 0 | AB8: 0 | AC8: 0 | AD8: 0 | AE8: 0 | AF8: 0 | AG8: 0 | AH8: 0 | AI8: 0 | AJ8: 0 | AK8: =ROUND(ABS(E8)+ABS(F8)+ABS(G8)+ABS(H8)+ABS(I8)+ABS(J8)+ABS(K8)+ABS(L8)+ABS(M8)+ABS(N8)+ABS(O8)+ABS(P8)+ABS(Q8)+ABS(R8)+ABS(S8)+ABS(T8)+ABS(U8)+ABS(V8)+ABS(W8)+ABS(X8)+ABS(Y8)+ABS(Z8)+ABS(AA8)+ABS(AB8)+ABS(AC8)+ABS(AD8)+ABS(AE8)+ABS(AF8)+ABS(AG8)+ABS(AH8)+ABS(AI8)+ABS(AJ8),6) -> 879.18426
D9: 持仓公允 | E9: -57.184259 | F9: 0 | G9: 0 | H9: 0 | I9: 0 | J9: 6 | K9: 10.5 | L9: -6 | M9: -3 | N9: -3 | O9: 0 | P9: 0 | Q9: 1.5 | R9: 1.5 | S9: -22.5 | T9: -7.5 | U9: -13.5 | V9: 0 | W9: 0 | X9: -3 | Y9: 15 | Z9: -9 | AA9: 6 | AB9: -6 | AC9: 0 | AD9: 0 | AE9: 1.5 | AF9: -4.5 | AG9: 4.5 | AH9: 13.5 | AI9: -9 | AJ9: 0 | AK9: =ROUND(ABS(E9)+ABS(F9)+ABS(G9)+ABS(H9)+ABS(I9)+ABS(J9)+ABS(K9)+ABS(L9)+ABS(M9)+ABS(N9)+ABS(O9)+ABS(P9)+ABS(Q9)+ABS(R9)+ABS(S9)+ABS(T9)+ABS(U9)+ABS(V9)+ABS(W9)+ABS(X9)+ABS(Y9)+ABS(Z9)+ABS(AA9)+ABS(AB9)+ABS(AC9)+ABS(AD9)+ABS(AE9)+ABS(AF9)+ABS(AG9)+ABS(AH9)+ABS(AI9)+ABS(AJ9),6) -> 204.18426
D10: OCI公允 | E10: 0 | F10: 0 | G10: 0 | H10: 0 | I10: 0 | J10: 6 | K10: 10.5 | L10: -6 | M10: -3 | N10: -3 | O10: 0 | P10: 0 | Q10: 1.5 | R10: 1.5 | S10: -22.5 | T10: -7.5 | U10: -13.5 | V10: 0 | W10: 0 | X10: -3 | Y10: 15 | Z10: -9 | AA10: 6 | AB10: -6 | AC10: 0 | AD10: 0 | AE10: 1.5 | AF10: -4.5 | AG10: 4.5 | AH10: 13.5 | AI10: -9 | AJ10: 0 | AK10: =ROUND(ABS(E10)+ABS(F10)+ABS(G10)+ABS(H10)+ABS(I10)+ABS(J10)+ABS(K10)+ABS(L10)+ABS(M10)+ABS(N10)+ABS(O10)+ABS(P10)+ABS(Q10)+ABS(R10)+ABS(S10)+ABS(T10)+ABS(U10)+ABS(V10)+ABS(W10)+ABS(X10)+ABS(Y10)+ABS(Z10)+ABS(AA10)+ABS(AB10)+ABS(AC10)+ABS(AD10)+ABS(AE10)+ABS(AF10)+ABS(AG10)+ABS(AH10)+ABS(AI10)+ABS(AJ10),6) -> 147
C11: 北控水务集团 | D11: 持仓成本 | E11: 452.26321 | F11: 0 | G11: 0 | H11: 0 | I11: 0 | J11: 0 | K11: 0 | L11: 0 | M11: 0 | N11: 0 | O11: 0 | P11: 0 | Q11: 0 | R11: 0 | S11: 0 | T11: 0 | U11: 0 | V11: 0 | W11: 0 | X11: 0 | Y11: 0 | Z11: 0 | AA11: 0 | AB11: 0 | AC11: 0 | AD11: 0 | AE11: 0 | AF11: 0 | AG11: 0 | AH11: 0 | AI11: 0 | AJ11: 0 | AK11: =ROUND(ABS(E11)+ABS(F11)+ABS(G11)+ABS(H11)+ABS(I11)+ABS(J11)+ABS(K11)+ABS(L11)+ABS(M11)+ABS(N11)+ABS(O11)+ABS(P11)+ABS(Q11)+ABS(R11)+ABS(S11)+ABS(T11)+ABS(U11)+ABS(V11)+ABS(W11)+ABS(X11)+ABS(Y11)+ABS(Z11)+ABS(AA11)+ABS(AB11)+ABS(AC11)+ABS(AD11)+ABS(AE11)+ABS(AF11)+ABS(AG11)+ABS(AH11)+ABS(AI11)+ABS(AJ11),6) -> 452.26321
D12: 持仓公允 | E12: -10.742409 | F12: 0 | G12: 0 | H12: 0 | I12: 0 | J12: 0.3622 | K12: 6.017 | L12: 1.9422 | M12: 0.7028 | N12: 0.9382 | O12: 0 | P12: 0 | Q12: -0.1008 | R12: 1.0322 | S12: 5.3646 | T12: 0.0512 | U12: -7.5064 | V12: 0 | W12: 0 | X12: -0.1512 | Y12: 8.5722 | Z12: 1.3206 | AA12: 11.3328 | AB12: -0.1056 | AC12: 0 | AD12: 0 | AE12: -1.7326 | AF12: -5.7202 | AG12: 7.0304 | AH12: 4.1226 | AI12: 3.558 | AJ12: 0 | AK12: =ROUND(ABS(E12)+ABS(F12)+ABS(G12)+ABS(H12)+ABS(I12)+ABS(J12)+ABS(K12)+ABS(L12)+ABS(M12)+ABS(N12)+ABS(O12)+ABS(P12)+ABS(Q12)+ABS(R12)+ABS(S12)+ABS(T12)+ABS(U12)+ABS(V12)+ABS(W12)+ABS(X12)+ABS(Y12)+ABS(Z12)+ABS(AA12)+ABS(AB12)+ABS(AC12)+ABS(AD12)+ABS(AE12)+ABS(AF12)+ABS(AG12)+ABS(AH12)+ABS(AI12)+ABS(AJ12),6) -> 78.406209
D13: OCI公允 | E13: 0 | F13: 0 | G13: 0 | H13: 0 | I13: 0 | J13: 0.3622 | K13: 6.017 | L13: 1.9422 | M13: 0.7028 | N13: 0.9382 | O13: 0 | P13: 0 | Q13: -0.1008 | R13: 1.0322 | S13: 5.3646 | T13: 0.0512 | U13: -7.5064 | V13: 0 | W13: 0 | X13: -0.1512 | Y13: 8.5722 | Z13: 1.3206 | AA13: 11.3328 | AB13: -0.1056 | AC13: 0 | AD13: 0 | AE13: -1.7326 | AF13: -5.7202 | AG13: 7.0304 | AH13: 4.1226 | AI13: 3.558 | AJ13: 0 | AK13: =ROUND(ABS(E13)+ABS(F13)+ABS(G13)+ABS(H13)+ABS(I13)+ABS(J13)+ABS(K13)+ABS(L13)+ABS(M13)+ABS(N13)+ABS(O13)+ABS(P13)+ABS(Q13)+ABS(R13)+ABS(S13)+ABS(T13)+ABS(U13)+ABS(V13)+ABS(W13)+ABS(X13)+ABS(Y13)+ABS(Z13)+ABS(AA13)+ABS(AB13)+ABS(AC13)+ABS(AD13)+ABS(AE13)+ABS(AF13)+ABS(AG13)+ABS(AH13)+ABS(AI13)+ABS(AJ13),6) -> 67.6638
C14: 工商银行 | D14: 持仓成本 | E14: 814.29188 | F14: 0 | G14: 0 | H14: 0 | I14: 0 | J14: 0 | K14: 0 | L14: 0 | M14: 0 | N14: 0 | O14: 0 | P14: 0 | Q14: 0 | R14: 0 | S14: 0 | T14: 0 | U14: 0 | V14: 0 | W14: 0 | X14: 0 | Y14: 0 | Z14: 0 | AA14: 0 | AB14: 0 | AC14: 0 | AD14: 0 | AE14: 0 | AF14: 0 | AG14: 0 | AH14: 0 | AI14: 0 | AJ14: 0 | AK14: =ROUND(ABS(E14)+ABS(F14)+ABS(G14)+ABS(H14)+ABS(I14)+ABS(J14)+ABS(K14)+ABS(L14)+ABS(M14)+ABS(N14)+ABS(O14)+ABS(P14)+ABS(Q14)+ABS(R14)+ABS(S14)+ABS(T14)+ABS(U14)+ABS(V14)+ABS(W14)+ABS(X14)+ABS(Y14)+ABS(Z14)+ABS(AA14)+ABS(AB14)+ABS(AC14)+ABS(AD14)+ABS(AE14)+ABS(AF14)+ABS(AG14)+ABS(AH14)+ABS(AI14)+ABS(AJ14),6) -> 814.29188
D15: 持仓公允 | E15: 145.29794 | F15: 0 | G15: 0 | H15: 0 | I15: 0 | J15: -15.26617 | K15: 1.37241 | L15: -10.34688 | M15: -4.64168 | N15: 2.80568 | O15: 0 | P15: 0 | Q15: 16.5393 | R15: 7.52862 | S15: -9.11982 | T15: 15.30748 | U15: 0.76449 | V15: 0 | W15: 0 | X15: -1.84229 | Y15: -5.30621 | Z15: -16.12263 | AA15: -4.8042 | AB15: -3.24462 | AC15: 0 | AD15: 0 | AE15: 13.76286 | AF15: 17.45424 | AG15: 34.65314 | AH15: 4.98406 | AI15: -22.68225 | AJ15: 0 | AK15: =ROUND(ABS(E15)+ABS(F15)+ABS(G15)+ABS(H15)+ABS(I15)+ABS(J15)+ABS(K15)+ABS(L15)+ABS(M15)+ABS(N15)+ABS(O15)+ABS(P15)+ABS(Q15)+ABS(R15)+ABS(S15)+ABS(T15)+ABS(U15)+ABS(V15)+ABS(W15)+ABS(X15)+ABS(Y15)+ABS(Z15)+ABS(AA15)+ABS(AB15)+ABS(AC15)+ABS(AD15)+ABS(AE15)+ABS(AF15)+ABS(AG15)+ABS(AH15)+ABS(AI15)+ABS(AJ15),6) -> 353.84697
D16: OCI公允 | E16: 0 | F16: 0 | G16: 0 | H16: 0 | I16: 0 | J16: -15.26617 | K16: 1.37241 | L16: -10.34688 | M16: -4.64168 | N16: 2.80568 | O16: 0 | P16: 0 | Q16: 16.5393 | R16: 7.52862 | S16: -9.11982 | T16: 15.30748 | U16: 0.76449 | V16: 0 | W16: 0 | X16: -1.84229 | Y16: -5.30621 | Z16: -16.12263 | AA16: -4.8042 | AB16: -3.24462 | AC16: 0 | AD16: 0 | AE16: 13.76286 | AF16: 17.45424 | AG16: 34.65314 | AH16: 4.98406 | AI16: -22.68225 | AJ16: 0 | AK16: =ROUND(ABS(E16)+ABS(F16)+ABS(G16)+ABS(H16)+ABS(I16)+ABS(J16)+ABS(K16)+ABS(L16)+ABS(M16)+ABS(N16)+ABS(O16)+ABS(P16)+ABS(Q16)+ABS(R16)+ABS(S16)+ABS(T16)+ABS(U16)+ABS(V16)+ABS(W16)+ABS(X16)+ABS(Y16)+ABS(Z16)+ABS(AA16)+ABS(AB16)+ABS(AC16)+ABS(AD16)+ABS(AE16)+ABS(AF16)+ABS(AG16)+ABS(AH16)+ABS(AI16)+ABS(AJ16),6) -> 208.54903
D17: 应收应付 | E17: 24.038 | F17: 0 | G17: 0 | H17: 0 | I17: 0 | J17: 0 | K17: 0 | L17: 0 | M17: 0 | N17: 0 | O17: 0 | P17: 0 | Q17: 0 | R17: 0 | S17: 0 | T17: 0 | U17: 0 | V17: 0 | W17: 0 | X17: 0 | Y17: 0 | Z17: 0 | AA17: 0 | AB17: 0 | AC17: 0 | AD17: 0 | AE17: 0 | AF17: 0 | AG17: -24.038 | AH17: 0 | AI17: 0 | AJ17: 0 | AK17: =ROUND(ABS(E17)+ABS(F17)+ABS(G17)+ABS(H17)+ABS(I17)+ABS(J17)+ABS(K17)+ABS(L17)+ABS(M17)+ABS(N17)+ABS(O17)+ABS(P17)+ABS(Q17)+ABS(R17)+ABS(S17)+ABS(T17)+ABS(U17)+ABS(V17)+ABS(W17)+ABS(X17)+ABS(Y17)+ABS(Z17)+ABS(AA17)+ABS(AB17)+ABS(AC17)+ABS(AD17)+ABS(AE17)+ABS(AF17)+ABS(AG17)+ABS(AH17)+ABS(AI17)+ABS(AJ17),6) -> 48.076
C18: 光大银行 | D18: 持仓成本 | E18: 976.68199 | F18: 0 | G18: 0 | H18: 0 | I18: 0 | J18: 0 | K18: 0 | L18: 0 | M18: 0 | N18: 0 | O18: 0 | P18: 0 | Q18: 0 | R18: 0 | S18: 0 | T18: 0 | U18: 0 | V18: 0 | W18: 0 | X18: 0 | Y18: 0 | Z18: 0 | AA18: 0 | AB18: 0 | AC18: 0 | AD18: 0 | AE18: 0 | AF18: 0 | AG18: 0 | AH18: 0 | AI18: 0 | AJ18: 0 | AK18: =ROUND(ABS(E18)+ABS(F18)+ABS(G18)+ABS(H18)+ABS(I18)+ABS(J18)+ABS(K18)+ABS(L18)+ABS(M18)+ABS(N18)+ABS(O18)+ABS(P18)+ABS(Q18)+ABS(R18)+ABS(S18)+ABS(T18)+ABS(U18)+ABS(V18)+ABS(W18)+ABS(X18)+ABS(Y18)+ABS(Z18)+ABS(AA18)+ABS(AB18)+ABS(AC18)+ABS(AD18)+ABS(AE18)+ABS(AF18)+ABS(AG18)+ABS(AH18)+ABS(AI18)+ABS(AJ18),6) -> 976.68199
D19: 持仓公允 | E19: -34.381994 | F19: 0 | G19: 0 | H19: 0 | I19: 0 | J19: -2.7 | K19: 5.4 | L19: -2.7 | M19: -5.4 | N19: -5.4 | O19: 0 | P19: 0 | Q19: 2.7 | R19: 0 | S19: -8.1 | T19: -13.5 | U19: -8.1 | V19: 0 | W19: 0 | X19: -2.7 | Y19: 13.5 | Z19: -8.1 | AA19: 5.4 | AB19: -2.7 | AC19: 0 | AD19: 0 | AE19: 2.7 | AF19: -5.4 | AG19: -10.8 | AH19: 5.4 | AI19: -5.4 | AJ19: 0 | AK19: =ROUND(ABS(E19)+ABS(F19)+ABS(G19)+ABS(H19)+ABS(I19)+ABS(J19)+ABS(K19)+ABS(L19)+ABS(M19)+ABS(N19)+ABS(O19)+ABS(P19)+ABS(Q19)+ABS(R19)+ABS(S19)+ABS(T19)+ABS(U19)+ABS(V19)+ABS(W19)+ABS(X19)+ABS(Y19)+ABS(Z19)+ABS(AA19)+ABS(AB19)+ABS(AC19)+ABS(AD19)+ABS(AE19)+ABS(AF19)+ABS(AG19)+ABS(AH19)+ABS(AI19)+ABS(AJ19),6) -> 150.48199
D20: OCI公允 | E20: 0 | F20: 0 | G20: 0 | H20: 0 | I20: 0 | J20: -2.7 | K20: 5.4 | L20: -2.7 | M20: -5.4 | N20: -5.4 | O20: 0 | P20: 0 | Q20: 2.7 | R20: 0 | S20: -8.1 | T20: -13.5 | U20: -8.1 | V20: 0 | W20: 0 | X20: -2.7 | Y20: 13.5 | Z20: -8.1 | AA20: 5.4 | AB20: -2.7 | AC20: 0 | AD20: 0 | AE20: 2.7 | AF20: -5.4 | AG20: -10.8 | AH20: 5.4 | AI20: -5.4 | AJ20: 0 | AK20: =ROUND(ABS(E20)+ABS(F20)+ABS(G20)+ABS(H20)+ABS(I20)+ABS(J20)+ABS(K20)+ABS(L20)+ABS(M20)+ABS(N20)+ABS(O20)+ABS(P20)+ABS(Q20)+ABS(R20)+ABS(S20)+ABS(T20)+ABS(U20)+ABS(V20)+ABS(W20)+ABS(X20)+ABS(Y20)+ABS(Z20)+ABS(AA20)+ABS(AB20)+ABS(AC20)+ABS(AD20)+ABS(AE20)+ABS(AF20)+ABS(AG20)+ABS(AH20)+ABS(AI20)+ABS(AJ20),6) -> 116.1
C21: 贵州茅台 | D21: 持仓成本 | E21: 14.83109 | F21: 0 | G21: 0 | H21: 0 | I21: 0 | J21: 0 | K21: 0 | L21: 0 | M21: 0 | N21: 0 | O21: 0 | P21: 0 | Q21: 0 | R21: 0 | S21: 0 | T21: 0 | U21: 0 | V21: 0 | W21: 0 | X21: 0 | Y21: 0 | Z21: 0 | AA21: 0 | AB21: 0 | AC21: 0 | AD21: 0 | AE21: -14.83109 | AF21: 0 | AG21: 0 | AH21: 0 | AI21: 0 | AJ21: 0 | AK21: =ROUND(ABS(E21)+ABS(F21)+ABS(G21)+ABS(H21)+ABS(I21)+ABS(J21)+ABS(K21)+ABS(L21)+ABS(M21)+ABS(N21)+ABS(O21)+ABS(P21)+ABS(Q21)+ABS(R21)+ABS(S21)+ABS(T21)+ABS(U21)+ABS(V21)+ABS(W21)+ABS(X21)+ABS(Y21)+ABS(Z21)+ABS(AA21)+ABS(AB21)+ABS(AC21)+ABS(AD21)+ABS(AE21)+ABS(AF21)+ABS(AG21)+ABS(AH21)+ABS(AI21)+ABS(AJ21),6) -> 29.66218
D22: 持仓公允 | E22: -1.05929 | F22: 0 | G22: 0 | H22: 0 | I22: 0 | J22: 0.4882 | K22: 0.0201 | L22: -0.0465 | M22: -0.1106 | N22: 0.068 | O22: 0 | P22: 0 | Q22: 0.0413 | R22: -0.1223 | S22: -0.1299 | T22: -0.0912 | U22: -0.0689 | V22: 0 | W22: 0 | X22: -0.06 | Y22: -0.0245 | Z22: -0.2249 | AA22: -0.11 | AB22: -0.0306 | AC22: 0 | AD22: 0 | AE22: 1.46109 | AF22: 0 | AG22: 0 | AH22: 0 | AI22: 0 | AJ22: 0 | AK22: =ROUND(ABS(E22)+ABS(F22)+ABS(G22)+ABS(H22)+ABS(I22)+ABS(J22)+ABS(K22)+ABS(L22)+ABS(M22)+ABS(N22)+ABS(O22)+ABS(P22)+ABS(Q22)+ABS(R22)+ABS(S22)+ABS(T22)+ABS(U22)+ABS(V22)+ABS(W22)+ABS(X22)+ABS(Y22)+ABS(Z22)+ABS(AA22)+ABS(AB22)+ABS(AC22)+ABS(AD22)+ABS(AE22)+ABS(AF22)+ABS(AG22)+ABS(AH22)+ABS(AI22)+ABS(AJ22),6) -> 4.15738
D23: OCI公允 | E23: 0 | F23: 0 | G23: 0 | H23: 0 | I23: 0 | J23: 0.4882 | K23: 0.0201 | L23: -0.0465 | M23: -0.1106 | N23: 0.068 | O23: 0 | P23: 0 | Q23: 0.0413 | R23: -0.1223 | S23: -0.1299 | T23: -0.0912 | U23: -0.0689 | V23: 0 | W23: 0 | X23: -0.06 | Y23: -0.0245 | Z23: -0.2249 | AA23: -0.11 | AB23: -0.0306 | AC23: 0 | AD23: 0 | AE23: 1.46109 | AF23: 0 | AG23: 0 | AH23: 0 | AI23: 0 | AJ23: 0 | AK23: =ROUND(ABS(E23)+ABS(F23)+ABS(G23)+ABS(H23)+ABS(I23)+ABS(J23)+ABS(K23)+ABS(L23)+ABS(M23)+ABS(N23)+ABS(O23)+ABS(P23)+ABS(Q23)+ABS(R23)+ABS(S23)+ABS(T23)+ABS(U23)+ABS(V23)+ABS(W23)+ABS(X23)+ABS(Y23)+ABS(Z23)+ABS(AA23)+ABS(AB23)+ABS(AC23)+ABS(AD23)+ABS(AE23)+ABS(AF23)+ABS(AG23)+ABS(AH23)+ABS(AI23)+ABS(AJ23),6) -> 3.09809
D24: OCI价差 | E24: 0 | F24: 0 | G24: 0 | H24: 0 | I24: 0 | J24: 0 | K24: 0 | L24: 0 | M24: 0 | N24: 0 | O24: 0 | P24: 0 | Q24: 0 | R24: 0 | S24: 0 | T24: 0 | U24: 0 | V24: 0 | W24: 0 | X24: 0 | Y24: 0 | Z24: 0 | AA24: 0 | AB24: 0 | AC24: 0 | AD24: 0 | AE24: -1.363692 | AF24: 0 | AG24: 0 | AH24: 0 | AI24: 0 | AJ24: 0 | AK24: =ROUND(ABS(E24)+ABS(F24)+ABS(G24)+ABS(H24)+ABS(I24)+ABS(J24)+ABS(K24)+ABS(L24)+ABS(M24)+ABS(N24)+ABS(O24)+ABS(P24)+ABS(Q24)+ABS(R24)+ABS(S24)+ABS(T24)+ABS(U24)+ABS(V24)+ABS(W24)+ABS(X24)+ABS(Y24)+ABS(Z24)+ABS(AA24)+ABS(AB24)+ABS(AC24)+ABS(AD24)+ABS(AE24)+ABS(AF24)+ABS(AG24)+ABS(AH24)+ABS(AI24)+ABS(AJ24),6) -> 1.363692
C25: 海底捞 | D25: 持仓成本 | E25: 536.57688 | F25: 0 | G25: 0 | H25: 0 | I25: 0 | J25: 0 | K25: 0 | L25: 0 | M25: 0 | N25: 0 | O25: 0 | P25: 0 | Q25: 0 | R25: 0 | S25: 0 | T25: 0 | U25: 0 | V25: 0 | W25: 0 | X25: 0 | Y25: 0 | Z25: 0 | AA25: 0 | AB25: 0 | AC25: 0 | AD25: 0 | AE25: 0 | AF25: 0 | AG25: 0 | AH25: 0 | AI25: 0 | AJ25: 0 | AK25: =ROUND(ABS(E25)+ABS(F25)+ABS(G25)+ABS(H25)+ABS(I25)+ABS(J25)+ABS(K25)+ABS(L25)+ABS(M25)+ABS(N25)+ABS(O25)+ABS(P25)+ABS(Q25)+ABS(R25)+ABS(S25)+ABS(T25)+ABS(U25)+ABS(V25)+ABS(W25)+ABS(X25)+ABS(Y25)+ABS(Z25)+ABS(AA25)+ABS(AB25)+ABS(AC25)+ABS(AD25)+ABS(AE25)+ABS(AF25)+ABS(AG25)+ABS(AH25)+ABS(AI25)+ABS(AJ25),6) -> 536.57688
D26: 持仓公允 | E26: -25.05888 | F26: 0 | G26: 0 | H26: 0 | I26: 0 | J26: -2.0108 | K26: -3.20104 | L26: 5.18772 | M26: -9.25288 | N26: -0.95132 | O26: 0 | P26: 0 | Q26: 27.8308 | R26: -13.4036 | S26: 47.20848 | T26: -3.51384 | U26: -6.15632 | V26: 0 | W26: 0 | X26: 0.5288 | Y26: 4.921 | Z26: -0.5634 | AA26: 6.108 | AB26: 5.2292 | AC26: 0 | AD26: 0 | AE26: -2.79284 | AF26: 1.69644 | AG26: -14.75296 | AH26: 18.85276 | AI26: -3.9138 | AJ26: 0 | AK26: =ROUND(ABS(E26)+ABS(F26)+ABS(G26)+ABS(H26)+ABS(I26)+ABS(J26)+ABS(K26)+ABS(L26)+ABS(M26)+ABS(N26)+ABS(O26)+ABS(P26)+ABS(Q26)+ABS(R26)+ABS(S26)+ABS(T26)+ABS(U26)+ABS(V26)+ABS(W26)+ABS(X26)+ABS(Y26)+ABS(Z26)+ABS(AA26)+ABS(AB26)+ABS(AC26)+ABS(AD26)+ABS(AE26)+ABS(AF26)+ABS(AG26)+ABS(AH26)+ABS(AI26)+ABS(AJ26),6) -> 203.13488
D27: OCI公允 | E27: 0 | F27: 0 | G27: 0 | H27: 0 | I27: 0 | J27: -2.0108 | K27: -3.20104 | L27: 5.18772 | M27: -9.25288 | N27: -0.95132 | O27: 0 | P27: 0 | Q27: 27.8308 | R27: -13.4036 | S27: 47.20848 | T27: -3.51384 | U27: -6.15632 | V27: 0 | W27: 0 | X27: 0.5288 | Y27: 4.921 | Z27: -0.5634 | AA27: 6.108 | AB27: 5.2292 | AC27: 0 | AD27: 0 | AE27: -2.79284 | AF27: 1.69644 | AG27: -14.75296 | AH27: 18.85276 | AI27: -3.9138 | AJ27: 0 | AK27: =ROUND(ABS(E27)+ABS(F27)+ABS(G27)+ABS(H27)+ABS(I27)+ABS(J27)+ABS(K27)+ABS(L27)+ABS(M27)+ABS(N27)+ABS(O27)+ABS(P27)+ABS(Q27)+ABS(R27)+ABS(S27)+ABS(T27)+ABS(U27)+ABS(V27)+ABS(W27)+ABS(X27)+ABS(Y27)+ABS(Z27)+ABS(AA27)+ABS(AB27)+ABS(AC27)+ABS(AD27)+ABS(AE27)+ABS(AF27)+ABS(AG27)+ABS(AH27)+ABS(AI27)+ABS(AJ27),6) -> 178.076
C28: 海尔智家 | D28: 持仓成本 | E28: 453.40333 | F28: 0 | G28: 0 | H28: 0 | I28: 0 | J28: 0 | K28: 0 | L28: 0 | M28: 0 | N28: 0 | O28: 0 | P28: 0 | Q28: 0 | R28: 0 | S28: 0 | T28: 0 | U28: 0 | V28: 0 | W28: 0 | X28: 0 | Y28: 0 | Z28: 0 | AA28: 0 | AB28: 0 | AC28: 0 | AD28: 0 | AE28: 0 | AF28: 0 | AG28: 0 | AH28: 0 | AI28: 0 | AJ28: 0 | AK28: =ROUND(ABS(E28)+ABS(F28)+ABS(G28)+ABS(H28)+ABS(I28)+ABS(J28)+ABS(K28)+ABS(L28)+ABS(M28)+ABS(N28)+ABS(O28)+ABS(P28)+ABS(Q28)+ABS(R28)+ABS(S28)+ABS(T28)+ABS(U28)+ABS(V28)+ABS(W28)+ABS(X28)+ABS(Y28)+ABS(Z28)+ABS(AA28)+ABS(AB28)+ABS(AC28)+ABS(AD28)+ABS(AE28)+ABS(AF28)+ABS(AG28)+ABS(AH28)+ABS(AI28)+ABS(AJ28),6) -> 453.40333
D29: 持仓公允 | E29: -17.625888 | F29: 0 | G29: 0 | H29: 0 | I29: 0 | J29: 15.76616 | K29: 4.59776 | L29: 5.17092 | M29: 0.36172 | N29: 4.142 | O29: 0 | P29: 0 | Q29: 3.83664 | R29: 3.50508 | S29: -1.43056 | T29: -0.30492 | U29: 1.77536 | V29: 0 | W29: 0 | X29: 0.1984 | Y29: 4.627 | Z29: -0.1254 | AA29: -7.92768 | AB29: -7.60312 | AC29: 0 | AD29: 0 | AE29: -4.59024 | AF29: 4.27944 | AG29: -4.38424 | AH29: 8.42624 | AI29: -7.116 | AJ29: 0 | AK29: =ROUND(ABS(E29)+ABS(F29)+ABS(G29)+ABS(H29)+ABS(I29)+ABS(J29)+ABS(K29)+ABS(L29)+ABS(M29)+ABS(N29)+ABS(O29)+ABS(P29)+ABS(Q29)+ABS(R29)+ABS(S29)+ABS(T29)+ABS(U29)+ABS(V29)+ABS(W29)+ABS(X29)+ABS(Y29)+ABS(Z29)+ABS(AA29)+ABS(AB29)+ABS(AC29)+ABS(AD29)+ABS(AE29)+ABS(AF29)+ABS(AG29)+ABS(AH29)+ABS(AI29)+ABS(AJ29),6) -> 107.79477
D30: OCI公允 | E30: 0 | F30: 0 | G30: 0 | H30: 0 | I30: 0 | J30: 15.76616 | K30: 4.59776 | L30: 5.17092 | M30: 0.36172 | N30: 4.142 | O30: 0 | P30: 0 | Q30: 3.83664 | R30: 3.50508 | S30: -1.43056 | T30: -0.30492 | U30: 1.77536 | V30: 0 | W30: 0 | X30: 0.1984 | Y30: 4.627 | Z30: -0.1254 | AA30: -7.92768 | AB30: -7.60312 | AC30: 0 | AD30: 0 | AE30: -4.59024 | AF30: 4.27944 | AG30: -4.38424 | AH30: 8.42624 | AI30: -7.116 | AJ30: 0 | AK30: =ROUND(ABS(E30)+ABS(F30)+ABS(G30)+ABS(H30)+ABS(I30)+ABS(J30)+ABS(K30)+ABS(L30)+ABS(M30)+ABS(N30)+ABS(O30)+ABS(P30)+ABS(Q30)+ABS(R30)+ABS(S30)+ABS(T30)+ABS(U30)+ABS(V30)+ABS(W30)+ABS(X30)+ABS(Y30)+ABS(Z30)+ABS(AA30)+ABS(AB30)+ABS(AC30)+ABS(AD30)+ABS(AE30)+ABS(AF30)+ABS(AG30)+ABS(AH30)+ABS(AI30)+ABS(AJ30),6) -> 90.16888
C31: 华电国际电力股份 | D31: 持仓成本 | E31: 607.74285 | F31: 0 | G31: 0 | H31: 0 | I31: 0 | J31: 0 | K31: 0 | L31: 0 | M31: 0 | N31: 0 | O31: 0 | P31: 0 | Q31: 0 | R31: 0 | S31: 0 | T31: 0 | U31: 0 | V31: 0 | W31: 0 | X31: 0 | Y31: 0 | Z31: 0 | AA31: 0 | AB31: 0 | AC31: 0 | AD31: 0 | AE31: 0 | AF31: 0 | AG31: 0 | AH31: 0 | AI31: 0 | AJ31: 0 | AK31: =ROUND(ABS(E31)+ABS(F31)+ABS(G31)+ABS(H31)+ABS(I31)+ABS(J31)+ABS(K31)+ABS(L31)+ABS(M31)+ABS(N31)+ABS(O31)+ABS(P31)+ABS(Q31)+ABS(R31)+ABS(S31)+ABS(T31)+ABS(U31)+ABS(V31)+ABS(W31)+ABS(X31)+ABS(Y31)+ABS(Z31)+ABS(AA31)+ABS(AB31)+ABS(AC31)+ABS(AD31)+ABS(AE31)+ABS(AF31)+ABS(AG31)+ABS(AH31)+ABS(AI31)+ABS(AJ31),6) -> 607.74285
D32: 持仓公允 | E32: -59.880148 | F32: 0 | G32: 0 | H32: 0 | I32: 0 | J32: 7.6218 | K32: 0.8073 | L32: -9.22275 | M32: 17.0097 | N32: -9.13065 | O32: 0 | P32: 0 | Q32: -0.1239 | R32: 8.4588 | S32: -5.3646 | T32: -2.6202 | U32: -4.45545 | V32: 0 | W32: 0 | X32: 2.49465 | Y32: 3.5826 | Z32: -3.2364 | AA32: -0.594 | AB32: -2.8017 | AC32: 0 | AD32: 0 | AE32: 0.06165 | AF32: 0.90645 | AG32: 5.2272 | AH32: -1.4352 | AI32: -4.00275 | AJ32: 0 | AK32: =ROUND(ABS(E32)+ABS(F32)+ABS(G32)+ABS(H32)+ABS(I32)+ABS(J32)+ABS(K32)+ABS(L32)+ABS(M32)+ABS(N32)+ABS(O32)+ABS(P32)+ABS(Q32)+ABS(R32)+ABS(S32)+ABS(T32)+ABS(U32)+ABS(V32)+ABS(W32)+ABS(X32)+ABS(Y32)+ABS(Z32)+ABS(AA32)+ABS(AB32)+ABS(AC32)+ABS(AD32)+ABS(AE32)+ABS(AF32)+ABS(AG32)+ABS(AH32)+ABS(AI32)+ABS(AJ32),6) -> 149.0379
D33: OCI公允 | E33: 0 | F33: 0 | G33: 0 | H33: 0 | I33: 0 | J33: 7.6218 | K33: 0.8073 | L33: -9.22275 | M33: 17.0097 | N33: -9.13065 | O33: 0 | P33: 0 | Q33: -0.1239 | R33: 8.4588 | S33: -5.3646 | T33: -2.6202 | U33: -4.45545 | V33: 0 | W33: 0 | X33: 2.49465 | Y33: 3.5826 | Z33: -3.2364 | AA33: -0.594 | AB33: -2.8017 | AC33: 0 | AD33: 0 | AE33: 0.06165 | AF33: 0.90645 | AG33: 5.2272 | AH33: -1.4352 | AI33: -4.00275 | AJ33: 0 | AK33: =ROUND(ABS(E33)+ABS(F33)+ABS(G33)+ABS(H33)+ABS(I33)+ABS(J33)+ABS(K33)+ABS(L33)+ABS(M33)+ABS(N33)+ABS(O33)+ABS(P33)+ABS(Q33)+ABS(R33)+ABS(S33)+ABS(T33)+ABS(U33)+ABS(V33)+ABS(W33)+ABS(X33)+ABS(Y33)+ABS(Z33)+ABS(AA33)+ABS(AB33)+ABS(AC33)+ABS(AD33)+ABS(AE33)+ABS(AF33)+ABS(AG33)+ABS(AH33)+ABS(AI33)+ABS(AJ33),6) -> 89.15775
C34: 华润电力 | D34: 持仓成本 | E34: 333.94923 | F34: 0 | G34: 0 | H34: 0 | I34: 0 | J34: 0 | K34: 0 | L34: 0 | M34: 0 | N34: 0 | O34: 0 | P34: 0 | Q34: 0 | R34: 0 | S34: 0 | T34: 0 | U34: 0 | V34: 0 | W34: 0 | X34: 0 | Y34: 0 | Z34: 0 | AA34: 0 | AB34: 0 | AC34: 0 | AD34: 0 | AE34: 0 | AF34: 0 | AG34: 0 | AH34: 0 | AI34: 0 | AJ34: 0 | AK34: =ROUND(ABS(E34)+ABS(F34)+ABS(G34)+ABS(H34)+ABS(I34)+ABS(J34)+ABS(K34)+ABS(L34)+ABS(M34)+ABS(N34)+ABS(O34)+ABS(P34)+ABS(Q34)+ABS(R34)+ABS(S34)+ABS(T34)+ABS(U34)+ABS(V34)+ABS(W34)+ABS(X34)+ABS(Y34)+ABS(Z34)+ABS(AA34)+ABS(AB34)+ABS(AC34)+ABS(AD34)+ABS(AE34)+ABS(AF34)+ABS(AG34)+ABS(AH34)+ABS(AI34)+ABS(AJ34),6) -> 333.94923
D35: 持仓公允 | E35: -23.269354 | F35: 0 | G35: 0 | H35: 0 | I35: 0 | J35: 8.83552 | K35: 0.64352 | L35: 1.18254 | M35: 2.83554 | N35: -2.5848 | O35: 0 | P35: 0 | Q35: 0.64468 | R35: 2.1426 | S35: 0 | T35: 1.28816 | U35: -3.82894 | V35: 0 | W35: 0 | X35: 1.14242 | Y35: -1.68112 | Z35: 0.38928 | AA35: 2.9328 | AB35: -4.00016 | AC35: 0 | AD35: 0 | AE35: 0.57154 | AF35: 0.10494 | AG35: 1.71156 | AH35: -0.83306 | AI35: -5.5149 | AJ35: 0 | AK35: =ROUND(ABS(E35)+ABS(F35)+ABS(G35)+ABS(H35)+ABS(I35)+ABS(J35)+ABS(K35)+ABS(L35)+ABS(M35)+ABS(N35)+ABS(O35)+ABS(P35)+ABS(Q35)+ABS(R35)+ABS(S35)+ABS(T35)+ABS(U35)+ABS(V35)+ABS(W35)+ABS(X35)+ABS(Y35)+ABS(Z35)+ABS(AA35)+ABS(AB35)+ABS(AC35)+ABS(AD35)+ABS(AE35)+ABS(AF35)+ABS(AG35)+ABS(AH35)+ABS(AI35)+ABS(AJ35),6) -> 66.137434
D36: OCI公允 | E36: 0 | F36: 0 | G36: 0 | H36: 0 | I36: 0 | J36: 8.83552 | K36: 0.64352 | L36: 1.18254 | M36: 2.83554 | N36: -2.5848 | O36: 0 | P36: 0 | Q36: 0.64468 | R36: 2.1426 | S36: 0 | T36: 1.28816 | U36: -3.82894 | V36: 0 | W36: 0 | X36: 1.14242 | Y36: -1.68112 | Z36: 0.38928 | AA36: 2.9328 | AB36: -4.00016 | AC36: 0 | AD36: 0 | AE36: 0.57154 | AF36: 0.10494 | AG36: 1.71156 | AH36: -0.83306 | AI36: -5.5149 | AJ36: 0 | AK36: =ROUND(ABS(E36)+ABS(F36)+ABS(G36)+ABS(H36)+ABS(I36)+ABS(J36)+ABS(K36)+ABS(L36)+ABS(M36)+ABS(N36)+ABS(O36)+ABS(P36)+ABS(Q36)+ABS(R36)+ABS(S36)+ABS(T36)+ABS(U36)+ABS(V36)+ABS(W36)+ABS(X36)+ABS(Y36)+ABS(Z36)+ABS(AA36)+ABS(AB36)+ABS(AC36)+ABS(AD36)+ABS(AE36)+ABS(AF36)+ABS(AG36)+ABS(AH36)+ABS(AI36)+ABS(AJ36),6) -> 42.86808
C37: 建设银行 | D37: 持仓成本 | E37: 766.76257 | F37: 0 | G37: 0 | H37: 0 | I37: 0 | J37: 0 | K37: 0 | L37: 0 | M37: 0 | N37: 0 | O37: 0 | P37: 0 | Q37: 0 | R37: 0 | S37: 0 | T37: 0 | U37: 0 | V37: 0 | W37: 0 | X37: 0 | Y37: 0 | Z37: 0 | AA37: 0 | AB37: 0 | AC37: 0 | AD37: 0 | AE37: 0 | AF37: 0 | AG37: 0 | AH37: 0 | AI37: 0 | AJ37: 0 | AK37: =ROUND(ABS(E37)+ABS(F37)+ABS(G37)+ABS(H37)+ABS(I37)+ABS(J37)+ABS(K37)+ABS(L37)+ABS(M37)+ABS(N37)+ABS(O37)+ABS(P37)+ABS(Q37)+ABS(R37)+ABS(S37)+ABS(T37)+ABS(U37)+ABS(V37)+ABS(W37)+ABS(X37)+ABS(Y37)+ABS(Z37)+ABS(AA37)+ABS(AB37)+ABS(AC37)+ABS(AD37)+ABS(AE37)+ABS(AF37)+ABS(AG37)+ABS(AH37)+ABS(AI37)+ABS(AJ37),6) -> 766.76257
D38: 持仓公允 | E38: -7.65191 | F38: 0 | G38: 0 | H38: 0 | I38: 0 | J38: -4.42101 | K38: 7.00909 | L38: -10.58772 | M38: 0.18623 | N38: -3.39383 | O38: 0 | P38: 0 | Q38: 12.6401 | R38: 7.57779 | S38: -3.93404 | T38: 7.95443 | U38: -2.57015 | V38: 0 | W38: 0 | X38: -3.20595 | Y38: -4.5276 | Z38: -9.59508 | AA38: -4.88004 | AB38: -0.16742 | AC38: 0 | AD38: 0 | AE38: 4.99356 | AF38: 10.20338 | AG38: 25.33454 | AH38: 10.68826 | AI38: -24.46125 | AJ38: 0 | AK38: =ROUND(ABS(E38)+ABS(F38)+ABS(G38)+ABS(H38)+ABS(I38)+ABS(J38)+ABS(K38)+ABS(L38)+ABS(M38)+ABS(N38)+ABS(O38)+ABS(P38)+ABS(Q38)+ABS(R38)+ABS(S38)+ABS(T38)+ABS(U38)+ABS(V38)+ABS(W38)+ABS(X38)+ABS(Y38)+ABS(Z38)+ABS(AA38)+ABS(AB38)+ABS(AC38)+ABS(AD38)+ABS(AE38)+ABS(AF38)+ABS(AG38)+ABS(AH38)+ABS(AI38)+ABS(AJ38),6) -> 165.98338
D39: OCI公允 | E39: 0 | F39: 0 | G39: 0 | H39: 0 | I39: 0 | J39: -4.42101 | K39: 7.00909 | L39: -10.58772 | M39: 0.18623 | N39: -3.39383 | O39: 0 | P39: 0 | Q39: 12.6401 | R39: 7.57779 | S39: -3.93404 | T39: 7.95443 | U39: -2.57015 | V39: 0 | W39: 0 | X39: -3.20595 | Y39: -4.5276 | Z39: -9.59508 | AA39: -4.88004 | AB39: -0.16742 | AC39: 0 | AD39: 0 | AE39: 4.99356 | AF39: 10.20338 | AG39: 25.33454 | AH39: 10.68826 | AI39: -24.46125 | AJ39: 0 | AK39: =ROUND(ABS(E39)+ABS(F39)+ABS(G39)+ABS(H39)+ABS(I39)+ABS(J39)+ABS(K39)+ABS(L39)+ABS(M39)+ABS(N39)+ABS(O39)+ABS(P39)+ABS(Q39)+ABS(R39)+ABS(S39)+ABS(T39)+ABS(U39)+ABS(V39)+ABS(W39)+ABS(X39)+ABS(Y39)+ABS(Z39)+ABS(AA39)+ABS(AB39)+ABS(AC39)+ABS(AD39)+ABS(AE39)+ABS(AF39)+ABS(AG39)+ABS(AH39)+ABS(AI39)+ABS(AJ39),6) -> 158.33147
D40: 应收应付 | E40: 13.006 | F40: 0 | G40: 0 | H40: 0 | I40: 0 | J40: 0 | K40: 0 | L40: 0 | M40: 0 | N40: 0 | O40: 0 | P40: 0 | Q40: 0 | R40: 0 | S40: 0 | T40: 0 | U40: 0 | V40: 0 | W40: 0 | X40: 0 | Y40: 0 | Z40: 0 | AA40: 0 | AB40: 0 | AC40: 0 | AD40: 0 | AE40: 0 | AF40: 0 | AG40: -13.006 | AH40: 0 | AI40: 0 | AJ40: 0 | AK40: =ROUND(ABS(E40)+ABS(F40)+ABS(G40)+ABS(H40)+ABS(I40)+ABS(J40)+ABS(K40)+ABS(L40)+ABS(M40)+ABS(N40)+ABS(O40)+ABS(P40)+ABS(Q40)+ABS(R40)+ABS(S40)+ABS(T40)+ABS(U40)+ABS(V40)+ABS(W40)+ABS(X40)+ABS(Y40)+ABS(Z40)+ABS(AA40)+ABS(AB40)+ABS(AC40)+ABS(AD40)+ABS(AE40)+ABS(AF40)+ABS(AG40)+ABS(AH40)+ABS(AI40)+ABS(AJ40),6) -> 26.012
C41: 江苏宁沪高速公路 | D41: 持仓成本 | E41: 586.33193 | F41: 0 | G41: 0 | H41: 0 | I41: 0 | J41: 0 | K41: 0 | L41: 0 | M41: 0 | N41: 0 | O41: 0 | P41: 0 | Q41: 0 | R41: 0 | S41: 0 | T41: 0 | U41: 0 | V41: 0 | W41: 0 | X41: 0 | Y41: 0 | Z41: 0 | AA41: 0 | AB41: 0 | AC41: 0 | AD41: 0 | AE41: 0 | AF41: 0 | AG41: 0 | AH41: 0 | AI41: 0 | AJ41: 0 | AK41: =ROUND(ABS(E41)+ABS(F41)+ABS(G41)+ABS(H41)+ABS(I41)+ABS(J41)+ABS(K41)+ABS(L41)+ABS(M41)+ABS(N41)+ABS(O41)+ABS(P41)+ABS(Q41)+ABS(R41)+ABS(S41)+ABS(T41)+ABS(U41)+ABS(V41)+ABS(W41)+ABS(X41)+ABS(Y41)+ABS(Z41)+ABS(AA41)+ABS(AB41)+ABS(AC41)+ABS(AD41)+ABS(AE41)+ABS(AF41)+ABS(AG41)+ABS(AH41)+ABS(AI41)+ABS(AJ41),6) -> 586.33193
D42: 持仓公允 | E42: -3.605239 | F42: 0 | G42: 0 | H42: 0 | I42: 0 | J42: -8.860215 | K42: -24.203595 | L42: -6.223035 | M42: -7.901595 | N42: -3.34347 | O42: 0 | P42: 0 | Q42: 2.20974 | R42: 4.9166 | S42: 1.743495 | T42: -2.845635 | U42: 3.06332 | V42: 0 | W42: 0 | X42: 3.88232 | Y42: 5.95413 | Z42: 0.60333 | AA42: 10.608 | AB42: 0.45422 | AC42: 0 | AD42: 0 | AE42: 16.890445 | AF42: 8.242455 | AG42: 17.83795 | AH42: 2.48495 | AI42: -12.71985 | AJ42: 0 | AK42: =ROUND(ABS(E42)+ABS(F42)+ABS(G42)+ABS(H42)+ABS(I42)+ABS(J42)+ABS(K42)+ABS(L42)+ABS(M42)+ABS(N42)+ABS(O42)+ABS(P42)+ABS(Q42)+ABS(R42)+ABS(S42)+ABS(T42)+ABS(U42)+ABS(V42)+ABS(W42)+ABS(X42)+ABS(Y42)+ABS(Z42)+ABS(AA42)+ABS(AB42)+ABS(AC42)+ABS(AD42)+ABS(AE42)+ABS(AF42)+ABS(AG42)+ABS(AH42)+ABS(AI42)+ABS(AJ42),6) -> 148.59359
D43: OCI公允 | E43: 0 | F43: 0 | G43: 0 | H43: 0 | I43: 0 | J43: -8.860215 | K43: -24.203595 | L43: -6.223035 | M43: -7.901595 | N43: -3.34347 | O43: 0 | P43: 0 | Q43: 2.20974 | R43: 4.9166 | S43: 1.743495 | T43: -2.845635 | U43: 3.06332 | V43: 0 | W43: 0 | X43: 3.88232 | Y43: 5.95413 | Z43: 0.60333 | AA43: 10.608 | AB43: 0.45422 | AC43: 0 | AD43: 0 | AE43: 16.890445 | AF43: 8.242455 | AG43: 17.83795 | AH43: 2.48495 | AI43: -12.71985 | AJ43: 0 | AK43: =ROUND(ABS(E43)+ABS(F43)+ABS(G43)+ABS(H43)+ABS(I43)+ABS(J43)+ABS(K43)+ABS(L43)+ABS(M43)+ABS(N43)+ABS(O43)+ABS(P43)+ABS(Q43)+ABS(R43)+ABS(S43)+ABS(T43)+ABS(U43)+ABS(V43)+ABS(W43)+ABS(X43)+ABS(Y43)+ABS(Z43)+ABS(AA43)+ABS(AB43)+ABS(AC43)+ABS(AD43)+ABS(AE43)+ABS(AF43)+ABS(AG43)+ABS(AH43)+ABS(AI43)+ABS(AJ43),6) -> 144.98835
C44: 交通银行 | D44: 持仓成本 | E44: 899.41097 | F44: 0 | G44: 0 | H44: 0 | I44: 0 | J44: 0 | K44: 0 | L44: 0 | M44: 0 | N44: 0 | O44: 0 | P44: 0 | Q44: 0 | R44: 0 | S44: 0 | T44: 0 | U44: 0 | V44: 0 | W44: 0 | X44: 0 | Y44: 0 | Z44: 0 | AA44: 0 | AB44: 0 | AC44: 0 | AD44: 0 | AE44: 0 | AF44: 0 | AG44: 0 | AH44: 0 | AI44: 0 | AJ44: 0 | AK44: =ROUND(ABS(E44)+ABS(F44)+ABS(G44)+ABS(H44)+ABS(I44)+ABS(J44)+ABS(K44)+ABS(L44)+ABS(M44)+ABS(N44)+ABS(O44)+ABS(P44)+ABS(Q44)+ABS(R44)+ABS(S44)+ABS(T44)+ABS(U44)+ABS(V44)+ABS(W44)+ABS(X44)+ABS(Y44)+ABS(Z44)+ABS(AA44)+ABS(AB44)+ABS(AC44)+ABS(AD44)+ABS(AE44)+ABS(AF44)+ABS(AG44)+ABS(AH44)+ABS(AI44)+ABS(AJ44),6) -> 899.41097
D45: 持仓公允 | E45: -89.05877 | F45: 0 | G45: 0 | H45: 0 | I45: 0 | J45: 3.6428 | K45: 1.183 | L45: -4.74516 | M45: -6.27284 | N45: 0.98504 | O45: 0 | P45: 0 | Q45: 14.86632 | R45: 3.63356 | S45: 0 | T45: 7.6034 | U45: -3.15252 | V45: 0 | W45: 0 | X45: -2.779 | Y45: -4.3953 | Z45: -3.3243 | AA45: -0.14952 | AB45: -3.93204 | AC45: 0 | AD45: 0 | AE45: 5.09026 | AF45: 10.5973 | AG45: 18.54188 | AH45: 10.26662 | AI45: -21.1701 | AJ45: 0 | AK45: =ROUND(ABS(E45)+ABS(F45)+ABS(G45)+ABS(H45)+ABS(I45)+ABS(J45)+ABS(K45)+ABS(L45)+ABS(M45)+ABS(N45)+ABS(O45)+ABS(P45)+ABS(Q45)+ABS(R45)+ABS(S45)+ABS(T45)+ABS(U45)+ABS(V45)+ABS(W45)+ABS(X45)+ABS(Y45)+ABS(Z45)+ABS(AA45)+ABS(AB45)+ABS(AC45)+ABS(AD45)+ABS(AE45)+ABS(AF45)+ABS(AG45)+ABS(AH45)+ABS(AI45)+ABS(AJ45),6) -> 215.38973
D46: OCI公允 | E46: 0 | F46: 0 | G46: 0 | H46: 0 | I46: 0 | J46: 3.6428 | K46: 1.183 | L46: -4.74516 | M46: -6.27284 | N46: 0.98504 | O46: 0 | P46: 0 | Q46: 14.86632 | R46: 3.63356 | S46: 0 | T46: 7.6034 | U46: -3.15252 | V46: 0 | W46: 0 | X46: -2.779 | Y46: -4.3953 | Z46: -3.3243 | AA46: -0.14952 | AB46: -3.93204 | AC46: 0 | AD46: 0 | AE46: 5.09026 | AF46: 10.5973 | AG46: 18.54188 | AH46: 10.26662 | AI46: -21.1701 | AJ46: 0 | AK46: =ROUND(ABS(E46)+ABS(F46)+ABS(G46)+ABS(H46)+ABS(I46)+ABS(J46)+ABS(K46)+ABS(L46)+ABS(M46)+ABS(N46)+ABS(O46)+ABS(P46)+ABS(Q46)+ABS(R46)+ABS(S46)+ABS(T46)+ABS(U46)+ABS(V46)+ABS(W46)+ABS(X46)+ABS(Y46)+ABS(Z46)+ABS(AA46)+ABS(AB46)+ABS(AC46)+ABS(AD46)+ABS(AE46)+ABS(AF46)+ABS(AG46)+ABS(AH46)+ABS(AI46)+ABS(AJ46),6) -> 126.33096
D47: 应收应付 | E47: 18.756 | F47: 0 | G47: 0 | H47: 0 | I47: 0 | J47: 0 | K47: 0 | L47: 0 | M47: 0 | N47: 0 | O47: 0 | P47: 0 | Q47: 0 | R47: 0 | S47: 0 | T47: 0 | U47: 0 | V47: 0 | W47: 0 | X47: 0 | Y47: 0 | Z47: 0 | AA47: 0 | AB47: 0 | AC47: 0 | AD47: 0 | AE47: 0 | AF47: 0 | AG47: 0 | AH47: 0 | AI47: -18.756 | AJ47: 0 | AK47: =ROUND(ABS(E47)+ABS(F47)+ABS(G47)+ABS(H47)+ABS(I47)+ABS(J47)+ABS(K47)+ABS(L47)+ABS(M47)+ABS(N47)+ABS(O47)+ABS(P47)+ABS(Q47)+ABS(R47)+ABS(S47)+ABS(T47)+ABS(U47)+ABS(V47)+ABS(W47)+ABS(X47)+ABS(Y47)+ABS(Z47)+ABS(AA47)+ABS(AB47)+ABS(AC47)+ABS(AD47)+ABS(AE47)+ABS(AF47)+ABS(AG47)+ABS(AH47)+ABS(AI47)+ABS(AJ47),6) -> 37.512
C48: 今世缘 | D48: 持仓成本 | E48: 246.09957 | F48: 0 | G48: 0 | H48: 0 | I48: 0 | J48: 0 | K48: 0 | L48: 0 | M48: 0 | N48: 0 | O48: 0 | P48: 0 | Q48: 0 | R48: 0 | S48: 0 | T48: 0 | U48: 0 | V48: 0 | W48: 0 | X48: 0 | Y48: 0 | Z48: 0 | AA48: -246.09957 | AB48: 0 | AC48: 0 | AD48: 0 | AE48: 0 | AF48: 0 | AG48: 0 | AH48: 0 | AI48: 0 | AJ48: 0 | AK48: =ROUND(ABS(E48)+ABS(F48)+ABS(G48)+ABS(H48)+ABS(I48)+ABS(J48)+ABS(K48)+ABS(L48)+ABS(M48)+ABS(N48)+ABS(O48)+ABS(P48)+ABS(Q48)+ABS(R48)+ABS(S48)+ABS(T48)+ABS(U48)+ABS(V48)+ABS(W48)+ABS(X48)+ABS(Y48)+ABS(Z48)+ABS(AA48)+ABS(AB48)+ABS(AC48)+ABS(AD48)+ABS(AE48)+ABS(AF48)+ABS(AG48)+ABS(AH48)+ABS(AI48)+ABS(AJ48),6) -> 492.19913
D49: 持仓公允 | E49: -37.419567 | F49: 0 | G49: 0 | H49: 0 | I49: 0 | J49: 1.68 | K49: 1.32 | L49: -0.66 | M49: 1.44 | N49: 0.36 | O49: 0 | P49: 0 | Q49: 2.28 | R49: -3.42 | S49: 0.6 | T49: -2.52 | U49: -2.28 | V49: 0 | W49: 0 | X49: 0 | Y49: 1.08 | Z49: -3.24 | AA49: 40.779567 | AB49: 0 | AC49: 0 | AD49: 0 | AE49: 0 | AF49: 0 | AG49: 0 | AH49: 0 | AI49: 0 | AJ49: 0 | AK49: =ROUND(ABS(E49)+ABS(F49)+ABS(G49)+ABS(H49)+ABS(I49)+ABS(J49)+ABS(K49)+ABS(L49)+ABS(M49)+ABS(N49)+ABS(O49)+ABS(P49)+ABS(Q49)+ABS(R49)+ABS(S49)+ABS(T49)+ABS(U49)+ABS(V49)+ABS(W49)+ABS(X49)+ABS(Y49)+ABS(Z49)+ABS(AA49)+ABS(AB49)+ABS(AC49)+ABS(AD49)+ABS(AE49)+ABS(AF49)+ABS(AG49)+ABS(AH49)+ABS(AI49)+ABS(AJ49),6) -> 99.079134
D50: OCI公允 | E50: 0 | F50: 0 | G50: 0 | H50: 0 | I50: 0 | J50: 1.68 | K50: 1.32 | L50: -0.66 | M50: 1.44 | N50: 0.36 | O50: 0 | P50: 0 | Q50: 2.28 | R50: -3.42 | S50: 0.6 | T50: -2.52 | U50: -2.28 | V50: 0 | W50: 0 | X50: 0 | Y50: 1.08 | Z50: -3.24 | AA50: 40.779567 | AB50: 0 | AC50: 0 | AD50: 0 | AE50: 0 | AF50: 0 | AG50: 0 | AH50: 0 | AI50: 0 | AJ50: 0 | AK50: =ROUND(ABS(E50)+ABS(F50)+ABS(G50)+ABS(H50)+ABS(I50)+ABS(J50)+ABS(K50)+ABS(L50)+ABS(M50)+ABS(N50)+ABS(O50)+ABS(P50)+ABS(Q50)+ABS(R50)+ABS(S50)+ABS(T50)+ABS(U50)+ABS(V50)+ABS(W50)+ABS(X50)+ABS(Y50)+ABS(Z50)+ABS(AA50)+ABS(AB50)+ABS(AC50)+ABS(AD50)+ABS(AE50)+ABS(AF50)+ABS(AG50)+ABS(AH50)+ABS(AI50)+ABS(AJ50),6) -> 61.659567
D51: OCI价差 | E51: 0 | F51: 0 | G51: 0 | H51: 0 | I51: 0 | J51: 0 | K51: 0 | L51: 0 | M51: 0 | N51: 0 | O51: 0 | P51: 0 | Q51: 0 | R51: 0 | S51: 0 | T51: 0 | U51: 0 | V51: 0 | W51: 0 | X51: 0 | Y51: 0 | Z51: 0 | AA51: -41.936995 | AB51: 0 | AC51: 0 | AD51: 0 | AE51: 0 | AF51: 0 | AG51: 0 | AH51: 0 | AI51: 0 | AJ51: 0 | AK51: =ROUND(ABS(E51)+ABS(F51)+ABS(G51)+ABS(H51)+ABS(I51)+ABS(J51)+ABS(K51)+ABS(L51)+ABS(M51)+ABS(N51)+ABS(O51)+ABS(P51)+ABS(Q51)+ABS(R51)+ABS(S51)+ABS(T51)+ABS(U51)+ABS(V51)+ABS(W51)+ABS(X51)+ABS(Y51)+ABS(Z51)+ABS(AA51)+ABS(AB51)+ABS(AC51)+ABS(AD51)+ABS(AE51)+ABS(AF51)+ABS(AG51)+ABS(AH51)+ABS(AI51)+ABS(AJ51),6) -> 41.936995
C52: 康师傅控股 | D52: 持仓成本 | E52: 634.36012 | F52: 0 | G52: 0 | H52: 0 | I52: 0 | J52: 0 | K52: 0 | L52: 0 | M52: 0 | N52: 0 | O52: 0 | P52: 0 | Q52: 0 | R52: 0 | S52: 0 | T52: 0 | U52: 0 | V52: 0 | W52: 0 | X52: 0 | Y52: 0 | Z52: 0 | AA52: 0 | AB52: 0 | AC52: 0 | AD52: 0 | AE52: 51.614145 | AF52: 0 | AG52: 0 | AH52: 0 | AI52: 0 | AJ52: 0 | AK52: =ROUND(ABS(E52)+ABS(F52)+ABS(G52)+ABS(H52)+ABS(I52)+ABS(J52)+ABS(K52)+ABS(L52)+ABS(M52)+ABS(N52)+ABS(O52)+ABS(P52)+ABS(Q52)+ABS(R52)+ABS(S52)+ABS(T52)+ABS(U52)+ABS(V52)+ABS(W52)+ABS(X52)+ABS(Y52)+ABS(Z52)+ABS(AA52)+ABS(AB52)+ABS(AC52)+ABS(AD52)+ABS(AE52)+ABS(AF52)+ABS(AG52)+ABS(AH52)+ABS(AI52)+ABS(AJ52),6) -> 685.97426
D53: 持仓公允 | E53: 0.460643 | F53: 0 | G53: 0 | H53: 0 | I53: 0 | J53: -2.58816 | K53: 0.91884 | L53: 9.35226 | M53: -25.9212 | N53: 23.55618 | O53: 0 | P53: 0 | Q53: 28.87452 | R53: -30.08934 | S53: 8.58336 | T53: -7.43886 | U53: 0.03504 | V53: 0 | W53: 0 | X53: -0.75084 | Y53: 3.24744 | Z53: 4.16664 | AA53: 4.08456 | AB53: 2.532 | AC53: 0 | AD53: 0 | AE53: -29.580525 | AF53: -8.64682 | AG53: 23.0373 | AH53: 6.893575 | AI53: -10.985325 | AJ53: 0 | AK53: =ROUND(ABS(E53)+ABS(F53)+ABS(G53)+ABS(H53)+ABS(I53)+ABS(J53)+ABS(K53)+ABS(L53)+ABS(M53)+ABS(N53)+ABS(O53)+ABS(P53)+ABS(Q53)+ABS(R53)+ABS(S53)+ABS(T53)+ABS(U53)+ABS(V53)+ABS(W53)+ABS(X53)+ABS(Y53)+ABS(Z53)+ABS(AA53)+ABS(AB53)+ABS(AC53)+ABS(AD53)+ABS(AE53)+ABS(AF53)+ABS(AG53)+ABS(AH53)+ABS(AI53)+ABS(AJ53),6) -> 231.74343
D54: OCI公允 | E54: 0 | F54: 0 | G54: 0 | H54: 0 | I54: 0 | J54: -2.58816 | K54: 0.91884 | L54: 9.35226 | M54: -25.9212 | N54: 23.55618 | O54: 0 | P54: 0 | Q54: 28.87452 | R54: -30.08934 | S54: 8.58336 | T54: -7.43886 | U54: 0.03504 | V54: 0 | W54: 0 | X54: -0.75084 | Y54: 3.24744 | Z54: 4.16664 | AA54: 4.08456 | AB54: 2.532 | AC54: 0 | AD54: 0 | AE54: -29.580525 | AF54: -8.64682 | AG54: 23.0373 | AH54: 6.893575 | AI54: -10.985325 | AJ54: 0 | AK54: =ROUND(ABS(E54)+ABS(F54)+ABS(G54)+ABS(H54)+ABS(I54)+ABS(J54)+ABS(K54)+ABS(L54)+ABS(M54)+ABS(N54)+ABS(O54)+ABS(P54)+ABS(Q54)+ABS(R54)+ABS(S54)+ABS(T54)+ABS(U54)+ABS(V54)+ABS(W54)+ABS(X54)+ABS(Y54)+ABS(Z54)+ABS(AA54)+ABS(AB54)+ABS(AC54)+ABS(AD54)+ABS(AE54)+ABS(AF54)+ABS(AG54)+ABS(AH54)+ABS(AI54)+ABS(AJ54),6) -> 231.28278
C55: 联邦制药 | D55: 持仓成本 | E55: 461.40776 | F55: 0 | G55: 0 | H55: 0 | I55: 0 | J55: 0 | K55: 0 | L55: 0 | M55: 0 | N55: 0 | O55: 0 | P55: 0 | Q55: 0 | R55: 0 | S55: 0 | T55: 0 | U55: 0 | V55: 0 | W55: 0 | X55: 0 | Y55: 0 | Z55: 0 | AA55: 0 | AB55: 0 | AC55: 0 | AD55: 0 | AE55: 0 | AF55: 0 | AG55: 0 | AH55: 0 | AI55: 0 | AJ55: 0 | AK55: =ROUND(ABS(E55)+ABS(F55)+ABS(G55)+ABS(H55)+ABS(I55)+ABS(J55)+ABS(K55)+ABS(L55)+ABS(M55)+ABS(N55)+ABS(O55)+ABS(P55)+ABS(Q55)+ABS(R55)+ABS(S55)+ABS(T55)+ABS(U55)+ABS(V55)+ABS(W55)+ABS(X55)+ABS(Y55)+ABS(Z55)+ABS(AA55)+ABS(AB55)+ABS(AC55)+ABS(AD55)+ABS(AE55)+ABS(AF55)+ABS(AG55)+ABS(AH55)+ABS(AI55)+ABS(AJ55),6) -> 461.40776
D56: 持仓公允 | E56: -45.373123 | F56: 0 | G56: 0 | H56: 0 | I56: 0 | J56: 12.96756 | K56: 3.49004 | L56: -3.08112 | M56: -3.63712 | N56: 2.77672 | O56: 0 | P56: 0 | Q56: -1.1704 | R56: 10.0134 | S56: -17.882 | T56: -2.09916 | U56: -0.68416 | V56: 0 | W56: 0 | X56: -11.2156 | Y56: 7.8932 | Z56: 8.14248 | AA56: 4.8528 | AB56: -6.1652 | AC56: 0 | AD56: 0 | AE56: 1.11832 | AF56: 12.5144 | AG56: -5.8048 | AH56: -2.1714 | AI56: -2.4906 | AJ56: 0 | AK56: =ROUND(ABS(E56)+ABS(F56)+ABS(G56)+ABS(H56)+ABS(I56)+ABS(J56)+ABS(K56)+ABS(L56)+ABS(M56)+ABS(N56)+ABS(O56)+ABS(P56)+ABS(Q56)+ABS(R56)+ABS(S56)+ABS(T56)+ABS(U56)+ABS(V56)+ABS(W56)+ABS(X56)+ABS(Y56)+ABS(Z56)+ABS(AA56)+ABS(AB56)+ABS(AC56)+ABS(AD56)+ABS(AE56)+ABS(AF56)+ABS(AG56)+ABS(AH56)+ABS(AI56)+ABS(AJ56),6) -> 165.5436
D57: OCI公允 | E57: 0 | F57: 0 | G57: 0 | H57: 0 | I57: 0 | J57: 12.96756 | K57: 3.49004 | L57: -3.08112 | M57: -3.63712 | N57: 2.77672 | O57: 0 | P57: 0 | Q57: -1.1704 | R57: 10.0134 | S57: -17.882 | T57: -2.09916 | U57: -0.68416 | V57: 0 | W57: 0 | X57: -11.2156 | Y57: 7.8932 | Z57: 8.14248 | AA57: 4.8528 | AB57: -6.1652 | AC57: 0 | AD57: 0 | AE57: 1.11832 | AF57: 12.5144 | AG57: -5.8048 | AH57: -2.1714 | AI57: -2.4906 | AJ57: 0 | AK57: =ROUND(ABS(E57)+ABS(F57)+ABS(G57)+ABS(H57)+ABS(I57)+ABS(J57)+ABS(K57)+ABS(L57)+ABS(M57)+ABS(N57)+ABS(O57)+ABS(P57)+ABS(Q57)+ABS(R57)+ABS(S57)+ABS(T57)+ABS(U57)+ABS(V57)+ABS(W57)+ABS(X57)+ABS(Y57)+ABS(Z57)+ABS(AA57)+ABS(AB57)+ABS(AC57)+ABS(AD57)+ABS(AE57)+ABS(AF57)+ABS(AG57)+ABS(AH57)+ABS(AI57)+ABS(AJ57),6) -> 120.17048
C58: 泸州老窖 | D58: 持仓成本 | E58: 304.30949 | F58: 0 | G58: 0 | H58: 0 | I58: 0 | J58: 0 | K58: 0 | L58: 0 | M58: 0 | N58: 0 | O58: 0 | P58: 0 | Q58: 0 | R58: 0 | S58: 0 | T58: 0 | U58: 0 | V58: 0 | W58: 0 | X58: 0 | Y58: 0 | Z58: 0 | AA58: 0 | AB58: 0 | AC58: 0 | AD58: 0 | AE58: 0 | AF58: 0 | AG58: 0 | AH58: 0 | AI58: 0 | AJ58: 0 | AK58: =ROUND(ABS(E58)+ABS(F58)+ABS(G58)+ABS(H58)+ABS(I58)+ABS(J58)+ABS(K58)+ABS(L58)+ABS(M58)+ABS(N58)+ABS(O58)+ABS(P58)+ABS(Q58)+ABS(R58)+ABS(S58)+ABS(T58)+ABS(U58)+ABS(V58)+ABS(W58)+ABS(X58)+ABS(Y58)+ABS(Z58)+ABS(AA58)+ABS(AB58)+ABS(AC58)+ABS(AD58)+ABS(AE58)+ABS(AF58)+ABS(AG58)+ABS(AH58)+ABS(AI58)+ABS(AJ58),6) -> 304.30949
D59: 持仓公允 | E59: -13.759493 | F59: 0 | G59: 0 | H59: 0 | I59: 0 | J59: 4.45 | K59: 1.55 | L59: -3.75 | M59: -1.325 | N59: 0.675 | O59: 0 | P59: 0 | Q59: 6.075 | R59: -3.225 | S59: -2.85 | T59: -3.75 | U59: -2.7 | V59: 0 | W59: 0 | X59: -1.725 | Y59: 6.675 | Z59: -7.7 | AA59: -2.075 | AB59: -0.775 | AC59: 0 | AD59: 0 | AE59: 0.975 | AF59: -0.175 | AG59: 1.45 | AH59: 28.225 | AI59: -8.325 | AJ59: 0 | AK59: =ROUND(ABS(E59)+ABS(F59)+ABS(G59)+ABS(H59)+ABS(I59)+ABS(J59)+ABS(K59)+ABS(L59)+ABS(M59)+ABS(N59)+ABS(O59)+ABS(P59)+ABS(Q59)+ABS(R59)+ABS(S59)+ABS(T59)+ABS(U59)+ABS(V59)+ABS(W59)+ABS(X59)+ABS(Y59)+ABS(Z59)+ABS(AA59)+ABS(AB59)+ABS(AC59)+ABS(AD59)+ABS(AE59)+ABS(AF59)+ABS(AG59)+ABS(AH59)+ABS(AI59)+ABS(AJ59),6) -> 102.20949
D60: 股利盈亏 | E60: 0 | F60: 0 | G60: 0 | H60: 0 | I60: 0 | J60: 0 | K60: 0 | L60: 0 | M60: 0 | N60: 0 | O60: 0 | P60: 0 | Q60: 0 | R60: 0 | S60: 0 | T60: 0 | U60: 0 | V60: 0 | W60: 0 | X60: 0 | Y60: 0 | Z60: 0 | AA60: 0 | AB60: 0 | AC60: 0 | AD60: 0 | AE60: 0 | AF60: 0 | AG60: 0 | AH60: 0 | AI60: 3.395 | AJ60: 0 | AK60: =ROUND(ABS(E60)+ABS(F60)+ABS(G60)+ABS(H60)+ABS(I60)+ABS(J60)+ABS(K60)+ABS(L60)+ABS(M60)+ABS(N60)+ABS(O60)+ABS(P60)+ABS(Q60)+ABS(R60)+ABS(S60)+ABS(T60)+ABS(U60)+ABS(V60)+ABS(W60)+ABS(X60)+ABS(Y60)+ABS(Z60)+ABS(AA60)+ABS(AB60)+ABS(AC60)+ABS(AD60)+ABS(AE60)+ABS(AF60)+ABS(AG60)+ABS(AH60)+ABS(AI60)+ABS(AJ60),6) -> 3.395
D61: OCI公允 | E61: 0 | F61: 0 | G61: 0 | H61: 0 | I61: 0 | J61: 4.45 | K61: 1.55 | L61: -3.75 | M61: -1.325 | N61: 0.675 | O61: 0 | P61: 0 | Q61: 6.075 | R61: -3.225 | S61: -2.85 | T61: -3.75 | U61: -2.7 | V61: 0 | W61: 0 | X61: -1.725 | Y61: 6.675 | Z61: -7.7 | AA61: -2.075 | AB61: -0.775 | AC61: 0 | AD61: 0 | AE61: 0.975 | AF61: -0.175 | AG61: 1.45 | AH61: 28.225 | AI61: -8.325 | AJ61: 0 | AK61: =ROUND(ABS(E61)+ABS(F61)+ABS(G61)+ABS(H61)+ABS(I61)+ABS(J61)+ABS(K61)+ABS(L61)+ABS(M61)+ABS(N61)+ABS(O61)+ABS(P61)+ABS(Q61)+ABS(R61)+ABS(S61)+ABS(T61)+ABS(U61)+ABS(V61)+ABS(W61)+ABS(X61)+ABS(Y61)+ABS(Z61)+ABS(AA61)+ABS(AB61)+ABS(AC61)+ABS(AD61)+ABS(AE61)+ABS(AF61)+ABS(AG61)+ABS(AH61)+ABS(AI61)+ABS(AJ61),6) -> 88.45
C62: 美的集团 | D62: 持仓成本 | E62: 693.38549 | F62: 0 | G62: 0 | H62: 0 | I62: 0 | J62: 0 | K62: 0 | L62: 0 | M62: 0 | N62: 0 | O62: 0 | P62: 0 | Q62: 0 | R62: 0 | S62: 0 | T62: 0 | U62: 0 | V62: 0 | W62: 0 | X62: 0 | Y62: 0 | Z62: 0 | AA62: 0 | AB62: 0 | AC62: 0 | AD62: 0 | AE62: 0 | AF62: 0 | AG62: 0 | AH62: 0 | AI62: 0 | AJ62: 0 | AK62: =ROUND(ABS(E62)+ABS(F62)+ABS(G62)+ABS(H62)+ABS(I62)+ABS(J62)+ABS(K62)+ABS(L62)+ABS(M62)+ABS(N62)+ABS(O62)+ABS(P62)+ABS(Q62)+ABS(R62)+ABS(S62)+ABS(T62)+ABS(U62)+ABS(V62)+ABS(W62)+ABS(X62)+ABS(Y62)+ABS(Z62)+ABS(AA62)+ABS(AB62)+ABS(AC62)+ABS(AD62)+ABS(AE62)+ABS(AF62)+ABS(AG62)+ABS(AH62)+ABS(AI62)+ABS(AJ62),6) -> 693.38549
D63: 持仓公允 | E63: 68.955811 | F63: 0 | G63: 0 | H63: 0 | I63: 0 | J63: 19.4517 | K63: -0.6554 | L63: 8.3265 | M63: -5.49785 | N63: 13.29575 | O63: 0 | P63: 0 | Q63: -22.568 | R63: -20.9677 | S63: 2.6823 | T63: 5.8969 | U63: 5.211 | V63: 0 | W63: 0 | X63: -0.7043 | Y63: 10.5553 | Z63: 1.8909 | AA63: -14.1288 | AB63: -3.7418 | AC63: 0 | AD63: 0 | AE63: 0.0853 | AF63: -9.0711 | AG63: -0.6146 | AH63: 15.40635 | AI63: -5.337 | AJ63: 0 | AK63: =ROUND(ABS(E63)+ABS(F63)+ABS(G63)+ABS(H63)+ABS(I63)+ABS(J63)+ABS(K63)+ABS(L63)+ABS(M63)+ABS(N63)+ABS(O63)+ABS(P63)+ABS(Q63)+ABS(R63)+ABS(S63)+ABS(T63)+ABS(U63)+ABS(V63)+ABS(W63)+ABS(X63)+ABS(Y63)+ABS(Z63)+ABS(AA63)+ABS(AB63)+ABS(AC63)+ABS(AD63)+ABS(AE63)+ABS(AF63)+ABS(AG63)+ABS(AH63)+ABS(AI63)+ABS(AJ63),6) -> 235.04436
D64: OCI公允 | E64: 0 | F64: 0 | G64: 0 | H64: 0 | I64: 0 | J64: 19.4517 | K64: -0.6554 | L64: 8.3265 | M64: -5.49785 | N64: 13.29575 | O64: 0 | P64: 0 | Q64: -22.568 | R64: -20.9677 | S64: 2.6823 | T64: 5.8969 | U64: 5.211 | V64: 0 | W64: 0 | X64: -0.7043 | Y64: 10.5553 | Z64: 1.8909 | AA64: -14.1288 | AB64: -3.7418 | AC64: 0 | AD64: 0 | AE64: 0.0853 | AF64: -9.0711 | AG64: -0.6146 | AH64: 15.40635 | AI64: -5.337 | AJ64: 0 | AK64: =ROUND(ABS(E64)+ABS(F64)+ABS(G64)+ABS(H64)+ABS(I64)+ABS(J64)+ABS(K64)+ABS(L64)+ABS(M64)+ABS(N64)+ABS(O64)+ABS(P64)+ABS(Q64)+ABS(R64)+ABS(S64)+ABS(T64)+ABS(U64)+ABS(V64)+ABS(W64)+ABS(X64)+ABS(Y64)+ABS(Z64)+ABS(AA64)+ABS(AB64)+ABS(AC64)+ABS(AD64)+ABS(AE64)+ABS(AF64)+ABS(AG64)+ABS(AH64)+ABS(AI64)+ABS(AJ64),6) -> 166.08855
C65: 蒙牛乳业 | D65: 持仓成本 | E65: 16.70255 | F65: 0 | G65: 0 | H65: 0 | I65: 0 | J65: 0 | K65: 0 | L65: 0 | M65: 0 | N65: 0 | O65: 0 | P65: 0 | Q65: 0 | R65: 0 | S65: 0 | T65: 0 | U65: 0 | V65: 0 | W65: 0 | X65: 0 | Y65: 0 | Z65: 0 | AA65: 0 | AB65: 0 | AC65: 0 | AD65: 0 | AE65: 0 | AF65: 0 | AG65: 0 | AH65: 0 | AI65: 0 | AJ65: 0 | AK65: =ROUND(ABS(E65)+ABS(F65)+ABS(G65)+ABS(H65)+ABS(I65)+ABS(J65)+ABS(K65)+ABS(L65)+ABS(M65)+ABS(N65)+ABS(O65)+ABS(P65)+ABS(Q65)+ABS(R65)+ABS(S65)+ABS(T65)+ABS(U65)+ABS(V65)+ABS(W65)+ABS(X65)+ABS(Y65)+ABS(Z65)+ABS(AA65)+ABS(AB65)+ABS(AC65)+ABS(AD65)+ABS(AE65)+ABS(AF65)+ABS(AG65)+ABS(AH65)+ABS(AI65)+ABS(AJ65),6) -> 16.70255
D66: 持仓公允 | E66: -3.322316 | F66: 0 | G66: 0 | H66: 0 | I66: 0 | J66: 0.296671 | K66: 0.046751 | L66: 0.13005 | M66: -0.086056 | N66: -0.357524 | O66: 0 | P66: 0 | Q66: 0.050742 | R66: 0.048983 | S66: 0.008941 | T66: 0.21612 | U66: 0.078598 | V66: 0 | W66: 0 | X66: 0.379438 | Y66: -0.064673 | Z66: 0.048165 | AA66: -0.079128 | AB66: 0.02362 | AC66: 0 | AD66: 0 | AE66: -0.31979 | AF66: 0.203258 | AG66: 0.523022 | AH66: 0.380598 | AI66: -0.40917 | AJ66: 0 | AK66: =ROUND(ABS(E66)+ABS(F66)+ABS(G66)+ABS(H66)+ABS(I66)+ABS(J66)+ABS(K66)+ABS(L66)+ABS(M66)+ABS(N66)+ABS(O66)+ABS(P66)+ABS(Q66)+ABS(R66)+ABS(S66)+ABS(T66)+ABS(U66)+ABS(V66)+ABS(W66)+ABS(X66)+ABS(Y66)+ABS(Z66)+ABS(AA66)+ABS(AB66)+ABS(AC66)+ABS(AD66)+ABS(AE66)+ABS(AF66)+ABS(AG66)+ABS(AH66)+ABS(AI66)+ABS(AJ66),6) -> 7.073614
D67: OCI公允 | E67: 0 | F67: 0 | G67: 0 | H67: 0 | I67: 0 | J67: 0.296671 | K67: 0.046751 | L67: 0.13005 | M67: -0.086056 | N67: -0.357524 | O67: 0 | P67: 0 | Q67: 0.050742 | R67: 0.048983 | S67: 0.008941 | T67: 0.21612 | U67: 0.078598 | V67: 0 | W67: 0 | X67: 0.379438 | Y67: -0.064673 | Z67: 0.048165 | AA67: -0.079128 | AB67: 0.02362 | AC67: 0 | AD67: 0 | AE67: -0.31979 | AF67: 0.203258 | AG67: 0.523022 | AH67: 0.380598 | AI67: -0.40917 | AJ67: 0 | AK67: =ROUND(ABS(E67)+ABS(F67)+ABS(G67)+ABS(H67)+ABS(I67)+ABS(J67)+ABS(K67)+ABS(L67)+ABS(M67)+ABS(N67)+ABS(O67)+ABS(P67)+ABS(Q67)+ABS(R67)+ABS(S67)+ABS(T67)+ABS(U67)+ABS(V67)+ABS(W67)+ABS(X67)+ABS(Y67)+ABS(Z67)+ABS(AA67)+ABS(AB67)+ABS(AC67)+ABS(AD67)+ABS(AE67)+ABS(AF67)+ABS(AG67)+ABS(AH67)+ABS(AI67)+ABS(AJ67),6) -> 3.751298
C68: 南方传媒 | D68: 持仓成本 | E68: 309.38963 | F68: 0 | G68: 0 | H68: 0 | I68: 0 | J68: 0 | K68: 0 | L68: 0 | M68: 0 | N68: 0 | O68: 0 | P68: 0 | Q68: 0 | R68: -309.38963 | S68: 0 | T68: 0 | U68: 0 | V68: 0 | W68: 0 | X68: 0 | Y68: 0 | Z68: 0 | AA68: 0 | AB68: 0 | AC68: 0 | AD68: 0 | AE68: 0 | AF68: 0 | AG68: 0 | AH68: 0 | AI68: 0 | AJ68: 0 | AK68: =ROUND(ABS(E68)+ABS(F68)+ABS(G68)+ABS(H68)+ABS(I68)+ABS(J68)+ABS(K68)+ABS(L68)+ABS(M68)+ABS(N68)+ABS(O68)+ABS(P68)+ABS(Q68)+ABS(R68)+ABS(S68)+ABS(T68)+ABS(U68)+ABS(V68)+ABS(W68)+ABS(X68)+ABS(Y68)+ABS(Z68)+ABS(AA68)+ABS(AB68)+ABS(AC68)+ABS(AD68)+ABS(AE68)+ABS(AF68)+ABS(AG68)+ABS(AH68)+ABS(AI68)+ABS(AJ68),6) -> 618.77926
D69: 持仓公允 | E69: -41.189629 | F69: 0 | G69: 0 | H69: 0 | I69: 0 | J69: 6 | K69: 1.6 | L69: -10.4 | M69: -0.6 | N69: 9.2 | O69: 0 | P69: 0 | Q69: 27.4 | R69: 7.989629 | S69: 0 | T69: 0 | U69: 0 | V69: 0 | W69: 0 | X69: 0 | Y69: 0 | Z69: 0 | AA69: 0 | AB69: 0 | AC69: 0 | AD69: 0 | AE69: 0 | AF69: 0 | AG69: 0 | AH69: 0 | AI69: 0 | AJ69: 0 | AK69: =ROUND(ABS(E69)+ABS(F69)+ABS(G69)+ABS(H69)+ABS(I69)+ABS(J69)+ABS(K69)+ABS(L69)+ABS(M69)+ABS(N69)+ABS(O69)+ABS(P69)+ABS(Q69)+ABS(R69)+ABS(S69)+ABS(T69)+ABS(U69)+ABS(V69)+ABS(W69)+ABS(X69)+ABS(Y69)+ABS(Z69)+ABS(AA69)+ABS(AB69)+ABS(AC69)+ABS(AD69)+ABS(AE69)+ABS(AF69)+ABS(AG69)+ABS(AH69)+ABS(AI69)+ABS(AJ69),6) -> 104.37926
D70: OCI公允 | E70: 0 | F70: 0 | G70: 0 | H70: 0 | I70: 0 | J70: 6 | K70: 1.6 | L70: -10.4 | M70: -0.6 | N70: 9.2 | O70: 0 | P70: 0 | Q70: 27.4 | R70: 7.989629 | S70: 0 | T70: 0 | U70: 0 | V70: 0 | W70: 0 | X70: 0 | Y70: 0 | Z70: 0 | AA70: 0 | AB70: 0 | AC70: 0 | AD70: 0 | AE70: 0 | AF70: 0 | AG70: 0 | AH70: 0 | AI70: 0 | AJ70: 0 | AK70: =ROUND(ABS(E70)+ABS(F70)+ABS(G70)+ABS(H70)+ABS(I70)+ABS(J70)+ABS(K70)+ABS(L70)+ABS(M70)+ABS(N70)+ABS(O70)+ABS(P70)+ABS(Q70)+ABS(R70)+ABS(S70)+ABS(T70)+ABS(U70)+ABS(V70)+ABS(W70)+ABS(X70)+ABS(Y70)+ABS(Z70)+ABS(AA70)+ABS(AB70)+ABS(AC70)+ABS(AD70)+ABS(AE70)+ABS(AF70)+ABS(AG70)+ABS(AH70)+ABS(AI70)+ABS(AJ70),6) -> 63.189629
D71: OCI价差 | E71: 0 | F71: 0 | G71: 0 | H71: 0 | I71: 0 | J71: 0 | K71: 0 | L71: 0 | M71: 0 | N71: 0 | O71: 0 | P71: 0 | Q71: 0 | R71: 17.178954 | S71: 0 | T71: 0 | U71: 0 | V71: 0 | W71: 0 | X71: 0 | Y71: 0 | Z71: 0 | AA71: 0 | AB71: 0 | AC71: 0 | AD71: 0 | AE71: 0 | AF71: 0 | AG71: 0 | AH71: 0 | AI71: 0 | AJ71: 0 | AK71: =ROUND(ABS(E71)+ABS(F71)+ABS(G71)+ABS(H71)+ABS(I71)+ABS(J71)+ABS(K71)+ABS(L71)+ABS(M71)+ABS(N71)+ABS(O71)+ABS(P71)+ABS(Q71)+ABS(R71)+ABS(S71)+ABS(T71)+ABS(U71)+ABS(V71)+ABS(W71)+ABS(X71)+ABS(Y71)+ABS(Z71)+ABS(AA71)+ABS(AB71)+ABS(AC71)+ABS(AD71)+ABS(AE71)+ABS(AF71)+ABS(AG71)+ABS(AH71)+ABS(AI71)+ABS(AJ71),6) -> 17.178954
C72: 南京银行 | D72: 持仓成本 | E72: 333.22904 | F72: 0 | G72: 0 | H72: 0 | I72: 0 | J72: 0 | K72: 0 | L72: 0 | M72: 0 | N72: 0 | O72: 0 | P72: 0 | Q72: 0 | R72: 0 | S72: 0 | T72: 0 | U72: 0 | V72: 0 | W72: 0 | X72: 0 | Y72: 0 | Z72: 0 | AA72: 0 | AB72: 0 | AC72: 0 | AD72: 0 | AE72: 0 | AF72: 0 | AG72: 0 | AH72: 0 | AI72: 0 | AJ72: 0 | AK72: =ROUND(ABS(E72)+ABS(F72)+ABS(G72)+ABS(H72)+ABS(I72)+ABS(J72)+ABS(K72)+ABS(L72)+ABS(M72)+ABS(N72)+ABS(O72)+ABS(P72)+ABS(Q72)+ABS(R72)+ABS(S72)+ABS(T72)+ABS(U72)+ABS(V72)+ABS(W72)+ABS(X72)+ABS(Y72)+ABS(Z72)+ABS(AA72)+ABS(AB72)+ABS(AC72)+ABS(AD72)+ABS(AE72)+ABS(AF72)+ABS(AG72)+ABS(AH72)+ABS(AI72)+ABS(AJ72),6) -> 333.22904
D73: 持仓公允 | E73: 9.670955 | F73: 0 | G73: 0 | H73: 0 | I73: 0 | J73: -3.3 | K73: -0.3 | L73: -6 | M73: -4.8 | N73: -3.6 | O73: 0 | P73: 0 | Q73: -2.4 | R73: 3.9 | S73: -5.7 | T73: -2.4 | U73: -4.8 | V73: 0 | W73: 0 | X73: -0.9 | Y73: 4.2 | Z73: -3.9 | AA73: -0.3 | AB73: -2.1 | AC73: 0 | AD73: 0 | AE73: 3 | AF73: -1.2 | AG73: -0.9 | AH73: 6.3 | AI73: -1.8 | AJ73: 0 | AK73: =ROUND(ABS(E73)+ABS(F73)+ABS(G73)+ABS(H73)+ABS(I73)+ABS(J73)+ABS(K73)+ABS(L73)+ABS(M73)+ABS(N73)+ABS(O73)+ABS(P73)+ABS(Q73)+ABS(R73)+ABS(S73)+ABS(T73)+ABS(U73)+ABS(V73)+ABS(W73)+ABS(X73)+ABS(Y73)+ABS(Z73)+ABS(AA73)+ABS(AB73)+ABS(AC73)+ABS(AD73)+ABS(AE73)+ABS(AF73)+ABS(AG73)+ABS(AH73)+ABS(AI73)+ABS(AJ73),6) -> 71.470955
D74: OCI公允 | E74: 0 | F74: 0 | G74: 0 | H74: 0 | I74: 0 | J74: -3.3 | K74: -0.3 | L74: -6 | M74: -4.8 | N74: -3.6 | O74: 0 | P74: 0 | Q74: -2.4 | R74: 3.9 | S74: -5.7 | T74: -2.4 | U74: -4.8 | V74: 0 | W74: 0 | X74: -0.9 | Y74: 4.2 | Z74: -3.9 | AA74: -0.3 | AB74: -2.1 | AC74: 0 | AD74: 0 | AE74: 3 | AF74: -1.2 | AG74: -0.9 | AH74: 6.3 | AI74: -1.8 | AJ74: 0 | AK74: =ROUND(ABS(E74)+ABS(F74)+ABS(G74)+ABS(H74)+ABS(I74)+ABS(J74)+ABS(K74)+ABS(L74)+ABS(M74)+ABS(N74)+ABS(O74)+ABS(P74)+ABS(Q74)+ABS(R74)+ABS(S74)+ABS(T74)+ABS(U74)+ABS(V74)+ABS(W74)+ABS(X74)+ABS(Y74)+ABS(Z74)+ABS(AA74)+ABS(AB74)+ABS(AC74)+ABS(AD74)+ABS(AE74)+ABS(AF74)+ABS(AG74)+ABS(AH74)+ABS(AI74)+ABS(AJ74),6) -> 61.8
C75: 平安银行 | D75: 持仓成本 | E75: 815.93726 | F75: 0 | G75: 0 | H75: 0 | I75: 0 | J75: 0 | K75: 0 | L75: 0 | M75: 0 | N75: 0 | O75: 0 | P75: 0 | Q75: 0 | R75: 0 | S75: 0 | T75: 0 | U75: 0 | V75: 0 | W75: 0 | X75: 0 | Y75: 0 | Z75: 0 | AA75: 0 | AB75: 0 | AC75: 0 | AD75: 0 | AE75: 0 | AF75: 0 | AG75: 0 | AH75: 0 | AI75: 0 | AJ75: 0 | AK75: =ROUND(ABS(E75)+ABS(F75)+ABS(G75)+ABS(H75)+ABS(I75)+ABS(J75)+ABS(K75)+ABS(L75)+ABS(M75)+ABS(N75)+ABS(O75)+ABS(P75)+ABS(Q75)+ABS(R75)+ABS(S75)+ABS(T75)+ABS(U75)+ABS(V75)+ABS(W75)+ABS(X75)+ABS(Y75)+ABS(Z75)+ABS(AA75)+ABS(AB75)+ABS(AC75)+ABS(AD75)+ABS(AE75)+ABS(AF75)+ABS(AG75)+ABS(AH75)+ABS(AI75)+ABS(AJ75),6) -> 815.93726
D76: 持仓公允 | E76: -17.237257 | F76: 0 | G76: 0 | H76: 0 | I76: 0 | J76: 6.3 | K76: 11.9 | L76: -2.1 | M76: -9.1 | N76: -3.5 | O76: 0 | P76: 0 | Q76: 1.4 | R76: -0.7 | S76: -7.7 | T76: -3.5 | U76: -8.4 | V76: 0 | W76: 0 | X76: -4.9 | Y76: 2.8 | Z76: -6.3 | AA76: 0 | AB76: -5.6 | AC76: 0 | AD76: 0 | AE76: -2.1 | AF76: -1.4 | AG76: -7 | AH76: 8.4 | AI76: -9.1 | AJ76: 0 | AK76: =ROUND(ABS(E76)+ABS(F76)+ABS(G76)+ABS(H76)+ABS(I76)+ABS(J76)+ABS(K76)+ABS(L76)+ABS(M76)+ABS(N76)+ABS(O76)+ABS(P76)+ABS(Q76)+ABS(R76)+ABS(S76)+ABS(T76)+ABS(U76)+ABS(V76)+ABS(W76)+ABS(X76)+ABS(Y76)+ABS(Z76)+ABS(AA76)+ABS(AB76)+ABS(AC76)+ABS(AD76)+ABS(AE76)+ABS(AF76)+ABS(AG76)+ABS(AH76)+ABS(AI76)+ABS(AJ76),6) -> 119.43726
D77: OCI公允 | E77: 0 | F77: 0 | G77: 0 | H77: 0 | I77: 0 | J77: 6.3 | K77: 11.9 | L77: -2.1 | M77: -9.1 | N77: -3.5 | O77: 0 | P77: 0 | Q77: 1.4 | R77: -0.7 | S77: -7.7 | T77: -3.5 | U77: -8.4 | V77: 0 | W77: 0 | X77: -4.9 | Y77: 2.8 | Z77: -6.3 | AA77: 0 | AB77: -5.6 | AC77: 0 | AD77: 0 | AE77: -2.1 | AF77: -1.4 | AG77: -7 | AH77: 8.4 | AI77: -9.1 | AJ77: 0 | AK77: =ROUND(ABS(E77)+ABS(F77)+ABS(G77)+ABS(H77)+ABS(I77)+ABS(J77)+ABS(K77)+ABS(L77)+ABS(M77)+ABS(N77)+ABS(O77)+ABS(P77)+ABS(Q77)+ABS(R77)+ABS(S77)+ABS(T77)+ABS(U77)+ABS(V77)+ABS(W77)+ABS(X77)+ABS(Y77)+ABS(Z77)+ABS(AA77)+ABS(AB77)+ABS(AC77)+ABS(AD77)+ABS(AE77)+ABS(AF77)+ABS(AG77)+ABS(AH77)+ABS(AI77)+ABS(AJ77),6) -> 102.2
C78: 山西汾酒 | D78: 持仓成本 | E78: 286.91269 | F78: 0 | G78: 0 | H78: 0 | I78: 0 | J78: 0 | K78: 0 | L78: 0 | M78: 0 | N78: 0 | O78: 0 | P78: 0 | Q78: 0 | R78: 0 | S78: 0 | T78: 0 | U78: 0 | V78: 0 | W78: 0 | X78: 0 | Y78: 0 | Z78: 0 | AA78: 0 | AB78: 0 | AC78: 0 | AD78: 0 | AE78: 0 | AF78: 0 | AG78: 0 | AH78: 0 | AI78: 0 | AJ78: 0 | AK78: =ROUND(ABS(E78)+ABS(F78)+ABS(G78)+ABS(H78)+ABS(I78)+ABS(J78)+ABS(K78)+ABS(L78)+ABS(M78)+ABS(N78)+ABS(O78)+ABS(P78)+ABS(Q78)+ABS(R78)+ABS(S78)+ABS(T78)+ABS(U78)+ABS(V78)+ABS(W78)+ABS(X78)+ABS(Y78)+ABS(Z78)+ABS(AA78)+ABS(AB78)+ABS(AC78)+ABS(AD78)+ABS(AE78)+ABS(AF78)+ABS(AG78)+ABS(AH78)+ABS(AI78)+ABS(AJ78),6) -> 286.91269
D79: 持仓公允 | E79: -12.192687 | F79: 0 | G79: 0 | H79: 0 | I79: 0 | J79: 8.464 | K79: 3.36 | L79: -2.56 | M79: -1.584 | N79: 0.08 | O79: 0 | P79: 0 | Q79: 5.248 | R79: -4.56 | S79: -2.4 | T79: -1.92 | U79: -3.056 | V79: 0 | W79: 0 | X79: -4.816 | Y79: 2.608 | Z79: -6.4 | AA79: -0.576 | AB79: -2.992 | AC79: 0 | AD79: 0 | AE79: -0.608 | AF79: -4.992 | AG79: 0.048 | AH79: 25.808 | AI79: -10.256 | AJ79: 0 | AK79: =ROUND(ABS(E79)+ABS(F79)+ABS(G79)+ABS(H79)+ABS(I79)+ABS(J79)+ABS(K79)+ABS(L79)+ABS(M79)+ABS(N79)+ABS(O79)+ABS(P79)+ABS(Q79)+ABS(R79)+ABS(S79)+ABS(T79)+ABS(U79)+ABS(V79)+ABS(W79)+ABS(X79)+ABS(Y79)+ABS(Z79)+ABS(AA79)+ABS(AB79)+ABS(AC79)+ABS(AD79)+ABS(AE79)+ABS(AF79)+ABS(AG79)+ABS(AH79)+ABS(AI79)+ABS(AJ79),6) -> 104.52869
D80: OCI公允 | E80: 0 | F80: 0 | G80: 0 | H80: 0 | I80: 0 | J80: 8.464 | K80: 3.36 | L80: -2.56 | M80: -1.584 | N80: 0.08 | O80: 0 | P80: 0 | Q80: 5.248 | R80: -4.56 | S80: -2.4 | T80: -1.92 | U80: -3.056 | V80: 0 | W80: 0 | X80: -4.816 | Y80: 2.608 | Z80: -6.4 | AA80: -0.576 | AB80: -2.992 | AC80: 0 | AD80: 0 | AE80: -0.608 | AF80: -4.992 | AG80: 0.048 | AH80: 25.808 | AI80: -10.256 | AJ80: 0 | AK80: =ROUND(ABS(E80)+ABS(F80)+ABS(G80)+ABS(H80)+ABS(I80)+ABS(J80)+ABS(K80)+ABS(L80)+ABS(M80)+ABS(N80)+ABS(O80)+ABS(P80)+ABS(Q80)+ABS(R80)+ABS(S80)+ABS(T80)+ABS(U80)+ABS(V80)+ABS(W80)+ABS(X80)+ABS(Y80)+ABS(Z80)+ABS(AA80)+ABS(AB80)+ABS(AC80)+ABS(AD80)+ABS(AE80)+ABS(AF80)+ABS(AG80)+ABS(AH80)+ABS(AI80)+ABS(AJ80),6) -> 92.336
C81: 上海医药 | D81: 持仓成本 | E81: 115.33917 | F81: 0 | G81: 0 | H81: 0 | I81: 0 | J81: 0 | K81: 0 | L81: 0 | M81: 0 | N81: 0 | O81: 0 | P81: 0 | Q81: 0 | R81: 0 | S81: 0 | T81: 0 | U81: 0 | V81: 0 | W81: 0 | X81: 0 | Y81: 0 | Z81: 0 | AA81: 0 | AB81: 0 | AC81: 0 | AD81: 0 | AE81: -115.33917 | AF81: 0 | AG81: 0 | AH81: 0 | AI81: 0 | AJ81: 0 | AK81: =ROUND(ABS(E81)+ABS(F81)+ABS(G81)+ABS(H81)+ABS(I81)+ABS(J81)+ABS(K81)+ABS(L81)+ABS(M81)+ABS(N81)+ABS(O81)+ABS(P81)+ABS(Q81)+ABS(R81)+ABS(S81)+ABS(T81)+ABS(U81)+ABS(V81)+ABS(W81)+ABS(X81)+ABS(Y81)+ABS(Z81)+ABS(AA81)+ABS(AB81)+ABS(AC81)+ABS(AD81)+ABS(AE81)+ABS(AF81)+ABS(AG81)+ABS(AH81)+ABS(AI81)+ABS(AJ81),6) -> 230.67835
D82: 持仓公允 | E82: -13.215053 | F82: 0 | G82: 0 | H82: 0 | I82: 0 | J82: 2.44293 | K82: 0.77903 | L82: 0.93138 | M82: 0.25579 | N82: 0.15653 | O82: 0 | P82: 0 | Q82: -0.47162 | R82: 0.44797 | S82: 0.08941 | T82: -0.614 | U82: -0.17244 | V82: 0 | W82: 0 | X82: -1.37538 | Y82: 1.70303 | Z82: -0.64215 | AA82: 0.1422 | AB82: 1.13668 | AC82: 0 | AD82: 0 | AE82: 8.405693 | AF82: 0 | AG82: 0 | AH82: 0 | AI82: 0 | AJ82: 0 | AK82: =ROUND(ABS(E82)+ABS(F82)+ABS(G82)+ABS(H82)+ABS(I82)+ABS(J82)+ABS(K82)+ABS(L82)+ABS(M82)+ABS(N82)+ABS(O82)+ABS(P82)+ABS(Q82)+ABS(R82)+ABS(S82)+ABS(T82)+ABS(U82)+ABS(V82)+ABS(W82)+ABS(X82)+ABS(Y82)+ABS(Z82)+ABS(AA82)+ABS(AB82)+ABS(AC82)+ABS(AD82)+ABS(AE82)+ABS(AF82)+ABS(AG82)+ABS(AH82)+ABS(AI82)+ABS(AJ82),6) -> 32.981286
D83: OCI公允 | E83: 0 | F83: 0 | G83: 0 | H83: 0 | I83: 0 | J83: 2.44293 | K83: 0.77903 | L83: 0.93138 | M83: 0.25579 | N83: 0.15653 | O83: 0 | P83: 0 | Q83: -0.47162 | R83: 0.44797 | S83: 0.08941 | T83: -0.614 | U83: -0.17244 | V83: 0 | W83: 0 | X83: -1.37538 | Y83: 1.70303 | Z83: -0.64215 | AA83: 0.1422 | AB83: 1.13668 | AC83: 0 | AD83: 0 | AE83: 8.405693 | AF83: 0 | AG83: 0 | AH83: 0 | AI83: 0 | AJ83: 0 | AK83: =ROUND(ABS(E83)+ABS(F83)+ABS(G83)+ABS(H83)+ABS(I83)+ABS(J83)+ABS(K83)+ABS(L83)+ABS(M83)+ABS(N83)+ABS(O83)+ABS(P83)+ABS(Q83)+ABS(R83)+ABS(S83)+ABS(T83)+ABS(U83)+ABS(V83)+ABS(W83)+ABS(X83)+ABS(Y83)+ABS(Z83)+ABS(AA83)+ABS(AB83)+ABS(AC83)+ABS(AD83)+ABS(AE83)+ABS(AF83)+ABS(AG83)+ABS(AH83)+ABS(AI83)+ABS(AJ83),6) -> 19.766233
D84: OCI价差 | E84: 0 | F84: 0 | G84: 0 | H84: 0 | I84: 0 | J84: 0 | K84: 0 | L84: 0 | M84: 0 | N84: 0 | O84: 0 | P84: 0 | Q84: 0 | R84: 0 | S84: 0 | T84: 0 | U84: 0 | V84: 0 | W84: 0 | X84: 0 | Y84: 0 | Z84: 0 | AA84: 0 | AB84: 0 | AC84: 0 | AD84: 0 | AE84: -7.803921 | AF84: 0 | AG84: 0 | AH84: 0 | AI84: 0 | AJ84: 0 | AK84: =ROUND(ABS(E84)+ABS(F84)+ABS(G84)+ABS(H84)+ABS(I84)+ABS(J84)+ABS(K84)+ABS(L84)+ABS(M84)+ABS(N84)+ABS(O84)+ABS(P84)+ABS(Q84)+ABS(R84)+ABS(S84)+ABS(T84)+ABS(U84)+ABS(V84)+ABS(W84)+ABS(X84)+ABS(Y84)+ABS(Z84)+ABS(AA84)+ABS(AB84)+ABS(AC84)+ABS(AD84)+ABS(AE84)+ABS(AF84)+ABS(AG84)+ABS(AH84)+ABS(AI84)+ABS(AJ84),6) -> 7.803921
D85: 应收应付 | E85: 1.2 | F85: 0 | G85: 0 | H85: 0 | I85: 0 | J85: 0 | K85: 0 | L85: 0 | M85: 0 | N85: 0 | O85: 0 | P85: 0 | Q85: 0 | R85: 0 | S85: 0 | T85: 0 | U85: 0 | V85: 0 | W85: 0 | X85: 0 | Y85: 0 | Z85: 0 | AA85: 0 | AB85: 0 | AC85: 0 | AD85: 0 | AE85: 0 | AF85: 0 | AG85: 0 | AH85: 0 | AI85: 0 | AJ85: 0 | AK85: =ROUND(ABS(E85)+ABS(F85)+ABS(G85)+ABS(H85)+ABS(I85)+ABS(J85)+ABS(K85)+ABS(L85)+ABS(M85)+ABS(N85)+ABS(O85)+ABS(P85)+ABS(Q85)+ABS(R85)+ABS(S85)+ABS(T85)+ABS(U85)+ABS(V85)+ABS(W85)+ABS(X85)+ABS(Y85)+ABS(Z85)+ABS(AA85)+ABS(AB85)+ABS(AC85)+ABS(AD85)+ABS(AE85)+ABS(AF85)+ABS(AG85)+ABS(AH85)+ABS(AI85)+ABS(AJ85),6) -> 1.2
C86: 深港通证券组合费 | D86: 交易费用 | E86: 0 | F86: 0 | G86: 0 | H86: 0 | I86: 0 | J86: -0.015455 | K86: -0.003123 | L86: -0.003141 | M86: -0.003133 | N86: -0.003101 | O86: 0 | P86: 0 | Q86: -0.009321 | R86: -0.00312 | S86: -0.003128 | T86: -0.003132 | U86: -0.003134 | V86: 0 | W86: 0 | X86: -0.009354 | Y86: -0.003106 | Z86: -0.003121 | AA86: -0.003103 | AB86: -0.003088 | AC86: 0 | AD86: 0 | AE86: -0.009252 | AF86: -0.003148 | AG86: -0.003188 | AH86: -0.003233 | AI86: -0.003263 | AJ86: 0 | AK86: =ROUND(ABS(E86)+ABS(F86)+ABS(G86)+ABS(H86)+ABS(I86)+ABS(J86)+ABS(K86)+ABS(L86)+ABS(M86)+ABS(N86)+ABS(O86)+ABS(P86)+ABS(Q86)+ABS(R86)+ABS(S86)+ABS(T86)+ABS(U86)+ABS(V86)+ABS(W86)+ABS(X86)+ABS(Y86)+ABS(Z86)+ABS(AA86)+ABS(AB86)+ABS(AC86)+ABS(AD86)+ABS(AE86)+ABS(AF86)+ABS(AG86)+ABS(AH86)+ABS(AI86)+ABS(AJ86),6) -> 0.093644
C87: 特步国际 | D87: 持仓成本 | E87: 368.76613 | F87: 0 | G87: 0 | H87: 0 | I87: 0 | J87: 0 | K87: 0 | L87: 0 | M87: 0 | N87: 0 | O87: 0 | P87: 0 | Q87: 0 | R87: 0 | S87: 0 | T87: 0 | U87: 0 | V87: 0 | W87: 0 | X87: 0 | Y87: 0 | Z87: 0 | AA87: 0 | AB87: 0 | AC87: 0 | AD87: 0 | AE87: 0 | AF87: 0 | AG87: 0 | AH87: 0 | AI87: 0 | AJ87: 0 | AK87: =ROUND(ABS(E87)+ABS(F87)+ABS(G87)+ABS(H87)+ABS(I87)+ABS(J87)+ABS(K87)+ABS(L87)+ABS(M87)+ABS(N87)+ABS(O87)+ABS(P87)+ABS(Q87)+ABS(R87)+ABS(S87)+ABS(T87)+ABS(U87)+ABS(V87)+ABS(W87)+ABS(X87)+ABS(Y87)+ABS(Z87)+ABS(AA87)+ABS(AB87)+ABS(AC87)+ABS(AD87)+ABS(AE87)+ABS(AF87)+ABS(AG87)+ABS(AH87)+ABS(AI87)+ABS(AJ87),6) -> 368.76613
D88: 持仓公允 | E88: -35.202549 | F88: 0 | G88: 0 | H88: 0 | I88: 0 | J88: 2.67897 | K88: 10.52163 | L88: -4.27476 | M88: -8.26042 | N88: -0.63308 | O88: 0 | P88: 0 | Q88: -0.7014 | R88: -3.6869 | S88: 1.25174 | T88: 1.91478 | U88: -3.38744 | V88: 0 | W88: 0 | X88: -3.23666 | Y88: 0.99421 | Z88: -4.69833 | AA88: 4.80816 | AB88: -9.44552 | AC88: 0 | AD88: 0 | AE88: -4.96356 | AF88: 0.3794 | AG88: 1.80264 | AH88: 16.00011 | AI88: -10.58505 | AJ88: 0 | AK88: =ROUND(ABS(E88)+ABS(F88)+ABS(G88)+ABS(H88)+ABS(I88)+ABS(J88)+ABS(K88)+ABS(L88)+ABS(M88)+ABS(N88)+ABS(O88)+ABS(P88)+ABS(Q88)+ABS(R88)+ABS(S88)+ABS(T88)+ABS(U88)+ABS(V88)+ABS(W88)+ABS(X88)+ABS(Y88)+ABS(Z88)+ABS(AA88)+ABS(AB88)+ABS(AC88)+ABS(AD88)+ABS(AE88)+ABS(AF88)+ABS(AG88)+ABS(AH88)+ABS(AI88)+ABS(AJ88),6) -> 129.42731
D89: OCI公允 | E89: 0 | F89: 0 | G89: 0 | H89: 0 | I89: 0 | J89: 2.67897 | K89: 10.52163 | L89: -4.27476 | M89: -8.26042 | N89: -0.63308 | O89: 0 | P89: 0 | Q89: -0.7014 | R89: -3.6869 | S89: 1.25174 | T89: 1.91478 | U89: -3.38744 | V89: 0 | W89: 0 | X89: -3.23666 | Y89: 0.99421 | Z89: -4.69833 | AA89: 4.80816 | AB89: -9.44552 | AC89: 0 | AD89: 0 | AE89: -4.96356 | AF89: 0.3794 | AG89: 1.80264 | AH89: 16.00011 | AI89: -10.58505 | AJ89: 0 | AK89: =ROUND(ABS(E89)+ABS(F89)+ABS(G89)+ABS(H89)+ABS(I89)+ABS(J89)+ABS(K89)+ABS(L89)+ABS(M89)+ABS(N89)+ABS(O89)+ABS(P89)+ABS(Q89)+ABS(R89)+ABS(S89)+ABS(T89)+ABS(U89)+ABS(V89)+ABS(W89)+ABS(X89)+ABS(Y89)+ABS(Z89)+ABS(AA89)+ABS(AB89)+ABS(AC89)+ABS(AD89)+ABS(AE89)+ABS(AF89)+ABS(AG89)+ABS(AH89)+ABS(AI89)+ABS(AJ89),6) -> 94.22476
C90: 五 粮 液 | D90: 持仓成本 | E90: 259.59689 | F90: 0 | G90: 0 | H90: 0 | I90: 0 | J90: 0 | K90: 0 | L90: 0 | M90: 0 | N90: 0 | O90: 0 | P90: 0 | Q90: 0 | R90: 0 | S90: 0 | T90: 0 | U90: 0 | V90: 0 | W90: 0 | X90: 0 | Y90: 0 | Z90: -259.59689 | AA90: 0 | AB90: 0 | AC90: 0 | AD90: 0 | AE90: 0 | AF90: 0 | AG90: 0 | AH90: 0 | AI90: 0 | AJ90: 0 | AK90: =ROUND(ABS(E90)+ABS(F90)+ABS(G90)+ABS(H90)+ABS(I90)+ABS(J90)+ABS(K90)+ABS(L90)+ABS(M90)+ABS(N90)+ABS(O90)+ABS(P90)+ABS(Q90)+ABS(R90)+ABS(S90)+ABS(T90)+ABS(U90)+ABS(V90)+ABS(W90)+ABS(X90)+ABS(Y90)+ABS(Z90)+ABS(AA90)+ABS(AB90)+ABS(AC90)+ABS(AD90)+ABS(AE90)+ABS(AF90)+ABS(AG90)+ABS(AH90)+ABS(AI90)+ABS(AJ90),6) -> 519.19378
D91: 持仓公允 | E91: -47.71689 | F91: 0 | G91: 0 | H91: 0 | I91: 0 | J91: 3.92 | K91: 0.54 | L91: -1.3 | M91: -1.24 | N91: 0.48 | O91: 0 | P91: 0 | Q91: 2.82 | R91: -1.1 | S91: -1.92 | T91: -1.9 | U91: -1.86 | V91: 0 | W91: 0 | X91: -1.22 | Y91: 0.72 | Z91: 49.77689 | AA91: 0 | AB91: 0 | AC91: 0 | AD91: 0 | AE91: 0 | AF91: 0 | AG91: 0 | AH91: 0 | AI91: 0 | AJ91: 0 | AK91: =ROUND(ABS(E91)+ABS(F91)+ABS(G91)+ABS(H91)+ABS(I91)+ABS(J91)+ABS(K91)+ABS(L91)+ABS(M91)+ABS(N91)+ABS(O91)+ABS(P91)+ABS(Q91)+ABS(R91)+ABS(S91)+ABS(T91)+ABS(U91)+ABS(V91)+ABS(W91)+ABS(X91)+ABS(Y91)+ABS(Z91)+ABS(AA91)+ABS(AB91)+ABS(AC91)+ABS(AD91)+ABS(AE91)+ABS(AF91)+ABS(AG91)+ABS(AH91)+ABS(AI91)+ABS(AJ91),6) -> 116.51378
D92: OCI公允 | E92: 0 | F92: 0 | G92: 0 | H92: 0 | I92: 0 | J92: 3.92 | K92: 0.54 | L92: -1.3 | M92: -1.24 | N92: 0.48 | O92: 0 | P92: 0 | Q92: 2.82 | R92: -1.1 | S92: -1.92 | T92: -1.9 | U92: -1.86 | V92: 0 | W92: 0 | X92: -1.22 | Y92: 0.72 | Z92: 49.77689 | AA92: 0 | AB92: 0 | AC92: 0 | AD92: 0 | AE92: 0 | AF92: 0 | AG92: 0 | AH92: 0 | AI92: 0 | AJ92: 0 | AK92: =ROUND(ABS(E92)+ABS(F92)+ABS(G92)+ABS(H92)+ABS(I92)+ABS(J92)+ABS(K92)+ABS(L92)+ABS(M92)+ABS(N92)+ABS(O92)+ABS(P92)+ABS(Q92)+ABS(R92)+ABS(S92)+ABS(T92)+ABS(U92)+ABS(V92)+ABS(W92)+ABS(X92)+ABS(Y92)+ABS(Z92)+ABS(AA92)+ABS(AB92)+ABS(AC92)+ABS(AD92)+ABS(AE92)+ABS(AF92)+ABS(AG92)+ABS(AH92)+ABS(AI92)+ABS(AJ92),6) -> 68.79689
D93: OCI价差 | E93: 0 | F93: 0 | G93: 0 | H93: 0 | I93: 0 | J93: 0 | K93: 0 | L93: 0 | M93: 0 | N93: 0 | O93: 0 | P93: 0 | Q93: 0 | R93: 0 | S93: 0 | T93: 0 | U93: 0 | V93: 0 | W93: 0 | X93: 0 | Y93: 0 | Z93: -53.681214 | AA93: 0 | AB93: 0 | AC93: 0 | AD93: 0 | AE93: 0 | AF93: 0 | AG93: 0 | AH93: 0 | AI93: 0 | AJ93: 0 | AK93: =ROUND(ABS(E93)+ABS(F93)+ABS(G93)+ABS(H93)+ABS(I93)+ABS(J93)+ABS(K93)+ABS(L93)+ABS(M93)+ABS(N93)+ABS(O93)+ABS(P93)+ABS(Q93)+ABS(R93)+ABS(S93)+ABS(T93)+ABS(U93)+ABS(V93)+ABS(W93)+ABS(X93)+ABS(Y93)+ABS(Z93)+ABS(AA93)+ABS(AB93)+ABS(AC93)+ABS(AD93)+ABS(AE93)+ABS(AF93)+ABS(AG93)+ABS(AH93)+ABS(AI93)+ABS(AJ93),6) -> 53.681214
C94: XD招商银 | D94: 股利盈亏 | E94: 0 | F94: 0 | G94: 0 | H94: 0 | I94: 0 | J94: 0 | K94: 0 | L94: 0 | M94: 0 | N94: 0 | O94: 0 | P94: 0 | Q94: 0 | R94: 0 | S94: 0 | T94: 0 | U94: 15.195 | V94: 0 | W94: 0 | X94: 0 | Y94: 0 | Z94: 0 | AA94: 0 | AB94: 0 | AC94: 0 | AD94: 0 | AE94: 0 | AF94: 0 | AG94: 0 | AH94: 0 | AI94: 0 | AJ94: 0 | AK94: =ROUND(ABS(E94)+ABS(F94)+ABS(G94)+ABS(H94)+ABS(I94)+ABS(J94)+ABS(K94)+ABS(L94)+ABS(M94)+ABS(N94)+ABS(O94)+ABS(P94)+ABS(Q94)+ABS(R94)+ABS(S94)+ABS(T94)+ABS(U94)+ABS(V94)+ABS(W94)+ABS(X94)+ABS(Y94)+ABS(Z94)+ABS(AA94)+ABS(AB94)+ABS(AC94)+ABS(AD94)+ABS(AE94)+ABS(AF94)+ABS(AG94)+ABS(AH94)+ABS(AI94)+ABS(AJ94),6) -> 15.195
C95: 新华文轩 | D95: 持仓成本 | E95: 297.18518 | F95: 0 | G95: 0 | H95: 0 | I95: 0 | J95: 0 | K95: 0 | L95: 0 | M95: 0 | N95: 0 | O95: 0 | P95: 0 | Q95: 0 | R95: 0 | S95: 0 | T95: 0 | U95: 0 | V95: 0 | W95: 0 | X95: 0 | Y95: 0 | Z95: 0 | AA95: 0 | AB95: 0 | AC95: 0 | AD95: 0 | AE95: 0 | AF95: 0 | AG95: 0 | AH95: 0 | AI95: 0 | AJ95: 0 | AK95: =ROUND(ABS(E95)+ABS(F95)+ABS(G95)+ABS(H95)+ABS(I95)+ABS(J95)+ABS(K95)+ABS(L95)+ABS(M95)+ABS(N95)+ABS(O95)+ABS(P95)+ABS(Q95)+ABS(R95)+ABS(S95)+ABS(T95)+ABS(U95)+ABS(V95)+ABS(W95)+ABS(X95)+ABS(Y95)+ABS(Z95)+ABS(AA95)+ABS(AB95)+ABS(AC95)+ABS(AD95)+ABS(AE95)+ABS(AF95)+ABS(AG95)+ABS(AH95)+ABS(AI95)+ABS(AJ95),6) -> 297.18518
D96: 持仓公允 | E96: -21.503904 | F96: 0 | G96: 0 | H96: 0 | I96: 0 | J96: -5.45283 | K96: 1.73643 | L96: 2.24172 | M96: 4.46715 | N96: 4.84695 | O96: 0 | P96: 0 | Q96: 0.74274 | R96: -1.54902 | S96: 1.60938 | T96: -0.77298 | U96: 0.58218 | V96: 0 | W96: 0 | X96: 0.97644 | Y96: -2.09769 | Z96: 0.51705 | AA96: 4.3992 | AB96: 2.6133 | AC96: 0 | AD96: 0 | AE96: -0.77088 | AF96: -3.70602 | AG96: 2.61126 | AH96: 0.05604 | AI96: 3.46905 | AJ96: 0 | AK96: =ROUND(ABS(E96)+ABS(F96)+ABS(G96)+ABS(H96)+ABS(I96)+ABS(J96)+ABS(K96)+ABS(L96)+ABS(M96)+ABS(N96)+ABS(O96)+ABS(P96)+ABS(Q96)+ABS(R96)+ABS(S96)+ABS(T96)+ABS(U96)+ABS(V96)+ABS(W96)+ABS(X96)+ABS(Y96)+ABS(Z96)+ABS(AA96)+ABS(AB96)+ABS(AC96)+ABS(AD96)+ABS(AE96)+ABS(AF96)+ABS(AG96)+ABS(AH96)+ABS(AI96)+ABS(AJ96),6) -> 66.722214
D97: OCI公允 | E97: 0 | F97: 0 | G97: 0 | H97: 0 | I97: 0 | J97: -5.45283 | K97: 1.73643 | L97: 2.24172 | M97: 4.46715 | N97: 4.84695 | O97: 0 | P97: 0 | Q97: 0.74274 | R97: -1.54902 | S97: 1.60938 | T97: -0.77298 | U97: 0.58218 | V97: 0 | W97: 0 | X97: 0.97644 | Y97: -2.09769 | Z97: 0.51705 | AA97: 4.3992 | AB97: 2.6133 | AC97: 0 | AD97: 0 | AE97: -0.77088 | AF97: -3.70602 | AG97: 2.61126 | AH97: 0.05604 | AI97: 3.46905 | AJ97: 0 | AK97: =ROUND(ABS(E97)+ABS(F97)+ABS(G97)+ABS(H97)+ABS(I97)+ABS(J97)+ABS(K97)+ABS(L97)+ABS(M97)+ABS(N97)+ABS(O97)+ABS(P97)+ABS(Q97)+ABS(R97)+ABS(S97)+ABS(T97)+ABS(U97)+ABS(V97)+ABS(W97)+ABS(X97)+ABS(Y97)+ABS(Z97)+ABS(AA97)+ABS(AB97)+ABS(AC97)+ABS(AD97)+ABS(AE97)+ABS(AF97)+ABS(AG97)+ABS(AH97)+ABS(AI97)+ABS(AJ97),6) -> 45.21831
C98: 兴业银行 | D98: 持仓成本 | E98: 634.79066 | F98: 0 | G98: 0 | H98: 0 | I98: 0 | J98: 0 | K98: 0 | L98: 0 | M98: 0 | N98: 0 | O98: 0 | P98: 0 | Q98: 0 | R98: 0 | S98: 0 | T98: 0 | U98: 0 | V98: 0 | W98: 0 | X98: 0 | Y98: 0 | Z98: 0 | AA98: 0 | AB98: 0 | AC98: 0 | AD98: 0 | AE98: 0 | AF98: 0 | AG98: 93.438988 | AH98: 0 | AI98: 0 | AJ98: 0 | AK98: =ROUND(ABS(E98)+ABS(F98)+ABS(G98)+ABS(H98)+ABS(I98)+ABS(J98)+ABS(K98)+ABS(L98)+ABS(M98)+ABS(N98)+ABS(O98)+ABS(P98)+ABS(Q98)+ABS(R98)+ABS(S98)+ABS(T98)+ABS(U98)+ABS(V98)+ABS(W98)+ABS(X98)+ABS(Y98)+ABS(Z98)+ABS(AA98)+ABS(AB98)+ABS(AC98)+ABS(AD98)+ABS(AE98)+ABS(AF98)+ABS(AG98)+ABS(AH98)+ABS(AI98)+ABS(AJ98),6) -> 728.22965
D99: 持仓公允 | E99: -2.99066 | F99: 0 | G99: 0 | H99: 0 | I99: 0 | J99: -0.3 | K99: 12.3 | L99: -6.6 | M99: -9.6 | N99: -2.4 | O99: 0 | P99: 0 | Q99: 2.4 | R99: 2.7 | S99: -15 | T99: -5.7 | U99: -7.2 | V99: 0 | W99: 0 | X99: 0 | Y99: 0.3 | Z99: -14.4 | AA99: -7.8 | AB99: -6.9 | AC99: 0 | AD99: 0 | AE99: -7.2 | AF99: -1.8 | AG99: -8.603488 | AH99: 11.9034 | AI99: -6.6519 | AJ99: 0 | AK99: =ROUND(ABS(E99)+ABS(F99)+ABS(G99)+ABS(H99)+ABS(I99)+ABS(J99)+ABS(K99)+ABS(L99)+ABS(M99)+ABS(N99)+ABS(O99)+ABS(P99)+ABS(Q99)+ABS(R99)+ABS(S99)+ABS(T99)+ABS(U99)+ABS(V99)+ABS(W99)+ABS(X99)+ABS(Y99)+ABS(Z99)+ABS(AA99)+ABS(AB99)+ABS(AC99)+ABS(AD99)+ABS(AE99)+ABS(AF99)+ABS(AG99)+ABS(AH99)+ABS(AI99)+ABS(AJ99),6) -> 132.74945
D100: OCI公允 | E100: 0 | F100: 0 | G100: 0 | H100: 0 | I100: 0 | J100: -0.3 | K100: 12.3 | L100: -6.6 | M100: -9.6 | N100: -2.4 | O100: 0 | P100: 0 | Q100: 2.4 | R100: 2.7 | S100: -15 | T100: -5.7 | U100: -7.2 | V100: 0 | W100: 0 | X100: 0 | Y100: 0.3 | Z100: -14.4 | AA100: -7.8 | AB100: -6.9 | AC100: 0 | AD100: 0 | AE100: -7.2 | AF100: -1.8 | AG100: -8.603488 | AH100: 11.9034 | AI100: -6.6519 | AJ100: 0 | AK100: =ROUND(ABS(E100)+ABS(F100)+ABS(G100)+ABS(H100)+ABS(I100)+ABS(J100)+ABS(K100)+ABS(L100)+ABS(M100)+ABS(N100)+ABS(O100)+ABS(P100)+ABS(Q100)+ABS(R100)+ABS(S100)+ABS(T100)+ABS(U100)+ABS(V100)+ABS(W100)+ABS(X100)+ABS(Y100)+ABS(Z100)+ABS(AA100)+ABS(AB100)+ABS(AC100)+ABS(AD100)+ABS(AE100)+ABS(AF100)+ABS(AG100)+ABS(AH100)+ABS(AI100)+ABS(AJ100),6) -> 129.75879
...

Sheet 本年累计
A1: 绩效归因产品口径一级分类 | B1: 绩效归因产品口径二级分类 | C1: 六级科目名称 | D1: 绩效归因科目口径 | E1: 2026年初 | F1: 2026-01-01 | G1: 2026-01-02 | H1: 2026-01-03 | I1: 2026-01-04 | J1: 2026-01-05 | K1: 2026-01-06 | L1: 2026-01-07 | M1: 2026-01-08 | N1: 2026-01-09 | O1: 2026-01-10 | P1: 2026-01-11 | Q1: 2026-01-12 | R1: 2026-01-13 | S1: 2026-01-14 | T1: 2026-01-15 | U1: 2026-01-16 | V1: 2026-01-17 | W1: 2026-01-18 | X1: 2026-01-19 | Y1: 2026-01-20 | Z1: 2026-01-21 | AA1: 2026-01-22 | AB1: 2026-01-23 | AC1: 2026-01-24 | AD1: 2026-01-25 | AE1: 2026-01-26 | AF1: 2026-01-27 | AG1: 2026-01-28 | AH1: 2026-01-29 | AI1: 2026-01-30 | AJ1: 2026-01-31
A2: 权益类产品 | B2: 股票 | C2: 安徽皖通高速公路 | D2: 持仓成本 | E2: 12.061917 | F2: =E2+Sheet54!F2 -> 12.061917 | G2: =F2+Sheet54!G2 -> 12.061917 | H2: =G2+Sheet54!H2 -> 12.061917 | I2: =H2+Sheet54!I2 -> 12.061917 | J2: =I2+Sheet54!J2 -> 12.061917 | K2: =J2+Sheet54!K2 -> 12.061917 | L2: =K2+Sheet54!L2 -> 12.061917 | M2: =L2+Sheet54!M2 -> 12.061917 | ... AJ2: =AI2+Sheet54!AJ2 -> 12.061917
D3: 持仓公允 | E3: -0.323925 | F3: =E3+Sheet54!F3 -> -0.323925 | G3: =F3+Sheet54!G3 -> -0.323925 | H3: =G3+Sheet54!H3 -> -0.323925 | I3: =H3+Sheet54!I3 -> -0.323925 | J3: =I3+Sheet54!J3 -> -0.504977 | K3: =J3+Sheet54!K3 -> -0.550887 | L3: =K3+Sheet54!L3 -> -0.52911 | M3: =L3+Sheet54!M3 -> -0.564942 | ... AJ3: =AI3+Sheet54!AJ3 -> 0.311028
D4: OCI公允 | E4: 0 | F4: =Sheet54!F4 -> 0 | G4: =Sheet54!G4 -> 0 | H4: =Sheet54!H4 -> 0 | I4: =Sheet54!I4 -> 0 | J4: =Sheet54!J4 -> -0.181052 | K4: =Sheet54!K4 -> -0.04591 | L4: =Sheet54!L4 -> 0.021777 | M4: =Sheet54!M4 -> -0.035832 | ... AJ4: =Sheet54!AJ4 -> 0
C5: 安踏体育 | D5: 持仓成本 | E5: 758.75399 | F5: =E5+Sheet54!F5 -> 758.75399 | G5: =F5+Sheet54!G5 -> 758.75399 | H5: =G5+Sheet54!H5 -> 758.75399 | I5: =H5+Sheet54!I5 -> 758.75399 | J5: =I5+Sheet54!J5 -> 758.75399 | K5: =J5+Sheet54!K5 -> 758.75399 | L5: =K5+Sheet54!L5 -> 758.75399 | M5: =L5+Sheet54!M5 -> 758.75399 | ... AJ5: =AI5+Sheet54!AJ5 -> 758.75399
D6: 持仓公允 | E6: -35.898292 | F6: =E6+Sheet54!F6 -> -35.898292 | G6: =F6+Sheet54!G6 -> -35.898292 | H6: =G6+Sheet54!H6 -> -35.898292 | I6: =H6+Sheet54!I6 -> -35.898292 | J6: =I6+Sheet54!J6 -> -40.023242 | K6: =J6+Sheet54!K6 -> -18.375292 | L6: =K6+Sheet54!L6 -> -28.432492 | M6: =L6+Sheet54!M6 -> -27.291492 | ... AJ6: =AI6+Sheet54!AJ6 -> -62.720242
D7: OCI公允 | E7: 0 | F7: =Sheet54!F7 -> 0 | G7: =Sheet54!G7 -> 0 | H7: =Sheet54!H7 -> 0 | I7: =Sheet54!I7 -> 0 | J7: =Sheet54!J7 -> -4.12495 | K7: =Sheet54!K7 -> 21.64795 | L7: =Sheet54!L7 -> -10.0572 | M7: =Sheet54!M7 -> 1.141 | ... AJ7: =Sheet54!AJ7 -> 0
C8: 北京银行 | D8: 持仓成本 | E8: 879.18426 | F8: =E8+Sheet54!F8 -> 879.18426 | G8: =F8+Sheet54!G8 -> 879.18426 | H8: =G8+Sheet54!H8 -> 879.18426 | I8: =H8+Sheet54!I8 -> 879.18426 | J8: =I8+Sheet54!J8 -> 879.18426 | K8: =J8+Sheet54!K8 -> 879.18426 | L8: =K8+Sheet54!L8 -> 879.18426 | M8: =L8+Sheet54!M8 -> 879.18426 | ... AJ8: =AI8+Sheet54!AJ8 -> 879.18426
D9: 持仓公允 | E9: -57.184259 | F9: =E9+Sheet54!F9 -> -57.184259 | G9: =F9+Sheet54!G9 -> -57.184259 | H9: =G9+Sheet54!H9 -> -57.184259 | I9: =H9+Sheet54!I9 -> -57.184259 | J9: =I9+Sheet54!J9 -> -51.184259 | K9: =J9+Sheet54!K9 -> -40.684259 | L9: =K9+Sheet54!L9 -> -46.684259 | M9: =L9+Sheet54!M9 -> -49.684259 | ... AJ9: =AI9+Sheet54!AJ9 -> -84.184259
D10: OCI公允 | E10: 0 | F10: =Sheet54!F10 -> 0 | G10: =Sheet54!G10 -> 0 | H10: =Sheet54!H10 -> 0 | I10: =Sheet54!I10 -> 0 | J10: =Sheet54!J10 -> 6 | K10: =Sheet54!K10 -> 10.5 | L10: =Sheet54!L10 -> -6 | M10: =Sheet54!M10 -> -3 | ... AJ10: =Sheet54!AJ10 -> 0
C11: 北控水务集团 | D11: 持仓成本 | E11: 452.26321 | F11: =E11+Sheet54!F11 -> 452.26321 | G11: =F11+Sheet54!G11 -> 452.26321 | H11: =G11+Sheet54!H11 -> 452.26321 | I11: =H11+Sheet54!I11 -> 452.26321 | J11: =I11+Sheet54!J11 -> 452.26321 | K11: =J11+Sheet54!K11 -> 452.26321 | L11: =K11+Sheet54!L11 -> 452.26321 | M11: =L11+Sheet54!M11 -> 452.26321 | ... AJ11: =AI11+Sheet54!AJ11 -> 452.26321
D12: 持仓公允 | E12: -10.742409 | F12: =E12+Sheet54!F12 -> -10.742409 | G12: =F12+Sheet54!G12 -> -10.742409 | H12: =G12+Sheet54!H12 -> -10.742409 | I12: =H12+Sheet54!I12 -> -10.742409 | J12: =I12+Sheet54!J12 -> -10.380209 | K12: =J12+Sheet54!K12 -> -4.363209 | L12: =K12+Sheet54!L12 -> -2.421009 | M12: =L12+Sheet54!M12 -> -1.718209 | ... AJ12: =AI12+Sheet54!AJ12 -> 26.287791
D13: OCI公允 | E13: 0 | F13: =Sheet54!F13 -> 0 | G13: =Sheet54!G13 -> 0 | H13: =Sheet54!H13 -> 0 | I13: =Sheet54!I13 -> 0 | J13: =Sheet54!J13 -> 0.3622 | K13: =Sheet54!K13 -> 6.017 | L13: =Sheet54!L13 -> 1.9422 | M13: =Sheet54!M13 -> 0.7028 | ... AJ13: =Sheet54!AJ13 -> 0
C14: 工商银行 | D14: 持仓成本 | E14: 814.29188 | F14: =E14+Sheet54!F14 -> 814.29188 | G14: =F14+Sheet54!G14 -> 814.29188 | H14: =G14+Sheet54!H14 -> 814.29188 | I14: =H14+Sheet54!I14 -> 814.29188 | J14: =I14+Sheet54!J14 -> 814.29188 | K14: =J14+Sheet54!K14 -> 814.29188 | L14: =K14+Sheet54!L14 -> 814.29188 | M14: =L14+Sheet54!M14 -> 814.29188 | ... AJ14: =AI14+Sheet54!AJ14 -> 814.29188
D15: 持仓公允 | E15: 145.29794 | F15: =E15+Sheet54!F15 -> 145.29794 | G15: =F15+Sheet54!G15 -> 145.29794 | H15: =G15+Sheet54!H15 -> 145.29794 | I15: =H15+Sheet54!I15 -> 145.29794 | J15: =I15+Sheet54!J15 -> 130.03177 | K15: =J15+Sheet54!K15 -> 131.40418 | L15: =K15+Sheet54!L15 -> 121.0573 | M15: =L15+Sheet54!M15 -> 116.41562 | ... AJ15: =AI15+Sheet54!AJ15 -> 167.09347
D16: OCI公允 | E16: 0 | F16: =Sheet54!F16 -> 0 | G16: =Sheet54!G16 -> 0 | H16: =Sheet54!H16 -> 0 | I16: =Sheet54!I16 -> 0 | J16: =Sheet54!J16 -> -15.26617 | K16: =Sheet54!K16 -> 1.37241 | L16: =Sheet54!L16 -> -10.34688 | M16: =Sheet54!M16 -> -4.64168 | ... AJ16: =Sheet54!AJ16 -> 0
D17: 应收应付 | E17: 24.038 | F17: =E17+Sheet54!F17 -> 24.038 | G17: =F17+Sheet54!G17 -> 24.038 | H17: =G17+Sheet54!H17 -> 24.038 | I17: =H17+Sheet54!I17 -> 24.038 | J17: =I17+Sheet54!J17 -> 24.038 | K17: =J17+Sheet54!K17 -> 24.038 | L17: =K17+Sheet54!L17 -> 24.038 | M17: =L17+Sheet54!M17 -> 24.038 | ... AJ17: =AI17+Sheet54!AJ17 -> 0
C18: 光大银行 | D18: 持仓成本 | E18: 976.68199 | F18: =E18+Sheet54!F18 -> 976.68199 | G18: =F18+Sheet54!G18 -> 976.68199 | H18: =G18+Sheet54!H18 -> 976.68199 | I18: =H18+Sheet54!I18 -> 976.68199 | J18: =I18+Sheet54!J18 -> 976.68199 | K18: =J18+Sheet54!K18 -> 976.68199 | L18: =K18+Sheet54!L18 -> 976.68199 | M18: =L18+Sheet54!M18 -> 976.68199 | ... AJ18: =AI18+Sheet54!AJ18 -> 976.68199
D19: 持仓公允 | E19: -34.381994 | F19: =E19+Sheet54!F19 -> -34.381994 | G19: =F19+Sheet54!G19 -> -34.381994 | H19: =G19+Sheet54!H19 -> -34.381994 | I19: =H19+Sheet54!I19 -> -34.381994 | J19: =I19+Sheet54!J19 -> -37.081994 | K19: =J19+Sheet54!K19 -> -31.681994 | L19: =K19+Sheet54!L19 -> -34.381994 | M19: =L19+Sheet54!M19 -> -39.781994 | ... AJ19: =AI19+Sheet54!AJ19 -> -80.281994
D20: OCI公允 | E20: 0 | F20: =Sheet54!F20 -> 0 | G20: =Sheet54!G20 -> 0 | H20: =Sheet54!H20 -> 0 | I20: =Sheet54!I20 -> 0 | J20: =Sheet54!J20 -> -2.7 | K20: =Sheet54!K20 -> 5.4 | L20: =Sheet54!L20 -> -2.7 | M20: =Sheet54!M20 -> -5.4 | ... AJ20: =Sheet54!AJ20 -> 0
C21: 贵州茅台 | D21: 持仓成本 | E21: 14.83109 | F21: =E21+Sheet54!F21 -> 14.83109 | G21: =F21+Sheet54!G21 -> 14.83109 | H21: =G21+Sheet54!H21 -> 14.83109 | I21: =H21+Sheet54!I21 -> 14.83109 | J21: =I21+Sheet54!J21 -> 14.83109 | K21: =J21+Sheet54!K21 -> 14.83109 | L21: =K21+Sheet54!L21 -> 14.83109 | M21: =L21+Sheet54!M21 -> 14.83109 | ... AJ21: =AI21+Sheet54!AJ21 -> 9.9475983e-14
D22: 持仓公允 | E22: -1.05929 | F22: =E22+Sheet54!F22 -> -1.05929 | G22: =F22+Sheet54!G22 -> -1.05929 | H22: =G22+Sheet54!H22 -> -1.05929 | I22: =H22+Sheet54!I22 -> -1.05929 | J22: =I22+Sheet54!J22 -> -0.57109 | K22: =J22+Sheet54!K22 -> -0.55099 | L22: =K22+Sheet54!L22 -> -0.59749 | M22: =L22+Sheet54!M22 -> -0.70809 | ... AJ22: =AI22+Sheet54!AJ22 -> -3.9968029e-14
D23: OCI公允 | E23: 0 | F23: =Sheet54!F23 -> 0 | G23: =Sheet54!G23 -> 0 | H23: =Sheet54!H23 -> 0 | I23: =Sheet54!I23 -> 0 | J23: =Sheet54!J23 -> 0.4882 | K23: =Sheet54!K23 -> 0.0201 | L23: =Sheet54!L23 -> -0.0465 | M23: =Sheet54!M23 -> -0.1106 | ... AJ23: =Sheet54!AJ23 -> 0
D24: OCI价差 | E24: 0 | F24: =Sheet54!F24 -> 0 | G24: =Sheet54!G24 -> 0 | H24: =Sheet54!H24 -> 0 | I24: =Sheet54!I24 -> 0 | J24: =Sheet54!J24 -> 0 | K24: =Sheet54!K24 -> 0 | L24: =Sheet54!L24 -> 0 | M24: =Sheet54!M24 -> 0 | ... AJ24: =Sheet54!AJ24 -> 0
C25: 海底捞 | D25: 持仓成本 | E25: 536.57688 | F25: =E25+Sheet54!F25 -> 536.57688 | G25: =F25+Sheet54!G25 -> 536.57688 | H25: =G25+Sheet54!H25 -> 536.57688 | I25: =H25+Sheet54!I25 -> 536.57688 | J25: =I25+Sheet54!J25 -> 536.57688 | K25: =J25+Sheet54!K25 -> 536.57688 | L25: =K25+Sheet54!L25 -> 536.57688 | M25: =L25+Sheet54!M25 -> 536.57688 | ... AJ25: =AI25+Sheet54!AJ25 -> 536.57688
D26: 持仓公允 | E26: -25.05888 | F26: =E26+Sheet54!F26 -> -25.05888 | G26: =F26+Sheet54!G26 -> -25.05888 | H26: =G26+Sheet54!H26 -> -25.05888 | I26: =H26+Sheet54!I26 -> -25.05888 | J26: =I26+Sheet54!J26 -> -27.06968 | K26: =J26+Sheet54!K26 -> -30.27072 | L26: =K26+Sheet54!L26 -> -25.083 | M26: =L26+Sheet54!M26 -> -34.33588 | ... AJ26: =AI26+Sheet54!AJ26 -> 31.99152
D27: OCI公允 | E27: 0 | F27: =Sheet54!F27 -> 0 | G27: =Sheet54!G27 -> 0 | H27: =Sheet54!H27 -> 0 | I27: =Sheet54!I27 -> 0 | J27: =Sheet54!J27 -> -2.0108 | K27: =Sheet54!K27 -> -3.20104 | L27: =Sheet54!L27 -> 5.18772 | M27: =Sheet54!M27 -> -9.25288 | ... AJ27: =Sheet54!AJ27 -> 0
C28: 海尔智家 | D28: 持仓成本 | E28: 453.40333 | F28: =E28+Sheet54!F28 -> 453.40333 | G28: =F28+Sheet54!G28 -> 453.40333 | H28: =G28+Sheet54!H28 -> 453.40333 | I28: =H28+Sheet54!I28 -> 453.40333 | J28: =I28+Sheet54!J28 -> 453.40333 | K28: =J28+Sheet54!K28 -> 453.40333 | L28: =K28+Sheet54!L28 -> 453.40333 | M28: =L28+Sheet54!M28 -> 453.40333 | ... AJ28: =AI28+Sheet54!AJ28 -> 453.40333
D29: 持仓公允 | E29: -17.625888 | F29: =E29+Sheet54!F29 -> -17.625888 | G29: =F29+Sheet54!G29 -> -17.625888 | H29: =G29+Sheet54!H29 -> -17.625888 | I29: =H29+Sheet54!I29 -> -17.625888 | J29: =I29+Sheet54!J29 -> -1.859728 | K29: =J29+Sheet54!K29 -> 2.738032 | L29: =K29+Sheet54!L29 -> 7.908952 | M29: =L29+Sheet54!M29 -> 8.270672 | ... AJ29: =AI29+Sheet54!AJ29 -> 5.578672
D30: OCI公允 | E30: 0 | F30: =Sheet54!F30 -> 0 | G30: =Sheet54!G30 -> 0 | H30: =Sheet54!H30 -> 0 | I30: =Sheet54!I30 -> 0 | J30: =Sheet54!J30 -> 15.76616 | K30: =Sheet54!K30 -> 4.59776 | L30: =Sheet54!L30 -> 5.17092 | M30: =Sheet54!M30 -> 0.36172 | ... AJ30: =Sheet54!AJ30 -> 0
C31: 华电国际电力股份 | D31: 持仓成本 | E31: 607.74285 | F31: =E31+Sheet54!F31 -> 607.74285 | G31: =F31+Sheet54!G31 -> 607.74285 | H31: =G31+Sheet54!H31 -> 607.74285 | I31: =H31+Sheet54!I31 -> 607.74285 | J31: =I31+Sheet54!J31 -> 607.74285 | K31: =J31+Sheet54!K31 -> 607.74285 | L31: =K31+Sheet54!L31 -> 607.74285 | M31: =L31+Sheet54!M31 -> 607.74285 | ... AJ31: =AI31+Sheet54!AJ31 -> 607.74285
D32: 持仓公允 | E32: -59.880148 | F32: =E32+Sheet54!F32 -> -59.880148 | G32: =F32+Sheet54!G32 -> -59.880148 | H32: =G32+Sheet54!H32 -> -59.880148 | I32: =H32+Sheet54!I32 -> -59.880148 | J32: =I32+Sheet54!J32 -> -52.258348 | K32: =J32+Sheet54!K32 -> -51.451048 | L32: =K32+Sheet54!L32 -> -60.673798 | M32: =L32+Sheet54!M32 -> -43.664098 | ... AJ32: =AI32+Sheet54!AJ32 -> -56.697598
D33: OCI公允 | E33: 0 | F33: =Sheet54!F33 -> 0 | G33: =Sheet54!G33 -> 0 | H33: =Sheet54!H33 -> 0 | I33: =Sheet54!I33 -> 0 | J33: =Sheet54!J33 -> 7.6218 | K33: =Sheet54!K33 -> 0.8073 | L33: =Sheet54!L33 -> -9.22275 | M33: =Sheet54!M33 -> 17.0097 | ... AJ33: =Sheet54!AJ33 -> 0
C34: 华润电力 | D34: 持仓成本 | E34: 333.94923 | F34: =E34+Sheet54!F34 -> 333.94923 | G34: =F34+Sheet54!G34 -> 333.94923 | H34: =G34+Sheet54!H34 -> 333.94923 | I34: =H34+Sheet54!I34 -> 333.94923 | J34: =I34+Sheet54!J34 -> 333.94923 | K34: =J34+Sheet54!K34 -> 333.94923 | L34: =K34+Sheet54!L34 -> 333.94923 | M34: =L34+Sheet54!M34 -> 333.94923 | ... AJ34: =AI34+Sheet54!AJ34 -> 333.94923
D35: 持仓公允 | E35: -23.269354 | F35: =E35+Sheet54!F35 -> -23.269354 | G35: =F35+Sheet54!G35 -> -23.269354 | H35: =G35+Sheet54!H35 -> -23.269354 | I35: =H35+Sheet54!I35 -> -23.269354 | J35: =I35+Sheet54!J35 -> -14.433834 | K35: =J35+Sheet54!K35 -> -13.790314 | L35: =K35+Sheet54!L35 -> -12.607774 | M35: =L35+Sheet54!M35 -> -9.772234 | ... AJ35: =AI35+Sheet54!AJ35 -> -17.287234
D36: OCI公允 | E36: 0 | F36: =Sheet54!F36 -> 0 | G36: =Sheet54!G36 -> 0 | H36: =Sheet54!H36 -> 0 | I36: =Sheet54!I36 -> 0 | J36: =Sheet54!J36 -> 8.83552 | K36: =Sheet54!K36 -> 0.64352 | L36: =Sheet54!L36 -> 1.18254 | M36: =Sheet54!M36 -> 2.83554 | ... AJ36: =Sheet54!AJ36 -> 0
C37: 建设银行 | D37: 持仓成本 | E37: 766.76257 | F37: =E37+Sheet54!F37 -> 766.76257 | G37: =F37+Sheet54!G37 -> 766.76257 | H37: =G37+Sheet54!H37 -> 766.76257 | I37: =H37+Sheet54!I37 -> 766.76257 | J37: =I37+Sheet54!J37 -> 766.76257 | K37: =J37+Sheet54!K37 -> 766.76257 | L37: =K37+Sheet54!L37 -> 766.76257 | M37: =L37+Sheet54!M37 -> 766.76257 | ... AJ37: =AI37+Sheet54!AJ37 -> 766.76257
D38: 持仓公允 | E38: -7.65191 | F38: =E38+Sheet54!F38 -> -7.65191 | G38: =F38+Sheet54!G38 -> -7.65191 | H38: =G38+Sheet54!H38 -> -7.65191 | I38: =H38+Sheet54!I38 -> -7.65191 | J38: =I38+Sheet54!J38 -> -12.07292 | K38: =J38+Sheet54!K38 -> -5.06383 | L38: =K38+Sheet54!L38 -> -15.65155 | M38: =L38+Sheet54!M38 -> -15.46532 | ... AJ38: =AI38+Sheet54!AJ38 -> 7.19138
D39: OCI公允 | E39: 0 | F39: =Sheet54!F39 -> 0 | G39: =Sheet54!G39 -> 0 | H39: =Sheet54!H39 -> 0 | I39: =Sheet54!I39 -> 0 | J39: =Sheet54!J39 -> -4.42101 | K39: =Sheet54!K39 -> 7.00909 | L39: =Sheet54!L39 -> -10.58772 | M39: =Sheet54!M39 -> 0.18623 | ... AJ39: =Sheet54!AJ39 -> 0
D40: 应收应付 | E40: 13.006 | F40: =E40+Sheet54!F40 -> 13.006 | G40: =F40+Sheet54!G40 -> 13.006 | H40: =G40+Sheet54!H40 -> 13.006 | I40: =H40+Sheet54!I40 -> 13.006 | J40: =I40+Sheet54!J40 -> 13.006 | K40: =J40+Sheet54!K40 -> 13.006 | L40: =K40+Sheet54!L40 -> 13.006 | M40: =L40+Sheet54!M40 -> 13.006 | ... AJ40: =AI40+Sheet54!AJ40 -> 0
C41: 江苏宁沪高速公路 | D41: 持仓成本 | E41: 586.33193 | F41: =E41+Sheet54!F41 -> 586.33193 | G41: =F41+Sheet54!G41 -> 586.33193 | H41: =G41+Sheet54!H41 -> 586.33193 | I41: =H41+Sheet54!I41 -> 586.33193 | J41: =I41+Sheet54!J41 -> 586.33193 | K41: =J41+Sheet54!K41 -> 586.33193 | L41: =K41+Sheet54!L41 -> 586.33193 | M41: =L41+Sheet54!M41 -> 586.33193 | ... AJ41: =AI41+Sheet54!AJ41 -> 586.33193
D42: 持仓公允 | E42: -3.605239 | F42: =E42+Sheet54!F42 -> -3.605239 | G42: =F42+Sheet54!G42 -> -3.605239 | H42: =G42+Sheet54!H42 -> -3.605239 | I42: =H42+Sheet54!I42 -> -3.605239 | J42: =I42+Sheet54!J42 -> -12.465454 | K42: =J42+Sheet54!K42 -> -36.669049 | L42: =K42+Sheet54!L42 -> -42.892084 | M42: =L42+Sheet54!M42 -> -50.793679 | ... AJ42: =AI42+Sheet54!AJ42 -> 9.188321
D43: OCI公允 | E43: 0 | F43: =Sheet54!F43 -> 0 | G43: =Sheet54!G43 -> 0 | H43: =Sheet54!H43 -> 0 | I43: =Sheet54!I43 -> 0 | J43: =Sheet54!J43 -> -8.860215 | K43: =Sheet54!K43 -> -24.203595 | L43: =Sheet54!L43 -> -6.223035 | M43: =Sheet54!M43 -> -7.901595 | ... AJ43: =Sheet54!AJ43 -> 0
C44: 交通银行 | D44: 持仓成本 | E44: 899.41097 | F44: =E44+Sheet54!F44 -> 899.41097 | G44: =F44+Sheet54!G44 -> 899.41097 | H44: =G44+Sheet54!H44 -> 899.41097 | I44: =H44+Sheet54!I44 -> 899.41097 | J44: =I44+Sheet54!J44 -> 899.41097 | K44: =J44+Sheet54!K44 -> 899.41097 | L44: =K44+Sheet54!L44 -> 899.41097 | M44: =L44+Sheet54!M44 -> 899.41097 | ... AJ44: =AI44+Sheet54!AJ44 -> 899.41097
D45: 持仓公允 | E45: -89.05877 | F45: =E45+Sheet54!F45 -> -89.05877 | G45: =F45+Sheet54!G45 -> -89.05877 | H45: =G45+Sheet54!H45 -> -89.05877 | I45: =H45+Sheet54!I45 -> -89.05877 | J45: =I45+Sheet54!J45 -> -85.41597 | K45: =J45+Sheet54!K45 -> -84.23297 | L45: =K45+Sheet54!L45 -> -88.97813 | M45: =L45+Sheet54!M45 -> -95.25097 | ... AJ45: =AI45+Sheet54!AJ45 -> -62.56937
D46: OCI公允 | E46: 0 | F46: =Sheet54!F46 -> 0 | G46: =Sheet54!G46 -> 0 | H46: =Sheet54!H46 -> 0 | I46: =Sheet54!I46 -> 0 | J46: =Sheet54!J46 -> 3.6428 | K46: =Sheet54!K46 -> 1.183 | L46: =Sheet54!L46 -> -4.74516 | M46: =Sheet54!M46 -> -6.27284 | ... AJ46: =Sheet54!AJ46 -> 0
D47: 应收应付 | E47: 18.756 | F47: =E47+Sheet54!F47 -> 18.756 | G47: =F47+Sheet54!G47 -> 18.756 | H47: =G47+Sheet54!H47 -> 18.756 | I47: =H47+Sheet54!I47 -> 18.756 | J47: =I47+Sheet54!J47 -> 18.756 | K47: =J47+Sheet54!K47 -> 18.756 | L47: =K47+Sheet54!L47 -> 18.756 | M47: =L47+Sheet54!M47 -> 18.756 | ... AJ47: =AI47+Sheet54!AJ47 -> 0
C48: 今世缘 | D48: 持仓成本 | E48: 246.09957 | F48: =E48+Sheet54!F48 -> 246.09957 | G48: =F48+Sheet54!G48 -> 246.09957 | H48: =G48+Sheet54!H48 -> 246.09957 | I48: =H48+Sheet54!I48 -> 246.09957 | J48: =I48+Sheet54!J48 -> 246.09957 | K48: =J48+Sheet54!K48 -> 246.09957 | L48: =K48+Sheet54!L48 -> 246.09957 | M48: =L48+Sheet54!M48 -> 246.09957 | ... AJ48: =AI48+Sheet54!AJ48 -> 0
D49: 持仓公允 | E49: -37.419567 | F49: =E49+Sheet54!F49 -> -37.419567 | G49: =F49+Sheet54!G49 -> -37.419567 | H49: =G49+Sheet54!H49 -> -37.419567 | I49: =H49+Sheet54!I49 -> -37.419567 | J49: =I49+Sheet54!J49 -> -35.739567 | K49: =J49+Sheet54!K49 -> -34.419567 | L49: =K49+Sheet54!L49 -> -35.079567 | M49: =L49+Sheet54!M49 -> -33.639567 | ... AJ49: =AI49+Sheet54!AJ49 -> 0
D50: OCI公允 | E50: 0 | F50: =Sheet54!F50 -> 0 | G50: =Sheet54!G50 -> 0 | H50: =Sheet54!H50 -> 0 | I50: =Sheet54!I50 -> 0 | J50: =Sheet54!J50 -> 1.68 | K50: =Sheet54!K50 -> 1.32 | L50: =Sheet54!L50 -> -0.66 | M50: =Sheet54!M50 -> 1.44 | ... AJ50: =Sheet54!AJ50 -> 0
D51: OCI价差 | E51: 0 | F51: =Sheet54!F51 -> 0 | G51: =Sheet54!G51 -> 0 | H51: =Sheet54!H51 -> 0 | I51: =Sheet54!I51 -> 0 | J51: =Sheet54!J51 -> 0 | K51: =Sheet54!K51 -> 0 | L51: =Sheet54!L51 -> 0 | M51: =Sheet54!M51 -> 0 | ... AJ51: =Sheet54!AJ51 -> 0
C52: 康师傅控股 | D52: 持仓成本 | E52: 634.36012 | F52: =E52+Sheet54!F52 -> 634.36012 | G52: =F52+Sheet54!G52 -> 634.36012 | H52: =G52+Sheet54!H52 -> 634.36012 | I52: =H52+Sheet54!I52 -> 634.36012 | J52: =I52+Sheet54!J52 -> 634.36012 | K52: =J52+Sheet54!K52 -> 634.36012 | L52: =K52+Sheet54!L52 -> 634.36012 | M52: =L52+Sheet54!M52 -> 634.36012 | ... AJ52: =AI52+Sheet54!AJ52 -> 685.97426
D53: 持仓公允 | E53: 0.460643 | F53: =E53+Sheet54!F53 -> 0.460643 | G53: =F53+Sheet54!G53 -> 0.460643 | H53: =G53+Sheet54!H53 -> 0.460643 | I53: =H53+Sheet54!I53 -> 0.460643 | J53: =I53+Sheet54!J53 -> -2.127517 | K53: =J53+Sheet54!K53 -> -1.208677 | L53: =K53+Sheet54!L53 -> 8.143583 | M53: =L53+Sheet54!M53 -> -17.777617 | ... AJ53: =AI53+Sheet54!AJ53 -> -0.258712
D54: OCI公允 | E54: 0 | F54: =Sheet54!F54 -> 0 | G54: =Sheet54!G54 -> 0 | H54: =Sheet54!H54 -> 0 | I54: =Sheet54!I54 -> 0 | J54: =Sheet54!J54 -> -2.58816 | K54: =Sheet54!K54 -> 0.91884 | L54: =Sheet54!L54 -> 9.35226 | M54: =Sheet54!M54 -> -25.9212 | ... AJ54: =Sheet54!AJ54 -> 0
C55: 联邦制药 | D55: 持仓成本 | E55: 461.40776 | F55: =E55+Sheet54!F55 -> 461.40776 | G55: =F55+Sheet54!G55 -> 461.40776 | H55: =G55+Sheet54!H55 -> 461.40776 | I55: =H55+Sheet54!I55 -> 461.40776 | J55: =I55+Sheet54!J55 -> 461.40776 | K55: =J55+Sheet54!K55 -> 461.40776 | L55: =K55+Sheet54!L55 -> 461.40776 | M55: =L55+Sheet54!M55 -> 461.40776 | ... AJ55: =AI55+Sheet54!AJ55 -> 461.40776
D56: 持仓公允 | E56: -45.373123 | F56: =E56+Sheet54!F56 -> -45.373123 | G56: =F56+Sheet54!G56 -> -45.373123 | H56: =G56+Sheet54!H56 -> -45.373123 | I56: =H56+Sheet54!I56 -> -45.373123 | J56: =I56+Sheet54!J56 -> -32.405563 | K56: =J56+Sheet54!K56 -> -28.915523 | L56: =K56+Sheet54!L56 -> -31.996643 | M56: =L56+Sheet54!M56 -> -35.633763 | ... AJ56: =AI56+Sheet54!AJ56 -> -38.005763
D57: OCI公允 | E57: 0 | F57: =Sheet54!F57 -> 0 | G57: =Sheet54!G57 -> 0 | H57: =Sheet54!H57 -> 0 | I57: =Sheet54!I57 -> 0 | J57: =Sheet54!J57 -> 12.96756 | K57: =Sheet54!K57 -> 3.49004 | L57: =Sheet54!L57 -> -3.08112 | M57: =Sheet54!M57 -> -3.63712 | ... AJ57: =Sheet54!AJ57 -> 0
C58: 泸州老窖 | D58: 持仓成本 | E58: 304.30949 | F58: =E58+Sheet54!F58 -> 304.30949 | G58: =F58+Sheet54!G58 -> 304.30949 | H58: =G58+Sheet54!H58 -> 304.30949 | I58: =H58+Sheet54!I58 -> 304.30949 | J58: =I58+Sheet54!J58 -> 304.30949 | K58: =J58+Sheet54!K58 -> 304.30949 | L58: =K58+Sheet54!L58 -> 304.30949 | M58: =L58+Sheet54!M58 -> 304.30949 | ... AJ58: =AI58+Sheet54!AJ58 -> 304.30949
D59: 持仓公允 | E59: -13.759493 | F59: =E59+Sheet54!F59 -> -13.759493 | G59: =F59+Sheet54!G59 -> -13.759493 | H59: =G59+Sheet54!H59 -> -13.759493 | I59: =H59+Sheet54!I59 -> -13.759493 | J59: =I59+Sheet54!J59 -> -9.309493 | K59: =J59+Sheet54!K59 -> -7.759493 | L59: =K59+Sheet54!L59 -> -11.509493 | M59: =L59+Sheet54!M59 -> -12.834493 | ... AJ59: =AI59+Sheet54!AJ59 -> -2.059493
D60: 股利盈亏 | E60: 0 | F60: =Sheet54!F60 -> 0 | G60: =Sheet54!G60 -> 0 | H60: =Sheet54!H60 -> 0 | I60: =Sheet54!I60 -> 0 | J60: =Sheet54!J60 -> 0 | K60: =Sheet54!K60 -> 0 | L60: =Sheet54!L60 -> 0 | M60: =Sheet54!M60 -> 0 | ... AJ60: =Sheet54!AJ60 -> 0
D61: OCI公允 | E61: 0 | F61: =Sheet54!F61 -> 0 | G61: =Sheet54!G61 -> 0 | H61: =Sheet54!H61 -> 0 | I61: =Sheet54!I61 -> 0 | J61: =Sheet54!J61 -> 4.45 | K61: =Sheet54!K61 -> 1.55 | L61: =Sheet54!L61 -> -3.75 | M61: =Sheet54!M61 -> -1.325 | ... AJ61: =Sheet54!AJ61 -> 0
C62: 美的集团 | D62: 持仓成本 | E62: 693.38549 | F62: =E62+Sheet54!F62 -> 693.38549 | G62: =F62+Sheet54!G62 -> 693.38549 | H62: =G62+Sheet54!H62 -> 693.38549 | I62: =H62+Sheet54!I62 -> 693.38549 | J62: =I62+Sheet54!J62 -> 693.38549 | K62: =J62+Sheet54!K62 -> 693.38549 | L62: =K62+Sheet54!L62 -> 693.38549 | M62: =L62+Sheet54!M62 -> 693.38549 | ... AJ62: =AI62+Sheet54!AJ62 -> 693.38549
D63: 持仓公允 | E63: 68.955811 | F63: =E63+Sheet54!F63 -> 68.955811 | G63: =F63+Sheet54!G63 -> 68.955811 | H63: =G63+Sheet54!H63 -> 68.955811 | I63: =H63+Sheet54!I63 -> 68.955811 | J63: =I63+Sheet54!J63 -> 88.407511 | K63: =J63+Sheet54!K63 -> 87.752111 | L63: =K63+Sheet54!L63 -> 96.078611 | M63: =L63+Sheet54!M63 -> 90.580761 | ... AJ63: =AI63+Sheet54!AJ63 -> 68.471261
D64: OCI公允 | E64: 0 | F64: =Sheet54!F64 -> 0 | G64: =Sheet54!G64 -> 0 | H64: =Sheet54!H64 -> 0 | I64: =Sheet54!I64 -> 0 | J64: =Sheet54!J64 -> 19.4517 | K64: =Sheet54!K64 -> -0.6554 | L64: =Sheet54!L64 -> 8.3265 | M64: =Sheet54!M64 -> -5.49785 | ... AJ64: =Sheet54!AJ64 -> 0
C65: 蒙牛乳业 | D65: 持仓成本 | E65: 16.70255 | F65: =E65+Sheet54!F65 -> 16.70255 | G65: =F65+Sheet54!G65 -> 16.70255 | H65: =G65+Sheet54!H65 -> 16.70255 | I65: =H65+Sheet54!I65 -> 16.70255 | J65: =I65+Sheet54!J65 -> 16.70255 | K65: =J65+Sheet54!K65 -> 16.70255 | L65: =K65+Sheet54!L65 -> 16.70255 | M65: =L65+Sheet54!M65 -> 16.70255 | ... AJ65: =AI65+Sheet54!AJ65 -> 16.70255
D66: 持仓公允 | E66: -3.322316 | F66: =E66+Sheet54!F66 -> -3.322316 | G66: =F66+Sheet54!G66 -> -3.322316 | H66: =G66+Sheet54!H66 -> -3.322316 | I66: =H66+Sheet54!I66 -> -3.322316 | J66: =I66+Sheet54!J66 -> -3.025645 | K66: =J66+Sheet54!K66 -> -2.978894 | L66: =K66+Sheet54!L66 -> -2.848844 | M66: =L66+Sheet54!M66 -> -2.9349 | ... AJ66: =AI66+Sheet54!AJ66 -> -2.2037
D67: OCI公允 | E67: 0 | F67: =Sheet54!F67 -> 0 | G67: =Sheet54!G67 -> 0 | H67: =Sheet54!H67 -> 0 | I67: =Sheet54!I67 -> 0 | J67: =Sheet54!J67 -> 0.296671 | K67: =Sheet54!K67 -> 0.046751 | L67: =Sheet54!L67 -> 0.13005 | M67: =Sheet54!M67 -> -0.086056 | ... AJ67: =Sheet54!AJ67 -> 0
C68: 南方传媒 | D68: 持仓成本 | E68: 309.38963 | F68: =E68+Sheet54!F68 -> 309.38963 | G68: =F68+Sheet54!G68 -> 309.38963 | H68: =G68+Sheet54!H68 -> 309.38963 | I68: =H68+Sheet54!I68 -> 309.38963 | J68: =I68+Sheet54!J68 -> 309.38963 | K68: =J68+Sheet54!K68 -> 309.38963 | L68: =K68+Sheet54!L68 -> 309.38963 | M68: =L68+Sheet54!M68 -> 309.38963 | ... AJ68: =AI68+Sheet54!AJ68 -> 0
D69: 持仓公允 | E69: -41.189629 | F69: =E69+Sheet54!F69 -> -41.189629 | G69: =F69+Sheet54!G69 -> -41.189629 | H69: =G69+Sheet54!H69 -> -41.189629 | I69: =H69+Sheet54!I69 -> -41.189629 | J69: =I69+Sheet54!J69 -> -35.189629 | K69: =J69+Sheet54!K69 -> -33.589629 | L69: =K69+Sheet54!L69 -> -43.989629 | M69: =L69+Sheet54!M69 -> -44.589629 | ... AJ69: =AI69+Sheet54!AJ69 -> 0
D70: OCI公允 | E70: 0 | F70: =Sheet54!F70 -> 0 | G70: =Sheet54!G70 -> 0 | H70: =Sheet54!H70 -> 0 | I70: =Sheet54!I70 -> 0 | J70: =Sheet54!J70 -> 6 | K70: =Sheet54!K70 -> 1.6 | L70: =Sheet54!L70 -> -10.4 | M70: =Sheet54!M70 -> -0.6 | ... AJ70: =Sheet54!AJ70 -> 0
D71: OCI价差 | E71: 0 | F71: =Sheet54!F71 -> 0 | G71: =Sheet54!G71 -> 0 | H71: =Sheet54!H71 -> 0 | I71: =Sheet54!I71 -> 0 | J71: =Sheet54!J71 -> 0 | K71: =Sheet54!K71 -> 0 | L71: =Sheet54!L71 -> 0 | M71: =Sheet54!M71 -> 0 | ... AJ71: =Sheet54!AJ71 -> 0
C72: 南京银行 | D72: 持仓成本 | E72: 333.22904 | F72: =E72+Sheet54!F72 -> 333.22904 | G72: =F72+Sheet54!G72 -> 333.22904 | H72: =G72+Sheet54!H72 -> 333.22904 | I72: =H72+Sheet54!I72 -> 333.22904 | J72: =I72+Sheet54!J72 -> 333.22904 | K72: =J72+Sheet54!K72 -> 333.22904 | L72: =K72+Sheet54!L72 -> 333.22904 | M72: =L72+Sheet54!M72 -> 333.22904 | ... AJ72: =AI72+Sheet54!AJ72 -> 333.22904
D73: 持仓公允 | E73: 9.670955 | F73: =E73+Sheet54!F73 -> 9.670955 | G73: =F73+Sheet54!G73 -> 9.670955 | H73: =G73+Sheet54!H73 -> 9.670955 | I73: =H73+Sheet54!I73 -> 9.670955 | J73: =I73+Sheet54!J73 -> 6.370955 | K73: =J73+Sheet54!K73 -> 6.070955 | L73: =K73+Sheet54!L73 -> 0.070955 | M73: =L73+Sheet54!M73 -> -4.729045 | ... AJ73: =AI73+Sheet54!AJ73 -> -17.329045
D74: OCI公允 | E74: 0 | F74: =Sheet54!F74 -> 0 | G74: =Sheet54!G74 -> 0 | H74: =Sheet54!H74 -> 0 | I74: =Sheet54!I74 -> 0 | J74: =Sheet54!J74 -> -3.3 | K74: =Sheet54!K74 -> -0.3 | L74: =Sheet54!L74 -> -6 | M74: =Sheet54!M74 -> -4.8 | ... AJ74: =Sheet54!AJ74 -> 0
C75: 平安银行 | D75: 持仓成本 | E75: 815.93726 | F75: =E75+Sheet54!F75 -> 815.93726 | G75: =F75+Sheet54!G75 -> 815.93726 | H75: =G75+Sheet54!H75 -> 815.93726 | I75: =H75+Sheet54!I75 -> 815.93726 | J75: =I75+Sheet54!J75 -> 815.93726 | K75: =J75+Sheet54!K75 -> 815.93726 | L75: =K75+Sheet54!L75 -> 815.93726 | M75: =L75+Sheet54!M75 -> 815.93726 | ... AJ75: =AI75+Sheet54!AJ75 -> 815.93726
D76: 持仓公允 | E76: -17.237257 | F76: =E76+Sheet54!F76 -> -17.237257 | G76: =F76+Sheet54!G76 -> -17.237257 | H76: =G76+Sheet54!H76 -> -17.237257 | I76: =H76+Sheet54!I76 -> -17.237257 | J76: =I76+Sheet54!J76 -> -10.937257 | K76: =J76+Sheet54!K76 -> 0.962743 | L76: =K76+Sheet54!L76 -> -1.137257 | M76: =L76+Sheet54!M76 -> -10.237257 | ... AJ76: =AI76+Sheet54!AJ76 -> -57.837257
D77: OCI公允 | E77: 0 | F77: =Sheet54!F77 -> 0 | G77: =Sheet54!G77 -> 0 | H77: =Sheet54!H77 -> 0 | I77: =Sheet54!I77 -> 0 | J77: =Sheet54!J77 -> 6.3 | K77: =Sheet54!K77 -> 11.9 | L77: =Sheet54!L77 -> -2.1 | M77: =Sheet54!M77 -> -9.1 | ... AJ77: =Sheet54!AJ77 -> 0
C78: 山西汾酒 | D78: 持仓成本 | E78: 286.91269 | F78: =E78+Sheet54!F78 -> 286.91269 | G78: =F78+Sheet54!G78 -> 286.91269 | H78: =G78+Sheet54!H78 -> 286.91269 | I78: =H78+Sheet54!I78 -> 286.91269 | J78: =I78+Sheet54!J78 -> 286.91269 | K78: =J78+Sheet54!K78 -> 286.91269 | L78: =K78+Sheet54!L78 -> 286.91269 | M78: =L78+Sheet54!M78 -> 286.91269 | ... AJ78: =AI78+Sheet54!AJ78 -> 286.91269
D79: 持仓公允 | E79: -12.192687 | F79: =E79+Sheet54!F79 -> -12.192687 | G79: =F79+Sheet54!G79 -> -12.192687 | H79: =G79+Sheet54!H79 -> -12.192687 | I79: =H79+Sheet54!I79 -> -12.192687 | J79: =I79+Sheet54!J79 -> -3.728687 | K79: =J79+Sheet54!K79 -> -0.368687 | L79: =K79+Sheet54!L79 -> -2.928687 | M79: =L79+Sheet54!M79 -> -4.512687 | ... AJ79: =AI79+Sheet54!AJ79 -> -13.296687
D80: OCI公允 | E80: 0 | F80: =Sheet54!F80 -> 0 | G80: =Sheet54!G80 -> 0 | H80: =Sheet54!H80 -> 0 | I80: =Sheet54!I80 -> 0 | J80: =Sheet54!J80 -> 8.464 | K80: =Sheet54!K80 -> 3.36 | L80: =Sheet54!L80 -> -2.56 | M80: =Sheet54!M80 -> -1.584 | ... AJ80: =Sheet54!AJ80 -> 0
C81: 上海医药 | D81: 持仓成本 | E81: 115.33917 | F81: =E81+Sheet54!F81 -> 115.33917 | G81: =F81+Sheet54!G81 -> 115.33917 | H81: =G81+Sheet54!H81 -> 115.33917 | I81: =H81+Sheet54!I81 -> 115.33917 | J81: =I81+Sheet54!J81 -> 115.33917 | K81: =J81+Sheet54!K81 -> 115.33917 | L81: =K81+Sheet54!L81 -> 115.33917 | M81: =L81+Sheet54!M81 -> 115.33917 | ... AJ81: =AI81+Sheet54!AJ81 -> 0
D82: 持仓公允 | E82: -13.215053 | F82: =E82+Sheet54!F82 -> -13.215053 | G82: =F82+Sheet54!G82 -> -13.215053 | H82: =G82+Sheet54!H82 -> -13.215053 | I82: =H82+Sheet54!I82 -> -13.215053 | J82: =I82+Sheet54!J82 -> -10.772123 | K82: =J82+Sheet54!K82 -> -9.993093 | L82: =K82+Sheet54!L82 -> -9.061713 | M82: =L82+Sheet54!M82 -> -8.805923 | ... AJ82: =AI82+Sheet54!AJ82 -> 0
D83: OCI公允 | E83: 0 | F83: =Sheet54!F83 -> 0 | G83: =Sheet54!G83 -> 0 | H83: =Sheet54!H83 -> 0 | I83: =Sheet54!I83 -> 0 | J83: =Sheet54!J83 -> 2.44293 | K83: =Sheet54!K83 -> 0.77903 | L83: =Sheet54!L83 -> 0.93138 | M83: =Sheet54!M83 -> 0.25579 | ... AJ83: =Sheet54!AJ83 -> 0
D84: OCI价差 | E84: 0 | F84: =Sheet54!F84 -> 0 | G84: =Sheet54!G84 -> 0 | H84: =Sheet54!H84 -> 0 | I84: =Sheet54!I84 -> 0 | J84: =Sheet54!J84 -> 0 | K84: =Sheet54!K84 -> 0 | L84: =Sheet54!L84 -> 0 | M84: =Sheet54!M84 -> 0 | ... AJ84: =Sheet54!AJ84 -> 0
D85: 应收应付 | E85: 1.2 | F85: =E85+Sheet54!F85 -> 1.2 | G85: =F85+Sheet54!G85 -> 1.2 | H85: =G85+Sheet54!H85 -> 1.2 | I85: =H85+Sheet54!I85 -> 1.2 | J85: =I85+Sheet54!J85 -> 1.2 | K85: =J85+Sheet54!K85 -> 1.2 | L85: =K85+Sheet54!L85 -> 1.2 | M85: =L85+Sheet54!M85 -> 1.2 | ... AJ85: =AI85+Sheet54!AJ85 -> 1.2
C86: 深港通证券组合费 | D86: 交易费用 | E86: 0 | F86: =Sheet54!F86 -> 0 | G86: =Sheet54!G86 -> 0 | H86: =Sheet54!H86 -> 0 | I86: =Sheet54!I86 -> 0 | J86: =Sheet54!J86 -> -0.015455 | K86: =Sheet54!K86 -> -0.003123 | L86: =Sheet54!L86 -> -0.003141 | M86: =Sheet54!M86 -> -0.003133 | ... AJ86: =Sheet54!AJ86 -> 0
C87: 特步国际 | D87: 持仓成本 | E87: 368.76613 | F87: =E87+Sheet54!F87 -> 368.76613 | G87: =F87+Sheet54!G87 -> 368.76613 | H87: =G87+Sheet54!H87 -> 368.76613 | I87: =H87+Sheet54!I87 -> 368.76613 | J87: =I87+Sheet54!J87 -> 368.76613 | K87: =J87+Sheet54!K87 -> 368.76613 | L87: =K87+Sheet54!L87 -> 368.76613 | M87: =L87+Sheet54!M87 -> 368.76613 | ... AJ87: =AI87+Sheet54!AJ87 -> 368.76613
D88: 持仓公允 | E88: -35.202549 | F88: =E88+Sheet54!F88 -> -35.202549 | G88: =F88+Sheet54!G88 -> -35.202549 | H88: =G88+Sheet54!H88 -> -35.202549 | I88: =H88+Sheet54!I88 -> -35.202549 | J88: =I88+Sheet54!J88 -> -32.523579 | K88: =J88+Sheet54!K88 -> -22.001949 | L88: =K88+Sheet54!L88 -> -26.276709 | M88: =L88+Sheet54!M88 -> -34.537129 | ... AJ88: =AI88+Sheet54!AJ88 -> -48.724029
D89: OCI公允 | E89: 0 | F89: =Sheet54!F89 -> 0 | G89: =Sheet54!G89 -> 0 | H89: =Sheet54!H89 -> 0 | I89: =Sheet54!I89 -> 0 | J89: =Sheet54!J89 -> 2.67897 | K89: =Sheet54!K89 -> 10.52163 | L89: =Sheet54!L89 -> -4.27476 | M89: =Sheet54!M89 -> -8.26042 | ... AJ89: =Sheet54!AJ89 -> 0
C90: 五 粮 液 | D90: 持仓成本 | E90: 259.59689 | F90: =E90+Sheet54!F90 -> 259.59689 | G90: =F90+Sheet54!G90 -> 259.59689 | H90: =G90+Sheet54!H90 -> 259.59689 | I90: =H90+Sheet54!I90 -> 259.59689 | J90: =I90+Sheet54!J90 -> 259.59689 | K90: =J90+Sheet54!K90 -> 259.59689 | L90: =K90+Sheet54!L90 -> 259.59689 | M90: =L90+Sheet54!M90 -> 259.59689 | ... AJ90: =AI90+Sheet54!AJ90 -> 0
D91: 持仓公允 | E91: -47.71689 | F91: =E91+Sheet54!F91 -> -47.71689 | G91: =F91+Sheet54!G91 -> -47.71689 | H91: =G91+Sheet54!H91 -> -47.71689 | I91: =H91+Sheet54!I91 -> -47.71689 | J91: =I91+Sheet54!J91 -> -43.79689 | K91: =J91+Sheet54!K91 -> -43.25689 | L91: =K91+Sheet54!L91 -> -44.55689 | M91: =L91+Sheet54!M91 -> -45.79689 | ... AJ91: =AI91+Sheet54!AJ91 -> 0
D92: OCI公允 | E92: 0 | F92: =Sheet54!F92 -> 0 | G92: =Sheet54!G92 -> 0 | H92: =Sheet54!H92 -> 0 | I92: =Sheet54!I92 -> 0 | J92: =Sheet54!J92 -> 3.92 | K92: =Sheet54!K92 -> 0.54 | L92: =Sheet54!L92 -> -1.3 | M92: =Sheet54!M92 -> -1.24 | ... AJ92: =Sheet54!AJ92 -> 0
D93: OCI价差 | E93: 0 | F93: =Sheet54!F93 -> 0 | G93: =Sheet54!G93 -> 0 | H93: =Sheet54!H93 -> 0 | I93: =Sheet54!I93 -> 0 | J93: =Sheet54!J93 -> 0 | K93: =Sheet54!K93 -> 0 | L93: =Sheet54!L93 -> 0 | M93: =Sheet54!M93 -> 0 | ... AJ93: =Sheet54!AJ93 -> 0
C94: XD招商银 | D94: 股利盈亏 | E94: 0 | F94: =Sheet54!F94 -> 0 | G94: =Sheet54!G94 -> 0 | H94: =Sheet54!H94 -> 0 | I94: =Sheet54!I94 -> 0 | J94: =Sheet54!J94 -> 0 | K94: =Sheet54!K94 -> 0 | L94: =Sheet54!L94 -> 0 | M94: =Sheet54!M94 -> 0 | ... AJ94: =Sheet54!AJ94 -> 0
C95: 新华文轩 | D95: 持仓成本 | E95: 297.18518 | F95: =E95+Sheet54!F95 -> 297.18518 | G95: =F95+Sheet54!G95 -> 297.18518 | H95: =G95+Sheet54!H95 -> 297.18518 | I95: =H95+Sheet54!I95 -> 297.18518 | J95: =I95+Sheet54!J95 -> 297.18518 | K95: =J95+Sheet54!K95 -> 297.18518 | L95: =K95+Sheet54!L95 -> 297.18518 | M95: =L95+Sheet54!M95 -> 297.18518 | ... AJ95: =AI95+Sheet54!AJ95 -> 297.18518
D96: 持仓公允 | E96: -21.503904 | F96: =E96+Sheet54!F96 -> -21.503904 | G96: =F96+Sheet54!G96 -> -21.503904 | H96: =G96+Sheet54!H96 -> -21.503904 | I96: =H96+Sheet54!I96 -> -21.503904 | J96: =I96+Sheet54!J96 -> -26.956734 | K96: =J96+Sheet54!K96 -> -25.220304 | L96: =K96+Sheet54!L96 -> -22.978584 | M96: =L96+Sheet54!M96 -> -18.511434 | ... AJ96: =AI96+Sheet54!AJ96 -> -4.984434
D97: OCI公允 | E97: 0 | F97: =Sheet54!F97 -> 0 | G97: =Sheet54!G97 -> 0 | H97: =Sheet54!H97 -> 0 | I97: =Sheet54!I97 -> 0 | J97: =Sheet54!J97 -> -5.45283 | K97: =Sheet54!K97 -> 1.73643 | L97: =Sheet54!L97 -> 2.24172 | M97: =Sheet54!M97 -> 4.46715 | ... AJ97: =Sheet54!AJ97 -> 0
C98: 兴业银行 | D98: 持仓成本 | E98: 634.79066 | F98: =E98+Sheet54!F98 -> 634.79066 | G98: =F98+Sheet54!G98 -> 634.79066 | H98: =G98+Sheet54!H98 -> 634.79066 | I98: =H98+Sheet54!I98 -> 634.79066 | J98: =I98+Sheet54!J98 -> 634.79066 | K98: =J98+Sheet54!K98 -> 634.79066 | L98: =K98+Sheet54!L98 -> 634.79066 | M98: =L98+Sheet54!M98 -> 634.79066 | ... AJ98: =AI98+Sheet54!AJ98 -> 728.22965
D99: 持仓公允 | E99: -2.99066 | F99: =E99+Sheet54!F99 -> -2.99066 | G99: =F99+Sheet54!G99 -> -2.99066 | H99: =G99+Sheet54!H99 -> -2.99066 | I99: =H99+Sheet54!I99 -> -2.99066 | J99: =I99+Sheet54!J99 -> -3.29066 | K99: =J99+Sheet54!K99 -> 9.00934 | L99: =K99+Sheet54!L99 -> 2.40934 | M99: =L99+Sheet54!M99 -> -7.19066 | ... AJ99: =AI99+Sheet54!AJ99 -> -73.542648
D100: OCI公允 | E100: 0 | F100: =Sheet54!F100 -> 0 | G100: =Sheet54!G100 -> 0 | H100: =Sheet54!H100 -> 0 | I100: =Sheet54!I100 -> 0 | J100: =Sheet54!J100 -> -0.3 | K100: =Sheet54!K100 -> 12.3 | L100: =Sheet54!L100 -> -6.6 | M100: =Sheet54!M100 -> -9.6 | ... AJ100: =Sheet54!AJ100 -> 0
...

Sheet 口径说明
B2: 资产类/负债类科目，口径为截止当日的累计余额
B3: 权益类/损益类科目，口径为当日的发生额
