Workbook

Sheet Part_II_a_领导考核
A1: Part II 投组 / 交易员考核
A2: II-a.1 领导考核 · 全账 + FIFO + 估值日盯市。估值日 2026-06-01（行情见「估值日行情」B1）；RPNL=SUMIFS(逐笔辅助!U)；MTM=SUMIFS(期末持仓!S)=市值(CNY)−FIFO剩余成本(期末持仓!T·本币透传)；汇率见 FX_RATES_TO_CNY_HIST；与引擎 position_end MTM 同口径。
A4: 指标 | B4: 口径 | C4: 权益现货（场内） | D4: 权益现货（深港） | E4: 权益现货 | F4: 股指期货 | G4: 权益类基金 | H4: 合计
A5: 成交笔数 | B5: 成交回报 | C5: =COUNTIFS('交易流水'!$X$2:$X$151,"*场内*") | D5: =COUNTIFS('交易流水'!$X$2:$X$151,"*深港*") | E5: =C5+D5 | F5: 0 | G5: 0 | H5: =C5+D5+F5+G5
A6: 买入笔数 | B6: 成交回报 | C6: =COUNTIFS('交易流水'!$X$2:$X$151,"*场内*",'交易流水'!$H$2:$H$151,"买入") | D6: =COUNTIFS('交易流水'!$X$2:$X$151,"*深港*",'交易流水'!$H$2:$H$151,"买入") | E6: =C6+D6 | F6: 0 | G6: 0 | H6: =C6+D6+F6+G6
A7: 卖出笔数 | B7: 成交回报 | C7: =COUNTIFS('交易流水'!$X$2:$X$151,"*场内*",'交易流水'!$H$2:$H$151,"卖出") | D7: =COUNTIFS('交易流水'!$X$2:$X$151,"*深港*",'交易流水'!$H$2:$H$151,"卖出") | E7: =C7+D7 | F7: 0 | G7: 0 | H7: =C7+D7+F7+G7
A8: 买入数量合计 | B8: 成交回报 | C8: =SUMIFS('交易流水'!$K$2:$K$151,'交易流水'!$X$2:$X$151,"*场内*",'交易流水'!$H$2:$H$151,"买入")/10000 | D8: =SUMIFS('交易流水'!$K$2:$K$151,'交易流水'!$X$2:$X$151,"*深港*",'交易流水'!$H$2:$H$151,"买入")/10000 | E8: =C8+D8 | F8: 0 | G8: 0 | H8: =C8+D8+F8+G8
A9: 卖出数量合计 | B9: 成交回报 | C9: =SUMIFS('交易流水'!$K$2:$K$151,'交易流水'!$X$2:$X$151,"*场内*",'交易流水'!$H$2:$H$151,"卖出")/10000 | D9: =SUMIFS('交易流水'!$K$2:$K$151,'交易流水'!$X$2:$X$151,"*深港*",'交易流水'!$H$2:$H$151,"卖出")/10000 | E9: =C9+D9 | F9: 0 | G9: 0 | H9: =C9+D9+F9+G9
A10: 买入金额合计(本币) | B10: 成交回报 | C10: =SUMIFS('交易流水'!$AR$2:$AR$151,'交易流水'!$X$2:$X$151,"*场内*",'交易流水'!$H$2:$H$151,"买入")/10000 | D10: =SUMIFS('交易流水'!$AR$2:$AR$151,'交易流水'!$X$2:$X$151,"*深港*",'交易流水'!$H$2:$H$151,"买入")/10000 | E10: =C10+D10 | F10: 0 | G10: 0 | H10: =C10+D10+F10+G10
A11: 卖出金额合计(本币) | B11: 成交回报 | C11: =SUMIFS('交易流水'!$AR$2:$AR$151,'交易流水'!$X$2:$X$151,"*场内*",'交易流水'!$H$2:$H$151,"卖出")/10000 | D11: =SUMIFS('交易流水'!$AR$2:$AR$151,'交易流水'!$X$2:$X$151,"*深港*",'交易流水'!$H$2:$H$151,"卖出")/10000 | E11: =C11+D11 | F11: 0 | G11: 0 | H11: =C11+D11+F11+G11
A12: 已实现损益（先买先卖 · 开平匹配） | B12: 全账考核 | C12: =SUMIFS('逐笔辅助'!$U$2:$U$191,'逐笔辅助'!$A$2:$A$191,"流水",'逐笔辅助'!$D$2:$D$191,"场内") | D12: =SUMIFS('逐笔辅助'!$U$2:$U$191,'逐笔辅助'!$A$2:$A$191,"流水",'逐笔辅助'!$D$2:$D$191,"深港") | E12: =C12+D12 | F12: 0 | G12: 0 | H12: =C12+D12+F12+G12
A13: 浮动盈亏（估值日盯市） | B13: 全账考核 | C13: =SUMIFS('期末持仓'!$S$2:$S$56,'期末持仓'!$A$2:$A$56,"场内") | D13: =SUMIFS('期末持仓'!$S$2:$S$56,'期末持仓'!$A$2:$A$56,"深港") | E13: =C13+D13 | F13: 0 | G13: 0 | H13: =C13+D13+F13+G13
A14: 股息收入（引擎日计提） | B14: 引擎 | C14: 274119.67 | D14: 284981.16 | E14: 559100.83 | H14: 559100.83
A15: 总损益（已实现 + 浮动 + 股息） | B15: 全账考核 | C15: =C12+C13+C14 | D15: =D12+D13+D14 | E15: =E12+E13+E14 | F15: =F12+F13+F14 | G15: =G12+G13+G14 | H15: =C15+D15+F15+G15
A16: 择时损益（相对931357.SH） | B16: 引擎/公式 | E16: 29901670 | H16: 29901670
A18: 期初投资（initial_capital）
A19: 自营权益4 | B19: 期初资金.xls | C19: 202510600
A20: 期初持仓成本合计 | C20: =SUM('期初批次'!$E$2:$E$41)
A21: 期初持仓市值合计 | C21: =SUM('期初批次'!$H$2:$H$41)

Sheet Part_II_a_运营财务
A1: Part II 投组 / 交易员考核
A2: II-a.2 运营 / 测试 / 财务 · 流水 + 加权均价。损益三行均为 Excel 公式：RPNL=SUMIFS(逐笔辅助!T 加权·CNY)；MTM=SUMIFS(期末持仓!W 流水净持仓盯市·CNY)；TOTAL=已实现+浮动；供运营手算对账，不与领导考核奖罚直接对比。
A4: 指标 | B4: 口径 | C4: 权益现货（场内） | D4: 权益现货（深港） | E4: 权益现货 | F4: 股指期货 | G4: 权益类基金 | H4: 合计
A5: 成交笔数 | B5: 成交回报 | C5: =COUNTIFS('交易流水'!$X$2:$X$151,"*场内*") | D5: =COUNTIFS('交易流水'!$X$2:$X$151,"*深港*") | E5: =C5+D5 | F5: 0 | G5: 0 | H5: =C5+D5+F5+G5
A6: 买入笔数 | B6: 成交回报 | C6: =COUNTIFS('交易流水'!$X$2:$X$151,"*场内*",'交易流水'!$H$2:$H$151,"买入") | D6: =COUNTIFS('交易流水'!$X$2:$X$151,"*深港*",'交易流水'!$H$2:$H$151,"买入") | E6: =C6+D6 | F6: 0 | G6: 0 | H6: =C6+D6+F6+G6
A7: 卖出笔数 | B7: 成交回报 | C7: =COUNTIFS('交易流水'!$X$2:$X$151,"*场内*",'交易流水'!$H$2:$H$151,"卖出") | D7: =COUNTIFS('交易流水'!$X$2:$X$151,"*深港*",'交易流水'!$H$2:$H$151,"卖出") | E7: =C7+D7 | F7: 0 | G7: 0 | H7: =C7+D7+F7+G7
A8: 买入数量合计 | B8: 成交回报 | C8: =SUMIFS('交易流水'!$K$2:$K$151,'交易流水'!$X$2:$X$151,"*场内*",'交易流水'!$H$2:$H$151,"买入")/10000 | D8: =SUMIFS('交易流水'!$K$2:$K$151,'交易流水'!$X$2:$X$151,"*深港*",'交易流水'!$H$2:$H$151,"买入")/10000 | E8: =C8+D8 | F8: 0 | G8: 0 | H8: =C8+D8+F8+G8
A9: 卖出数量合计 | B9: 成交回报 | C9: =SUMIFS('交易流水'!$K$2:$K$151,'交易流水'!$X$2:$X$151,"*场内*",'交易流水'!$H$2:$H$151,"卖出")/10000 | D9: =SUMIFS('交易流水'!$K$2:$K$151,'交易流水'!$X$2:$X$151,"*深港*",'交易流水'!$H$2:$H$151,"卖出")/10000 | E9: =C9+D9 | F9: 0 | G9: 0 | H9: =C9+D9+F9+G9
A10: 买入金额合计(本币) | B10: 成交回报 | C10: =SUMIFS('交易流水'!$AR$2:$AR$151,'交易流水'!$X$2:$X$151,"*场内*",'交易流水'!$H$2:$H$151,"买入")/10000 | D10: =SUMIFS('交易流水'!$AR$2:$AR$151,'交易流水'!$X$2:$X$151,"*深港*",'交易流水'!$H$2:$H$151,"买入")/10000 | E10: =C10+D10 | F10: 0 | G10: 0 | H10: =C10+D10+F10+G10
A11: 卖出金额合计(本币) | B11: 成交回报 | C11: =SUMIFS('交易流水'!$AR$2:$AR$151,'交易流水'!$X$2:$X$151,"*场内*",'交易流水'!$H$2:$H$151,"卖出")/10000 | D11: =SUMIFS('交易流水'!$AR$2:$AR$151,'交易流水'!$X$2:$X$151,"*深港*",'交易流水'!$H$2:$H$151,"卖出")/10000 | E11: =C11+D11 | F11: 0 | G11: 0 | H11: =C11+D11+F11+G11
A12: 已实现损益（加权均价） | B12: 流水对账 | C12: =SUMIFS('逐笔辅助'!$T$2:$T$191,'逐笔辅助'!$A$2:$A$191,"流水",'逐笔辅助'!$D$2:$D$191,"场内") | D12: =SUMIFS('逐笔辅助'!$T$2:$T$191,'逐笔辅助'!$A$2:$A$191,"流水",'逐笔辅助'!$D$2:$D$191,"深港") | E12: =C12+D12 | F12: 0 | G12: 0 | H12: =C12+D12+F12+G12
A13: 浮动盈亏（流水净持仓盯市） | B13: 流水对账 | C13: =SUMIFS('期末持仓'!$W$2:$W$56,'期末持仓'!$A$2:$A$56,"场内") | D13: =SUMIFS('期末持仓'!$W$2:$W$56,'期末持仓'!$A$2:$A$56,"深港") | E13: =C13+D13 | F13: 0 | G13: 0 | H13: =C13+D13+F13+G13
A14: 总损益（加权 + 流水浮动） | B14: 流水对账 | C14: =C12+C13 | D14: =D12+D13 | E14: =E12+E13 | F14: =F12+F13 | G14: =G12+G13 | H14: =C14+D14+F14+G14
A16: 期初投资（initial_capital）
A17: 自营权益4 | B17: 期初资金.xls | C17: 202510600
A18: 期初持仓成本合计 | C18: =SUM('期初批次'!$E$2:$E$41)
A19: 期初持仓市值合计 | C19: =SUM('期初批次'!$H$2:$H$41)

Sheet Part_II_a_第三轨
A1: Part II 投组 / 交易员考核
A2: II-a.3 第三轨试算 · 全账加权均价（期初纳入成本池）。RPNL=SUMIFS(逐笔辅助!AJ)；MTM=SUMIFS(期末持仓!Q−O)（全账净持仓×估值日市价−全账加权成本）；与运营轨(仅流水加权) / 考核轨(FIFO) 对比见下方。逐笔明细见逐笔辅助 AG–AL 列。
A4: 指标 | B4: 口径 | C4: 权益现货（场内） | D4: 权益现货（深港） | E4: 权益现货 | F4: 股指期货 | G4: 权益类基金 | H4: 合计
A5: 成交笔数 | B5: 成交回报 | C5: =COUNTIFS('交易流水'!$X$2:$X$151,"*场内*") | D5: =COUNTIFS('交易流水'!$X$2:$X$151,"*深港*") | E5: =C5+D5 | F5: 0 | G5: 0 | H5: =C5+D5+F5+G5
A6: 买入笔数 | B6: 成交回报 | C6: =COUNTIFS('交易流水'!$X$2:$X$151,"*场内*",'交易流水'!$H$2:$H$151,"买入") | D6: =COUNTIFS('交易流水'!$X$2:$X$151,"*深港*",'交易流水'!$H$2:$H$151,"买入") | E6: =C6+D6 | F6: 0 | G6: 0 | H6: =C6+D6+F6+G6
A7: 卖出笔数 | B7: 成交回报 | C7: =COUNTIFS('交易流水'!$X$2:$X$151,"*场内*",'交易流水'!$H$2:$H$151,"卖出") | D7: =COUNTIFS('交易流水'!$X$2:$X$151,"*深港*",'交易流水'!$H$2:$H$151,"卖出") | E7: =C7+D7 | F7: 0 | G7: 0 | H7: =C7+D7+F7+G7
A8: 买入数量合计 | B8: 成交回报 | C8: =SUMIFS('交易流水'!$K$2:$K$151,'交易流水'!$X$2:$X$151,"*场内*",'交易流水'!$H$2:$H$151,"买入")/10000 | D8: =SUMIFS('交易流水'!$K$2:$K$151,'交易流水'!$X$2:$X$151,"*深港*",'交易流水'!$H$2:$H$151,"买入")/10000 | E8: =C8+D8 | F8: 0 | G8: 0 | H8: =C8+D8+F8+G8
A9: 卖出数量合计 | B9: 成交回报 | C9: =SUMIFS('交易流水'!$K$2:$K$151,'交易流水'!$X$2:$X$151,"*场内*",'交易流水'!$H$2:$H$151,"卖出")/10000 | D9: =SUMIFS('交易流水'!$K$2:$K$151,'交易流水'!$X$2:$X$151,"*深港*",'交易流水'!$H$2:$H$151,"卖出")/10000 | E9: =C9+D9 | F9: 0 | G9: 0 | H9: =C9+D9+F9+G9
A10: 买入金额合计(本币) | B10: 成交回报 | C10: =SUMIFS('交易流水'!$AR$2:$AR$151,'交易流水'!$X$2:$X$151,"*场内*",'交易流水'!$H$2:$H$151,"买入")/10000 | D10: =SUMIFS('交易流水'!$AR$2:$AR$151,'交易流水'!$X$2:$X$151,"*深港*",'交易流水'!$H$2:$H$151,"买入")/10000 | E10: =C10+D10 | F10: 0 | G10: 0 | H10: =C10+D10+F10+G10
A11: 卖出金额合计(本币) | B11: 成交回报 | C11: =SUMIFS('交易流水'!$AR$2:$AR$151,'交易流水'!$X$2:$X$151,"*场内*",'交易流水'!$H$2:$H$151,"卖出")/10000 | D11: =SUMIFS('交易流水'!$AR$2:$AR$151,'交易流水'!$X$2:$X$151,"*深港*",'交易流水'!$H$2:$H$151,"卖出")/10000 | E11: =C11+D11 | F11: 0 | G11: 0 | H11: =C11+D11+F11+G11
A12: 已实现损益（全账加权均价·含期初） | B12: 第三轨 | C12: =SUMIFS('逐笔辅助'!$AJ$2:$AJ$191,'逐笔辅助'!$A$2:$A$191,"流水",'逐笔辅助'!$D$2:$D$191,"场内") | D12: =SUMIFS('逐笔辅助'!$AJ$2:$AJ$191,'逐笔辅助'!$A$2:$A$191,"流水",'逐笔辅助'!$D$2:$D$191,"深港") | E12: =C12+D12 | F12: 0 | G12: 0 | H12: =C12+D12+F12+G12
A13: 浮动盈亏（全账净持仓·加权成本盯市） | B13: 第三轨 | C13: =SUMIFS('期末持仓'!$Q$2:$Q$56,'期末持仓'!$A$2:$A$56,"场内")-SUMIFS('期末持仓'!$O$2:$O$56,'期末持仓'!$A$2:$A$56,"场内") | D13: =SUMIFS('期末持仓'!$Q$2:$Q$56,'期末持仓'!$A$2:$A$56,"深港")-SUMIFS('期末持仓'!$O$2:$O$56,'期末持仓'!$A$2:$A$56,"深港") | E13: =C13+D13 | F13: 0 | G13: 0 | H13: =C13+D13+F13+G13
A14: 总损益（全账加权 + 浮动） | B14: 第三轨 | C14: =C12+C13 | D14: =D12+D13 | E14: =E12+E13 | F14: =F12+F13 | G14: =G12+G13 | H14: =C14+D14+F14+G14
A16: ▼ 三轨 RPNL 对比（仅已实现）
A17: 已实现损益（流水加权均价·运营轨） | B17: 运营轨对比 | C17: =SUMIFS('逐笔辅助'!$T$2:$T$191,'逐笔辅助'!$A$2:$A$191,"流水",'逐笔辅助'!$D$2:$D$191,"场内") | D17: =SUMIFS('逐笔辅助'!$T$2:$T$191,'逐笔辅助'!$A$2:$A$191,"流水",'逐笔辅助'!$D$2:$D$191,"深港") | E17: =C17+D17 | F17: 0 | G17: 0 | H17: =C17+D17+F17+G17
A18: 第三轨 − 运营轨（RPNL） | B18: 差额 | C18: =C12-C17 | D18: =D12-D17 | E18: =C12-C17+D12-D17 | F18: 0 | G18: 0 | H18: =C12-C17+D12-D17
A19: 已实现损益（FIFO·考核轨） | B19: 考核轨对比 | C19: =SUMIFS('逐笔辅助'!$U$2:$U$191,'逐笔辅助'!$A$2:$A$191,"流水",'逐笔辅助'!$D$2:$D$191,"场内") | D19: =SUMIFS('逐笔辅助'!$U$2:$U$191,'逐笔辅助'!$A$2:$A$191,"流水",'逐笔辅助'!$D$2:$D$191,"深港") | E19: =C19+D19 | F19: 0 | G19: 0 | H19: =C19+D19+F19+G19
A21: 期初投资（initial_capital）
A22: 自营权益4 | B22: 期初资金.xls | C22: 202510600
A23: 期初持仓成本合计 | C23: =SUM('期初批次'!$E$2:$E$41)
A24: 期初持仓市值合计 | C24: =SUM('期初批次'!$H$2:$H$41)

Sheet 交易流水
A1: 序号 | B1: 发生日期 | C1: 账户编号 | D1: 账户名称 | E1: 账户代码 | F1: 证券代码 | G1: 证券名称 | H1: 委托方向 | I1: 最新价 | J1: 市场成交均价 | K1: 成交数量 | L1: 成交金额 | M1: 成交次数 | N1: 成交最低价 | O1: 成交最高价 | P1: 成交均价 | Q1: 成交均价(全价) | R1: 成交均价(净价) | S1: 交易市场 | T1: 市场成交数量 | U1: 数量成交比例(%) | V1: 市场成交金额 | W1: 组合编号 | X1: 组合名称 | Y1: 委托数量 | Z1: 市场最高价 | AA1: 市场最低价 | AB1: 委托次数 | AC1: 操作员 | AD1: 资产类别 | AE1: 涨跌幅(%) | AF1: 金额成交比例(%) | AG1: 价格差额比例(%) | AH1: 指令数量 | AI1: 资产单元序号 | AJ1: 资产单元名称 | AK1: 交易币种 | AL1: 交易席位 | AM1: 投资类型 | AN1: 资产单元编号 | AO1: 股东代码 | AP1: 指令下达人 | AQ1: 本币币种 | AR1: 本币成交金额 | AS1: RIC | AT1: Bloomberg | AU1: CUSIP | AV1: SEDOL | AW1: ISIN | AX1: 指令操作级别 | AY1: 账户组类型 | AZ1: 账户组 | BA1: 成交金额占净值(%) | BB1: 券商编号 | BC1: 券商名称 | BD1: 业务分类 | BE1: 是否ETF补券 | BF1: 发生金额(全价) | BG1: 今开盘价 | BH1: 是否强平委托 | BI1: 代下达人 | BJ1: 是否强平 | BK1: 价格类型 | BL1: 杂项分类 | BM1: 平仓盈亏 | BN1: 成交时间(分) | BO1: 证券类别 | BP1: 交易对手 | BQ1: 对方席位号 | BR1: 交易实例序号 | BS1: 成交状态
A2: 1 | B2: 2026-01-13 | C2: 3008 | D2: 自营权益4 | E2: 3008 | F2: 601098 | G2: 中南传媒 | H2: 买入 | I2: 11.56 | J2: 11.68 | K2: 200000 | L2: 2330000 | M2: 73 | N2: 11.65 | O2: 11.65 | P2: 11.65 | Q2: 11.65 | R2: 11.65 | S2: 上交所A | T2: 25567700 | U2: 0.7822 | V2: 298680747 | W2: 300821 | X2: 自营权益4（场内） | Y2: 200000 | Z2: 11.93 | AA2: 11.52 | AB2: 1 | AC2: 叶盛 | AD2: 股票资产 | AE2: -1.1121 | AF2: 0.7801 | AG2: 0.2739 | AH2: 200000 | AI2: 46 | AJ2: 自营权益4（场内） | AK2: 人民币 | AL2: 40878 | AN2: 30082 | AP2: 顾吟湫 | AQ2: 人民币 | AR2: 2330000 | AS2: 601098 | AT2: 601098 | AU2: 601098 | AV2: 601098 | AW2: 601098 | AX2: 无 | BA2: 1.1409 | BB2: 0 | BC2: 缺省券商 | BD2: 交易所业务 | BE2: 不是ETF补券指令 | BF2: -2,330,000.00 | BG2: 11.81 | BH2: 非强平 | BI2: 顾吟湫 | BJ2: 否 | BK2: 限价 | BM2: 0 | BN2: 31.266667 | BO2: 股票 | BR2: 0 | BS2: 已成交
A3: 2 | B3: 2026-01-13 | C3: 3008 | D3: 自营权益4 | E3: 3008 | F3: 601900 | G3: 南方传媒 | H3: 卖出 | I3: 15.31 | J3: 16.03 | K3: 200000 | L3: 3267529 | M3: 64 | N3: 16.05 | O3: 16.58 | P3: 16.337645 | Q3: 16.337645 | R3: 16.337645 | S3: 上交所A | T3: 86139472 | U3: 0.2322 | V3: 1380565150 | W3: 300821 | X3: 自营权益4（场内） | Y3: 200000 | Z3: 16.58 | AA3: 15.3 | AB3: 4 | AC3: 叶盛 | AD3: 股票资产 | AE3: 1.5926 | AF3: 0.2367 | AG3: 1.9373 | AH3: 200000 | AI3: 46 | AJ3: 自营权益4（场内） | AK3: 人民币 | AL3: 40878 | AN3: 30082 | AP3: 顾吟湫 | AQ3: 人民币 | AR3: 3267529 | AX3: 无 | BA3: 1.5999 | BB3: 0 | BC3: 缺省券商 | BD3: 交易所业务 | BE3: 不是ETF补券指令 | BF3: 3,267,529.00 | BG3: 16.58 | BH3: 非强平 | BI3: 顾吟湫 | BJ3: 否 | BK3: 限价 | BM3: 0 | BN3: 2.7 | BO3: 股票 | BR3: 0 | BS3: 已成交
A4: 3 | B4: 2026-01-20 | C4: 3008 | D4: 自营权益4 | E4: 3008 | F4: 2318 | G4: 中国平安 | H4: 卖出 | I4: 69 | J4: 68.85 | K4: 10000 | L4: 690500 | M4: 6 | N4: 69.05 | O4: 69.05 | P4: 69.05 | Q4: 69.05 | R4: 69.05 | S4: 港股通（深） | T4: 30771432 | U4: 0.0325 | V4: 2.1187495e+09 | W4: 300841 | X4: 自营权益4（深港） | Y4: 60000 | Z4: 69.65 | AA4: 68.1 | AB4: 6 | AC4: 叶盛 | AD4: 股票资产 | AE4: 0.8772 | AF4: 0.0326 | AG4: 0.2841 | AH4: 20000 | AI4: 53 | AJ4: 自营权益4（深港） | AK4: 人民币 | AL4: 6111 | AN4: 30084 | AP4: 顾吟湫 | AQ4: 人民币 | AR4: 616271.25 | AW4: CNE1000003X6 | AX4: 无 | BA4: 0.3063 | BB4: 0 | BC4: 缺省券商 | BD4: 交易所业务 | BE4: 不是ETF补券指令 | BF4: 690,500.00 | BG4: 0 | BH4: 非强平 | BI4: 顾吟湫 | BJ4: 否 | BK4: 增强限价盘 | BM4: 0 | BN4: 7.8333333 | BO4: 股票 | BR4: 0 | BS4: 已成交
A5: 4 | B5: 2026-01-21 | C5: 3008 | D5: 自营权益4 | E5: 3008 | F5: 858 | G5: 五 粮 液 | H5: 卖出 | I5: 103.05 | J5: 103.4 | K5: 20000 | L5: 2060319 | M5: 20 | N5: 103 | O5: 103.02 | P5: 103.01595 | Q5: 103.01595 | R5: 103.01595 | S5: 深交所A | T5: 26228280 | U5: 0.0763 | V5: 2.7118849e+09 | W5: 300821 | X5: 自营权益4（场内） | Y5: 20000 | Z5: 104.7 | AA5: 103 | AB5: 1 | AC5: 叶盛 | AD5: 股票资产 | AE5: -1.7729 | AF5: 0.076 | AG5: -0.367 | AH5: 20000 | AI5: 46 | AJ5: 自营权益4（场内） | AK5: 人民币 | AL5: 6111 | AN5: 30082 | AP5: 顾吟湫 | AQ5: 人民币 | AR5: 2060319 | AS5: 858 | AT5: 858 | AU5: 858 | AV5: 858 | AW5: 000858 | AX5: 无 | BA5: 1.0334 | BB5: 0 | BC5: 缺省券商 | BD5: 交易所业务 | BE5: 不是ETF补券指令 | BF5: 2,060,319.00 | BG5: 104.62 | BH5: 非强平 | BI5: 顾吟湫 | BJ5: 否 | BK5: 限价 | BM5: 0 | BN5: 0 | BO5: 股票 | BR5: 0 | BS5: 已成交
A6: 5 | B6: 2026-01-22 | C6: 3008 | D6: 自营权益4 | E6: 3008 | F6: 603198 | G6: 迎驾贡酒 | H6: 卖出 | I6: 38.84 | J6: 38.85 | K6: 60000 | L6: 2329000 | M6: 93 | N6: 38.79 | O6: 38.95 | P6: 38.816667 | Q6: 38.816667 | R6: 38.816667 | S6: 上交所A | T6: 3329948 | U6: 1.8018 | V6: 129356872 | W6: 300821 | X6: 自营权益4（场内） | Y6: 60000 | Z6: 39.05 | AA6: 38.7 | AB6: 18 | AC6: 叶盛 | AD6: 股票资产 | AE6: -0.308 | AF6: 1.8004 | AG6: -0.0767 | AH6: 60000 | AI6: 46 | AJ6: 自营权益4（场内） | AK6: 人民币 | AL6: 40878 | AN6: 30082 | AP6: 顾吟湫 | AQ6: 人民币 | AR6: 2329000 | AS6: 603198 | AT6: 603198 | AU6: 603198 | AV6: 603198 | AW6: 603198 | AX6: 无 | BA6: 1.1648 | BB6: 0 | BC6: 缺省券商 | BD6: 交易所业务 | BE6: 不是ETF补券指令 | BF6: 2,329,000.00 | BG6: 38.94 | BH6: 非强平 | BI6: 顾吟湫 | BJ6: 否 | BK6: 限价 | BM6: 0 | BN6: 46.25 | BO6: 股票 | BR6: 0 | BS6: 已成交
A7: 6 | B7: 2026-01-22 | C7: 3008 | D7: 自营权益4 | E7: 3008 | F7: 603369 | G7: 今世缘 | H7: 卖出 | I7: 33.91 | J7: 34.06 | K7: 60000 | L7: 2042778 | M7: 110 | N7: 34.04 | O7: 34.06 | P7: 34.0463 | Q7: 34.0463 | R7: 34.0463 | S7: 上交所A | T7: 7359607 | U7: 0.8153 | V7: 250690671 | W7: 300821 | X7: 自营权益4（场内） | Y7: 60000 | Z7: 34.31 | AA7: 33.88 | AB7: 7 | AC7: 叶盛 | AD7: 股票资产 | AE7: -0.9059 | AF7: 0.8149 | AG7: -0.0493 | AH7: 60000 | AI7: 46 | AJ7: 自营权益4（场内） | AK7: 人民币 | AL7: 40878 | AN7: 30082 | AP7: 顾吟湫 | AQ7: 人民币 | AR7: 2042778 | AS7: 603369 | AT7: 603369 | AU7: 603369 | AV7: 603369 | AW7: 603369 | AX7: 无 | BA7: 1.0217 | BB7: 0 | BC7: 缺省券商 | BD7: 交易所业务 | BE7: 不是ETF补券指令 | BF7: 2,042,778.00 | BG7: 34.2 | BH7: 非强平 | BI7: 顾吟湫 | BJ7: 否 | BK7: 限价 | BM7: 0 | BN7: 26.616667 | BO7: 股票 | BR7: 0 | BS7: 已成交
A8: 7 | B8: 2026-01-22 | C8: 3008 | D8: 自营权益4 | E8: 3008 | F8: 788 | G8: 中国铁塔 | H8: 买入 | I8: 11.46 | J8: 11.42 | K8: 300000 | L8: 3426200 | M8: 65 | N8: 11.4 | O8: 11.44 | P8: 11.420667 | Q8: 11.420667 | R8: 11.420667 | S8: 港股通（深） | T8: 11116072 | U8: 2.6988 | V8: 1.2690714e+08 | W8: 300841 | X8: 自营权益4（深港） | Y8: 300000 | Z8: 11.46 | AA8: 11.35 | AB8: 9 | AC8: 叶盛 | AD8: 股票资产 | AE8: 0.5263 | AF8: 2.6998 | AG8: -0.0368 | AH8: 300000 | AI8: 53 | AJ8: 自营权益4（深港） | AK8: 人民币 | AL8: 6111 | AN8: 30084 | AP8: 顾吟湫 | AQ8: 人民币 | AR8: 3058945.6 | AW8: CNE100006V65 | AX8: 无 | BA8: 1.5299 | BB8: 0 | BC8: 缺省券商 | BD8: 交易所业务 | BE8: 不是ETF补券指令 | BF8: -3,426,200.00 | BG8: 0 | BH8: 非强平 | BI8: 顾吟湫 | BJ8: 否 | BK8: 增强限价盘 | BM8: 0 | BN8: 61.383333 | BO8: 股票 | BR8: 0 | BS8: 已成交
A9: 8 | B9: 2026-01-23 | C9: 3008 | D9: 自营权益4 | E9: 3008 | F9: 788 | G9: 中国铁塔 | H9: 买入 | I9: 11.38 | J9: 11.38 | K9: 100000 | L9: 1137000 | M9: 26 | N9: 11.37 | O9: 11.37 | P9: 11.37 | Q9: 11.37 | R9: 11.37 | S9: 港股通（深） | T9: 9203678 | U9: 1.0865 | V9: 1.0476768e+08 | W9: 300841 | X9: 自营权益4（深港） | Y9: 100000 | Z9: 11.46 | AA9: 11.35 | AB9: 1 | AC9: 叶盛 | AD9: 股票资产 | AE9: -0.6981 | AF9: 1.0853 | AG9: 0.116 | AH9: 100000 | AI9: 53 | AJ9: 自营权益4（深港） | AK9: 人民币 | AL9: 6111 | AN9: 30084 | AP9: 顾吟湫 | AQ9: 人民币 | AR9: 1014897.6 | AW9: CNE100006V65 | AX9: 无 | BA9: 0.5178 | BB9: 0 | BC9: 缺省券商 | BD9: 交易所业务 | BE9: 不是ETF补券指令 | BF9: -1,137,000.00 | BG9: 0 | BH9: 非强平 | BI9: 顾吟湫 | BJ9: 否 | BK9: 增强限价盘 | BM9: 0 | BN9: 0 | BO9: 股票 | BR9: 0 | BS9: 已成交
A10: 9 | B10: 2026-01-26 | C10: 3008 | D10: 自营权益4 | E10: 3008 | F10: 600519 | G10: 贵州茅台 | H10: 卖出 | I10: 1342 | J10: 1341.12 | K10: 100 | L10: 134750 | M10: 1 | N10: 1347.5 | O10: 1347.5 | P10: 1347.5 | Q10: 1347.5 | R10: 1347.5 | S10: 上交所A | T10: 8016606 | U10: 0.0012 | V10: 10751225525 | W10: 300821 | X10: 自营权益4（场内） | Y10: 100 | Z10: 1355 | AA10: 1325.12 | AB10: 1 | AC10: 叶盛 | AD10: 股票资产 | AE10: 0.374 | AF10: 0.0013 | AG10: 0.4758 | AH10: 100 | AI10: 46 | AJ10: 自营权益4（场内） | AK10: 人民币 | AL10: 40878 | AN10: 30082 | AP10: 顾吟湫 | AQ10: 人民币 | AR10: 134750 | AS10: 600519 | AT10: 600519 | AU10: 600519 | AV10: 600519 | AW10: 600519 | AX10: 无 | BA10: 0.0688 | BB10: 0 | BC10: 缺省券商 | BD10: 交易所业务 | BE10: 不是ETF补券指令 | BF10: 134,750.00 | BG10: 1340.51 | BH10: 非强平 | BI10: 顾吟湫 | BJ10: 否 | BK10: 限价 | BM10: 0 | BN10: 0.016666667 | BO10: 股票 | BR10: 0 | BS10: 已成交
A11: 10 | B11: 2026-01-26 | C11: 3008 | D11: 自营权益4 | E11: 3008 | F11: 322 | G11: 康师傅控股 | H11: 买入 | I11: 11.64 | J11: 11.7 | K11: 50000 | L11: 577500 | M11: 19 | N11: 11.55 | O11: 11.55 | P11: 11.55 | Q11: 11.55 | R11: 11.55 | S11: 港股通（深） | T11: 18004148 | U11: 0.2777 | V11: 2.1064094e+08 | W11: 300841 | X11: 自营权益4（深港） | Y11: 50000 | Z11: 12.4 | AA11: 11.5 | AB11: 1 | AC11: 叶盛 | AD11: 股票资产 | AE11: -4.5902 | AF11: 0.2742 | AG11: 1.2787 | AH11: 50000 | AI11: 53 | AJ11: 自营权益4（深港） | AK11: 人民币 | AL11: 6111 | AN11: 30084 | AP11: 顾吟湫 | AQ11: 人民币 | AR11: 515545.76 | AW11: KYG8878S1030 | AX11: 无 | BA11: 0.263 | BB11: 0 | BC11: 缺省券商 | BD11: 交易所业务 | BE11: 不是ETF补券指令 | BF11: -577,500.00 | BG11: 0 | BH11: 非强平 | BI11: 顾吟湫 | BJ11: 否 | BK11: 增强限价盘 | BM11: 0 | BN11: 4.4166667 | BO11: 股票 | BR11: 0 | BS11: 已成交
A12: 11 | B12: 2026-01-26 | C12: 3008 | D12: 自营权益4 | E12: 3008 | F12: 2607 | G12: 上海医药 | H12: 卖出 | I12: 12.12 | J12: 12.06 | K12: 100000 | L12: 1206000 | M12: 13 | N12: 12.05 | O12: 12.07 | P12: 12.06 | Q12: 12.06 | R12: 12.06 | S12: 港股通（深） | T12: 2259945 | U12: 4.4249 | V12: 27259166 | W12: 300841 | X12: 自营权益4（深港） | Y12: 100000 | Z12: 12.12 | AA12: 11.94 | AB12: 3 | AC12: 叶盛 | AD12: 股票资产 | AE12: 1.1686 | AF12: 4.4242 | AG12: -0.0158 | AH12: 100000 | AI12: 53 | AJ12: 自营权益4（深港） | AK12: 人民币 | AL12: 6111 | AN12: 30084 | AP12: 顾吟湫 | AQ12: 人民币 | AR12: 1076572.1 | AW12: CNE1000012B3 | AX12: 无 | BA12: 0.5493 | BB12: 0 | BC12: 缺省券商 | BD12: 交易所业务 | BE12: 不是ETF补券指令 | BF12: 1,206,000.00 | BG12: 0 | BH12: 非强平 | BI12: 顾吟湫 | BJ12: 否 | BK12: 增强限价盘 | BM12: 0 | BN12: 2.0833333 | BO12: 股票 | BR12: 0 | BS12: 已成交
A13: 12 | B13: 2026-01-27 | C13: 3008 | D13: 自营权益4 | E13: 3008 | F13: 2318 | G13: 中国平安 | H13: 卖出 | I13: 69.7 | J13: 69.48 | K13: 10000 | L13: 689500 | M13: 4 | N13: 68.95 | O13: 68.95 | P13: 68.95 | Q13: 68.95 | R13: 68.95 | S13: 港股通（深） | T13: 47392544 | U13: 0.0211 | V13: 3.2928292e+09 | W13: 300841 | X13: 自营权益4（深港） | Y13: 10000 | Z13: 70.05 | AA13: 67.9 | AB13: 2 | AC13: 叶盛 | AD13: 股票资产 | AE13: 2.3495 | AF13: 0.0209 | AG13: -0.7627 | AH13: 10000 | AI13: 53 | AJ13: 自营权益4（深港） | AK13: 人民币 | AL13: 6111 | AN13: 30084 | AP13: 顾吟湫 | AQ13: 人民币 | AR13: 615034 | AW13: CNE1000003X6 | AX13: 无 | BA13: 0.3138 | BB13: 0 | BC13: 缺省券商 | BD13: 交易所业务 | BE13: 不是ETF补券指令 | BF13: 689,500.00 | BG13: 0 | BH13: 非强平 | BI13: 顾吟湫 | BJ13: 否 | BK13: 增强限价盘 | BM13: 0 | BN13: 0.066666667 | BO13: 股票 | BR13: 0 | BS13: 已成交
A14: 13 | B14: 2026-01-28 | C14: 3008 | D14: 自营权益4 | E14: 3008 | F14: 600036 | G14: 招商银行 | H14: 买入 | I14: 37.8 | J14: 38 | K14: 28100 | L14: 1070084 | M14: 8 | N14: 38.03 | O14: 38.14 | P14: 38.081281 | Q14: 38.081281 | R14: 38.081281 | S14: 上交所A | T14: 204166688 | U14: 0.0138 | V14: 7757392685 | W14: 300821 | X14: 自营权益4（场内） | Y14: 28100 | Z14: 38.44 | AA14: 37.7 | AB14: 2 | AC14: 叶盛 | AD14: 股票资产 | AE14: -0.7874 | AF14: 0.0138 | AG14: -0.2261 | AH14: 28100 | AI14: 46 | AJ14: 自营权益4（场内） | AK14: 人民币 | AL14: 40878 | AN14: 30082 | AP14: 顾吟湫 | AQ14: 人民币 | AR14: 1070084 | AS14: 600036 | AT14: 600036 | AU14: 600036 | AV14: 600036 | AW14: 600036 | AX14: 无 | BA14: 0.5342 | BB14: 0 | BC14: 缺省券商 | BD14: 交易所业务 | BE14: 不是ETF补券指令 | BF14: -1,070,084.00 | BG14: 38.12 | BH14: 非强平 | BI14: 顾吟湫 | BJ14: 否 | BK14: 限价 | BM14: 0 | BN14: 0.083333333 | BO14: 股票 | BR14: 0 | BS14: 已成交
A15: 14 | B15: 2026-01-28 | C15: 3008 | D15: 自营权益4 | E15: 3008 | F15: 601166 | G15: 兴业银行 | H15: 买入 | I15: 18.55 | J15: 18.67 | K15: 50100 | L15: 934330 | M15: 33 | N15: 18.64 | O15: 18.66 | P15: 18.649301 | Q15: 18.649301 | R15: 18.649301 | S15: 上交所A | T15: 204522726 | U15: 0.0245 | V15: 3817641687 | W15: 300821 | X15: 自营权益4（场内） | Y15: 50100 | Z15: 18.89 | AA15: 18.51 | AB15: 3 | AC15: 叶盛 | AD15: 股票资产 | AE15: -1.4346 | AF15: 0.0245 | AG15: 0.09 | AH15: 50100 | AI15: 46 | AJ15: 自营权益4（场内） | AK15: 人民币 | AL15: 40878 | AN15: 30082 | AP15: 顾吟湫 | AQ15: 人民币 | AR15: 934330 | AS15: 601166 | AT15: 601166 | AU15: 601166 | AV15: 601166 | AW15: 601166 | AX15: 无 | BA15: 0.4665 | BB15: 0 | BC15: 缺省券商 | BD15: 交易所业务 | BE15: 不是ETF补券指令 | BF15: -934,330.00 | BG15: 18.81 | BH15: 非强平 | BI15: 顾吟湫 | BJ15: 否 | BK15: 限价 | BM15: 0 | BN15: 2.0333333 | BO15: 股票 | BR15: 0 | BS15: 已成交
A16: 15 | B16: 2026-02-05 | C16: 3008 | D16: 自营权益4 | E16: 3008 | F16: 600036 | G16: 招商银行 | H16: 买入 | I16: 39.71 | J16: 39.46 | K16: 21900 | L16: 860633 | M16: 34 | N16: 38.97 | O16: 39.33 | P16: 39.298311 | Q16: 39.298311 | R16: 39.298311 | S16: 上交所A | T16: 121889452 | U16: 0.018 | V16: 4810048757 | W16: 300821 | X16: 自营权益4（场内） | Y16: 21900 | Z16: 39.92 | AA16: 38.91 | AB16: 3 | AC16: 叶盛 | AD16: 股票资产 | AE16: 1.7944 | AF16: 0.0179 | AG16: 0.4158 | AH16: 21900 | AI16: 46 | AJ16: 自营权益4（场内） | AK16: 人民币 | AL16: 40878 | AN16: 30082 | AP16: 顾吟湫 | AQ16: 人民币 | AR16: 860633 | AS16: 600036 | AT16: 600036 | AU16: 600036 | AV16: 600036 | AW16: 600036 | AX16: 无 | BA16: 0.4241 | BB16: 0 | BC16: 缺省券商 | BD16: 交易所业务 | BE16: 不是ETF补券指令 | BF16: -860,633.00 | BG16: 38.94 | BH16: 非强平 | BI16: 顾吟湫 | BJ16: 否 | BK16: 限价 | BM16: 0 | BN16: 11.766667 | BO16: 股票 | BR16: 0 | BS16: 已成交
A17: 16 | B17: 2026-02-05 | C17: 3008 | D17: 自营权益4 | E17: 3008 | F17: 601166 | G17: 兴业银行 | H17: 买入 | I17: 19.38 | J17: 19.34 | K17: 49900 | L17: 961478 | M17: 46 | N17: 19.22 | O17: 19.28 | P17: 19.268096 | Q17: 19.268096 | R17: 19.268096 | S17: 上交所A | T17: 119848229 | U17: 0.0416 | V17: 2318435836 | W17: 300821 | X17: 自营权益4（场内） | Y17: 49900 | Z17: 19.49 | AA17: 19.2 | AB17: 2 | AC17: 叶盛 | AD17: 股票资产 | AE17: 1.0428 | AF17: 0.0415 | AG17: 0.3965 | AH17: 49900 | AI17: 46 | AJ17: 自营权益4（场内） | AK17: 人民币 | AL17: 40878 | AN17: 30082 | AP17: 顾吟湫 | AQ17: 人民币 | AR17: 961478 | AS17: 601166 | AT17: 601166 | AU17: 601166 | AV17: 601166 | AW17: 601166 | AX17: 无 | BA17: 0.4738 | BB17: 0 | BC17: 缺省券商 | BD17: 交易所业务 | BE17: 不是ETF补券指令 | BF17: -961,478.00 | BG17: 19.2 | BH17: 非强平 | BI17: 顾吟湫 | BJ17: 否 | BK17: 限价 | BM17: 0 | BN17: 2.1 | BO17: 股票 | BR17: 0 | BS17: 已成交
A18: 17 | B18: 2026-02-09 | C18: 3008 | D18: 自营权益4 | E18: 3008 | F18: 600036 | G18: 招商银行 | H18: 买入 | I18: 39.48 | J18: 39.48 | K18: 40000 | L18: 1576800 | M18: 41 | N18: 39.42 | O18: 39.42 | P18: 39.42 | Q18: 39.42 | R18: 39.42 | S18: 上交所A | T18: 65894891 | U18: 0.0607 | V18: 2601539089 | W18: 300821 | X18: 自营权益4（场内） | Y18: 40000 | Z18: 39.74 | AA18: 39.33 | AB18: 1 | AC18: 叶盛 | AD18: 股票资产 | AE18: -0.303 | AF18: 0.0606 | AG18: 0.1522 | AH18: 40000 | AI18: 46 | AJ18: 自营权益4（场内） | AK18: 人民币 | AL18: 40878 | AN18: 30082 | AP18: 顾吟湫 | AQ18: 人民币 | AR18: 1576800 | AS18: 600036 | AT18: 600036 | AU18: 600036 | AV18: 600036 | AW18: 600036 | AX18: 无 | BA18: 0.7781 | BB18: 0 | BC18: 缺省券商 | BD18: 交易所业务 | BE18: 不是ETF补券指令 | BF18: -1,576,800.00 | BG18: 39.6 | BH18: 非强平 | BI18: 顾吟湫 | BJ18: 否 | BK18: 限价 | BM18: 0 | BN18: 42.533333 | BO18: 股票 | BR18: 0 | BS18: 已成交
A19: 18 | B19: 2026-02-09 | C19: 3008 | D19: 自营权益4 | E19: 3008 | F19: 601009 | G19: 南京银行 | H19: 卖出 | I19: 11.26 | J19: 11.2 | K19: 300000 | L19: 3372000 | M19: 23 | N19: 11.24 | O19: 11.24 | P19: 11.24 | Q19: 11.24 | R19: 11.24 | S19: 上交所A | T19: 52474996 | U19: 0.5717 | V19: 587653443 | W19: 300821 | X19: 自营权益4（场内） | Y19: 300000 | Z19: 11.29 | AA19: 11.05 | AB19: 1 | AC19: 叶盛 | AD19: 股票资产 | AE19: 0.9865 | AF19: 0.5738 | AG19: 0.3688 | AH19: 300000 | AI19: 46 | AJ19: 自营权益4（场内） | AK19: 人民币 | AL19: 40878 | AN19: 30082 | AP19: 顾吟湫 | AQ19: 人民币 | AR19: 3372000 | AS19: 601009 | AT19: 601009 | AU19: 601009 | AV19: 601009 | AW19: 601009 | AX19: 无 | BA19: 1.6639 | BB19: 0 | BC19: 缺省券商 | BD19: 交易所业务 | BE19: 不是ETF补券指令 | BF19: 3,372,000.00 | BG19: 11.1 | BH19: 非强平 | BI19: 顾吟湫 | BJ19: 否 | BK19: 限价 | BM19: 0 | BN19: 0.38333333 | BO19: 股票 | BR19: 0 | BS19: 已成交
A20: 19 | B20: 2026-02-09 | C20: 3008 | D20: 自营权益4 | E20: 3008 | F20: 601166 | G20: 兴业银行 | H20: 买入 | I20: 18.88 | J20: 18.86 | K20: 90000 | L20: 1699200 | M20: 149 | N20: 18.88 | O20: 18.88 | P20: 18.88 | Q20: 18.88 | R20: 18.88 | S20: 上交所A | T20: 64439529 | U20: 0.1397 | V20: 1215569554 | W20: 300821 | X20: 自营权益4（场内） | Y20: 90000 | Z20: 18.97 | AA20: 18.76 | AB20: 1 | AC20: 叶盛 | AD20: 股票资产 | AE20: 0.1592 | AF20: 0.1398 | AG20: -0.0864 | AH20: 90000 | AI20: 46 | AJ20: 自营权益4（场内） | AK20: 人民币 | AL20: 40878 | AN20: 30082 | AP20: 顾吟湫 | AQ20: 人民币 | AR20: 1699200 | AS20: 601166 | AT20: 601166 | AU20: 601166 | AV20: 601166 | AW20: 601166 | AX20: 无 | BA20: 0.8385 | BB20: 0 | BC20: 缺省券商 | BD20: 交易所业务 | BE20: 不是ETF补券指令 | BF20: -1,699,200.00 | BG20: 18.85 | BH20: 非强平 | BI20: 顾吟湫 | BJ20: 否 | BK20: 限价 | BM20: 0 | BN20: 2.0833333 | BO20: 股票 | BR20: 0 | BS20: 已成交
A21: 20 | B21: 2026-02-09 | C21: 3008 | D21: 自营权益4 | E21: 3008 | F21: 2319 | G21: 蒙牛乳业 | H21: 卖出 | I21: 17.47 | J21: 17.62 | K21: 10000 | L21: 175400 | M21: 1 | N21: 17.54 | O21: 17.54 | P21: 17.54 | Q21: 17.54 | R21: 17.54 | S21: 港股通（深） | T21: 36756086 | U21: 0.0272 | V21: 6.4764329e+08 | W21: 300841 | X21: 自营权益4（深港） | Y21: 10000 | Z21: 17.88 | AA21: 17.45 | AB21: 1 | AC21: 叶盛 | AD21: 股票资产 | AE21: -1.1319 | AF21: 0.0271 | AG21: -0.454 | AH21: 10000 | AI21: 53 | AJ21: 自营权益4（深港） | AK21: 人民币 | AL21: 6111 | AN21: 30084 | AP21: 顾吟湫 | AQ21: 人民币 | AR21: 155786.77 | AW21: KYG210961051 | AX21: 无 | BA21: 0.0769 | BB21: 0 | BC21: 缺省券商 | BD21: 交易所业务 | BE21: 不是ETF补券指令 | BF21: 175,400.00 | BG21: 0 | BH21: 非强平 | BI21: 顾吟湫 | BJ21: 否 | BK21: 增强限价盘 | BM21: 0 | BN21: 0.76666667 | BO21: 股票 | BR21: 0 | BS21: 已成交
A22: 21 | B22: 2026-02-09 | C22: 3008 | D22: 自营权益4 | E22: 3008 | F22: 3988 | G22: 中国银行 | H22: 卖出 | I22: 4.7 | J22: 4.69 | K22: 100000 | L22: 469000 | M22: 2 | N22: 4.69 | O22: 4.69 | P22: 4.69 | Q22: 4.69 | R22: 4.69 | S22: 港股通（深） | T22: 125338863 | U22: 0.0798 | V22: 5.8794872e+08 | W22: 300841 | X22: 自营权益4（深港） | Y22: 100000 | Z22: 4.73 | AA22: 4.66 | AB22: 1 | AC22: 叶盛 | AD22: 股票资产 | AE22: 0.8584 | AF22: 0.0798 | AG22: -0.0192 | AH22: 100000 | AI22: 53 | AJ22: 自营权益4（深港） | AK22: 人民币 | AL22: 6111 | AN22: 30084 | AP22: 顾吟湫 | AQ22: 人民币 | AR22: 416556.42 | AW22: CNE1000001Z5 | AX22: 无 | BA22: 0.2056 | BB22: 0 | BC22: 缺省券商 | BD22: 交易所业务 | BE22: 不是ETF补券指令 | BF22: 469,000.00 | BG22: 0 | BH22: 非强平 | BI22: 顾吟湫 | BJ22: 否 | BK22: 增强限价盘 | BM22: 0 | BN22: 20.133333 | BO22: 股票 | BR22: 0 | BS22: 已成交
A23: 22 | B23: 2026-02-10 | C23: 3008 | D23: 自营权益4 | E23: 3008 | F23: 600809 | G23: 山西汾酒 | H23: 卖出 | I23: 170.28 | J23: 170.77 | K23: 9000 | L23: 1532820 | M23: 41 | N23: 170.3 | O23: 170.34 | P23: 170.31333 | Q23: 170.31333 | R23: 170.31333 | S23: 上交所A | T23: 6789052 | U23: 0.1326 | V23: 1159371222 | W23: 300821 | X23: 自营权益4（场内） | Y23: 9000 | Z23: 174.12 | AA23: 169.61 | AB23: 2 | AC23: 叶盛 | AD23: 股票资产 | AE23: -2.5301 | AF23: 0.1322 | AG23: -0.2678 | AH23: 9000 | AI23: 46 | AJ23: 自营权益4（场内） | AK23: 人民币 | AL23: 40878 | AN23: 30082 | AP23: 顾吟湫 | AQ23: 人民币 | AR23: 1532820 | AS23: 600809 | AT23: 600809 | AU23: 600809 | AV23: 600809 | AW23: 600809 | AX23: 无 | BA23: 0.7542 | BB23: 0 | BC23: 缺省券商 | BD23: 交易所业务 | BE23: 不是ETF补券指令 | BF23: 1,532,820.00 | BG23: 174 | BH23: 非强平 | BI23: 顾吟湫 | BJ23: 否 | BK23: 限价 | BM23: 0 | BN23: 8.6333333 | BO23: 股票 | BR23: 0 | BS23: 已成交
A24: 23 | B24: 2026-02-10 | C24: 3008 | D24: 自营权益4 | E24: 3008 | F24: 600887 | G24: 伊利股份 | H24: 买入 | I24: 26.75 | J24: 26.75 | K24: 20000 | L24: 535200 | M24: 5 | N24: 26.76 | O24: 26.76 | P24: 26.76 | Q24: 26.76 | R24: 26.76 | S24: 上交所A | T24: 56476485 | U24: 0.0354 | V24: 1510541822 | W24: 300821 | X24: 自营权益4（场内） | Y24: 20000 | Z24: 27.03 | AA24: 26.64 | AB24: 1 | AC24: 叶盛 | AD24: 股票资产 | AE24: -1.2186 | AF24: 0.0354 | AG24: -0.0508 | AH24: 20000 | AI24: 46 | AJ24: 自营权益4（场内） | AK24: 人民币 | AL24: 40878 | AN24: 30082 | AP24: 顾吟湫 | AQ24: 人民币 | AR24: 535200 | AS24: 600887 | AT24: 600887 | AU24: 600887 | AV24: 600887 | AW24: 600887 | AX24: 无 | BA24: 0.2633 | BB24: 0 | BC24: 缺省券商 | BD24: 交易所业务 | BE24: 不是ETF补券指令 | BF24: -535,200.00 | BG24: 27.03 | BH24: 非强平 | BI24: 顾吟湫 | BJ24: 否 | BK24: 限价 | BM24: 0 | BN24: 0 | BO24: 股票 | BR24: 0 | BS24: 已成交
A25: 24 | B25: 2026-02-10 | C25: 3008 | D25: 自营权益4 | E25: 3008 | F25: 600919 | G25: 江苏银行 | H25: 买入 | I25: 10.48 | J25: 10.48 | K25: 150000 | L25: 1572000 | M25: 108 | N25: 10.48 | O25: 10.48 | P25: 10.48 | Q25: 10.48 | R25: 10.48 | S25: 上交所A | T25: 66595470 | U25: 0.2252 | V25: 698017694 | W25: 300821 | X25: 自营权益4（场内） | Y25: 150000 | Z25: 10.54 | AA25: 10.43 | AB25: 2 | AC25: 叶盛 | AD25: 股票资产 | AE25: 0.4794 | AF25: 0.2252 | AG25: 0.0143 | AH25: 150000 | AI25: 46 | AJ25: 自营权益4（场内） | AK25: 人民币 | AL25: 40878 | AN25: 30082 | AP25: 顾吟湫 | AQ25: 人民币 | AR25: 1572000 | AX25: 无 | BA25: 0.7734 | BB25: 0 | BC25: 缺省券商 | BD25: 交易所业务 | BE25: 不是ETF补券指令 | BF25: -1,572,000.00 | BG25: 10.43 | BH25: 非强平 | BI25: 顾吟湫 | BJ25: 否 | BK25: 限价 | BM25: 0 | BN25: 0 | BO25: 股票 | BR25: 0 | BS25: 已成交
A26: 25 | B26: 2026-02-10 | C26: 3008 | D26: 自营权益4 | E26: 3008 | F26: 601166 | G26: 兴业银行 | H26: 买入 | I26: 18.82 | J26: 18.86 | K26: 10000 | L26: 188250 | M26: 2 | N26: 18.82 | O26: 18.83 | P26: 18.825 | Q26: 18.825 | R26: 18.825 | S26: 上交所A | T26: 51870605 | U26: 0.0193 | V26: 978050860 | W26: 300821 | X26: 自营权益4（场内） | Y26: 10000 | Z26: 18.96 | AA26: 18.8 | AB26: 2 | AC26: 叶盛 | AD26: 股票资产 | AE26: -0.3178 | AF26: 0.0192 | AG26: 0.1623 | AH26: 10000 | AI26: 46 | AJ26: 自营权益4（场内） | AK26: 人民币 | AL26: 40878 | AN26: 30082 | AP26: 顾吟湫 | AQ26: 人民币 | AR26: 188250 | AS26: 601166 | AT26: 601166 | AU26: 601166 | AV26: 601166 | AW26: 601166 | AX26: 无 | BA26: 0.0926 | BB26: 0 | BC26: 缺省券商 | BD26: 交易所业务 | BE26: 不是ETF补券指令 | BF26: -188,250.00 | BG26: 18.88 | BH26: 非强平 | BI26: 顾吟湫 | BJ26: 否 | BK26: 限价 | BM26: 0 | BN26: 1.7833333 | BO26: 股票 | BR26: 0 | BS26: 已成交
A27: 26 | B27: 2026-02-10 | C27: 3008 | D27: 自营权益4 | E27: 3008 | F27: 601825 | G27: 沪农商行 | H27: 买入 | I27: 8.64 | J27: 8.62 | K27: 120000 | L27: 1035600 | M27: 76 | N27: 8.63 | O27: 8.63 | P27: 8.63 | Q27: 8.63 | R27: 8.63 | S27: 上交所A | T27: 15048230 | U27: 0.7974 | V27: 129756751 | W27: 300821 | X27: 自营权益4（场内） | Y27: 120000 | Z27: 8.66 | AA27: 8.56 | AB27: 2 | AC27: 叶盛 | AD27: 股票资产 | AE27: 0.6993 | AF27: 0.7981 | AG27: -0.0847 | AH27: 120000 | AI27: 46 | AJ27: 自营权益4（场内） | AK27: 人民币 | AL27: 40878 | AN27: 30082 | AP27: 顾吟湫 | AQ27: 人民币 | AR27: 1035600 | AX27: 无 | BA27: 0.5095 | BB27: 0 | BC27: 缺省券商 | BD27: 交易所业务 | BE27: 不是ETF补券指令 | BF27: -1,035,600.00 | BG27: 8.6 | BH27: 非强平 | BI27: 顾吟湫 | BJ27: 否 | BK27: 限价 | BM27: 0 | BN27: 180.08333 | BO27: 股票 | BR27: 0 | BS27: 已成交
A28: 27 | B28: 2026-02-10 | C28: 3008 | D28: 自营权益4 | E28: 3008 | F28: 568 | G28: 泸州老窖 | H28: 卖出 | I28: 118.19 | J28: 118.35 | K28: 15000 | L28: 1769314 | M28: 38 | N28: 117.95 | O28: 118.03 | P28: 117.95427 | Q28: 117.95427 | R28: 117.95427 | S28: 深交所A | T28: 12866212 | U28: 0.1166 | V28: 1.5226833e+09 | W28: 300821 | X28: 自营权益4（场内） | Y28: 15000 | Z28: 121 | AA28: 117.6 | AB28: 2 | AC28: 叶盛 | AD28: 股票资产 | AE28: -2.5559 | AF28: 0.1162 | AG28: -0.3322 | AH28: 15000 | AI28: 46 | AJ28: 自营权益4（场内） | AK28: 人民币 | AL28: 6111 | AN28: 30082 | AP28: 顾吟湫 | AQ28: 人民币 | AR28: 1769314 | AS28: 568 | AT28: 568 | AU28: 568 | AV28: 568 | AW28: 000568 | AX28: 无 | BA28: 0.8705 | BB28: 0 | BC28: 缺省券商 | BD28: 交易所业务 | BE28: 不是ETF补券指令 | BF28: 1,769,314.00 | BG28: 121 | BH28: 非强平 | BI28: 顾吟湫 | BJ28: 否 | BK28: 限价 | BM28: 0 | BN28: 30.483333 | BO28: 股票 | BR28: 0 | BS28: 已成交
A29: 28 | B29: 2026-02-11 | C29: 3008 | D29: 自营权益4 | E29: 3008 | F29: 600036 | G29: 招商银行 | H29: 买入 | I29: 39.4 | J29: 39.34 | K29: 10000 | L29: 393353 | M29: 5 | N29: 39.33 | O29: 39.34 | P29: 39.3353 | Q29: 39.3353 | R29: 39.3353 | S29: 上交所A | T29: 52881696 | U29: 0.0189 | V29: 2080370293 | W29: 300821 | X29: 自营权益4（场内） | Y29: 10000 | Z29: 39.45 | AA29: 39.2 | AB29: 1 | AC29: 叶盛 | AD29: 股票资产 | AE29: 0.1525 | AF29: 0.0189 | AG29: 0.0122 | AH29: 10000 | AI29: 46 | AJ29: 自营权益4（场内） | AK29: 人民币 | AL29: 40878 | AN29: 30082 | AP29: 顾吟湫 | AQ29: 人民币 | AR29: 393353 | AS29: 600036 | AT29: 600036 | AU29: 600036 | AV29: 600036 | AW29: 600036 | AX29: 无 | BA29: 0.1927 | BB29: 0 | BC29: 缺省券商 | BD29: 交易所业务 | BE29: 不是ETF补券指令 | BF29: -393,353.00 | BG29: 39.36 | BH29: 非强平 | BI29: 顾吟湫 | BJ29: 否 | BK29: 限价 | BM29: 0 | BN29: 0 | BO29: 股票 | BR29: 0 | BS29: 已成交
A30: 29 | B30: 2026-02-12 | C30: 3008 | D30: 自营权益4 | E30: 3008 | F30: 600809 | G30: 山西汾酒 | H30: 卖出 | I30: 166.31 | J30: 166.8 | K30: 7000 | L30: 1177820 | M30: 3 | N30: 168.26 | O30: 168.26 | P30: 168.26 | Q30: 168.26 | R30: 168.26 | S30: 上交所A | T30: 5856835 | U30: 0.1195 | V30: 976918471 | W30: 300821 | X30: 自营权益4（场内） | Y30: 7000 | Z30: 169.18 | AA30: 165.82 | AB30: 2 | AC30: 叶盛 | AD30: 股票资产 | AE30: -1.9745 | AF30: 0.1206 | AG30: 0.8755 | AH30: 7000 | AI30: 46 | AJ30: 自营权益4（场内） | AK30: 人民币 | AL30: 40878 | AN30: 30082 | AP30: 顾吟湫 | AQ30: 人民币 | AR30: 1177820 | AS30: 600809 | AT30: 600809 | AU30: 600809 | AV30: 600809 | AW30: 600809 | AX30: 无 | BA30: 0.5844 | BB30: 0 | BC30: 缺省券商 | BD30: 交易所业务 | BE30: 不是ETF补券指令 | BF30: 1,177,820.00 | BG30: 168.5 | BH30: 非强平 | BI30: 顾吟湫 | BJ30: 否 | BK30: 限价 | BM30: 0 | BN30: 0.13333333 | BO30: 股票 | BR30: 0 | BS30: 已成交
A31: 30 | B31: 2026-02-12 | C31: 3008 | D31: 自营权益4 | E31: 3008 | F31: 568 | G31: 泸州老窖 | H31: 卖出 | I31: 115.62 | J31: 116.15 | K31: 10000 | L31: 1171300 | M31: 8 | N31: 117.13 | O31: 117.13 | P31: 117.13 | Q31: 117.13 | R31: 117.13 | S31: 深交所A | T31: 9332215 | U31: 0.1072 | V31: 1.0839812e+09 | W31: 300821 | X31: 自营权益4（场内） | Y31: 10000 | Z31: 117.94 | AA31: 115.57 | AB31: 2 | AC31: 叶盛 | AD31: 股票资产 | AE31: -1.9671 | AF31: 0.1081 | AG31: 0.8396 | AH31: 10000 | AI31: 46 | AJ31: 自营权益4（场内） | AK31: 人民币 | AL31: 6111 | AN31: 30082 | AP31: 顾吟湫 | AQ31: 人民币 | AR31: 1171300 | AS31: 568 | AT31: 568 | AU31: 568 | AV31: 568 | AW31: 000568 | AX31: 无 | BA31: 0.5812 | BB31: 0 | BC31: 缺省券商 | BD31: 交易所业务 | BE31: 不是ETF补券指令 | BF31: 1,171,300.00 | BG31: 117.55 | BH31: 非强平 | BI31: 顾吟湫 | BJ31: 否 | BK31: 限价 | BM31: 0 | BN31: 0.15 | BO31: 股票 | BR31: 0 | BS31: 已成交
A32: 31 | B32: 2026-02-24 | C32: 3008 | D32: 自营权益4 | E32: 3008 | F32: 600919 | G32: 江苏银行 | H32: 买入 | I32: 10.32 | J32: 10.38 | K32: 30000 | L32: 311700 | M32: 26 | N32: 10.39 | O32: 10.39 | P32: 10.39 | Q32: 10.39 | R32: 10.39 | S32: 上交所A | T32: 76468662 | U32: 0.0392 | V32: 793715267 | W32: 300821 | X32: 自营权益4（场内） | Y32: 30000 | Z32: 10.48 | AA32: 10.32 | AB32: 1 | AC32: 叶盛 | AD32: 股票资产 | AE32: -0.6737 | AF32: 0.0393 | AG32: -0.1002 | AH32: 30000 | AI32: 46 | AJ32: 自营权益4（场内） | AK32: 人民币 | AL32: 40878 | AN32: 30082 | AP32: 顾吟湫 | AQ32: 人民币 | AR32: 311700 | AX32: 无 | BA32: 0.1547 | BB32: 0 | BC32: 缺省券商 | BD32: 交易所业务 | BE32: 不是ETF补券指令 | BF32: -311,700.00 | BG32: 10.43 | BH32: 非强平 | BI32: 顾吟湫 | BJ32: 否 | BK32: 限价 | BM32: 0 | BN32: 5.8166667 | BO32: 股票 | BR32: 0 | BS32: 已成交
A33: 32 | B33: 2026-02-24 | C33: 3008 | D33: 自营权益4 | E33: 3008 | F33: 601825 | G33: 沪农商行 | H33: 买入 | I33: 8.44 | J33: 8.47 | K33: 30000 | L33: 253800 | M33: 27 | N33: 8.46 | O33: 8.46 | P33: 8.46 | Q33: 8.46 | R33: 8.46 | S33: 上交所A | T33: 12886600 | U33: 0.2328 | V33: 109120584 | W33: 300821 | X33: 自营权益4（场内） | Y33: 30000 | Z33: 8.55 | AA33: 8.43 | AB33: 1 | AC33: 叶盛 | AD33: 股票资产 | AE33: -0.4717 | AF33: 0.2326 | AG33: 0.0921 | AH33: 30000 | AI33: 46 | AJ33: 自营权益4（场内） | AK33: 人民币 | AL33: 40878 | AN33: 30082 | AP33: 顾吟湫 | AQ33: 人民币 | AR33: 253800 | AX33: 无 | BA33: 0.126 | BB33: 0 | BC33: 缺省券商 | BD33: 交易所业务 | BE33: 不是ETF补券指令 | BF33: -253,800.00 | BG33: 8.47 | BH33: 非强平 | BI33: 顾吟湫 | BJ33: 否 | BK33: 限价 | BM33: 0 | BN33: 41.666667 | BO33: 股票 | BR33: 0 | BS33: 已成交
A34: 33 | B34: 2026-02-24 | C34: 3008 | D34: 自营权益4 | E34: 3008 | F34: 333 | G34: 美的集团 | H34: 买入 | I34: 79.52 | J34: 80 | K34: 30000 | L34: 2404500 | M34: 38 | N34: 80.15 | O34: 80.15 | P34: 80.15 | Q34: 80.15 | R34: 80.15 | S34: 深交所A | T34: 25251393 | U34: 0.1188 | V34: 2.0201032e+09 | W34: 300821 | X34: 自营权益4（场内） | Y34: 30000 | Z34: 80.6 | AA34: 79.52 | AB34: 1 | AC34: 叶盛 | AD34: 股票资产 | AE34: 0.5946 | AF34: 0.119 | AG34: -0.1879 | AH34: 30000 | AI34: 46 | AJ34: 自营权益4（场内） | AK34: 人民币 | AL34: 6111 | AN34: 30082 | AP34: 顾吟湫 | AQ34: 人民币 | AR34: 2404500 | AS34: 333 | AT34: 333 | AU34: 333 | AV34: 333 | AW34: 000333 | AX34: 无 | BA34: 1.1938 | BB34: 0 | BC34: 缺省券商 | BD34: 交易所业务 | BE34: 不是ETF补券指令 | BF34: -2,404,500.00 | BG34: 80.2 | BH34: 非强平 | BI34: 顾吟湫 | BJ34: 否 | BK34: 限价 | BM34: 0 | BN34: 8.1333333 | BO34: 股票 | BR34: 0 | BS34: 已成交
A35: 34 | B35: 2026-02-24 | C35: 3008 | D35: 自营权益4 | E35: 3008 | F35: 300 | G35: 美的集团 | H35: 卖出 | I35: 92.25 | J35: 92.18 | K35: 50000 | L35: 4610000 | M35: 12 | N35: 92.05 | O35: 92.35 | P35: 92.2 | Q35: 92.2 | R35: 92.2 | S35: 港股通（深） | T35: 2980600 | U35: 1.6775 | V35: 2.7474805e+08 | W35: 300841 | X35: 自营权益4（深港） | Y35: 70000 | Z35: 93.5 | AA35: 91.5 | AB35: 5 | AC35: 叶盛 | AD35: 股票资产 | AE35: -1.3369 | AF35: 1.6779 | AG35: 0.023 | AH35: 70000 | AI35: 53 | AJ35: 自营权益4（深港） | AK35: 人民币 | AL35: 6111 | AN35: 30084 | AP35: 顾吟湫 | AQ35: 人民币 | AR35: 4059658.2 | AW35: CNE100006M58 | AX35: 无 | BA35: 2.0155 | BB35: 0 | BC35: 缺省券商 | BD35: 交易所业务 | BE35: 不是ETF补券指令 | BF35: 4,610,000.00 | BG35: 0 | BH35: 非强平 | BI35: 顾吟湫 | BJ35: 否 | BK35: 增强限价盘 | BM35: 0 | BN35: 5.55 | BO35: 股票 | BR35: 0 | BS35: 已成交
A36: 35 | B36: 2026-02-24 | C36: 3008 | D36: 自营权益4 | E36: 3008 | F36: 728 | G36: 中国电信 | H36: 买入 | I36: 4.96 | J36: 4.97 | K36: 200000 | L36: 996000 | M36: 20 | N36: 4.98 | O36: 4.98 | P36: 4.98 | Q36: 4.98 | R36: 4.98 | S36: 港股通（深） | T36: 41625412 | U36: 0.4805 | V36: 2.0668144e+08 | W36: 300841 | X36: 自营权益4（深港） | Y36: 200000 | Z36: 4.98 | AA36: 4.93 | AB36: 3 | AC36: 叶盛 | AD36: 股票资产 | AE36: -0.4016 | AF36: 0.4819 | AG36: -0.2961 | AH36: 200000 | AI36: 53 | AJ36: 自营权益4（深港） | AK36: 人民币 | AL36: 6111 | AN36: 30084 | AP36: 顾吟湫 | AQ36: 人民币 | AR36: 877057.68 | AW36: CNE1000002V2 | AX36: 无 | BA36: 0.4354 | BB36: 0 | BC36: 缺省券商 | BD36: 交易所业务 | BE36: 不是ETF补券指令 | BF36: -996,000.00 | BG36: 0 | BH36: 非强平 | BI36: 顾吟湫 | BJ36: 否 | BK36: 增强限价盘 | BM36: 0 | BN36: 0 | BO36: 股票 | BR36: 0 | BS36: 已成交
A37: 36 | B37: 2026-02-24 | C37: 3008 | D37: 自营权益4 | E37: 3008 | F37: 836 | G37: 华润电力 | H37: 卖出 | I37: 18.25 | J37: 18.15 | K37: 200000 | L37: 3622600 | M37: 11 | N37: 18.1 | O37: 18.14 | P37: 18.113 | Q37: 18.113 | R37: 18.113 | S37: 港股通（深） | T37: 13329354 | U37: 1.5004 | V37: 2.4193548e+08 | W37: 300841 | X37: 自营权益4（深港） | Y37: 200000 | Z37: 18.28 | AA37: 18.06 | AB37: 5 | AC37: 叶盛 | AD37: 股票资产 | AE37: -0.2732 | AF37: 1.4973 | AG37: -0.2072 | AH37: 200000 | AI37: 53 | AJ37: 自营权益4（深港） | AK37: 人民币 | AL37: 6111 | AN37: 30084 | AP37: 顾吟湫 | AQ37: 人民币 | AR37: 3190134 | AW37: HK0836012952 | AX37: 无 | BA37: 1.5838 | BB37: 0 | BC37: 缺省券商 | BD37: 交易所业务 | BE37: 不是ETF补券指令 | BF37: 3,622,600.00 | BG37: 0 | BH37: 非强平 | BI37: 顾吟湫 | BJ37: 否 | BK37: 增强限价盘 | BM37: 0 | BN37: 3.9166667 | BO37: 股票 | BR37: 0 | BS37: 已成交
A38: 37 | B38: 2026-02-24 | C38: 3008 | D38: 自营权益4 | E38: 3008 | F38: 883 | G38: 中国海洋石油 | H38: 买入 | I38: 25.58 | J38: 25.61 | K38: 150000 | L38: 3835000 | M38: 35 | N38: 25.56 | O38: 25.58 | P38: 25.566667 | Q38: 25.566667 | R38: 25.566667 | S38: 港股通（深） | T38: 80946824 | U38: 0.1853 | V38: 2.0732571e+09 | W38: 300841 | X38: 自营权益4（深港） | Y38: 150000 | Z38: 25.94 | AA38: 25.42 | AB38: 3 | AC38: 叶盛 | AD38: 股票资产 | AE38: -1.0062 | AF38: 0.185 | AG38: 0.1792 | AH38: 150000 | AI38: 53 | AJ38: 自营权益4（深港） | AK38: 人民币 | AL38: 6111 | AN38: 30084 | AP38: 顾吟湫 | AQ38: 人民币 | AR38: 3377024.2 | AW38: HK0883013259 | AX38: 无 | BA38: 1.6766 | BB38: 0 | BC38: 缺省券商 | BD38: 交易所业务 | BE38: 不是ETF补券指令 | BF38: -3,835,000.00 | BG38: 0 | BH38: 非强平 | BI38: 顾吟湫 | BJ38: 否 | BK38: 增强限价盘 | BM38: 0 | BN38: 57.05 | BO38: 股票 | BR38: 0 | BS38: 已成交
A39: 38 | B39: 2026-02-24 | C39: 3008 | D39: 自营权益4 | E39: 3008 | F39: 995 | G39: 安徽皖通高速公路 | H39: 买入 | I39: 13.43 | J39: 13.35 | K39: 22000 | L39: 289960 | M39: 2 | N39: 13.18 | O39: 13.18 | P39: 13.18 | Q39: 13.18 | R39: 13.18 | S39: 港股通（深） | T39: 1916227 | U39: 1.1481 | V39: 25589755 | W39: 300841 | X39: 自营权益4（深港） | Y39: 60000 | Z39: 13.68 | AA39: 13.14 | AB39: 2 | AC39: 叶盛 | AD39: 股票资产 | AE39: 1.5117 | AF39: 1.1331 | AG39: 1.3045 | AH39: 60000 | AI39: 53 | AJ39: 自营权益4（深港） | AK39: 人民币 | AL39: 6111 | AN39: 30084 | AP39: 顾吟湫 | AQ39: 人民币 | AR39: 255332.98 | AW39: CNE1000001X0 | AX39: 无 | BA39: 0.1268 | BB39: 0 | BC39: 缺省券商 | BD39: 交易所业务 | BE39: 不是ETF补券指令 | BF39: -289,960.00 | BG39: 0 | BH39: 非强平 | BI39: 顾吟湫 | BJ39: 否 | BK39: 增强限价盘 | BM39: 0 | BN39: 0.9 | BO39: 股票 | BR39: 0 | BS39: 已成交
A40: 39 | B40: 2026-02-24 | C40: 3008 | D40: 自营权益4 | E40: 3008 | F40: 1071 | G40: 华电国际电力股份 | H40: 卖出 | I40: 4.23 | J40: 4.22 | K40: 1500000 | L40: 6319420 | M40: 105 | N40: 4.21 | O40: 4.23 | P40: 4.2129467 | Q40: 4.2129467 | R40: 4.2129467 | S40: 港股通（深） | T40: 9624893 | U40: 15.5846 | V40: 40632077 | W40: 300841 | X40: 自营权益4（深港） | Y40: 1500000 | Z40: 4.26 | AA40: 4.2 | AB40: 8 | AC40: 叶盛 | AD40: 股票资产 | AE40: -1.1682 | AF40: 15.5528 | AG40: -0.2061 | AH40: 1500000 | AI40: 53 | AJ40: 自营权益4（深港） | AK40: 人民币 | AL40: 6111 | AN40: 30084 | AP40: 顾吟湫 | AQ40: 人民币 | AR40: 5565007.6 | AW40: CNE1000003D8 | AX40: 无 | BA40: 2.7628 | BB40: 0 | BC40: 缺省券商 | BD40: 交易所业务 | BE40: 不是ETF补券指令 | BF40: 6,319,420.00 | BG40: 0 | BH40: 非强平 | BI40: 顾吟湫 | BJ40: 否 | BK40: 增强限价盘 | BM40: 0 | BN40: 1527.3167 | BO40: 股票 | BR40: 0 | BS40: 已成交
A41: 40 | B41: 2026-02-24 | C41: 3008 | D41: 自营权益4 | E41: 3008 | F41: 1088 | G41: 中国神华 | H41: 买入 | I41: 43.9 | J41: 43.9 | K41: 100000 | L41: 4402050 | M41: 39 | N41: 44 | O41: 44.04 | P41: 44.0205 | Q41: 44.0205 | R41: 44.0205 | S41: 港股通（深） | T41: 7047701 | U41: 1.4189 | V41: 3.0938749e+08 | W41: 300841 | X41: 自营权益4（深港） | Y41: 100000 | Z41: 44.12 | AA41: 43.5 | AB41: 1 | AC41: 叶盛 | AD41: 股票资产 | AE41: -0.3179 | AF41: 1.4228 | AG41: -0.2765 | AH41: 100000 | AI41: 53 | AJ41: 自营权益4（深港） | AK41: 人民币 | AL41: 6111 | AN41: 30084 | AP41: 顾吟湫 | AQ41: 人民币 | AR41: 3876357.2 | AW41: CNE1000002R0 | AX41: 无 | BA41: 1.9245 | BB41: 0 | BC41: 缺省券商 | BD41: 交易所业务 | BE41: 不是ETF补券指令 | BF41: -4,402,050.00 | BG41: 0 | BH41: 非强平 | BI41: 顾吟湫 | BJ41: 否 | BK41: 增强限价盘 | BM41: 0 | BN41: 0 | BO41: 股票 | BR41: 0 | BS41: 已成交
A42: 41 | B42: 2026-02-24 | C42: 3008 | D42: 自营权益4 | E42: 3008 | F42: 3933 | G42: 联邦制药 | H42: 买入 | I42: 12.17 | J42: 12.24 | K42: 100000 | L42: 1217000 | M42: 6 | N42: 12.17 | O42: 12.17 | P42: 12.17 | Q42: 12.17 | R42: 12.17 | S42: 港股通（深） | T42: 6074463 | U42: 1.6462 | V42: 74337061 | W42: 300841 | X42: 自营权益4（深港） | Y42: 100000 | Z42: 12.6 | AA42: 12.09 | AB42: 3 | AC42: 叶盛 | AD42: 股票资产 | AE42: -3.2591 | AF42: 1.6371 | AG42: 0.5524 | AH42: 100000 | AI42: 53 | AJ42: 自营权益4（深港） | AK42: 人民币 | AL42: 6111 | AN42: 30084 | AP42: 顾吟湫 | AQ42: 人民币 | AR42: 1071665.9 | AW42: KYG8813K1085 | AX42: 无 | BA42: 0.532 | BB42: 0 | BC42: 缺省券商 | BD42: 交易所业务 | BE42: 不是ETF补券指令 | BF42: -1,217,000.00 | BG42: 0 | BH42: 非强平 | BI42: 顾吟湫 | BJ42: 否 | BK42: 增强限价盘 | BM42: 0 | BN42: 23.416667 | BO42: 股票 | BR42: 0 | BS42: 已成交
A43: 42 | B43: 2026-02-25 | C43: 3008 | D43: 自营权益4 | E43: 3008 | F43: 300 | G43: 美的集团 | H43: 卖出 | I43: 92.3 | J43: 92.58 | K43: 50000 | L43: 4633750 | M43: 78 | N43: 91.95 | O43: 92.95 | P43: 92.675 | Q43: 92.675 | R43: 92.675 | S43: 港股通（深） | T43: 2962612 | U43: 1.6877 | V43: 2.7427885e+08 | W43: 300841 | X43: 自营权益4（深港） | Y43: 50000 | Z43: 93.95 | AA43: 91.85 | AB43: 11 | AC43: 叶盛 | AD43: 股票资产 | AE43: 0.0542 | AF43: 1.6894 | AG43: 0.1025 | AH43: 50000 | AI43: 53 | AJ43: 自营权益4（深港） | AK43: 人民币 | AL43: 6111 | AN43: 30084 | AP43: 顾吟湫 | AQ43: 人民币 | AR43: 4077097.5 | AW43: CNE100006M58 | AX43: 无 | BA43: 2.017 | BB43: 0 | BC43: 缺省券商 | BD43: 交易所业务 | BE43: 不是ETF补券指令 | BF43: 4,633,750.00 | BG43: 0 | BH43: 非强平 | BI43: 顾吟湫 | BJ43: 否 | BK43: 增强限价盘 | BM43: 0 | BN43: 401.38333 | BO43: 股票 | BR43: 0 | BS43: 已成交
A44: 43 | B44: 2026-02-25 | C44: 3008 | D44: 自营权益4 | E44: 3008 | F44: 995 | G44: 安徽皖通高速公路 | H44: 买入 | I44: 13.5 | J44: 13.69 | K44: 28000 | L44: 376600 | M44: 7 | N44: 13.45 | O44: 13.45 | P44: 13.45 | Q44: 13.45 | R44: 13.45 | S44: 港股通（深） | T44: 1951329 | U44: 1.4349 | V44: 26720873 | W44: 300841 | X44: 自营权益4（深港） | Y44: 28000 | Z44: 13.97 | AA44: 13.17 | AB44: 2 | AC44: 叶盛 | AD44: 股票资产 | AE44: 0.5212 | AF44: 1.4094 | AG44: 1.7797 | AH44: 28000 | AI44: 53 | AJ44: 自营权益4（深港） | AK44: 人民币 | AL44: 6111 | AN44: 30084 | AP44: 顾吟湫 | AQ44: 人民币 | AR44: 331306.31 | AW44: CNE1000001X0 | AX44: 无 | BA44: 0.1639 | BB44: 0 | BC44: 缺省券商 | BD44: 交易所业务 | BE44: 不是ETF补券指令 | BF44: -376,600.00 | BG44: 0 | BH44: 非强平 | BI44: 顾吟湫 | BJ44: 否 | BK44: 增强限价盘 | BM44: 0 | BN44: 0 | BO44: 股票 | BR44: 0 | BS44: 已成交
A45: 44 | B45: 2026-02-25 | C45: 3008 | D45: 自营权益4 | E45: 3008 | F45: 1398 | G45: 工商银行 | H45: 卖出 | I45: 6.46 | J45: 6.47 | K45: 200000 | L45: 1300000 | M45: 3 | N45: 6.5 | O45: 6.5 | P45: 6.5 | Q45: 6.5 | R45: 6.5 | S45: 港股通（深） | T45: 143643677 | U45: 0.1392 | V45: 9.2963311e+08 | W45: 300841 | X45: 自营权益4（深港） | Y45: 200000 | Z45: 6.51 | AA45: 6.42 | AB45: 1 | AC45: 叶盛 | AD45: 股票资产 | AE45: 0.155 | AF45: 0.1398 | AG45: 0.4357 | AH45: 200000 | AI45: 53 | AJ45: 自营权益4（深港） | AK45: 人民币 | AL45: 6111 | AN45: 30084 | AP45: 顾吟湫 | AQ45: 人民币 | AR45: 1143831 | AW45: CNE1000003G1 | AX45: 无 | BA45: 0.5659 | BB45: 0 | BC45: 缺省券商 | BD45: 交易所业务 | BE45: 不是ETF补券指令 | BF45: 1,300,000.00 | BG45: 0 | BH45: 非强平 | BI45: 顾吟湫 | BJ45: 否 | BK45: 增强限价盘 | BM45: 0 | BN45: 0.23333333 | BO45: 股票 | BR45: 0 | BS45: 已成交
A46: 45 | B46: 2026-02-25 | C46: 3008 | D46: 自营权益4 | E46: 3008 | F46: 9985 | G46: 卫龙美味 | H46: 买入 | I46: 11.96 | J46: 12.02 | K46: 300000 | L46: 3575920 | M46: 114 | N46: 11.9 | O46: 11.96 | P46: 11.919733 | Q46: 11.919733 | R46: 11.919733 | S46: 港股通（深） | T46: 7157800 | U46: 4.1912 | V46: 86001811 | W46: 300841 | X46: 自营权益4（深港） | Y46: 300000 | Z46: 12.58 | AA46: 11.79 | AB46: 9 | AC46: 叶盛 | AD46: 股票资产 | AE46: -4.1667 | AF46: 4.158 | AG46: 0.794 | AH46: 300000 | AI46: 53 | AJ46: 自营权益4（深港） | AK46: 人民币 | AL46: 6111 | AN46: 30084 | AP46: 顾吟湫 | AQ46: 人民币 | AR46: 3145844.1 | AW46: KYG9T20T1051 | AX46: 无 | BA46: 1.5563 | BB46: 0 | BC46: 缺省券商 | BD46: 交易所业务 | BE46: 不是ETF补券指令 | BF46: -3,575,920.00 | BG46: 0 | BH46: 非强平 | BI46: 顾吟湫 | BJ46: 否 | BK46: 增强限价盘 | BM46: 0 | BN46: 258.95 | BO46: 股票 | BR46: 0 | BS46: 已成交
A47: 46 | B47: 2026-02-26 | C47: 3008 | D47: 自营权益4 | E47: 3008 | F47: 3328 | G47: 交通银行 | H47: 卖出 | I47: 6.93 | J47: 6.95 | K47: 600000 | L47: 4188000 | M47: 163 | N47: 6.97 | O47: 6.99 | P47: 6.98 | Q47: 6.98 | R47: 6.98 | S47: 港股通（深） | T47: 25006123 | U47: 2.3994 | V47: 1.7386031e+08 | W47: 300841 | X47: 自营权益4（深港） | Y47: 600000 | Z47: 7 | AA47: 6.92 | AB47: 4 | AC47: 叶盛 | AD47: 股票资产 | AE47: -0.2878 | AF47: 2.4088 | AG47: 0.3927 | AH47: 600000 | AI47: 53 | AJ47: 自营权益4（深港） | AK47: 人民币 | AL47: 6111 | AN47: 30084 | AP47: 顾吟湫 | AQ47: 人民币 | AR47: 3674090.4 | AW47: CNE100000205 | AX47: 无 | BA47: 1.8372 | BB47: 0 | BC47: 缺省券商 | BD47: 交易所业务 | BE47: 不是ETF补券指令 | BF47: 4,188,000.00 | BG47: 0 | BH47: 非强平 | BI47: 顾吟湫 | BJ47: 否 | BK47: 增强限价盘 | BM47: 0 | BN47: 11463.433 | BO47: 股票 | BR47: 0 | BS47: 已成交
A48: 47 | B48: 2026-02-27 | C48: 3008 | D48: 自营权益4 | E48: 3008 | F48: 600887 | G48: 伊利股份 | H48: 买入 | I48: 26.08 | J48: 26.15 | K48: 90000 | L48: 2358900 | M48: 83 | N48: 26.21 | O48: 26.21 | P48: 26.21 | Q48: 26.21 | R48: 26.21 | S48: 上交所A | T48: 39534029 | U48: 0.2277 | V48: 1033896673 | W48: 300821 | X48: 自营权益4（场内） | Y48: 90000 | Z48: 26.26 | AA48: 26.01 | AB48: 1 | AC48: 叶盛 | AD48: 股票资产 | AE48: -0.1531 | AF48: 0.2282 | AG48: -0.2214 | AH48: 90000 | AI48: 46 | AJ48: 自营权益4（场内） | AK48: 人民币 | AL48: 40878 | AN48: 30082 | AP48: 顾吟湫 | AQ48: 人民币 | AR48: 2358900 | AS48: 600887 | AT48: 600887 | AU48: 600887 | AV48: 600887 | AW48: 600887 | AX48: 无 | BA48: 1.1788 | BB48: 0 | BC48: 缺省券商 | BD48: 交易所业务 | BE48: 不是ETF补券指令 | BF48: -2,358,900.00 | BG48: 26.13 | BH48: 非强平 | BI48: 顾吟湫 | BJ48: 否 | BK48: 限价 | BM48: 0 | BN48: 51.416667 | BO48: 股票 | BR48: 0 | BS48: 已成交
A49: 48 | B49: 2026-02-27 | C49: 3008 | D49: 自营权益4 | E49: 3008 | F49: 333 | G49: 美的集团 | H49: 买入 | I49: 78.64 | J49: 78.89 | K49: 10000 | L49: 794500 | M49: 9 | N49: 79.45 | O49: 79.45 | P49: 79.45 | Q49: 79.45 | R49: 79.45 | S49: 深交所A | T49: 20160388 | U49: 0.0496 | V49: 1.5904638e+09 | W49: 300821 | X49: 自营权益4（场内） | Y49: 10000 | Z49: 79.5 | AA49: 78.5 | AB49: 3 | AC49: 叶盛 | AD49: 股票资产 | AE49: -0.7697 | AF49: 0.05 | AG49: -0.7092 | AH49: 10000 | AI49: 46 | AJ49: 自营权益4（场内） | AK49: 人民币 | AL49: 6111 | AN49: 30082 | AP49: 顾吟湫 | AQ49: 人民币 | AR49: 794500 | AS49: 333 | AT49: 333 | AU49: 333 | AV49: 333 | AW49: 000333 | AX49: 无 | BA49: 0.397 | BB49: 0 | BC49: 缺省券商 | BD49: 交易所业务 | BE49: 不是ETF补券指令 | BF49: -794,500.00 | BG49: 79.03 | BH49: 非强平 | BI49: 顾吟湫 | BJ49: 否 | BK49: 限价 | BM49: 0 | BN49: 2.55 | BO49: 股票 | BR49: 0 | BS49: 已成交
A50: 49 | B50: 2026-02-27 | C50: 3008 | D50: 自营权益4 | E50: 3008 | F50: 9985 | G50: 卫龙美味 | H50: 买入 | I50: 11.71 | J50: 11.7 | K50: 50000 | L50: 589940 | M50: 5 | N50: 11.79 | O50: 11.8 | P50: 11.7988 | Q50: 11.7988 | R50: 11.7988 | S50: 港股通（深） | T50: 2288000 | U50: 2.1853 | V50: 26773205 | W50: 300841 | X50: 自营权益4（深港） | Y50: 50000 | Z50: 11.96 | AA50: 11.54 | AB50: 2 | AC50: 叶盛 | AD50: 股票资产 | AE50: -0.5098 | AF50: 2.2035 | AG50: -0.8307 | AH50: 50000 | AI50: 53 | AJ50: 自营权益4（深港） | AK50: 人民币 | AL50: 6111 | AN50: 30084 | AP50: 顾吟湫 | AQ50: 人民币 | AR50: 515855.33 | AW50: KYG9T20T1051 | AX50: 无 | BA50: 0.2578 | BB50: 0 | BC50: 缺省券商 | BD50: 交易所业务 | BE50: 不是ETF补券指令 | BF50: -589,940.00 | BG50: 0 | BH50: 非强平 | BI50: 顾吟湫 | BJ50: 否 | BK50: 增强限价盘 | BM50: 0 | BN50: 10.016667 | BO50: 股票 | BR50: 0 | BS50: 已成交
A51: 50 | B51: 2026-03-02 | C51: 3008 | D51: 自营权益4 | E51: 3008 | F51: 600887 | G51: 伊利股份 | H51: 买入 | I51: 26 | J51: 25.89 | K51: 40000 | L51: 1038400 | M51: 40 | N51: 25.96 | O51: 25.96 | P51: 25.96 | Q51: 25.96 | R51: 25.96 | S51: 上交所A | T51: 57790563 | U51: 0.0692 | V51: 1496480387 | W51: 300821 | X51: 自营权益4（场内） | Y51: 40000 | Z51: 26.14 | AA51: 25.66 | AB51: 2 | AC51: 叶盛 | AD51: 股票资产 | AE51: -0.3067 | AF51: 0.0694 | AG51: -0.2514 | AH51: 40000 | AI51: 46 | AJ51: 自营权益4（场内） | AK51: 人民币 | AL51: 40878 | AN51: 30082 | AP51: 顾吟湫 | AQ51: 人民币 | AR51: 1038400 | AS51: 600887 | AT51: 600887 | AU51: 600887 | AV51: 600887 | AW51: 600887 | AX51: 无 | BA51: 0.522 | BB51: 0 | BC51: 缺省券商 | BD51: 交易所业务 | BE51: 不是ETF补券指令 | BF51: -1,038,400.00 | BG51: 25.95 | BH51: 非强平 | BI51: 顾吟湫 | BJ51: 否 | BK51: 限价 | BM51: 0 | BN51: 0.98333333 | BO51: 股票 | BR51: 0 | BS51: 已成交
A52: 51 | B52: 2026-03-02 | C52: 3008 | D52: 自营权益4 | E52: 3008 | F52: 600908 | G52: 无锡银行 | H52: 买入 | I52: 5.92 | J52: 5.9 | K52: 2000 | L52: 11780 | M52: 2 | N52: 5.89 | O52: 5.89 | P52: 5.89 | Q52: 5.89 | R52: 5.89 | S52: 上交所A | T52: 21277400 | U52: 0.0094 | V52: 125501989 | W52: 300821 | X52: 自营权益4（场内） | Y52: 2000 | Z52: 5.94 | AA52: 5.84 | AB52: 1 | AC52: 叶盛 | AD52: 股票资产 | AE52: 0.8518 | AF52: 0.0094 | AG52: 0.1424 | AH52: 2000 | AI52: 46 | AJ52: 自营权益4（场内） | AK52: 人民币 | AL52: 40878 | AN52: 30082 | AP52: 顾吟湫 | AQ52: 人民币 | AR52: 11780 | AX52: 无 | BA52: 0.0059 | BB52: 0 | BC52: 缺省券商 | BD52: 交易所业务 | BE52: 不是ETF补券指令 | BF52: -11,780.00 | BG52: 5.86 | BH52: 非强平 | BI52: 顾吟湫 | BJ52: 否 | BK52: 限价 | BM52: 0 | BN52: 0 | BO52: 股票 | BR52: 0 | BS52: 已成交
A53: 52 | B53: 2026-03-02 | C53: 3008 | D53: 自营权益4 | E53: 3008 | F53: 601577 | G53: 长沙银行 | H53: 买入 | I53: 9.78 | J53: 9.77 | K53: 2000 | L53: 19540 | M53: 1 | N53: 9.77 | O53: 9.77 | P53: 9.77 | Q53: 9.77 | R53: 9.77 | S53: 上交所A | T53: 19535309 | U53: 0.0102 | V53: 190865883 | W53: 300821 | X53: 自营权益4（场内） | Y53: 2000 | Z53: 9.87 | AA53: 9.66 | AB53: 1 | AC53: 叶盛 | AD53: 股票资产 | AE53: -0.2041 | AF53: 0.0102 | AG53: 0.0031 | AH53: 2000 | AI53: 46 | AJ53: 自营权益4（场内） | AK53: 人民币 | AL53: 40878 | AN53: 30082 | AP53: 顾吟湫 | AQ53: 人民币 | AR53: 19540 | AX53: 无 | BA53: 0.0098 | BB53: 0 | BC53: 缺省券商 | BD53: 交易所业务 | BE53: 不是ETF补券指令 | BF53: -19,540.00 | BG53: 9.71 | BH53: 非强平 | BI53: 顾吟湫 | BJ53: 否 | BK53: 限价 | BM53: 0 | BN53: 0 | BO53: 股票 | BR53: 0 | BS53: 已成交
A54: 53 | B54: 2026-03-02 | C54: 3008 | D54: 自营权益4 | E54: 3008 | F54: 333 | G54: 美的集团 | H54: 买入 | I54: 77.45 | J54: 77.4 | K54: 10000 | L54: 772461 | M54: 15 | N54: 77.24 | O54: 77.25 | P54: 77.2461 | Q54: 77.2461 | R54: 77.2461 | S54: 深交所A | T54: 27478559 | U54: 0.0364 | V54: 2.1267564e+09 | W54: 300821 | X54: 自营权益4（场内） | Y54: 10000 | Z54: 78.06 | AA54: 76.7 | AB54: 2 | AC54: 叶盛 | AD54: 股票资产 | AE54: -1.5132 | AF54: 0.0363 | AG54: 0.1948 | AH54: 10000 | AI54: 46 | AJ54: 自营权益4（场内） | AK54: 人民币 | AL54: 6111 | AN54: 30082 | AP54: 顾吟湫 | AQ54: 人民币 | AR54: 772461 | AS54: 333 | AT54: 333 | AU54: 333 | AV54: 333 | AW54: 000333 | AX54: 无 | BA54: 0.3883 | BB54: 0 | BC54: 缺省券商 | BD54: 交易所业务 | BE54: 不是ETF补券指令 | BF54: -772,461.00 | BG54: 78 | BH54: 非强平 | BI54: 顾吟湫 | BJ54: 否 | BK54: 限价 | BM54: 0 | BN54: 0 | BO54: 股票 | BR54: 0 | BS54: 已成交
A55: 54 | B55: 2026-03-02 | C55: 3008 | D55: 自营权益4 | E55: 3008 | F55: 2807 | G55: 江阴银行 | H55: 买入 | I55: 4.6 | J55: 4.6 | K55: 4000 | L55: 18400 | M55: 1 | N55: 4.6 | O55: 4.6 | P55: 4.6 | Q55: 4.6 | R55: 4.6 | S55: 深交所A | T55: 44208289 | U55: 0.009 | V55: 2.032114e+08 | W55: 300821 | X55: 自营权益4（场内） | Y55: 4000 | Z55: 4.63 | AA55: 4.55 | AB55: 1 | AC55: 叶盛 | AD55: 股票资产 | AE55: 0.2179 | AF55: 0.0091 | AG55: -0.0718 | AH55: 4000 | AI55: 46 | AJ55: 自营权益4（场内） | AK55: 人民币 | AL55: 6111 | AN55: 30082 | AP55: 顾吟湫 | AQ55: 人民币 | AR55: 18400 | AX55: 无 | BA55: 0.0092 | BB55: 0 | BC55: 缺省券商 | BD55: 交易所业务 | BE55: 不是ETF补券指令 | BF55: -18,400.00 | BG55: 4.57 | BH55: 非强平 | BI55: 顾吟湫 | BJ55: 否 | BK55: 限价 | BM55: 0 | BN55: 0 | BO55: 股票 | BR55: 0 | BS55: 已成交
A56: 55 | B56: 2026-03-02 | C56: 3008 | D56: 自营权益4 | E56: 3008 | F56: 2839 | G56: 张家港行 | H56: 买入 | I56: 4.58 | J56: 4.58 | K56: 4000 | L56: 18280 | M56: 13 | N56: 4.57 | O56: 4.57 | P56: 4.57 | Q56: 4.57 | R56: 4.57 | S56: 深交所A | T56: 37504226 | U56: 0.0107 | V56: 1.7173092e+08 | W56: 300821 | X56: 自营权益4（场内） | Y56: 4000 | Z56: 4.61 | AA56: 4.53 | AB56: 1 | AC56: 叶盛 | AD56: 股票资产 | AE56: 0 | AF56: 0.0106 | AG56: 0.1965 | AH56: 4000 | AI56: 46 | AJ56: 自营权益4（场内） | AK56: 人民币 | AL56: 6111 | AN56: 30082 | AP56: 顾吟湫 | AQ56: 人民币 | AR56: 18280 | AX56: 无 | BA56: 0.0092 | BB56: 0 | BC56: 缺省券商 | BD56: 交易所业务 | BE56: 不是ETF补券指令 | BF56: -18,280.00 | BG56: 4.57 | BH56: 非强平 | BI56: 顾吟湫 | BJ56: 否 | BK56: 限价 | BM56: 0 | BN56: 0 | BO56: 股票 | BR56: 0 | BS56: 已成交
A57: 56 | B57: 2026-03-03 | C57: 3008 | D57: 自营权益4 | E57: 3008 | F57: 600887 | G57: 伊利股份 | H57: 买入 | I57: 25.93 | J57: 25.97 | K57: 50000 | L57: 1298500 | M57: 24 | N57: 25.97 | O57: 25.97 | P57: 25.97 | Q57: 25.97 | R57: 25.97 | S57: 上交所A | T57: 55289165 | U57: 0.0904 | V57: 1436052974 | W57: 300821 | X57: 自营权益4（场内） | Y57: 50000 | Z57: 26.26 | AA57: 25.78 | AB57: 1 | AC57: 叶盛 | AD57: 股票资产 | AE57: -0.2692 | AF57: 0.0904 | AG57: 0.0135 | AH57: 50000 | AI57: 46 | AJ57: 自营权益4（场内） | AK57: 人民币 | AL57: 40878 | AN57: 30082 | AP57: 顾吟湫 | AQ57: 人民币 | AR57: 1298500 | AS57: 600887 | AT57: 600887 | AU57: 600887 | AV57: 600887 | AW57: 600887 | AX57: 无 | BA57: 0.6517 | BB57: 0 | BC57: 缺省券商 | BD57: 交易所业务 | BE57: 不是ETF补券指令 | BF57: -1,298,500.00 | BG57: 26 | BH57: 非强平 | BI57: 顾吟湫 | BJ57: 否 | BK57: 限价 | BM57: 0 | BN57: 21.816667 | BO57: 股票 | BR57: 0 | BS57: 已成交
A58: 57 | B58: 2026-03-03 | C58: 3008 | D58: 自营权益4 | E58: 3008 | F58: 600908 | G58: 无锡银行 | H58: 买入 | I58: 5.87 | J58: 5.89 | K58: 88000 | L58: 520000 | M58: 66 | N58: 5.9 | O58: 5.91 | P58: 5.9090909 | Q58: 5.9090909 | R58: 5.9090909 | S58: 上交所A | T58: 24786100 | U58: 0.355 | V58: 146097630 | W58: 300821 | X58: 自营权益4（场内） | Y58: 88000 | Z58: 5.94 | AA58: 5.84 | AB58: 2 | AC58: 叶盛 | AD58: 股票资产 | AE58: -0.8446 | AF58: 0.3559 | AG58: -0.2511 | AH58: 88000 | AI58: 46 | AJ58: 自营权益4（场内） | AK58: 人民币 | AL58: 40878 | AN58: 30082 | AP58: 顾吟湫 | AQ58: 人民币 | AR58: 520000 | AX58: 无 | BA58: 0.261 | BB58: 0 | BC58: 缺省券商 | BD58: 交易所业务 | BE58: 不是ETF补券指令 | BF58: -520,000.00 | BG58: 5.91 | BH58: 非强平 | BI58: 顾吟湫 | BJ58: 否 | BK58: 限价 | BM58: 0 | BN58: 1.4333333 | BO58: 股票 | BR58: 0 | BS58: 已成交
A59: 58 | B59: 2026-03-03 | C59: 3008 | D59: 自营权益4 | E59: 3008 | F59: 601577 | G59: 长沙银行 | H59: 买入 | I59: 9.75 | J59: 9.76 | K59: 50000 | L59: 486500 | M59: 22 | N59: 9.73 | O59: 9.73 | P59: 9.73 | Q59: 9.73 | R59: 9.73 | S59: 上交所A | T59: 21269176 | U59: 0.2351 | V59: 207529676 | W59: 300821 | X59: 自营权益4（场内） | Y59: 50000 | Z59: 9.85 | AA59: 9.69 | AB59: 1 | AC59: 叶盛 | AD59: 股票资产 | AE59: -0.3067 | AF59: 0.2344 | AG59: 0.2798 | AH59: 50000 | AI59: 46 | AJ59: 自营权益4（场内） | AK59: 人民币 | AL59: 40878 | AN59: 30082 | AP59: 顾吟湫 | AQ59: 人民币 | AR59: 486500 | AX59: 无 | BA59: 0.2442 | BB59: 0 | BC59: 缺省券商 | BD59: 交易所业务 | BE59: 不是ETF补券指令 | BF59: -486,500.00 | BG59: 9.78 | BH59: 非强平 | BI59: 顾吟湫 | BJ59: 否 | BK59: 限价 | BM59: 0 | BN59: 2.45 | BO59: 股票 | BR59: 0 | BS59: 已成交
A60: 59 | B60: 2026-03-03 | C60: 3008 | D60: 自营权益4 | E60: 3008 | F60: 2807 | G60: 江阴银行 | H60: 买入 | I60: 4.58 | J60: 4.6 | K60: 100000 | L60: 460000 | M60: 14 | N60: 4.6 | O60: 4.6 | P60: 4.6 | Q60: 4.6 | R60: 4.6 | S60: 深交所A | T60: 52983360 | U60: 0.1887 | V60: 2.4355331e+08 | W60: 300821 | X60: 自营权益4（场内） | Y60: 100000 | Z60: 4.64 | AA60: 4.56 | AB60: 1 | AC60: 叶盛 | AD60: 股票资产 | AE60: -0.4348 | AF60: 0.1889 | AG60: -0.0696 | AH60: 100000 | AI60: 46 | AJ60: 自营权益4（场内） | AK60: 人民币 | AL60: 6111 | AN60: 30082 | AP60: 顾吟湫 | AQ60: 人民币 | AR60: 460000 | AX60: 无 | BA60: 0.2309 | BB60: 0 | BC60: 缺省券商 | BD60: 交易所业务 | BE60: 不是ETF补券指令 | BF60: -460,000.00 | BG60: 4.61 | BH60: 非强平 | BI60: 顾吟湫 | BJ60: 否 | BK60: 限价 | BM60: 0 | BN60: 0 | BO60: 股票 | BR60: 0 | BS60: 已成交
A61: 60 | B61: 2026-03-03 | C61: 3008 | D61: 自营权益4 | E61: 3008 | F61: 2839 | G61: 张家港行 | H61: 买入 | I61: 4.54 | J61: 4.57 | K61: 100000 | L61: 457000 | M61: 42 | N61: 4.57 | O61: 4.57 | P61: 4.57 | Q61: 4.57 | R61: 4.57 | S61: 深交所A | T61: 42860118 | U61: 0.2333 | V61: 1.9582105e+08 | W61: 300821 | X61: 自营权益4（场内） | Y61: 100000 | Z61: 4.61 | AA61: 4.52 | AB61: 1 | AC61: 叶盛 | AD61: 股票资产 | AE61: -0.8734 | AF61: 0.2334 | AG61: -0.0263 | AH61: 100000 | AI61: 46 | AJ61: 自营权益4（场内） | AK61: 人民币 | AL61: 6111 | AN61: 30082 | AP61: 顾吟湫 | AQ61: 人民币 | AR61: 457000 | AX61: 无 | BA61: 0.2294 | BB61: 0 | BC61: 缺省券商 | BD61: 交易所业务 | BE61: 不是ETF补券指令 | BF61: -457,000.00 | BG61: 4.58 | BH61: 非强平 | BI61: 顾吟湫 | BJ61: 否 | BK61: 限价 | BM61: 0 | BN61: 3.0333333 | BO61: 股票 | BR61: 0 | BS61: 已成交
A62: 61 | B62: 2026-03-11 | C62: 3008 | D62: 自营权益4 | E62: 3008 | F62: 995 | G62: 安徽皖通高速公路 | H62: 卖出 | I62: 13.75 | J62: 13.58 | K62: 20000 | L62: 274900 | M62: 5 | N62: 13.74 | O62: 13.75 | P62: 13.745 | Q62: 13.745 | R62: 13.745 | S62: 港股通（深） | T62: 1150000 | U62: 1.7391 | V62: 15615840 | W62: 300841 | X62: 自营权益4（深港） | Y62: 360000 | Z62: 13.75 | AA62: 13.38 | AB62: 12 | AC62: 叶盛 | AD62: 股票资产 | AE62: 2.9963 | AF62: 1.7604 | AG62: 1.2225 | AH62: 60000 | AI62: 53 | AJ62: 自营权益4（深港） | AK62: 人民币 | AL62: 6111 | AN62: 30084 | AP62: 顾吟湫 | AQ62: 人民币 | AR62: 241562.89 | AW62: CNE1000001X0 | AX62: 无 | BA62: 0.121 | BB62: 0 | BC62: 缺省券商 | BD62: 交易所业务 | BE62: 不是ETF补券指令 | BF62: 274,900.00 | BG62: 0 | BH62: 非强平 | BI62: 顾吟湫 | BJ62: 否 | BK62: 增强限价盘 | BM62: 0 | BN62: 300.21667 | BO62: 股票 | BR62: 0 | BS62: 已成交
A63: 62 | B63: 2026-03-11 | C63: 3008 | D63: 自营权益4 | E63: 3008 | F63: 3328 | G63: 交通银行 | H63: 卖出 | I63: 6.79 | J63: 6.8 | K63: 800000 | L63: 5435000 | M63: 56 | N63: 6.79 | O63: 6.8 | P63: 6.79375 | Q63: 6.79375 | R63: 6.79375 | S63: 港股通（深） | T63: 18231130 | U63: 4.3881 | V63: 1.2398969e+08 | W63: 300841 | X63: 自营权益4（深港） | Y63: 800000 | Z63: 6.84 | AA63: 6.76 | AB63: 8 | AC63: 叶盛 | AD63: 股票资产 | AE63: 0.4438 | AF63: 4.3834 | AG63: -0.1059 | AH63: 800000 | AI63: 53 | AJ63: 自营权益4（深港） | AK63: 人民币 | AL63: 6111 | AN63: 30084 | AP63: 顾吟湫 | AQ63: 人民币 | AR63: 4775897.5 | AW63: CNE100000205 | AX63: 无 | BA63: 2.3928 | BB63: 0 | BC63: 缺省券商 | BD63: 交易所业务 | BE63: 不是ETF补券指令 | BF63: 5,435,000.00 | BG63: 0 | BH63: 非强平 | BI63: 顾吟湫 | BJ63: 否 | BK63: 增强限价盘 | BM63: 0 | BN63: 483.11667 | BO63: 股票 | BR63: 0 | BS63: 已成交
A64: 63 | B64: 2026-03-12 | C64: 3008 | D64: 自营权益4 | E64: 3008 | F64: 995 | G64: 安徽皖通高速公路 | H64: 卖出 | I64: 13.82 | J64: 13.9 | K64: 40000 | L64: 550600 | M64: 9 | N64: 13.75 | O64: 13.78 | P64: 13.765 | Q64: 13.765 | R64: 13.765 | S64: 港股通（深） | T64: 596000 | U64: 6.7114 | V64: 8281500 | W64: 300841 | X64: 自营权益4（深港） | Y64: 40000 | Z64: 14.07 | AA64: 13.65 | AB64: 4 | AC64: 叶盛 | AD64: 股票资产 | AE64: 0.5091 | AF64: 6.6486 | AG64: -0.9363 | AH64: 40000 | AI64: 53 | AJ64: 自营权益4（深港） | AK64: 人民币 | AL64: 6111 | AN64: 30084 | AP64: 顾吟湫 | AQ64: 人民币 | AR64: 483366.26 | AW64: CNE1000001X0 | AX64: 无 | BA64: 0.2414 | BB64: 0 | BC64: 缺省券商 | BD64: 交易所业务 | BE64: 不是ETF补券指令 | BF64: 550,600.00 | BG64: 0 | BH64: 非强平 | BI64: 顾吟湫 | BJ64: 否 | BK64: 竞价限价盘 | BM64: 0 | BN64: 548.05 | BO64: 股票 | BR64: 0 | BS64: 已成交
A65: 64 | B65: 2026-03-12 | C65: 3008 | D65: 自营权益4 | E65: 3008 | F65: 1368 | G65: 特步国际 | H65: 卖出 | I65: 5.02 | J65: 5.03 | K65: 300000 | L65: 1506000 | M65: 39 | N65: 5.02 | O65: 5.02 | P65: 5.02 | Q65: 5.02 | R65: 5.02 | S65: 港股通（深） | T65: 3980500 | U65: 7.5367 | V65: 20019198 | W65: 300841 | X65: 自营权益4（深港） | Y65: 300000 | Z65: 5.11 | AA65: 5.01 | AB65: 1 | AC65: 叶盛 | AD65: 股票资产 | AE65: -1.9531 | AF65: 7.5228 | AG65: -0.1849 | AH65: 300000 | AI65: 53 | AJ65: 自营权益4（深港） | AK65: 人民币 | AL65: 6111 | AN65: 30084 | AP65: 顾吟湫 | AQ65: 人民币 | AR65: 1322102.3 | AW65: KYG982771092 | AX65: 无 | BA65: 0.6602 | BB65: 0 | BC65: 缺省券商 | BD65: 交易所业务 | BE65: 不是ETF补券指令 | BF65: 1,506,000.00 | BG65: 0 | BH65: 非强平 | BI65: 顾吟湫 | BJ65: 否 | BK65: 增强限价盘 | BM65: 0 | BN65: 185.16667 | BO65: 股票 | BR65: 0 | BS65: 已成交
A66: 65 | B66: 2026-03-12 | C66: 3008 | D66: 自营权益4 | E66: 3008 | F66: 3998 | G66: 波司登 | H66: 买入 | I66: 4.1 | J66: 4.1 | K66: 450000 | L66: 1845000 | M66: 13 | N66: 4.1 | O66: 4.1 | P66: 4.1 | Q66: 4.1 | R66: 4.1 | S66: 港股通（深） | T66: 42673090 | U66: 1.0545 | V66: 1.748119e+08 | W66: 300841 | X66: 自营权益4（深港） | Y66: 450000 | Z66: 4.13 | AA66: 4.01 | AB66: 2 | AC66: 叶盛 | AD66: 股票资产 | AE66: 0.4902 | AF66: 1.0554 | AG66: -0.0854 | AH66: 450000 | AI66: 53 | AJ66: 自营权益4（深港） | AK66: 人民币 | AL66: 6111 | AN66: 30084 | AP66: 顾吟湫 | AQ66: 人民币 | AR66: 1620112.9 | AW66: KYG126521064 | AX66: 无 | BA66: 0.809 | BB66: 0 | BC66: 缺省券商 | BD66: 交易所业务 | BE66: 不是ETF补券指令 | BF66: -1,845,000.00 | BG66: 0 | BH66: 非强平 | BI66: 顾吟湫 | BJ66: 否 | BK66: 增强限价盘 | BM66: 0 | BN66: 0 | BO66: 股票 | BR66: 0 | BS66: 已成交
A67: 66 | B67: 2026-03-18 | C67: 3008 | D67: 自营权益4 | E67: 3008 | F67: 600908 | G67: 无锡银行 | H67: 买入 | I67: 5.97 | J67: 5.98 | K67: 110000 | L67: 657500 | M67: 55 | N67: 5.97 | O67: 5.98 | P67: 5.9772727 | Q67: 5.9772727 | R67: 5.9772727 | S67: 上交所A | T67: 13803400 | U67: 0.7969 | V67: 82568931 | W67: 300821 | X67: 自营权益4（场内） | Y67: 110000 | Z67: 6.04 | AA67: 5.95 | AB67: 2 | AC67: 叶盛 | AD67: 股票资产 | AE67: -0.995 | AF67: 0.7963 | AG67: 0.0752 | AH67: 110000 | AI67: 46 | AJ67: 自营权益4（场内） | AK67: 人民币 | AL67: 40878 | AN67: 30082 | AP67: 顾吟湫 | AQ67: 人民币 | AR67: 657500 | AX67: 无 | BA67: 0.3306 | BB67: 0 | BC67: 缺省券商 | BD67: 交易所业务 | BE67: 不是ETF补券指令 | BF67: -657,500.00 | BG67: 6.03 | BH67: 非强平 | BI67: 顾吟湫 | BJ67: 否 | BK67: 限价 | BM67: 0 | BN67: 426.98333 | BO67: 股票 | BR67: 0 | BS67: 已成交
A68: 67 | B68: 2026-03-18 | C68: 3008 | D68: 自营权益4 | E68: 3008 | F68: 601577 | G68: 长沙银行 | H68: 买入 | I68: 9.94 | J68: 9.95 | K68: 48000 | L68: 478560 | M68: 37 | N68: 9.97 | O68: 9.97 | P68: 9.97 | Q68: 9.97 | R68: 9.97 | S68: 上交所A | T68: 14700955 | U68: 0.3265 | V68: 146297022 | W68: 300821 | X68: 自营权益4（场内） | Y68: 48000 | Z68: 10.03 | AA68: 9.88 | AB68: 1 | AC68: 叶盛 | AD68: 股票资产 | AE68: -0.6993 | AF68: 0.3271 | AG68: -0.1859 | AH68: 48000 | AI68: 46 | AJ68: 自营权益4（场内） | AK68: 人民币 | AL68: 40878 | AN68: 30082 | AP68: 顾吟湫 | AQ68: 人民币 | AR68: 478560 | AX68: 无 | BA68: 0.2406 | BB68: 0 | BC68: 缺省券商 | BD68: 交易所业务 | BE68: 不是ETF补券指令 | BF68: -478,560.00 | BG68: 10.01 | BH68: 非强平 | BI68: 顾吟湫 | BJ68: 否 | BK68: 限价 | BM68: 0 | BN68: 7.4666667 | BO68: 股票 | BR68: 0 | BS68: 已成交
A69: 68 | B69: 2026-03-18 | C69: 3008 | D69: 自营权益4 | E69: 3008 | F69: 2807 | G69: 江阴银行 | H69: 买入 | I69: 4.65 | J69: 4.65 | K69: 96000 | L69: 446400 | M69: 1 | N69: 4.65 | O69: 4.65 | P69: 4.65 | Q69: 4.65 | R69: 4.65 | S69: 深交所A | T69: 47604195 | U69: 0.2017 | V69: 2.2152756e+08 | W69: 300821 | X69: 自营权益4（场内） | Y69: 96000 | Z69: 4.71 | AA69: 4.62 | AB69: 2 | AC69: 叶盛 | AD69: 股票资产 | AE69: -1.2739 | AF69: 0.2015 | AG69: 0.0752 | AH69: 96000 | AI69: 46 | AJ69: 自营权益4（场内） | AK69: 人民币 | AL69: 6111 | AN69: 30082 | AP69: 顾吟湫 | AQ69: 人民币 | AR69: 446400 | AX69: 无 | BA69: 0.2245 | BB69: 0 | BC69: 缺省券商 | BD69: 交易所业务 | BE69: 不是ETF补券指令 | BF69: -446,400.00 | BG69: 4.7 | BH69: 非强平 | BI69: 顾吟湫 | BJ69: 否 | BK69: 限价 | BM69: 0 | BN69: 3.95 | BO69: 股票 | BR69: 0 | BS69: 已成交
A70: 69 | B70: 2026-03-18 | C70: 3008 | D70: 自营权益4 | E70: 3008 | F70: 2839 | G70: 张家港行 | H70: 买入 | I70: 4.62 | J70: 4.63 | K70: 96000 | L70: 443520 | M70: 6 | N70: 4.62 | O70: 4.62 | P70: 4.62 | Q70: 4.62 | R70: 4.62 | S70: 深交所A | T70: 28631590 | U70: 0.3353 | V70: 1.3257759e+08 | W70: 300821 | X70: 自营权益4（场内） | Y70: 96000 | Z70: 4.68 | AA70: 4.59 | AB70: 2 | AC70: 叶盛 | AD70: 股票资产 | AE70: -1.0707 | AF70: 0.3345 | AG70: 0.2268 | AH70: 96000 | AI70: 46 | AJ70: 自营权益4（场内） | AK70: 人民币 | AL70: 6111 | AN70: 30082 | AP70: 顾吟湫 | AQ70: 人民币 | AR70: 443520 | AX70: 无 | BA70: 0.223 | BB70: 0 | BC70: 缺省券商 | BD70: 交易所业务 | BE70: 不是ETF补券指令 | BF70: -443,520.00 | BG70: 4.67 | BH70: 非强平 | BI70: 顾吟湫 | BJ70: 否 | BK70: 限价 | BM70: 0 | BN70: 29.9 | BO70: 股票 | BR70: 0 | BS70: 已成交
A71: 70 | B71: 2026-03-18 | C71: 3008 | D71: 自营权益4 | E71: 3008 | F71: 2020 | G71: 安踏体育 | H71: 买入 | I71: 78.65 | J71: 78.68 | K71: 10000 | L71: 786000 | M71: 27 | N71: 78.55 | O71: 78.65 | P71: 78.6 | Q71: 78.6 | R71: 78.6 | S71: 港股通（深） | T71: 3465076 | U71: 0.2886 | V71: 2.7263901e+08 | W71: 300841 | X71: 自营权益4（深港） | Y71: 10000 | Z71: 79.95 | AA71: 78.05 | AB71: 2 | AC71: 叶盛 | AD71: 股票资产 | AE71: -1.2555 | AF71: 0.2883 | AG71: 0.1042 | AH71: 10000 | AI71: 53 | AJ71: 自营权益4（深港） | AK71: 人民币 | AL71: 6111 | AN71: 30084 | AP71: 顾吟湫 | AQ71: 人民币 | AR71: 690791.89 | AW71: KYG040111059 | AX71: 无 | BA71: 0.3473 | BB71: 0 | BC71: 缺省券商 | BD71: 交易所业务 | BE71: 不是ETF补券指令 | BF71: -786,000.00 | BG71: 0 | BH71: 非强平 | BI71: 顾吟湫 | BJ71: 否 | BK71: 增强限价盘 | BM71: 0 | BN71: 0 | BO71: 股票 | BR71: 0 | BS71: 已成交
A72: 71 | B72: 2026-03-18 | C72: 3008 | D72: 自营权益4 | E72: 3008 | F72: 3998 | G72: 波司登 | H72: 买入 | I72: 4.09 | J72: 4.09 | K72: 150000 | L72: 615500 | M72: 11 | N72: 4.1 | O72: 4.11 | P72: 4.1033333 | Q72: 4.1033333 | R72: 4.1033333 | S72: 港股通（深） | T72: 19909328 | U72: 0.7534 | V72: 81438578 | W72: 300841 | X72: 自营权益4（深港） | Y72: 150000 | Z72: 4.14 | AA72: 4.06 | AB72: 3 | AC72: 叶盛 | AD72: 股票资产 | AE72: -0.7282 | AF72: 0.7558 | AG72: -0.3129 | AH72: 150000 | AI72: 53 | AJ72: 自营权益4（深港） | AK72: 人民币 | AL72: 6111 | AN72: 30084 | AP72: 混合 | AQ72: 人民币 | AR72: 540944.47 | AW72: KYG126521064 | AX72: 无 | BA72: 0.272 | BB72: 0 | BC72: 缺省券商 | BD72: 交易所业务 | BE72: 不是ETF补券指令 | BF72: -615,500.00 | BG72: 0 | BH72: 非强平 | BI72: 混合 | BJ72: 否 | BK72: 增强限价盘 | BM72: 0 | BN72: 7.65 | BO72: 股票 | BR72: 0 | BS72: 已成交
A73: 72 | B73: 2026-03-19 | C73: 3008 | D73: 自营权益4 | E73: 3008 | F73: 9985 | G73: 卫龙美味 | H73: 买入 | I73: 10.74 | J73: 10.77 | K73: 50000 | L73: 549500 | M73: 6 | N73: 10.99 | O73: 10.99 | P73: 10.99 | Q73: 10.99 | R73: 10.99 | S73: 港股通（深） | T73: 8948800 | U73: 0.5587 | V73: 96375969 | W73: 300841 | X73: 自营权益4（深港） | Y73: 50000 | Z73: 11.37 | AA73: 10.58 | AB73: 1 | AC73: 叶盛 | AD73: 股票资产 | AE73: -5.5409 | AF73: 0.5702 | AG73: -2.0456 | AH73: 50000 | AI73: 53 | AJ73: 自营权益4（深港） | AK73: 人民币 | AL73: 6111 | AN73: 30084 | AP73: 顾吟湫 | AQ73: 人民币 | AR73: 482455.5 | AW73: KYG9T20T1051 | AX73: 无 | BA73: 0.2445 | BB73: 0 | BC73: 缺省券商 | BD73: 交易所业务 | BE73: 不是ETF补券指令 | BF73: -549,500.00 | BG73: 0 | BH73: 非强平 | BI73: 顾吟湫 | BJ73: 否 | BK73: 增强限价盘 | BM73: 0 | BN73: 9.2833333 | BO73: 股票 | BR73: 0 | BS73: 已成交
A74: 73 | B74: 2026-03-24 | C74: 3008 | D74: 自营权益4 | E74: 3008 | F74: 1368 | G74: 特步国际 | H74: 卖出 | I74: 5.15 | J74: 5.11 | K74: 200000 | L74: 1032000 | M74: 31 | N74: 5.16 | O74: 5.16 | P74: 5.16 | Q74: 5.16 | R74: 5.16 | S74: 港股通（深） | T74: 13763332 | U74: 1.4531 | V74: 70291515 | W74: 300841 | X74: 自营权益4（深港） | Y74: 200000 | Z74: 5.2 | AA74: 4.91 | AB74: 1 | AC74: 叶盛 | AD74: 股票资产 | AE74: 4.4625 | AF74: 1.4682 | AG74: 1.0338 | AH74: 200000 | AI74: 53 | AJ74: 自营权益4（深港） | AK74: 人民币 | AL74: 6111 | AN74: 30084 | AP74: 顾吟湫 | AQ74: 人民币 | AR74: 910296.23 | AW74: KYG982771092 | AX74: 无 | BA74: 0.4643 | BB74: 0 | BC74: 缺省券商 | BD74: 交易所业务 | BE74: 不是ETF补券指令 | BF74: 1,032,000.00 | BG74: 0 | BH74: 非强平 | BI74: 顾吟湫 | BJ74: 否 | BK74: 增强限价盘 | BM74: 0 | BN74: 5.9 | BO74: 股票 | BR74: 0 | BS74: 已成交
A75: 74 | B75: 2026-03-24 | C75: 3008 | D75: 自营权益4 | E75: 3008 | F75: 9985 | G75: 卫龙美味 | H75: 买入 | I75: 10.48 | J75: 10.29 | K75: 100000 | L75: 1046716 | M75: 14 | N75: 10.44 | O75: 10.47 | P75: 10.46716 | Q75: 10.46716 | R75: 10.46716 | S75: 港股通（深） | T75: 3433600 | U75: 2.9124 | V75: 35325154 | W75: 300841 | X75: 自营权益4（深港） | Y75: 100000 | Z75: 10.52 | AA75: 10.06 | AB75: 4 | AC75: 叶盛 | AD75: 股票资产 | AE75: 3.0482 | AF75: 2.9631 | AG75: -1.7408 | AH75: 100000 | AI75: 53 | AJ75: 自营权益4（深港） | AK75: 人民币 | AL75: 6111 | AN75: 30084 | AP75: 顾吟湫 | AQ75: 人民币 | AR75: 924595.66 | AW75: KYG9T20T1051 | AX75: 无 | BA75: 0.4716 | BB75: 0 | BC75: 缺省券商 | BD75: 交易所业务 | BE75: 不是ETF补券指令 | BF75: -1,046,716.00 | BG75: 0 | BH75: 非强平 | BI75: 顾吟湫 | BJ75: 否 | BK75: 增强限价盘 | BM75: 0 | BN75: 1.3833333 | BO75: 股票 | BR75: 0 | BS75: 已成交
A76: 75 | B76: 2026-03-25 | C76: 3008 | D76: 自营权益4 | E76: 3008 | F76: 6862 | G76: 海底捞 | H76: 买入 | I76: 14.22 | J76: 14.53 | K76: 50000 | L76: 716100 | M76: 6 | N76: 14.22 | O76: 14.39 | P76: 14.322 | Q76: 14.322 | R76: 14.322 | S76: 港股通（深） | T76: 93441071 | U76: 0.0535 | V76: 1.357458e+09 | W76: 300841 | X76: 自营权益4（深港） | Y76: 50000 | Z76: 15.6 | AA76: 14.2 | AB76: 2 | AC76: 叶盛 | AD76: 股票资产 | AE76: -11.0694 | AF76: 0.0528 | AG76: 1.4139 | AH76: 50000 | AI76: 53 | AJ76: 自营权益4（深港） | AK76: 人民币 | AL76: 6111 | AN76: 30084 | AP76: 顾吟湫 | AQ76: 人民币 | AR76: 630447.29 | AW76: KYG4290A1013 | AX76: 无 | BA76: 0.3199 | BB76: 0 | BC76: 缺省券商 | BD76: 交易所业务 | BE76: 不是ETF补券指令 | BF76: -716,100.00 | BG76: 0 | BH76: 非强平 | BI76: 顾吟湫 | BJ76: 否 | BK76: 增强限价盘 | BM76: 0 | BN76: 1.5333333 | BO76: 股票 | BR76: 0 | BS76: 已成交
A77: 76 | B77: 2026-03-27 | C77: 3008 | D77: 自营权益4 | E77: 3008 | F77: 1368 | G77: 特步国际 | H77: 买入 | I77: 4.51 | J77: 4.57 | K77: 200000 | L77: 918000 | M77: 48 | N77: 4.58 | O77: 4.6 | P77: 4.59 | Q77: 4.59 | R77: 4.59 | S77: 港股通（深） | T77: 48761530 | U77: 0.4102 | V77: 2.2300252e+08 | W77: 300841 | X77: 自营权益4（深港） | Y77: 200000 | Z77: 4.81 | AA77: 4.5 | AB77: 2 | AC77: 叶盛 | AD77: 股票资产 | AE77: -5.6485 | AF77: 0.4117 | AG77: -0.3652 | AH77: 200000 | AI77: 53 | AJ77: 自营权益4（深港） | AK77: 人民币 | AL77: 6111 | AN77: 30084 | AP77: 顾吟湫 | AQ77: 人民币 | AR77: 810694.96 | AW77: KYG982771092 | AX77: 无 | BA77: 0.4131 | BB77: 0 | BC77: 缺省券商 | BD77: 交易所业务 | BE77: 不是ETF补券指令 | BF77: -918,000.00 | BG77: 0 | BH77: 非强平 | BI77: 顾吟湫 | BJ77: 否 | BK77: 增强限价盘 | BM77: 0 | BN77: 18.183333 | BO77: 股票 | BR77: 0 | BS77: 已成交
A78: 77 | B78: 2026-04-01 | C78: 3008 | D78: 自营权益4 | E78: 3008 | F78: 762 | G78: 中国联通 | H78: 卖出 | I78: 7.12 | J78: 7.12 | K78: 40000 | L78: 285200 | M78: 5 | N78: 7.13 | O78: 7.13 | P78: 7.13 | Q78: 7.13 | R78: 7.13 | S78: 港股通（深） | T78: 20366363 | U78: 0.1964 | V78: 1.4506123e+08 | W78: 300841 | X78: 自营权益4（深港） | Y78: 40000 | Z78: 7.17 | AA78: 7.09 | AB78: 1 | AC78: 叶盛 | AD78: 股票资产 | AE78: 0.7072 | AF78: 0.1966 | AG78: 0.1039 | AH78: 40000 | AI78: 53 | AJ78: 自营权益4（深港） | AK78: 人民币 | AL78: 6111 | AN78: 30084 | AP78: 顾吟湫 | AQ78: 人民币 | AR78: 251332.52 | AW78: HK0000049939 | AX78: 无 | BA78: 0.1267 | BB78: 0 | BC78: 缺省券商 | BD78: 交易所业务 | BE78: 不是ETF补券指令 | BF78: 285,200.00 | BG78: 0 | BH78: 非强平 | BI78: 顾吟湫 | BJ78: 否 | BK78: 增强限价盘 | BM78: 0 | BN78: 45.783333 | BO78: 股票 | BR78: 0 | BS78: 已成交
A79: 78 | B79: 2026-04-01 | C79: 3008 | D79: 自营权益4 | E79: 3008 | F79: 1368 | G79: 特步国际 | H79: 买入 | I79: 4.55 | J79: 4.52 | K79: 150000 | L79: 684000 | M79: 25 | N79: 4.56 | O79: 4.56 | P79: 4.56 | Q79: 4.56 | R79: 4.56 | S79: 港股通（深） | T79: 17673500 | U79: 0.8487 | V79: 79957140 | W79: 300841 | X79: 自营权益4（深港） | Y79: 150000 | Z79: 4.58 | AA79: 4.46 | AB79: 3 | AC79: 叶盛 | AD79: 股票资产 | AE79: 1.7897 | AF79: 0.8555 | AG79: -0.7935 | AH79: 150000 | AI79: 53 | AJ79: 自营权益4（深港） | AK79: 人民币 | AL79: 6111 | AN79: 30084 | AP79: 顾吟湫 | AQ79: 人民币 | AR79: 603527.44 | AW79: KYG982771092 | AX79: 无 | BA79: 0.3042 | BB79: 0 | BC79: 缺省券商 | BD79: 交易所业务 | BE79: 不是ETF补券指令 | BF79: -684,000.00 | BG79: 0 | BH79: 非强平 | BI79: 顾吟湫 | BJ79: 否 | BK79: 增强限价盘 | BM79: 0 | BN79: 151.38333 | BO79: 股票 | BR79: 0 | BS79: 已成交
A80: 79 | B80: 2026-04-01 | C80: 3008 | D80: 自营权益4 | E80: 3008 | F80: 1398 | G80: 工商银行 | H80: 卖出 | I80: 6.88 | J80: 6.9 | K80: 200000 | L80: 1376000 | M80: 1 | N80: 6.88 | O80: 6.88 | P80: 6.88 | Q80: 6.88 | R80: 6.88 | S80: 港股通（深） | T80: 277117681 | U80: 0.0722 | V80: 1.9117465e+09 | W80: 300841 | X80: 自营权益4（深港） | Y80: 200000 | Z80: 6.96 | AA80: 6.85 | AB80: 1 | AC80: 叶盛 | AD80: 股票资产 | AE80: 0.2915 | AF80: 0.072 | AG80: -0.2711 | AH80: 200000 | AI80: 53 | AJ80: 自营权益4（深港） | AK80: 人民币 | AL80: 6111 | AN80: 30084 | AP80: 顾吟湫 | AQ80: 人民币 | AR80: 1212600 | AW80: CNE1000003G1 | AX80: 无 | BA80: 0.6111 | BB80: 0 | BC80: 缺省券商 | BD80: 交易所业务 | BE80: 不是ETF补券指令 | BF80: 1,376,000.00 | BG80: 0 | BH80: 非强平 | BI80: 顾吟湫 | BJ80: 否 | BK80: 增强限价盘 | BM80: 0 | BN80: 8.5833333 | BO80: 股票 | BR80: 0 | BS80: 已成交
A81: 80 | B81: 2026-04-01 | C81: 3008 | D81: 自营权益4 | E81: 3008 | F81: 3988 | G81: 中国银行 | H81: 卖出 | I81: 5.01 | J81: 5 | K81: 100000 | L81: 500000 | M81: 1 | N81: 5 | O81: 5 | P81: 5 | Q81: 5 | R81: 5 | S81: 港股通（深） | T81: 343698026 | U81: 0.0291 | V81: 1.7176443e+09 | W81: 300841 | X81: 自营权益4（深港） | Y81: 100000 | Z81: 5.02 | AA81: 4.96 | AB81: 1 | AC81: 叶盛 | AD81: 股票资产 | AE81: 0.8048 | AF81: 0.0291 | AG81: 0.05 | AH81: 100000 | AI81: 53 | AJ81: 自营权益4（深港） | AK81: 人民币 | AL81: 6111 | AN81: 30084 | AP81: 顾吟湫 | AQ81: 人民币 | AR81: 440625 | AW81: CNE1000001Z5 | AX81: 无 | BA81: 0.2221 | BB81: 0 | BC81: 缺省券商 | BD81: 交易所业务 | BE81: 不是ETF补券指令 | BF81: 500,000.00 | BG81: 0 | BH81: 非强平 | BI81: 顾吟湫 | BJ81: 否 | BK81: 增强限价盘 | BM81: 0 | BN81: 16.966667 | BO81: 股票 | BR81: 0 | BS81: 已成交
A82: 81 | B82: 2026-04-01 | C82: 3008 | D82: 自营权益4 | E82: 3008 | F82: 3998 | G82: 波司登 | H82: 买入 | I82: 4.07 | J82: 4.07 | K82: 300000 | L82: 1230520 | M82: 34 | N82: 4.1 | O82: 4.11 | P82: 4.1017333 | Q82: 4.1017333 | R82: 4.1017333 | S82: 港股通（深） | T82: 15046817 | U82: 1.9938 | V82: 61184707 | W82: 300841 | X82: 自营权益4（深港） | Y82: 300000 | Z82: 4.12 | AA82: 4.01 | AB82: 2 | AC82: 叶盛 | AD82: 股票资产 | AE82: 1.75 | AF82: 2.0112 | AG82: -0.8706 | AH82: 300000 | AI82: 53 | AJ82: 自营权益4（深港） | AK82: 人民币 | AL82: 6111 | AN82: 30084 | AP82: 顾吟湫 | AQ82: 人民币 | AR82: 1085749.3 | AW82: KYG126521064 | AX82: 无 | BA82: 0.5472 | BB82: 0 | BC82: 缺省券商 | BD82: 交易所业务 | BE82: 不是ETF补券指令 | BF82: -1,230,520.00 | BG82: 0 | BH82: 非强平 | BI82: 顾吟湫 | BJ82: 否 | BK82: 增强限价盘 | BM82: 0 | BN82: 6.8166667 | BO82: 股票 | BR82: 0 | BS82: 已成交
... A91: 90 | B91: 2026-04-09 | C91: 3008 | D91: 自营权益4 | E91: 3008 | F91: 9985 | G91: 卫龙美味 | H91: 买入 | I91: 9.5 | J91: 9.58 | K91: 30000 | L91: 286000 | M91: 14 | N91: 9.5 | O91: 9.55 | P91: 9.5333333 | Q91: 9.5333333 | R91: 9.5333333 | S91: 港股通（深） | T91: 7597576 | U91: 0.3949 | V91: 72761958 | W91: 300841 | X91: 自营权益4（深港） | Y91: 30000 | Z91: 9.9 | AA91: 9.47 | AB91: 2 | AC91: 叶盛 | AD91: 股票资产 | AE91: -2.7636 | AF91: 0.3931 | AG91: 0.4563 | AH91: 30000 | AI91: 53 | AJ91: 自营权益4（深港） | AK91: 人民币 | AL91: 6111 | AN91: 30084 | AP91: 顾吟湫 | AQ91: 人民币 | AR91: 249337.65 | AW91: KYG9T20T1051 | AX91: 无 | BA91: 0.1261 | BB91: 0 | BC91: 缺省券商 | BD91: 交易所业务 | BE91: 不是ETF补券指令 | BF91: -286,000.00 | BG91: 0 | BH91: 非强平 | BI91: 顾吟湫 | BJ91: 否 | BK91: 增强限价盘 | BM91: 0 | BN91: 6.25 | BO91: 股票 | BR91: 0 | BS91: 已成交
A92: 91 | B92: 2026-04-10 | C92: 3008 | D92: 自营权益4 | E92: 3008 | F92: 600887 | G92: 伊利股份 | H92: 买入 | I92: 26.14 | J92: 26.31 | K92: 50000 | L92: 1313500 | M92: 31 | N92: 26.27 | O92: 26.27 | P92: 26.27 | Q92: 26.27 | R92: 26.27 | S92: 上交所A | T92: 28061054 | U92: 0.1782 | V92: 738245207 | W92: 300821 | X92: 自营权益4（场内） | Y92: 50000 | Z92: 26.48 | AA92: 26.1 | AB92: 1 | AC92: 叶盛 | AD92: 股票资产 | AE92: 0.0766 | AF92: 0.1779 | AG92: 0.1463 | AH92: 50000 | AI92: 46 | AJ92: 自营权益4（场内） | AK92: 人民币 | AL92: 40878 | AN92: 30082 | AP92: 顾吟湫 | AQ92: 人民币 | AR92: 1313500 | AS92: 600887 | AT92: 600887 | AU92: 600887 | AV92: 600887 | AW92: 600887 | AX92: 无 | BA92: 0.662 | BB92: 0 | BC92: 缺省券商 | BD92: 交易所业务 | BE92: 不是ETF补券指令 | BF92: -1,313,500.00 | BG92: 26.25 | BH92: 非强平 | BI92: 顾吟湫 | BJ92: 否 | BK92: 限价 | BM92: 0 | BN92: 156.25 | BO92: 股票 | BR92: 0 | BS92: 已成交
A93: 92 | B93: 2026-04-10 | C93: 3008 | D93: 自营权益4 | E93: 3008 | F93: 601825 | G93: 沪农商行 | H93: 卖出 | I93: 9.2 | J93: 9.17 | K93: 150000 | L93: 1380000 | M93: 95 | N93: 9.2 | O93: 9.2 | P93: 9.2 | Q93: 9.2 | R93: 9.2 | S93: 上交所A | T93: 22728696 | U93: 0.66 | V93: 208461610 | W93: 300821 | X93: 自营权益4（场内） | Y93: 150000 | Z93: 9.29 | AA93: 8.98 | AB93: 2 | AC93: 叶盛 | AD93: 股票资产 | AE93: 1.7699 | AF93: 0.662 | AG93: 0.3086 | AH93: 150000 | AI93: 46 | AJ93: 自营权益4（场内） | AK93: 人民币 | AL93: 40878 | AN93: 30082 | AP93: 顾吟湫 | AQ93: 人民币 | AR93: 1380000 | AX93: 无 | BA93: 0.6956 | BB93: 0 | BC93: 缺省券商 | BD93: 交易所业务 | BE93: 不是ETF补券指令 | BF93: 1,380,000.00 | BG93: 9.05 | BH93: 非强平 | BI93: 顾吟湫 | BJ93: 否 | BK93: 限价 | BM93: 0 | BN93: 1.1166667 | BO93: 股票 | BR93: 0 | BS93: 已成交
A94: 93 | B94: 2026-04-10 | C94: 3008 | D94: 自营权益4 | E94: 3008 | F94: 998 | G94: 中信银行 | H94: 卖出 | I94: 7.91 | J94: 7.88 | K94: 300000 | L94: 2361000 | M94: 1 | N94: 7.87 | O94: 7.87 | P94: 7.87 | Q94: 7.87 | R94: 7.87 | S94: 港股通（深） | T94: 15248818 | U94: 1.9674 | V94: 1.2022684e+08 | W94: 300841 | X94: 自营权益4（深港） | Y94: 300000 | Z94: 7.92 | AA94: 7.85 | AB94: 2 | AC94: 叶盛 | AD94: 股票资产 | AE94: 0.1266 | AF94: 1.9638 | AG94: -0.1814 | AH94: 300000 | AI94: 53 | AJ94: 自营权益4（深港） | AK94: 人民币 | AL94: 6111 | AN94: 30084 | AP94: 顾吟湫 | AQ94: 人民币 | AR94: 2061318.3 | AW94: CNE1000001Q4 | AX94: 无 | BA94: 1.039 | BB94: 0 | BC94: 缺省券商 | BD94: 交易所业务 | BE94: 不是ETF补券指令 | BF94: 2,361,000.00 | BG94: 0 | BH94: 非强平 | BI94: 顾吟湫 | BJ94: 否 | BK94: 增强限价盘 | BM94: 0 | BN94: 14.866667 | BO94: 股票 | BR94: 0 | BS94: 已成交
A95: 94 | B95: 2026-04-10 | C95: 3008 | D95: 自营权益4 | E95: 3008 | F95: 1398 | G95: 工商银行 | H95: 卖出 | I95: 6.97 | J95: 6.96 | K95: 100000 | L95: 697000 | M95: 22 | N95: 6.97 | O95: 6.97 | P95: 6.97 | Q95: 6.97 | R95: 6.97 | S95: 港股通（深） | T95: 140216132 | U95: 0.0713 | V95: 9.7559576e+08 | W95: 300841 | X95: 自营权益4（深港） | Y95: 200000 | Z95: 6.98 | AA95: 6.93 | AB95: 2 | AC95: 叶盛 | AD95: 股票资产 | AE95: 0.5772 | AF95: 0.0714 | AG95: 0.1753 | AH95: 200000 | AI95: 53 | AJ95: 自营权益4（深港） | AK95: 人民币 | AL95: 6111 | AN95: 30084 | AP95: 顾吟湫 | AQ95: 人民币 | AR95: 608529.82 | AW95: CNE1000003G1 | AX95: 无 | BA95: 0.3067 | BB95: 0 | BC95: 缺省券商 | BD95: 交易所业务 | BE95: 不是ETF补券指令 | BF95: 697,000.00 | BG95: 0 | BH95: 非强平 | BI95: 顾吟湫 | BJ95: 否 | BK95: 增强限价盘 | BM95: 0 | BN95: 179.61667 | BO95: 股票 | BR95: 0 | BS95: 已成交
A96: 95 | B96: 2026-04-10 | C96: 3008 | D96: 自营权益4 | E96: 3008 | F96: 3988 | G96: 中国银行 | H96: 卖出 | I96: 5.04 | J96: 5.03 | K96: 300000 | L96: 1512000 | M96: 1 | N96: 5.04 | O96: 5.04 | P96: 5.04 | Q96: 5.04 | R96: 5.04 | S96: 港股通（深） | T96: 157669567 | U96: 0.1903 | V96: 7.9272844e+08 | W96: 300841 | X96: 自营权益4（深港） | Y96: 500000 | Z96: 5.05 | AA96: 5 | AB96: 2 | AC96: 叶盛 | AD96: 股票资产 | AE96: 0.1988 | AF96: 0.1907 | AG96: 0.2427 | AH96: 500000 | AI96: 53 | AJ96: 自营权益4（深港） | AK96: 人民币 | AL96: 6111 | AN96: 30084 | AP96: 顾吟湫 | AQ96: 人民币 | AR96: 1320081.8 | AW96: CNE1000001Z5 | AX96: 无 | BA96: 0.6654 | BB96: 0 | BC96: 缺省券商 | BD96: 交易所业务 | BE96: 不是ETF补券指令 | BF96: 1,512,000.00 | BG96: 0 | BH96: 非强平 | BI96: 顾吟湫 | BJ96: 否 | BK96: 增强限价盘 | BM96: 0 | BN96: 56.65 | BO96: 股票 | BR96: 0 | BS96: 已成交
A97: 96 | B97: 2026-04-10 | C97: 3008 | D97: 自营权益4 | E97: 3008 | F97: 6818 | G97: 中国光大银行 | H97: 买入 | I97: 3.12 | J97: 3.1 | K97: 780000 | L97: 2418000 | M97: 57 | N97: 3.1 | O97: 3.1 | P97: 3.1 | Q97: 3.1 | R97: 3.1 | S97: 港股通（深） | T97: 9528038 | U97: 8.1864 | V97: 29510882 | W97: 300841 | X97: 自营权益4（深港） | Y97: 780000 | Z97: 3.13 | AA97: 3.06 | AB97: 2 | AC97: 叶盛 | AD97: 股票资产 | AE97: 2.2951 | AF97: 8.1936 | AG97: -0.0872 | AH97: 780000 | AI97: 53 | AJ97: 自营权益4（深港） | AK97: 人民币 | AL97: 6111 | AN97: 30084 | AP97: 顾吟湫 | AQ97: 人民币 | AR97: 2111228.4 | AW97: CNE100001QW3 | AX97: 无 | BA97: 1.0641 | BB97: 0 | BC97: 缺省券商 | BD97: 交易所业务 | BE97: 不是ETF补券指令 | BF97: -2,418,000.00 | BG97: 0 | BH97: 非强平 | BI97: 顾吟湫 | BJ97: 否 | BK97: 增强限价盘 | BM97: 0 | BN97: 0 | BO97: 股票 | BR97: 0 | BS97: 已成交
A98: 97 | B98: 2026-04-10 | C98: 3008 | D98: 自营权益4 | E98: 3008 | F98: 9985 | G98: 卫龙美味 | H98: 买入 | I98: 9.55 | J98: 9.5 | K98: 50000 | L98: 477000 | M98: 4 | N98: 9.54 | O98: 9.54 | P98: 9.54 | Q98: 9.54 | R98: 9.54 | S98: 港股通（深） | T98: 3319400 | U98: 1.5063 | V98: 31531385 | W98: 300841 | X98: 自营权益4（深港） | Y98: 50000 | Z98: 9.62 | AA98: 9.42 | AB98: 1 | AC98: 叶盛 | AD98: 股票资产 | AE98: 0.5263 | AF98: 1.5128 | AG98: -0.4306 | AH98: 50000 | AI98: 53 | AJ98: 自营权益4（深港） | AK98: 人民币 | AL98: 6111 | AN98: 30084 | AP98: 顾吟湫 | AQ98: 人民币 | AR98: 416483 | AW98: KYG9T20T1051 | AX98: 无 | BA98: 0.2099 | BB98: 0 | BC98: 缺省券商 | BD98: 交易所业务 | BE98: 不是ETF补券指令 | BF98: -477,000.00 | BG98: 0 | BH98: 非强平 | BI98: 顾吟湫 | BJ98: 否 | BK98: 增强限价盘 | BM98: 0 | BN98: 0.5 | BO98: 股票 | BR98: 0 | BS98: 已成交
A99: 98 | B99: 2026-04-13 | C99: 3008 | D99: 自营权益4 | E99: 3008 | F99: 3933 | G99: 联邦制药 | H99: 买入 | I99: 9.8 | J99: 9.82 | K99: 20000 | L99: 196000 | M99: 5 | N99: 9.8 | O99: 9.8 | P99: 9.8 | Q99: 9.8 | R99: 9.8 | S99: 港股通（深） | T99: 5255920 | U99: 0.3805 | V99: 51601795 | W99: 300841 | X99: 自营权益4（深港） | Y99: 20000 | Z99: 10.14 | AA99: 9.76 | AB99: 1 | AC99: 叶盛 | AD99: 股票资产 | AE99: -2.8741 | AF99: 0.3798 | AG99: 0.1813 | AH99: 20000 | AI99: 53 | AJ99: 自营权益4（深港） | AK99: 人民币 | AL99: 6111 | AN99: 30084 | AP99: 顾吟湫 | AQ99: 人民币 | AR99: 170990.4 | AW99: KYG8813K1085 | AX99: 无 | BA99: 0.0866 | BB99: 0 | BC99: 缺省券商 | BD99: 交易所业务 | BE99: 不是ETF补券指令 | BF99: -196,000.00 | BG99: 0 | BH99: 非强平 | BI99: 顾吟湫 | BJ99: 否 | BK99: 增强限价盘 | BM99: 0 | BN99: 13.466667 | BO99: 股票 | BR99: 0 | BS99: 已成交
A100: 99 | B100: 2026-04-13 | C100: 3008 | D100: 自营权益4 | E100: 3008 | F100: 6818 | G100: 中国光大银行 | H100: 买入 | I100: 3.12 | J100: 3.12 | K100: 420000 | L100: 1303920 | M100: 65 | N100: 3.1 | O100: 3.13 | P100: 3.1045714 | Q100: 3.1045714 | R100: 3.1045714 | S100: 港股通（深） | T100: 16794025 | U100: 2.5009 | V100: 52344552 | W100: 300841 | X100: 自营权益4（深港） | Y100: 420000 | Z100: 3.13 | AA100: 3.07 | AB100: 7 | AC100: 叶盛 | AD100: 股票资产 | AE100: 0 | AF100: 2.491 | AG100: 0.3946 | AH100: 420000 | AI100: 53 | AJ100: 自营权益4（深港） | AK100: 人民币 | AL100: 6111 | AN100: 30084 | AP100: 顾吟湫 | AQ100: 人民币 | AR100: 1137539.8 | AW100: CNE100001QW3 | AX100: 无 | BA100: 0.5762 | BB100: 0 | BC100: 缺省券商 | BD100: 交易所业务 | BE100: 不是ETF补券指令 | BF100: -1,303,920.00 | BG100: 0 | BH100: 非强平 | BI100: 顾吟湫 | BJ100: 否 | BK100: 增强限价盘 | BM100: 0 | BN100: 439.13333 | BO100: 股票 | BR100: 0 | BS100: 已成交
A101: 100 | B101: 2026-04-13 | C101: 3008 | D101: 自营权益4 | E101: 3008 | F101: 9985 | G101: 卫龙美味 | H101: 买入 | I101: 9.34 | J101: 9.34 | K101: 20000 | L101: 186600 | M101: 5 | N101: 9.33 | O101: 9.33 | P101: 9.33 | Q101: 9.33 | R101: 9.33 | S101: 港股通（深） | T101: 3447400 | U101: 0.5801 | V101: 32196379 | W101: 300841 | X101: 自营权益4（深港） | Y101: 20000 | Z101: 9.51 | AA101: 9.25 | AB101: 1 | AC101: 叶盛 | AD101: 股票资产 | AE101: -2.199 | AF101: 0.5796 | AG101: 0.0996 | AH101: 20000 | AI101: 53 | AJ101: 自营权益4（深港） | AK101: 人民币 | AL101: 6111 | AN101: 30084 | AP101: 顾吟湫 | AQ101: 人民币 | AR101: 162789.85 | AW101: KYG9T20T1051 | AX101: 无 | BA101: 0.0825 | BB101: 0 | BC101: 缺省券商 | BD101: 交易所业务 | BE101: 不是ETF补券指令 | BF101: -186,600.00 | BG101: 0 | BH101: 非强平 | BI101: 顾吟湫 | BJ101: 否 | BK101: 增强限价盘 | BM101: 0 | BN101: 1.25 | BO101: 股票 | BR101: 0 | BS101: 已成交
A102: 101 | B102: 2026-04-14 | C102: 3008 | D102: 自营权益4 | E102: 3008 | F102: 3988 | G102: 中国银行 | H102: 卖出 | I102: 5.11 | J102: 5.09 | K102: 200000 | L102: 1020000 | M102: 12 | N102: 5.1 | O102: 5.1 | P102: 5.1 | Q102: 5.1 | R102: 5.1 | S102: 港股通（深） | T102: 203974553 | U102: 0.0981 | V102: 1.0386053e+09 | W102: 300841 | X102: 自营权益4（深港） | Y102: 200000 | Z102: 5.12 | AA102: 5.02 | AB102: 1 | AC102: 叶盛 | AD102: 股票资产 | AE102: 1.3889 | AF102: 0.0982 | AG102: 0.161 | AH102: 200000 | AI102: 53 | AJ102: 自营权益4（深港） | AK102: 人民币 | AL102: 6111 | AN102: 30084 | AP102: 顾吟湫 | AQ102: 人民币 | AR102: 889929.6 | AW102: CNE1000001Z5 | AX102: 无 | BA102: 0.4476 | BB102: 0 | BC102: 缺省券商 | BD102: 交易所业务 | BE102: 不是ETF补券指令 | BF102: 1,020,000.00 | BG102: 0 | BH102: 非强平 | BI102: 顾吟湫 | BJ102: 否 | BK102: 增强限价盘 | BM102: 0 | BN102: 0 | BO102: 股票 | BR102: 0 | BS102: 已成交
A103: 102 | B103: 2026-04-14 | C103: 3008 | D103: 自营权益4 | E103: 3008 | F103: 6818 | G103: 中国光大银行 | H103: 买入 | I103: 3.14 | J103: 3.12 | K103: 300000 | L103: 939000 | M103: 5 | N103: 3.13 | O103: 3.13 | P103: 3.13 | Q103: 3.13 | R103: 3.13 | S103: 港股通（深） | T103: 16556000 | U103: 1.812 | V103: 51734778 | W103: 300841 | X103: 自营权益4（深港） | Y103: 300000 | Z103: 3.16 | AA103: 3.09 | AB103: 2 | AC103: 叶盛 | AD103: 股票资产 | AE103: 0.641 | AF103: 1.815 | AG103: -0.1664 | AH103: 300000 | AI103: 53 | AJ103: 自营权益4（深港） | AK103: 人民币 | AL103: 6111 | AN103: 30084 | AP103: 顾吟湫 | AQ103: 人民币 | AR103: 819484.08 | AW103: CNE100001QW3 | AX103: 无 | BA103: 0.4122 | BB103: 0 | BC103: 缺省券商 | BD103: 交易所业务 | BE103: 不是ETF补券指令 | BF103: -939,000.00 | BG103: 0 | BH103: 非强平 | BI103: 顾吟湫 | BJ103: 否 | BK103: 增强限价盘 | BM103: 0 | BN103: 0 | BO103: 股票 | BR103: 0 | BS103: 已成交
A104: 103 | B104: 2026-04-15 | C104: 3008 | D104: 自营权益4 | E104: 3008 | F104: 600690 | G104: 海尔智家 | H104: 买入 | I104: 21.05 | J104: 21.09 | K104: 90000 | L104: 1908810 | M104: 42 | N104: 21.2 | O104: 21.21 | P104: 21.209 | Q104: 21.209 | R104: 21.209 | S104: 上交所A | T104: 46258157 | U104: 0.1946 | V104: 975587540 | W104: 300821 | X104: 自营权益4（场内） | Y104: 90000 | Z104: 21.25 | AA104: 20.95 | AB104: 3 | AC104: 叶盛 | AD104: 股票资产 | AE104: 0.5253 | AF104: 0.1957 | AG104: -0.5638 | AH104: 90000 | AI104: 46 | AJ104: 自营权益4（场内） | AK104: 人民币 | AL104: 40878 | AN104: 30082 | AP104: 顾吟湫 | AQ104: 人民币 | AR104: 1908810 | AS104: 600690 | AT104: 600690 | AU104: 600690 | AV104: 600690 | AW104: 600690 | AX104: 无 | BA104: 0.9607 | BB104: 0 | BC104: 缺省券商 | BD104: 交易所业务 | BE104: 不是ETF补券指令 | BF104: -1,908,810.00 | BG104: 21.06 | BH104: 非强平 | BI104: 顾吟湫 | BJ104: 否 | BK104: 限价 | BM104: 0 | BN104: 6.7166667 | BO104: 股票 | BR104: 0 | BS104: 已成交
A105: 104 | B105: 2026-04-15 | C105: 3008 | D105: 自营权益4 | E105: 3008 | F105: 600908 | G105: 无锡银行 | H105: 卖出 | I105: 5.69 | J105: 5.68 | K105: 200000 | L105: 1134000 | M105: 112 | N105: 5.67 | O105: 5.67 | P105: 5.67 | Q105: 5.67 | R105: 5.67 | S105: 上交所A | T105: 13570678 | U105: 1.4738 | V105: 77052107 | W105: 300821 | X105: 自营权益4（场内） | Y105: 200000 | Z105: 5.7 | AA105: 5.63 | AB105: 1 | AC105: 叶盛 | AD105: 股票资产 | AE105: 0.8865 | AF105: 1.4717 | AG105: -0.1374 | AH105: 200000 | AI105: 46 | AJ105: 自营权益4（场内） | AK105: 人民币 | AL105: 40878 | AN105: 30082 | AP105: 顾吟湫 | AQ105: 人民币 | AR105: 1134000 | AX105: 无 | BA105: 0.5707 | BB105: 0 | BC105: 缺省券商 | BD105: 交易所业务 | BE105: 不是ETF补券指令 | BF105: 1,134,000.00 | BG105: 5.64 | BH105: 非强平 | BI105: 顾吟湫 | BJ105: 否 | BK105: 限价 | BM105: 0 | BN105: 0.033333333 | BO105: 股票 | BR105: 0 | BS105: 已成交
A106: 105 | B106: 2026-04-15 | C106: 3008 | D106: 自营权益4 | E106: 3008 | F106: 600919 | G106: 江苏银行 | H106: 卖出 | I106: 10.95 | J106: 10.89 | K106: 180000 | L106: 1958400 | M106: 77 | N106: 10.88 | O106: 10.88 | P106: 10.88 | Q106: 10.88 | R106: 10.88 | S106: 上交所A | T106: 66740966 | U106: 0.2697 | V106: 726655764 | W106: 300821 | X106: 自营权益4（场内） | Y106: 180000 | Z106: 10.96 | AA106: 10.79 | AB106: 1 | AC106: 叶盛 | AD106: 股票资产 | AE106: 1.2015 | AF106: 0.2695 | AG106: -0.0707 | AH106: 180000 | AI106: 46 | AJ106: 自营权益4（场内） | AK106: 人民币 | AL106: 40878 | AN106: 30082 | AP106: 顾吟湫 | AQ106: 人民币 | AR106: 1958400 | AX106: 无 | BA106: 0.9857 | BB106: 0 | BC106: 缺省券商 | BD106: 交易所业务 | BE106: 不是ETF补券指令 | BF106: 1,958,400.00 | BG106: 10.8 | BH106: 非强平 | BI106: 顾吟湫 | BJ106: 否 | BK106: 限价 | BM106: 0 | BN106: 0.7 | BO106: 股票 | BR106: 0 | BS106: 已成交
A107: 106 | B107: 2026-04-15 | C107: 3008 | D107: 自营权益4 | E107: 3008 | F107: 601577 | G107: 长沙银行 | H107: 卖出 | I107: 9.47 | J107: 9.46 | K107: 100000 | L107: 945000 | M107: 23 | N107: 9.45 | O107: 9.45 | P107: 9.45 | Q107: 9.45 | R107: 9.45 | S107: 上交所A | T107: 14974821 | U107: 0.6678 | V107: 141611422 | W107: 300821 | X107: 自营权益4（场内） | Y107: 100000 | Z107: 9.5 | AA107: 9.4 | AB107: 1 | AC107: 叶盛 | AD107: 股票资产 | AE107: 0.852 | AF107: 0.6673 | AG107: -0.0698 | AH107: 100000 | AI107: 46 | AJ107: 自营权益4（场内） | AK107: 人民币 | AL107: 40878 | AN107: 30082 | AP107: 顾吟湫 | AQ107: 人民币 | AR107: 945000 | AX107: 无 | BA107: 0.4756 | BB107: 0 | BC107: 缺省券商 | BD107: 交易所业务 | BE107: 不是ETF补券指令 | BF107: 945,000.00 | BG107: 9.44 | BH107: 非强平 | BI107: 顾吟湫 | BJ107: 否 | BK107: 限价 | BM107: 0 | BN107: 0 | BO107: 股票 | BR107: 0 | BS107: 已成交
A108: 107 | B108: 2026-04-15 | C108: 3008 | D108: 自营权益4 | E108: 3008 | F108: 333 | G108: 美的集团 | H108: 买入 | I108: 77.49 | J108: 77.29 | K108: 50000 | L108: 3871600 | M108: 62 | N108: 77.43 | O108: 77.44 | P108: 77.432 | Q108: 77.432 | R108: 77.432 | S108: 深交所A | T108: 31845072 | U108: 0.157 | V108: 2.4612869e+09 | W108: 300821 | X108: 自营权益4（场内） | Y108: 50000 | Z108: 77.88 | AA108: 76.2 | AB108: 4 | AC108: 叶盛 | AD108: 股票资产 | AE108: 1.228 | AF108: 0.1573 | AG108: -0.1845 | AH108: 50000 | AI108: 46 | AJ108: 自营权益4（场内） | AK108: 人民币 | AL108: 6111 | AN108: 30082 | AP108: 顾吟湫 | AQ108: 人民币 | AR108: 3871600 | AS108: 333 | AT108: 333 | AU108: 333 | AV108: 333 | AW108: 000333 | AX108: 无 | BA108: 1.9486 | BB108: 0 | BC108: 缺省券商 | BD108: 交易所业务 | BE108: 不是ETF补券指令 | BF108: -3,871,600.00 | BG108: 76.55 | BH108: 非强平 | BI108: 顾吟湫 | BJ108: 否 | BK108: 限价 | BM108: 0 | BN108: 64.033333 | BO108: 股票 | BR108: 0 | BS108: 已成交
...

Sheet 初始持仓
A1: 股票代码 | B1: 股票名称 | C1: 数量 | D1: 成本 | E1: 市价 | F1: 市值 | G1: 账户名称
A2: 600036 | B2: 招商银行 | C2: 150000 | D2: 6307325.2 | E2: 42.1 | F2: 6315000 | G2: 自营权益4
A3: 600519 | B3: 贵州茅台 | C3: 100 | D3: 148310.9 | E3: 1377.18 | F3: 137718 | G3: 自营权益4
A4: 600809 | B4: 山西汾酒 | C4: 16000 | D4: 2869126.9 | E4: 171.7 | F4: 2747200 | G4: 自营权益4
A5: 601009 | B5: 南京银行 | C5: 300000 | D5: 3332290.5 | E5: 11.43 | F5: 3429000 | G5: 自营权益4
A6: 601098 | B6: 中南传媒 | C6: 300000 | D6: 3912034 | E6: 11.26 | F6: 3378000 | G6: 自营权益4
A7: 601166 | B7: 兴业银行 | C7: 300000 | D7: 6347906.6 | E7: 21.06 | F7: 6318000 | G7: 自营权益4
A8: 601169 | B8: 北京银行 | C8: 1500000 | D8: 8791842.6 | E8: 5.48 | F8: 8220000 | G8: 自营权益4
A9: 601818 | B9: 光大银行 | C9: 2700000 | D9: 9766819.9 | E9: 3.49 | F9: 9423000 | G9: 自营权益4
A10: 601900 | B10: 南方传媒 | C10: 200000 | D10: 3093896.3 | E10: 13.41 | F10: 2682000 | G10: 自营权益4
A11: 603198 | B11: 迎驾贡酒 | C11: 60000 | D11: 2637959.9 | E11: 39.56 | F11: 2373600 | G11: 自营权益4
A12: 603369 | B12: 今世缘 | C12: 60000 | D12: 2460995.7 | E12: 34.78 | F12: 2086800 | G12: 自营权益4
A13: 1 | B13: 平安银行 | C13: 700000 | D13: 8159372.6 | E13: 11.41 | F13: 7987000 | G13: 自营权益4
... A41: 6862 | B41: 海底捞 | C41: 400000 | D41: 5365768.8 | E41: 12.78795 | F41: 5115180 | G41: 自营权益4

Sheet 初始资金
A1: 账户名称 | B1: 期初资金
A2: 自营权益4 | B2: 202510600

Sheet 映射
A1: 组合名称样例 | B1: II-a 列 | C1: COUNTIFS 通配
A2: 自营权益4（深港） | B2: 深港 | C2: *深港*
A3: 自营权益4（场内） | B3: 场内 | C3: *场内*
A5: 说明 | B5: 场内/深港 由组合名称关键字判定；股指/基金本样例为 0

Sheet 期初批次
A1: 账户名称 | B1: 证券代码 | C1: 证券名称 | D1: 数量 | E1: 成本总额(CNY) | F1: 成本单价(CNY) | G1: 市价(CNY) | H1: 市值(CNY) | I1: 叶子投组 | J1: 标准代码 | K1: 期初折算汇率(HKD/CNY) | L1: 成本单价(原币) | M1: 成本总额(原币)
A2: 自营权益4 | B2: 600036 | C2: 招商银行 | D2: 150000 | E2: 6307325.2 | F2: 42.048835 | G2: 42.1 | H2: 6315000 | I2: 场内 | J2: 600036.SH | K2: ='FX_RATES_TO_CNY_HIST'!$B$5 | L2: =IF(I2="深港",IF(K2>0,F2/K2,""),F2) | M2: =IF(I2="深港",IF(K2>0,E2/K2,""),E2)
A3: 自营权益4 | B3: 600519 | C3: 贵州茅台 | D3: 100 | E3: 148310.9 | F3: 1483.109 | G3: 1377.18 | H3: 137718 | I3: 场内 | J3: 600519.SH | K3: ='FX_RATES_TO_CNY_HIST'!$B$5 | L3: =IF(I3="深港",IF(K3>0,F3/K3,""),F3) | M3: =IF(I3="深港",IF(K3>0,E3/K3,""),E3)
A4: 自营权益4 | B4: 600809 | C4: 山西汾酒 | D4: 16000 | E4: 2869126.9 | F4: 179.32043 | G4: 171.7 | H4: 2747200 | I4: 场内 | J4: 600809.SH | K4: ='FX_RATES_TO_CNY_HIST'!$B$5 | L4: =IF(I4="深港",IF(K4>0,F4/K4,""),F4) | M4: =IF(I4="深港",IF(K4>0,E4/K4,""),E4)
A5: 自营权益4 | B5: 601009 | C5: 南京银行 | D5: 300000 | E5: 3332290.5 | F5: 11.107635 | G5: 11.43 | H5: 3429000 | I5: 场内 | J5: 601009.SH | K5: ='FX_RATES_TO_CNY_HIST'!$B$5 | L5: =IF(I5="深港",IF(K5>0,F5/K5,""),F5) | M5: =IF(I5="深港",IF(K5>0,E5/K5,""),E5)
A6: 自营权益4 | B6: 601098 | C6: 中南传媒 | D6: 300000 | E6: 3912034 | F6: 13.040114 | G6: 11.26 | H6: 3378000 | I6: 场内 | J6: 601098.SH | K6: ='FX_RATES_TO_CNY_HIST'!$B$5 | L6: =IF(I6="深港",IF(K6>0,F6/K6,""),F6) | M6: =IF(I6="深港",IF(K6>0,E6/K6,""),E6)
A7: 自营权益4 | B7: 601166 | C7: 兴业银行 | D7: 300000 | E7: 6347906.6 | F7: 21.159689 | G7: 21.06 | H7: 6318000 | I7: 场内 | J7: 601166.SH | K7: ='FX_RATES_TO_CNY_HIST'!$B$5 | L7: =IF(I7="深港",IF(K7>0,F7/K7,""),F7) | M7: =IF(I7="深港",IF(K7>0,E7/K7,""),E7)
A8: 自营权益4 | B8: 601169 | C8: 北京银行 | D8: 1500000 | E8: 8791842.6 | F8: 5.8612284 | G8: 5.48 | H8: 8220000 | I8: 场内 | J8: 601169.SH | K8: ='FX_RATES_TO_CNY_HIST'!$B$5 | L8: =IF(I8="深港",IF(K8>0,F8/K8,""),F8) | M8: =IF(I8="深港",IF(K8>0,E8/K8,""),E8)
A9: 自营权益4 | B9: 601818 | C9: 光大银行 | D9: 2700000 | E9: 9766819.9 | F9: 3.6173407 | G9: 3.49 | H9: 9423000 | I9: 场内 | J9: 601818.SH | K9: ='FX_RATES_TO_CNY_HIST'!$B$5 | L9: =IF(I9="深港",IF(K9>0,F9/K9,""),F9) | M9: =IF(I9="深港",IF(K9>0,E9/K9,""),E9)
A10: 自营权益4 | B10: 601900 | C10: 南方传媒 | D10: 200000 | E10: 3093896.3 | F10: 15.469481 | G10: 13.41 | H10: 2682000 | I10: 场内 | J10: 601900.SH | K10: ='FX_RATES_TO_CNY_HIST'!$B$5 | L10: =IF(I10="深港",IF(K10>0,F10/K10,""),F10) | M10: =IF(I10="深港",IF(K10>0,E10/K10,""),E10)
A11: 自营权益4 | B11: 603198 | C11: 迎驾贡酒 | D11: 60000 | E11: 2637959.9 | F11: 43.965998 | G11: 39.56 | H11: 2373600 | I11: 场内 | J11: 603198.SH | K11: ='FX_RATES_TO_CNY_HIST'!$B$5 | L11: =IF(I11="深港",IF(K11>0,F11/K11,""),F11) | M11: =IF(I11="深港",IF(K11>0,E11/K11,""),E11)
A12: 自营权益4 | B12: 603369 | C12: 今世缘 | D12: 60000 | E12: 2460995.7 | F12: 41.016594 | G12: 34.78 | H12: 2086800 | I12: 场内 | J12: 603369.SH | K12: ='FX_RATES_TO_CNY_HIST'!$B$5 | L12: =IF(I12="深港",IF(K12>0,F12/K12,""),F12) | M12: =IF(I12="深港",IF(K12>0,E12/K12,""),E12)
A13: 自营权益4 | B13: 1 | C13: 平安银行 | D13: 700000 | E13: 8159372.6 | F13: 11.656247 | G13: 11.41 | H13: 7987000 | I13: 场内 | J13: 000001.SZ | K13: ='FX_RATES_TO_CNY_HIST'!$B$5 | L13: =IF(I13="深港",IF(K13>0,F13/K13,""),F13) | M13: =IF(I13="深港",IF(K13>0,E13/K13,""),E13)
... A41: 自营权益4 | B41: 6862 | C41: 海底捞 | D41: 400000 | E41: 5365768.8 | F41: 13.414422 | G41: 12.78795 | H41: 5115180 | I41: 深港 | J41: 6862.HK | K41: ='FX_RATES_TO_CNY_HIST'!$B$5 | L41: =IF(I41="深港",IF(K41>0,F41/K41,""),F41) | M41: =IF(I41="深港",IF(K41>0,E41/K41,""),E41)

Sheet FX_RATES_TO_CNY
A1: currency | B1: rate_to_cny
A2: CNY | B2: 1
A3: USD | B3: 7.125
A4: EUR | B4: 7.731
A5: GBP | B5: 9.011
A6: JPY | B6: 0.0475
A7: HKD | B7: 0.86315
A8: CNH | B8: 1
A9: THB | B9: 0.2016

Sheet FX_RATES_TO_CNY_HIST
A1: 报表货币 | B1: CNY
A2: 估值日 | B2: 2026-06-01
A3: 估值日 HKD→CNY | B3: 0.86315
A4: 期初折算日(参数) | B4: 2026-01-01
A5: 期初日 HKD→CNY | B5: 0.89834
A6: 说明 | B6: B3/B5：1 HKD = rate CNY；B3 供估值日盯市折合，B5 供期初深港成本 CNY→HKD（÷B5）。历史表已过滤异常汇率并锁定前海锚点日。
A8: valuation_date | B8: currency | C8: rate_to_cny
A9: 2024-06-03 | B9: USD | C9: 7.1257
A10: 2024-06-04 | B10: USD | C10: 7.0647
A11: 2024-06-05 | B11: USD | C11: 7.2688
A12: 2024-07-11 | B12: HKD | C12: 0.92953
A13: 2024-07-12 | B13: HKD | C13: 0.92857
A14: 2024-07-15 | B14: HKD | C14: 0.92989
A15: 2024-07-16 | B15: HKD | C15: 0.93092
A16: 2024-07-17 | B16: HKD | C16: 0.92998
A17: 2024-07-18 | B17: HKD | C17: 0.92955
A18: 2024-07-19 | B18: HKD | C18: 0.93075
A19: 2024-07-22 | B19: HKD | C19: 0.93165
A20: 2024-07-23 | B20: HKD | C20: 0.93152
... A1301: 2026-06-10 | B1301: HKD | C1301: 0.86444

Sheet 估值日行情
A1: 估值日(实际使用) | B1: 2026-06-01 | C1: 行情缺失→期初持仓兜底(深港CNY÷HKD/CNY)
A2: instrument_code | B2: valuation_date | C2: price | D2: volume | E2: 备注
A3: 000001.SZ | B3: 6/1/2026 | C3: 11.41
A4: 0001.HK | B4: 6/1/2026 | C4: 69.3 | D4: 9282578
A5: 000333.SZ | B5: 2026-06-01 | C5: 81.7 | D5: 37671119 | E5: 补充行情
A6: 000568.SZ | B6: 2026-06-01 | C6: 90.4 | D6: 14082175 | E6: 补充行情
A7: 000858.SZ | B7: 2026-06-01 | C7: 83.41 | D7: 27998720 | E7: 补充行情
A8: 002807.SZ | B8: 2026-06-01 | C8: 4.09 | D8: 47812807 | E8: 补充行情
A9: 002839.SZ | B9: 2026-06-01 | C9: 4.34 | D9: 28288760 | E9: 补充行情
A10: 0177.HK | B10: 6/1/2026 | C10: 10.84 | D10: 26550114
A11: 0300.HK | B11: 2026-06-01 | C11: 89.3 | D11: 13612908 | E11: 补充行情
A12: 0322.HK | B12: 2026-06-01 | C12: 12.41 | D12: 22819396 | E12: 补充行情
A13: 0371.HK | B13: 6/1/2026 | C13: 2.7 | D13: 24656000
A14: 0568.HK | B14: 6/1/2026 | C14: 5.46 | D14: 19684200
A15: 0576.HK | B15: 2026-06-01 | C15: 6.9 | D15: 8524743 | E15: 补充行情
A16: 0728.HK | B16: 2026-06-01 | C16: 5.24 | D16: 71673454 | E16: 补充行情
A17: 0762.HK | B17: 2026-06-01 | C17: 7.75 | D17: 18511329 | E17: 补充行情
A18: 0788.HK | B18: 2026-06-01 | C18: 10.02 | D18: 17748131 | E18: 补充行情
A19: 0811.HK | B19: 6/1/2026 | C19: 9.65 | D19: 816600
A20: 0836.HK | B20: 2026-06-01 | C20: 21.64 | D20: 29719349 | E20: 补充行情
A21: 0858.HK | B21: 6/1/2026 | C21: 0.081 | D21: 2880000
A22: 0883.HK | B22: 2026-06-01 | C22: 26.7 | D22: 85992482 | E22: 补充行情
A23: 0939.HK | B23: 2026-06-01 | C23: 8.53 | D23: 350866907 | E23: 补充行情
A24: 0941.HK | B24: 2026-06-01 | C24: 85.15 | D24: 10941368 | E24: 补充行情
A25: 0995.HK | B25: 2026-06-01 | C25: 16.82 | D25: 1808000 | E25: 补充行情
A26: 0998.HK | B26: 2026-06-01 | C26: 7.31 | D26: 33269624 | E26: 补充行情
A27: 1071.HK | B27: 2026-06-01 | C27: 4.75 | D27: 24856000 | E27: 补充行情
A28: 1088.HK | B28: 2026-06-01 | C28: 47.24 | D28: 21515703 | E28: 补充行情
A29: 1368.HK | B29: 2026-06-01 | C29: 4.46 | D29: 19309068 | E29: 补充行情
A30: 1398.HK | B30: 2026-06-01 | C30: 6.65 | D30: 174592527 | E30: 补充行情
A31: 2016.HK | B31: 2026-06-01 | C31: 2.45 | D31: 5700878 | E31: 补充行情
A32: 2020.HK | B32: 2026-06-01 | C32: 76.4 | D32: 7195973 | E32: 补充行情
A33: 2318.HK | B33: 2026-06-01 | C33: 60.2 | D33: 34250928 | E33: 补充行情
... A49: 601166.SH | B49: 2026-06-01 | C49: 18.44 | D49: 117584490 | E49: 补充行情
A50: 601169.SH | B50: 6/1/2026 | C50: 5.17 | D50: 126704143
A51: 601577.SH | B51: 2026-06-01 | C51: 9.69 | D51: 27029767 | E51: 补充行情
A52: 601818.SH | B52: 6/1/2026 | C52: 3.14 | D52: 182501573
A53: 601825.SH | B53: 2026-06-01 | C53: 8.64 | D53: 23074260 | E53: 补充行情
A54: 601900.SH | B54: 2026-06-01 | C54: 12.39 | D54: 12928667 | E54: 补充行情
A55: 603198.SH | B55: 2026-06-01 | C55: 37.55 | D55: 12125509 | E55: 补充行情
A56: 603369.SH | B56: 2026-06-01 | C56: 29.96 | D56: 22439158 | E56: 补充行情
A57: 6690.HK | B57: 2026-06-01 | C57: 20.36 | D57: 27937683 | E57: 补充行情
A58: 6818.HK | B58: 2026-06-01 | C58: 3.11 | D58: 14403596 | E58: 补充行情
A59: 6862.HK | B59: 2026-06-01 | C59: 13.16 | D59: 24444201 | E59: 补充行情
A60: 931357.SH | B60: 6/1/2026 | C60: 2512.7019 | D60: 1322640511
A61: 9985.HK | B61: 2026-06-01 | C61: 8.57 | D61: 7276657 | E61: 补充行情

Sheet 逐笔辅助
A1: 来源 | B1: 日期 | C1: 组合名称 | D1: 叶子投组 | E1: 证券代码 | F1: 证券名称 | G1: 方向 | H1: 数量 | I1: 原币成交单价(深港=HKD/场内=CNY) | J1: 原币成交金额(深港=HKD/场内=CNY) | K1: 本币成交金额(CNY) | L1: 本币成交单价(CNY) | M1: 买入数量 | N1: 买入本币金额(CNY) | O1: 卖出数量 | P1: 卖出本币金额(CNY) | Q1: 累计买入数量(同叶+码) | R1: 累计买入本币金额(CNY) | S1: 加权成本单价(CNY) | T1: 流水已实现损益(加权RPNL)(CNY) | U1: FIFO已实现(RPNL)(CNY) | V1: 折算汇率(本币÷原币) | W1: 加权RPNL算式(引用L/S/H) | X1: FIFO RPNL算式(先买先卖·含期初) | Y1: 标准代码 | Z1: 估值日市价(原币) | AA1: 兑CNY汇率(估值日) | AB1: 估值日市价(CNY) | AC1: 累计净持仓(至本行) | AD1: 成本单价(加权)(原币) | AE1: 盯市损益(MTM)(原币) | AF1: 盯市损益(MTM)(CNY) | AG1: 全账累计买入数量(含期初) | AH1: 全账累计买入本币金额(含期初) | AI1: 全账加权成本单价(CNY) | AJ1: 全账加权RPNL(CNY) | AK1: 第三轨−运营轨(RPNL差额) | AL1: 全账加权RPNL算式
A2: 期初 | D2: 场内 | E2: 600036 | F2: 招商银行 | G2: 买入 | H2: 150000 | I2: 42.048835 | J2: 6307325.2 | K2: 6307325.2 | L2: 42.048835 | M2: 150000 | N2: 6307325.2 | U2: 0 | Y2: 600036.SH | Z2: =IF(Y2="","",IFERROR(INDEX('估值日行情'!$C$3:$C$61,MATCH(Y2,'估值日行情'!$A$3:$A$61,0)),"")) | AA2: =IF(D2="深港",IFERROR('FX_RATES_TO_CNY_HIST'!$B$3,""),1) | AB2: =IF(Z2<>"",Z2*AA2,"") | AC2: =SUMIFS($H$2:H2,$D$2:D2,D2,$E$2:E2,E2,$G$2:G2,"买入")-SUMIFS($H$2:H2,$D$2:D2,D2,$E$2:E2,E2,$G$2:G2,"卖出") | AD2: =L2 | AE2: =IF(AC2>0,AC2*Z2-AC2*AD2,0) | AF2: =IF(AC2>0,IF(D2="深港",AE2*AA2,AE2),0) | AG2: =H2 | AH2: =K2 | AI2: =L2 | AJ2: 0
A3: 期初 | D3: 场内 | E3: 600519 | F3: 贵州茅台 | G3: 买入 | H3: 100 | I3: 1483.109 | J3: 148310.9 | K3: 148310.9 | L3: 1483.109 | M3: 100 | N3: 148310.9 | U3: 0 | Y3: 600519.SH | Z3: =IF(Y3="","",IFERROR(INDEX('估值日行情'!$C$3:$C$61,MATCH(Y3,'估值日行情'!$A$3:$A$61,0)),"")) | AA3: =IF(D3="深港",IFERROR('FX_RATES_TO_CNY_HIST'!$B$3,""),1) | AB3: =IF(Z3<>"",Z3*AA3,"") | AC3: =SUMIFS($H$2:H3,$D$2:D3,D3,$E$2:E3,E3,$G$2:G3,"买入")-SUMIFS($H$2:H3,$D$2:D3,D3,$E$2:E3,E3,$G$2:G3,"卖出") | AD3: =L3 | AE3: =IF(AC3>0,AC3*Z3-AC3*AD3,0) | AF3: =IF(AC3>0,IF(D3="深港",AE3*AA3,AE3),0) | AG3: =H3 | AH3: =K3 | AI3: =L3 | AJ3: 0
A4: 期初 | D4: 场内 | E4: 600809 | F4: 山西汾酒 | G4: 买入 | H4: 16000 | I4: 179.32043 | J4: 2869126.9 | K4: 2869126.9 | L4: 179.32043 | M4: 16000 | N4: 2869126.9 | U4: 0 | Y4: 600809.SH | Z4: =IF(Y4="","",IFERROR(INDEX('估值日行情'!$C$3:$C$61,MATCH(Y4,'估值日行情'!$A$3:$A$61,0)),"")) | AA4: =IF(D4="深港",IFERROR('FX_RATES_TO_CNY_HIST'!$B$3,""),1) | AB4: =IF(Z4<>"",Z4*AA4,"") | AC4: =SUMIFS($H$2:H4,$D$2:D4,D4,$E$2:E4,E4,$G$2:G4,"买入")-SUMIFS($H$2:H4,$D$2:D4,D4,$E$2:E4,E4,$G$2:G4,"卖出") | AD4: =L4 | AE4: =IF(AC4>0,AC4*Z4-AC4*AD4,0) | AF4: =IF(AC4>0,IF(D4="深港",AE4*AA4,AE4),0) | AG4: =H4 | AH4: =K4 | AI4: =L4 | AJ4: 0
A5: 期初 | D5: 场内 | E5: 601009 | F5: 南京银行 | G5: 买入 | H5: 300000 | I5: 11.107635 | J5: 3332290.5 | K5: 3332290.5 | L5: 11.107635 | M5: 300000 | N5: 3332290.5 | U5: 0 | Y5: 601009.SH | Z5: =IF(Y5="","",IFERROR(INDEX('估值日行情'!$C$3:$C$61,MATCH(Y5,'估值日行情'!$A$3:$A$61,0)),"")) | AA5: =IF(D5="深港",IFERROR('FX_RATES_TO_CNY_HIST'!$B$3,""),1) | AB5: =IF(Z5<>"",Z5*AA5,"") | AC5: =SUMIFS($H$2:H5,$D$2:D5,D5,$E$2:E5,E5,$G$2:G5,"买入")-SUMIFS($H$2:H5,$D$2:D5,D5,$E$2:E5,E5,$G$2:G5,"卖出") | AD5: =L5 | AE5: =IF(AC5>0,AC5*Z5-AC5*AD5,0) | AF5: =IF(AC5>0,IF(D5="深港",AE5*AA5,AE5),0) | AG5: =H5 | AH5: =K5 | AI5: =L5 | AJ5: 0
A6: 期初 | D6: 场内 | E6: 601098 | F6: 中南传媒 | G6: 买入 | H6: 300000 | I6: 13.040114 | J6: 3912034 | K6: 3912034 | L6: 13.040114 | M6: 300000 | N6: 3912034 | U6: 0 | Y6: 601098.SH | Z6: =IF(Y6="","",IFERROR(INDEX('估值日行情'!$C$3:$C$61,MATCH(Y6,'估值日行情'!$A$3:$A$61,0)),"")) | AA6: =IF(D6="深港",IFERROR('FX_RATES_TO_CNY_HIST'!$B$3,""),1) | AB6: =IF(Z6<>"",Z6*AA6,"") | AC6: =SUMIFS($H$2:H6,$D$2:D6,D6,$E$2:E6,E6,$G$2:G6,"买入")-SUMIFS($H$2:H6,$D$2:D6,D6,$E$2:E6,E6,$G$2:G6,"卖出") | AD6: =L6 | AE6: =IF(AC6>0,AC6*Z6-AC6*AD6,0) | AF6: =IF(AC6>0,IF(D6="深港",AE6*AA6,AE6),0) | AG6: =H6 | AH6: =K6 | AI6: =L6 | AJ6: 0
A7: 期初 | D7: 场内 | E7: 601166 | F7: 兴业银行 | G7: 买入 | H7: 300000 | I7: 21.159689 | J7: 6347906.6 | K7: 6347906.6 | L7: 21.159689 | M7: 300000 | N7: 6347906.6 | U7: 0 | Y7: 601166.SH | Z7: =IF(Y7="","",IFERROR(INDEX('估值日行情'!$C$3:$C$61,MATCH(Y7,'估值日行情'!$A$3:$A$61,0)),"")) | AA7: =IF(D7="深港",IFERROR('FX_RATES_TO_CNY_HIST'!$B$3,""),1) | AB7: =IF(Z7<>"",Z7*AA7,"") | AC7: =SUMIFS($H$2:H7,$D$2:D7,D7,$E$2:E7,E7,$G$2:G7,"买入")-SUMIFS($H$2:H7,$D$2:D7,D7,$E$2:E7,E7,$G$2:G7,"卖出") | AD7: =L7 | AE7: =IF(AC7>0,AC7*Z7-AC7*AD7,0) | AF7: =IF(AC7>0,IF(D7="深港",AE7*AA7,AE7),0) | AG7: =H7 | AH7: =K7 | AI7: =L7 | AJ7: 0
A8: 期初 | D8: 场内 | E8: 601169 | F8: 北京银行 | G8: 买入 | H8: 1500000 | I8: 5.8612284 | J8: 8791842.6 | K8: 8791842.6 | L8: 5.8612284 | M8: 1500000 | N8: 8791842.6 | U8: 0 | Y8: 601169.SH | Z8: =IF(Y8="","",IFERROR(INDEX('估值日行情'!$C$3:$C$61,MATCH(Y8,'估值日行情'!$A$3:$A$61,0)),"")) | AA8: =IF(D8="深港",IFERROR('FX_RATES_TO_CNY_HIST'!$B$3,""),1) | AB8: =IF(Z8<>"",Z8*AA8,"") | AC8: =SUMIFS($H$2:H8,$D$2:D8,D8,$E$2:E8,E8,$G$2:G8,"买入")-SUMIFS($H$2:H8,$D$2:D8,D8,$E$2:E8,E8,$G$2:G8,"卖出") | AD8: =L8 | AE8: =IF(AC8>0,AC8*Z8-AC8*AD8,0) | AF8: =IF(AC8>0,IF(D8="深港",AE8*AA8,AE8),0) | AG8: =H8 | AH8: =K8 | AI8: =L8 | AJ8: 0
A9: 期初 | D9: 场内 | E9: 601818 | F9: 光大银行 | G9: 买入 | H9: 2700000 | I9: 3.6173407 | J9: 9766819.9 | K9: 9766819.9 | L9: 3.6173407 | M9: 2700000 | N9: 9766819.9 | U9: 0 | Y9: 601818.SH | Z9: =IF(Y9="","",IFERROR(INDEX('估值日行情'!$C$3:$C$61,MATCH(Y9,'估值日行情'!$A$3:$A$61,0)),"")) | AA9: =IF(D9="深港",IFERROR('FX_RATES_TO_CNY_HIST'!$B$3,""),1) | AB9: =IF(Z9<>"",Z9*AA9,"") | AC9: =SUMIFS($H$2:H9,$D$2:D9,D9,$E$2:E9,E9,$G$2:G9,"买入")-SUMIFS($H$2:H9,$D$2:D9,D9,$E$2:E9,E9,$G$2:G9,"卖出") | AD9: =L9 | AE9: =IF(AC9>0,AC9*Z9-AC9*AD9,0) | AF9: =IF(AC9>0,IF(D9="深港",AE9*AA9,AE9),0) | AG9: =H9 | AH9: =K9 | AI9: =L9 | AJ9: 0
A10: 期初 | D10: 场内 | E10: 601900 | F10: 南方传媒 | G10: 买入 | H10: 200000 | I10: 15.469481 | J10: 3093896.3 | K10: 3093896.3 | L10: 15.469481 | M10: 200000 | N10: 3093896.3 | U10: 0 | Y10: 601900.SH | Z10: =IF(Y10="","",IFERROR(INDEX('估值日行情'!$C$3:$C$61,MATCH(Y10,'估值日行情'!$A$3:$A$61,0)),"")) | AA10: =IF(D10="深港",IFERROR('FX_RATES_TO_CNY_HIST'!$B$3,""),1) | AB10: =IF(Z10<>"",Z10*AA10,"") | AC10: =SUMIFS($H$2:H10,$D$2:D10,D10,$E$2:E10,E10,$G$2:G10,"买入")-SUMIFS($H$2:H10,$D$2:D10,D10,$E$2:E10,E10,$G$2:G10,"卖出") | AD10: =L10 | AE10: =IF(AC10>0,AC10*Z10-AC10*AD10,0) | AF10: =IF(AC10>0,IF(D10="深港",AE10*AA10,AE10),0) | AG10: =H10 | AH10: =K10 | AI10: =L10 | AJ10: 0
A11: 期初 | D11: 场内 | E11: 603198 | F11: 迎驾贡酒 | G11: 买入 | H11: 60000 | I11: 43.965998 | J11: 2637959.9 | K11: 2637959.9 | L11: 43.965998 | M11: 60000 | N11: 2637959.9 | U11: 0 | Y11: 603198.SH | Z11: =IF(Y11="","",IFERROR(INDEX('估值日行情'!$C$3:$C$61,MATCH(Y11,'估值日行情'!$A$3:$A$61,0)),"")) | AA11: =IF(D11="深港",IFERROR('FX_RATES_TO_CNY_HIST'!$B$3,""),1) | AB11: =IF(Z11<>"",Z11*AA11,"") | AC11: =SUMIFS($H$2:H11,$D$2:D11,D11,$E$2:E11,E11,$G$2:G11,"买入")-SUMIFS($H$2:H11,$D$2:D11,D11,$E$2:E11,E11,$G$2:G11,"卖出") | AD11: =L11 | AE11: =IF(AC11>0,AC11*Z11-AC11*AD11,0) | AF11: =IF(AC11>0,IF(D11="深港",AE11*AA11,AE11),0) | AG11: =H11 | AH11: =K11 | AI11: =L11 | AJ11: 0
A12: 期初 | D12: 场内 | E12: 603369 | F12: 今世缘 | G12: 买入 | H12: 60000 | I12: 41.016594 | J12: 2460995.7 | K12: 2460995.7 | L12: 41.016594 | M12: 60000 | N12: 2460995.7 | U12: 0 | Y12: 603369.SH | Z12: =IF(Y12="","",IFERROR(INDEX('估值日行情'!$C$3:$C$61,MATCH(Y12,'估值日行情'!$A$3:$A$61,0)),"")) | AA12: =IF(D12="深港",IFERROR('FX_RATES_TO_CNY_HIST'!$B$3,""),1) | AB12: =IF(Z12<>"",Z12*AA12,"") | AC12: =SUMIFS($H$2:H12,$D$2:D12,D12,$E$2:E12,E12,$G$2:G12,"买入")-SUMIFS($H$2:H12,$D$2:D12,D12,$E$2:E12,E12,$G$2:G12,"卖出") | AD12: =L12 | AE12: =IF(AC12>0,AC12*Z12-AC12*AD12,0) | AF12: =IF(AC12>0,IF(D12="深港",AE12*AA12,AE12),0) | AG12: =H12 | AH12: =K12 | AI12: =L12 | AJ12: 0
A13: 期初 | D13: 场内 | E13: 1 | F13: 平安银行 | G13: 买入 | H13: 700000 | I13: 11.656247 | J13: 8159372.6 | K13: 8159372.6 | L13: 11.656247 | M13: 700000 | N13: 8159372.6 | U13: 0 | Y13: 000001.SZ | Z13: =IF(Y13="","",IFERROR(INDEX('估值日行情'!$C$3:$C$61,MATCH(Y13,'估值日行情'!$A$3:$A$61,0)),"")) | AA13: =IF(D13="深港",IFERROR('FX_RATES_TO_CNY_HIST'!$B$3,""),1) | AB13: =IF(Z13<>"",Z13*AA13,"") | AC13: =SUMIFS($H$2:H13,$D$2:D13,D13,$E$2:E13,E13,$G$2:G13,"买入")-SUMIFS($H$2:H13,$D$2:D13,D13,$E$2:E13,E13,$G$2:G13,"卖出") | AD13: =L13 | AE13: =IF(AC13>0,AC13*Z13-AC13*AD13,0) | AF13: =IF(AC13>0,IF(D13="深港",AE13*AA13,AE13),0) | AG13: =H13 | AH13: =K13 | AI13: =L13 | AJ13: 0
... A15: 期初 | D15: 场内 | E15: 858 | F15: 五 粮 液 | G15: 买入 | H15: 20000 | I15: 129.79844 | J15: 2595968.9 | K15: 2595968.9 | L15: 129.79844 | M15: 20000 | N15: 2595968.9 | U15: 0 | Y15: 000858.SZ | Z15: =IF(Y15="","",IFERROR(INDEX('估值日行情'!$C$3:$C$61,MATCH(Y15,'估值日行情'!$A$3:$A$61,0)),"")) | AA15: =IF(D15="深港",IFERROR('FX_RATES_TO_CNY_HIST'!$B$3,""),1) | AB15: =IF(Z15<>"",Z15*AA15,"") | AC15: =SUMIFS($H$2:H15,$D$2:D15,D15,$E$2:E15,E15,$G$2:G15,"买入")-SUMIFS($H$2:H15,$D$2:D15,D15,$E$2:E15,E15,$G$2:G15,"卖出") | AD15: =L15 | AE15: =IF(AC15>0,AC15*Z15-AC15*AD15,0) | AF15: =IF(AC15>0,IF(D15="深港",AE15*AA15,AE15),0) | AG15: =H15 | AH15: =K15 | AI15: =L15 | AJ15: 0
A16: 期初 | D16: 深港 | E16: 177 | F16: 江苏宁沪高速公路 | G16: 买入 | H16: 650000 | I16: =IF('FX_RATES_TO_CNY_HIST'!$B$5>0,L16/'FX_RATES_TO_CNY_HIST'!$B$5,"") | J16: =IF(I16<>"",I16*H16,"") | K16: 5863319.3 | L16: 9.0204912 | M16: 650000 | N16: 5863319.3 | U16: 0 | Y16: 0177.HK | Z16: =IF(Y16="","",IFERROR(INDEX('估值日行情'!$C$3:$C$61,MATCH(Y16,'估值日行情'!$A$3:$A$61,0)),"")) | AA16: =IF(D16="深港",IFERROR('FX_RATES_TO_CNY_HIST'!$B$3,""),1) | AB16: =IF(Z16<>"",Z16*AA16,"") | AC16: =SUMIFS($H$2:H16,$D$2:D16,D16,$E$2:E16,E16,$G$2:G16,"买入")-SUMIFS($H$2:H16,$D$2:D16,D16,$E$2:E16,E16,$G$2:G16,"卖出") | AD16: =I16 | AE16: =IF(AC16>0,AC16*Z16-AC16*AD16,0) | AF16: =IF(AC16>0,IF(D16="深港",AE16*AA16,AE16),0) | AG16: =H16 | AH16: =K16 | AI16: =L16 | AJ16: 0
A17: 期初 | D17: 深港 | E17: 300 | F17: 美的集团 | G17: 买入 | H17: 100000 | I17: =IF('FX_RATES_TO_CNY_HIST'!$B$5>0,L17/'FX_RATES_TO_CNY_HIST'!$B$5,"") | J17: =IF(I17<>"",I17*H17,"") | K17: 6933854.9 | L17: 69.338549 | M17: 100000 | N17: 6933854.9 | U17: 0 | Y17: 0300.HK | Z17: =IF(Y17="","",IFERROR(INDEX('估值日行情'!$C$3:$C$61,MATCH(Y17,'估值日行情'!$A$3:$A$61,0)),"")) | AA17: =IF(D17="深港",IFERROR('FX_RATES_TO_CNY_HIST'!$B$3,""),1) | AB17: =IF(Z17<>"",Z17*AA17,"") | AC17: =SUMIFS($H$2:H17,$D$2:D17,D17,$E$2:E17,E17,$G$2:G17,"买入")-SUMIFS($H$2:H17,$D$2:D17,D17,$E$2:E17,E17,$G$2:G17,"卖出") | AD17: =I17 | AE17: =IF(AC17>0,AC17*Z17-AC17*AD17,0) | AF17: =IF(AC17>0,IF(D17="深港",AE17*AA17,AE17),0) | AG17: =H17 | AH17: =K17 | AI17: =L17 | AJ17: 0
A18: 期初 | D18: 深港 | E18: 322 | F18: 康师傅控股 | G18: 买入 | H18: 600000 | I18: =IF('FX_RATES_TO_CNY_HIST'!$B$5>0,L18/'FX_RATES_TO_CNY_HIST'!$B$5,"") | J18: =IF(I18<>"",I18*H18,"") | K18: 6343601.2 | L18: 10.572669 | M18: 600000 | N18: 6343601.2 | U18: 0 | Y18: 0322.HK | Z18: =IF(Y18="","",IFERROR(INDEX('估值日行情'!$C$3:$C$61,MATCH(Y18,'估值日行情'!$A$3:$A$61,0)),"")) | AA18: =IF(D18="深港",IFERROR('FX_RATES_TO_CNY_HIST'!$B$3,""),1) | AB18: =IF(Z18<>"",Z18*AA18,"") | AC18: =SUMIFS($H$2:H18,$D$2:D18,D18,$E$2:E18,E18,$G$2:G18,"买入")-SUMIFS($H$2:H18,$D$2:D18,D18,$E$2:E18,E18,$G$2:G18,"卖出") | AD18: =I18 | AE18: =IF(AC18>0,AC18*Z18-AC18*AD18,0) | AF18: =IF(AC18>0,IF(D18="深港",AE18*AA18,AE18),0) | AG18: =H18 | AH18: =K18 | AI18: =L18 | AJ18: 0
A19: 期初 | D19: 深港 | E19: 371 | F19: 北控水务集团 | G19: 买入 | H19: 2000000 | I19: =IF('FX_RATES_TO_CNY_HIST'!$B$5>0,L19/'FX_RATES_TO_CNY_HIST'!$B$5,"") | J19: =IF(I19<>"",I19*H19,"") | K19: 4522632.1 | L19: 2.261316 | M19: 2000000 | N19: 4522632.1 | U19: 0 | Y19: 0371.HK | Z19: =IF(Y19="","",IFERROR(INDEX('估值日行情'!$C$3:$C$61,MATCH(Y19,'估值日行情'!$A$3:$A$61,0)),"")) | AA19: =IF(D19="深港",IFERROR('FX_RATES_TO_CNY_HIST'!$B$3,""),1) | AB19: =IF(Z19<>"",Z19*AA19,"") | AC19: =SUMIFS($H$2:H19,$D$2:D19,D19,$E$2:E19,E19,$G$2:G19,"买入")-SUMIFS($H$2:H19,$D$2:D19,D19,$E$2:E19,E19,$G$2:G19,"卖出") | AD19: =I19 | AE19: =IF(AC19>0,AC19*Z19-AC19*AD19,0) | AF19: =IF(AC19>0,IF(D19="深港",AE19*AA19,AE19),0) | AG19: =H19 | AH19: =K19 | AI19: =L19 | AJ19: 0
A20: 期初 | D20: 深港 | E20: 576 | F20: 浙江沪杭甬 | G20: 买入 | H20: 600000 | I20: =IF('FX_RATES_TO_CNY_HIST'!$B$5>0,L20/'FX_RATES_TO_CNY_HIST'!$B$5,"") | J20: =IF(I20<>"",I20*H20,"") | K20: 3539217.4 | L20: 5.8986956 | M20: 600000 | N20: 3539217.4 | U20: 0 | Y20: 0576.HK | Z20: =IF(Y20="","",IFERROR(INDEX('估值日行情'!$C$3:$C$61,MATCH(Y20,'估值日行情'!$A$3:$A$61,0)),"")) | AA20: =IF(D20="深港",IFERROR('FX_RATES_TO_CNY_HIST'!$B$3,""),1) | AB20: =IF(Z20<>"",Z20*AA20,"") | AC20: =SUMIFS($H$2:H20,$D$2:D20,D20,$E$2:E20,E20,$G$2:G20,"买入")-SUMIFS($H$2:H20,$D$2:D20,D20,$E$2:E20,E20,$G$2:G20,"卖出") | AD20: =I20 | AE20: =IF(AC20>0,AC20*Z20-AC20*AD20,0) | AF20: =IF(AC20>0,IF(D20="深港",AE20*AA20,AE20),0) | AG20: =H20 | AH20: =K20 | AI20: =L20 | AJ20: 0
A21: 期初 | D21: 深港 | E21: 728 | F21: 中国电信 | G21: 买入 | H21: 1700000 | I21: =IF('FX_RATES_TO_CNY_HIST'!$B$5>0,L21/'FX_RATES_TO_CNY_HIST'!$B$5,"") | J21: =IF(I21<>"",I21*H21,"") | K21: 8799860.9 | L21: 5.1763887 | M21: 1700000 | N21: 8799860.9 | U21: 0 | Y21: 0728.HK | Z21: =IF(Y21="","",IFERROR(INDEX('估值日行情'!$C$3:$C$61,MATCH(Y21,'估值日行情'!$A$3:$A$61,0)),"")) | AA21: =IF(D21="深港",IFERROR('FX_RATES_TO_CNY_HIST'!$B$3,""),1) | AB21: =IF(Z21<>"",Z21*AA21,"") | AC21: =SUMIFS($H$2:H21,$D$2:D21,D21,$E$2:E21,E21,$G$2:G21,"买入")-SUMIFS($H$2:H21,$D$2:D21,D21,$E$2:E21,E21,$G$2:G21,"卖出") | AD21: =I21 | AE21: =IF(AC21>0,AC21*Z21-AC21*AD21,0) | AF21: =IF(AC21>0,IF(D21="深港",AE21*AA21,AE21),0) | AG21: =H21 | AH21: =K21 | AI21: =L21 | AJ21: 0
A22: 期初 | D22: 深港 | E22: 762 | F22: 中国联通 | G22: 买入 | H22: 1240000 | I22: =IF('FX_RATES_TO_CNY_HIST'!$B$5>0,L22/'FX_RATES_TO_CNY_HIST'!$B$5,"") | J22: =IF(I22<>"",I22*H22,"") | K22: 9950233.4 | L22: 8.0243818 | M22: 1240000 | N22: 9950233.4 | U22: 0 | Y22: 0762.HK | Z22: =IF(Y22="","",IFERROR(INDEX('估值日行情'!$C$3:$C$61,MATCH(Y22,'估值日行情'!$A$3:$A$61,0)),"")) | AA22: =IF(D22="深港",IFERROR('FX_RATES_TO_CNY_HIST'!$B$3,""),1) | AB22: =IF(Z22<>"",Z22*AA22,"") | AC22: =SUMIFS($H$2:H22,$D$2:D22,D22,$E$2:E22,E22,$G$2:G22,"买入")-SUMIFS($H$2:H22,$D$2:D22,D22,$E$2:E22,E22,$G$2:G22,"卖出") | AD22: =I22 | AE22: =IF(AC22>0,AC22*Z22-AC22*AD22,0) | AF22: =IF(AC22>0,IF(D22="深港",AE22*AA22,AE22),0) | AG22: =H22 | AH22: =K22 | AI22: =L22 | AJ22: 0
A23: 期初 | D23: 深港 | E23: 788 | F23: 中国铁塔 | G23: 买入 | H23: 200000 | I23: =IF('FX_RATES_TO_CNY_HIST'!$B$5>0,L23/'FX_RATES_TO_CNY_HIST'!$B$5,"") | J23: =IF(I23<>"",I23*H23,"") | K23: 2121426.3 | L23: 10.607132 | M23: 200000 | N23: 2121426.3 | U23: 0 | Y23: 0788.HK | Z23: =IF(Y23="","",IFERROR(INDEX('估值日行情'!$C$3:$C$61,MATCH(Y23,'估值日行情'!$A$3:$A$61,0)),"")) | AA23: =IF(D23="深港",IFERROR('FX_RATES_TO_CNY_HIST'!$B$3,""),1) | AB23: =IF(Z23<>"",Z23*AA23,"") | AC23: =SUMIFS($H$2:H23,$D$2:D23,D23,$E$2:E23,E23,$G$2:G23,"买入")-SUMIFS($H$2:H23,$D$2:D23,D23,$E$2:E23,E23,$G$2:G23,"卖出") | AD23: =I23 | AE23: =IF(AC23>0,AC23*Z23-AC23*AD23,0) | AF23: =IF(AC23>0,IF(D23="深港",AE23*AA23,AE23),0) | AG23: =H23 | AH23: =K23 | AI23: =L23 | AJ23: 0
A24: 期初 | D24: 深港 | E24: 811 | F24: 新华文轩 | G24: 买入 | H24: 300000 | I24: =IF('FX_RATES_TO_CNY_HIST'!$B$5>0,L24/'FX_RATES_TO_CNY_HIST'!$B$5,"") | J24: =IF(I24<>"",I24*H24,"") | K24: 2971851.8 | L24: 9.9061728 | M24: 300000 | N24: 2971851.8 | U24: 0 | Y24: 0811.HK | Z24: =IF(Y24="","",IFERROR(INDEX('估值日行情'!$C$3:$C$61,MATCH(Y24,'估值日行情'!$A$3:$A$61,0)),"")) | AA24: =IF(D24="深港",IFERROR('FX_RATES_TO_CNY_HIST'!$B$3,""),1) | AB24: =IF(Z24<>"",Z24*AA24,"") | AC24: =SUMIFS($H$2:H24,$D$2:D24,D24,$E$2:E24,E24,$G$2:G24,"买入")-SUMIFS($H$2:H24,$D$2:D24,D24,$E$2:E24,E24,$G$2:G24,"卖出") | AD24: =I24 | AE24: =IF(AC24>0,AC24*Z24-AC24*AD24,0) | AF24: =IF(AC24>0,IF(D24="深港",AE24*AA24,AE24),0) | AG24: =H24 | AH24: =K24 | AI24: =L24 | AJ24: 0
A25: 期初 | D25: 深港 | E25: 836 | F25: 华润电力 | G25: 买入 | H25: 200000 | I25: =IF('FX_RATES_TO_CNY_HIST'!$B$5>0,L25/'FX_RATES_TO_CNY_HIST'!$B$5,"") | J25: =IF(I25<>"",I25*H25,"") | K25: 3339492.3 | L25: 16.697462 | M25: 200000 | N25: 3339492.3 | U25: 0 | Y25: 0836.HK | Z25: =IF(Y25="","",IFERROR(INDEX('估值日行情'!$C$3:$C$61,MATCH(Y25,'估值日行情'!$A$3:$A$61,0)),"")) | AA25: =IF(D25="深港",IFERROR('FX_RATES_TO_CNY_HIST'!$B$3,""),1) | AB25: =IF(Z25<>"",Z25*AA25,"") | AC25: =SUMIFS($H$2:H25,$D$2:D25,D25,$E$2:E25,E25,$G$2:G25,"买入")-SUMIFS($H$2:H25,$D$2:D25,D25,$E$2:E25,E25,$G$2:G25,"卖出") | AD25: =I25 | AE25: =IF(AC25>0,AC25*Z25-AC25*AD25,0) | AF25: =IF(AC25>0,IF(D25="深港",AE25*AA25,AE25),0) | AG25: =H25 | AH25: =K25 | AI25: =L25 | AJ25: 0
A26: 期初 | D26: 深港 | E26: 939 | F26: 建设银行 | G26: 买入 | H26: 1100000 | I26: =IF('FX_RATES_TO_CNY_HIST'!$B$5>0,L26/'FX_RATES_TO_CNY_HIST'!$B$5,"") | J26: =IF(I26<>"",I26*H26,"") | K26: 7667625.7 | L26: 6.9705688 | M26: 1100000 | N26: 7667625.7 | U26: 0 | Y26: 0939.HK | Z26: =IF(Y26="","",IFERROR(INDEX('估值日行情'!$C$3:$C$61,MATCH(Y26,'估值日行情'!$A$3:$A$61,0)),"")) | AA26: =IF(D26="深港",IFERROR('FX_RATES_TO_CNY_HIST'!$B$3,""),1) | AB26: =IF(Z26<>"",Z26*AA26,"") | AC26: =SUMIFS($H$2:H26,$D$2:D26,D26,$E$2:E26,E26,$G$2:G26,"买入")-SUMIFS($H$2:H26,$D$2:D26,D26,$E$2:E26,E26,$G$2:G26,"卖出") | AD26: =I26 | AE26: =IF(AC26>0,AC26*Z26-AC26*AD26,0) | AF26: =IF(AC26>0,IF(D26="深港",AE26*AA26,AE26),0) | AG26: =H26 | AH26: =K26 | AI26: =L26 | AJ26: 0
A27: 期初 | D27: 深港 | E27: 941 | F27: 中国移动 | G27: 买入 | H27: 120000 | I27: =IF('FX_RATES_TO_CNY_HIST'!$B$5>0,L27/'FX_RATES_TO_CNY_HIST'!$B$5,"") | J27: =IF(I27<>"",I27*H27,"") | K27: 9653485.8 | L27: 80.445715 | M27: 120000 | N27: 9653485.8 | U27: 0 | Y27: 0941.HK | Z27: =IF(Y27="","",IFERROR(INDEX('估值日行情'!$C$3:$C$61,MATCH(Y27,'估值日行情'!$A$3:$A$61,0)),"")) | AA27: =IF(D27="深港",IFERROR('FX_RATES_TO_CNY_HIST'!$B$3,""),1) | AB27: =IF(Z27<>"",Z27*AA27,"") | AC27: =SUMIFS($H$2:H27,$D$2:D27,D27,$E$2:E27,E27,$G$2:G27,"买入")-SUMIFS($H$2:H27,$D$2:D27,D27,$E$2:E27,E27,$G$2:G27,"卖出") | AD27: =I27 | AE27: =IF(AC27>0,AC27*Z27-AC27*AD27,0) | AF27: =IF(AC27>0,IF(D27="深港",AE27*AA27,AE27),0) | AG27: =H27 | AH27: =K27 | AI27: =L27 | AJ27: 0
... A41: 期初 | D41: 深港 | E41: 6862 | F41: 海底捞 | G41: 买入 | H41: 400000 | I41: =IF('FX_RATES_TO_CNY_HIST'!$B$5>0,L41/'FX_RATES_TO_CNY_HIST'!$B$5,"") | J41: =IF(I41<>"",I41*H41,"") | K41: 5365768.8 | L41: 13.414422 | M41: 400000 | N41: 5365768.8 | U41: 0 | Y41: 6862.HK | Z41: =IF(Y41="","",IFERROR(INDEX('估值日行情'!$C$3:$C$61,MATCH(Y41,'估值日行情'!$A$3:$A$61,0)),"")) | AA41: =IF(D41="深港",IFERROR('FX_RATES_TO_CNY_HIST'!$B$3,""),1) | AB41: =IF(Z41<>"",Z41*AA41,"") | AC41: =SUMIFS($H$2:H41,$D$2:D41,D41,$E$2:E41,E41,$G$2:G41,"买入")-SUMIFS($H$2:H41,$D$2:D41,D41,$E$2:E41,E41,$G$2:G41,"卖出") | AD41: =I41 | AE41: =IF(AC41>0,AC41*Z41-AC41*AD41,0) | AF41: =IF(AC41>0,IF(D41="深港",AE41*AA41,AE41),0) | AG41: =H41 | AH41: =K41 | AI41: =L41 | AJ41: 0
A42: =IF('交易流水'!A2<>"","流水","") | B42: ='交易流水'!B2 | C42: ='交易流水'!X2 | D42: =IF(ISNUMBER(SEARCH("深港",C42)),"深港",IF(ISNUMBER(SEARCH("场内",C42)),"场内","其他")) | E42: ='交易流水'!F2 | F42: ='交易流水'!G2 | G42: ='交易流水'!H2 | H42: ='交易流水'!K2 | I42: ='交易流水'!P2 | J42: ='交易流水'!L2 | K42: ='交易流水'!AR2 | L42: =IF(H42>0,K42/H42,"") | M42: =IF(G42="买入",H42,0) | N42: =IF(G42="买入",K42,0) | O42: =IF(G42="卖出",H42,0) | P42: =IF(G42="卖出",K42,0) | Q42: =SUMIFS($H$2:H41,$A$2:A41,"流水",$D$2:D41,D42,$E$2:E41,E42,$G$2:G41,"买入") | R42: =SUMIFS($K$2:K41,$A$2:A41,"流水",$D$2:D41,D42,$E$2:E41,E42,$G$2:G41,"买入") | S42: =IF(Q42>0,R42/Q42,"") | T42: =IF(G42="卖出",IF(S42="","",(L42-S42)*H42),0) | U42: 0 | V42: =IF(AND(J42>0,D42="深港"),K42/J42,"") | W42: =IF(G42="卖出","(L42-S42)×H42 = ("&TEXT(L42,"0.######")&"-"&TEXT(S42,"0.######")&")×"&H42,"") | Y42: =IF(E42="","",IF(D42="深港",TEXT(--E42,"0000")&".HK",IF(--E42>=600000,TEXT(--E42,"000000")&".SH",TEXT(--E42,"000000")&".SZ"))) | Z42: =IF(Y42="","",IFERROR(INDEX('估值日行情'!$C$3:$C$61,MATCH(Y42,'估值日行情'!$A$3:$A$61,0)),"")) | AA42: =IF(D42="深港",IFERROR('FX_RATES_TO_CNY_HIST'!$B$3,""),1) | AB42: =IF(Z42<>"",Z42*AA42,"") | AC42: =SUMIFS($H$2:H42,$D$2:D42,D42,$E$2:E42,E42,$G$2:G42,"买入")-SUMIFS($H$2:H42,$D$2:D42,D42,$E$2:E42,E42,$G$2:G42,"卖出") | AD42: =IF(D42="深港",IF(Q42>0,SUMIFS($J$2:J41,$D$2:D41,D42,$E$2:E41,E42,$G$2:G41,"买入")/SUMIFS($H$2:H41,$D$2:D41,D42,$E$2:E41,E42,$G$2:G41,"买入"),""),S42) | AE42: =IF(AC42>0,AC42*Z42-AC42*AD42,0) | AF42: =IF(AC42>0,IF(D42="深港",AE42*AA42,AE42),0) | AG42: =SUMIFS($H$2:H41,$D$2:D41,D42,$E$2:E41,E42,$G$2:G41,"买入") | AH42: =SUMIFS($K$2:K41,$D$2:D41,D42,$E$2:E41,E42,$G$2:G41,"买入") | AI42: =IF(AG42>0,AH42/AG42,"") | AJ42: =IF(G42="卖出",IF(AI42="","",(L42-AI42)*H42),0) | AK42: =IF(G42="卖出",AJ42-T42,"") | AL42: =IF(G42="卖出","(L42-AI42)×H42 = ("&TEXT(L42,"0.######")&"-"&TEXT(AI42,"0.######")&")×"&H42,"")
A43: =IF('交易流水'!A3<>"","流水","") | B43: ='交易流水'!B3 | C43: ='交易流水'!X3 | D43: =IF(ISNUMBER(SEARCH("深港",C43)),"深港",IF(ISNUMBER(SEARCH("场内",C43)),"场内","其他")) | E43: ='交易流水'!F3 | F43: ='交易流水'!G3 | G43: ='交易流水'!H3 | H43: ='交易流水'!K3 | I43: ='交易流水'!P3 | J43: ='交易流水'!L3 | K43: ='交易流水'!AR3 | L43: =IF(H43>0,K43/H43,"") | M43: =IF(G43="买入",H43,0) | N43: =IF(G43="买入",K43,0) | O43: =IF(G43="卖出",H43,0) | P43: =IF(G43="卖出",K43,0) | Q43: =SUMIFS($H$2:H42,$A$2:A42,"流水",$D$2:D42,D43,$E$2:E42,E43,$G$2:G42,"买入") | R43: =SUMIFS($K$2:K42,$A$2:A42,"流水",$D$2:D42,D43,$E$2:E42,E43,$G$2:G42,"买入") | S43: =IF(Q43>0,R43/Q43,"") | T43: =IF(G43="卖出",IF(S43="","",(L43-S43)*H43),0) | U43: 173632.71 | V43: =IF(AND(J43>0,D43="深港"),K43/J43,"") | W43: =IF(G43="卖出","(L43-S43)×H43 = ("&TEXT(L43,"0.######")&"-"&TEXT(S43,"0.######")&")×"&H43,"") | X43: (L43-L10)×200000=(16.337645-15.469481)×200000=173632.71 → 173632.71 | Y43: =IF(E43="","",IF(D43="深港",TEXT(--E43,"0000")&".HK",IF(--E43>=600000,TEXT(--E43,"000000")&".SH",TEXT(--E43,"000000")&".SZ"))) | Z43: =IF(Y43="","",IFERROR(INDEX('估值日行情'!$C$3:$C$61,MATCH(Y43,'估值日行情'!$A$3:$A$61,0)),"")) | AA43: =IF(D43="深港",IFERROR('FX_RATES_TO_CNY_HIST'!$B$3,""),1) | AB43: =IF(Z43<>"",Z43*AA43,"") | AC43: =SUMIFS($H$2:H43,$D$2:D43,D43,$E$2:E43,E43,$G$2:G43,"买入")-SUMIFS($H$2:H43,$D$2:D43,D43,$E$2:E43,E43,$G$2:G43,"卖出") | AD43: =IF(D43="深港",IF(Q43>0,SUMIFS($J$2:J42,$D$2:D42,D43,$E$2:E42,E43,$G$2:G42,"买入")/SUMIFS($H$2:H42,$D$2:D42,D43,$E$2:E42,E43,$G$2:G42,"买入"),""),S43) | AE43: =IF(AC43>0,AC43*Z43-AC43*AD43,0) | AF43: =IF(AC43>0,IF(D43="深港",AE43*AA43,AE43),0) | AG43: =SUMIFS($H$2:H42,$D$2:D42,D43,$E$2:E42,E43,$G$2:G42,"买入") | AH43: =SUMIFS($K$2:K42,$D$2:D42,D43,$E$2:E42,E43,$G$2:G42,"买入") | AI43: =IF(AG43>0,AH43/AG43,"") | AJ43: =IF(G43="卖出",IF(AI43="","",(L43-AI43)*H43),0) | AK43: =IF(G43="卖出",AJ43-T43,"") | AL43: =IF(G43="卖出","(L43-AI43)×H43 = ("&TEXT(L43,"0.######")&"-"&TEXT(AI43,"0.######")&")×"&H43,"")
A44: =IF('交易流水'!A4<>"","流水","") | B44: ='交易流水'!B4 | C44: ='交易流水'!X4 | D44: =IF(ISNUMBER(SEARCH("深港",C44)),"深港",IF(ISNUMBER(SEARCH("场内",C44)),"场内","其他")) | E44: ='交易流水'!F4 | F44: ='交易流水'!G4 | G44: ='交易流水'!H4 | H44: ='交易流水'!K4 | I44: ='交易流水'!P4 | J44: ='交易流水'!L4 | K44: ='交易流水'!AR4 | L44: =IF(H44>0,K44/H44,"") | M44: =IF(G44="买入",H44,0) | N44: =IF(G44="买入",K44,0) | O44: =IF(G44="卖出",H44,0) | P44: =IF(G44="卖出",K44,0) | Q44: =SUMIFS($H$2:H43,$A$2:A43,"流水",$D$2:D43,D44,$E$2:E43,E44,$G$2:G43,"买入") | R44: =SUMIFS($K$2:K43,$A$2:A43,"流水",$D$2:D43,D44,$E$2:E43,E44,$G$2:G43,"买入") | S44: =IF(Q44>0,R44/Q44,"") | T44: =IF(G44="卖出",IF(S44="","",(L44-S44)*H44),0) | U44: 192067.38 | V44: =IF(AND(J44>0,D44="深港"),K44/J44,"") | W44: =IF(G44="卖出","(L44-S44)×H44 = ("&TEXT(L44,"0.######")&"-"&TEXT(S44,"0.######")&")×"&H44,"") | X44: (L44-L34)×10000=(61.627125-42.420387)×10000=192067.38 → 192067.38 | Y44: =IF(E44="","",IF(D44="深港",TEXT(--E44,"0000")&".HK",IF(--E44>=600000,TEXT(--E44,"000000")&".SH",TEXT(--E44,"000000")&".SZ"))) | Z44: =IF(Y44="","",IFERROR(INDEX('估值日行情'!$C$3:$C$61,MATCH(Y44,'估值日行情'!$A$3:$A$61,0)),"")) | AA44: =IF(D44="深港",IFERROR('FX_RATES_TO_CNY_HIST'!$B$3,""),1) | AB44: =IF(Z44<>"",Z44*AA44,"") | AC44: =SUMIFS($H$2:H44,$D$2:D44,D44,$E$2:E44,E44,$G$2:G44,"买入")-SUMIFS($H$2:H44,$D$2:D44,D44,$E$2:E44,E44,$G$2:G44,"卖出") | AD44: =IF(D44="深港",IF(Q44>0,SUMIFS($J$2:J43,$D$2:D43,D44,$E$2:E43,E44,$G$2:G43,"买入")/SUMIFS($H$2:H43,$D$2:D43,D44,$E$2:E43,E44,$G$2:G43,"买入"),""),S44) | AE44: =IF(AC44>0,AC44*Z44-AC44*AD44,0) | AF44: =IF(AC44>0,IF(D44="深港",AE44*AA44,AE44),0) | AG44: =SUMIFS($H$2:H43,$D$2:D43,D44,$E$2:E43,E44,$G$2:G43,"买入") | AH44: =SUMIFS($K$2:K43,$D$2:D43,D44,$E$2:E43,E44,$G$2:G43,"买入") | AI44: =IF(AG44>0,AH44/AG44,"") | AJ44: =IF(G44="卖出",IF(AI44="","",(L44-AI44)*H44),0) | AK44: =IF(G44="卖出",AJ44-T44,"") | AL44: =IF(G44="卖出","(L44-AI44)×H44 = ("&TEXT(L44,"0.######")&"-"&TEXT(AI44,"0.######")&")×"&H44,"")
A45: =IF('交易流水'!A5<>"","流水","") | B45: ='交易流水'!B5 | C45: ='交易流水'!X5 | D45: =IF(ISNUMBER(SEARCH("深港",C45)),"深港",IF(ISNUMBER(SEARCH("场内",C45)),"场内","其他")) | E45: ='交易流水'!F5 | F45: ='交易流水'!G5 | G45: ='交易流水'!H5 | H45: ='交易流水'!K5 | I45: ='交易流水'!P5 | J45: ='交易流水'!L5 | K45: ='交易流水'!AR5 | L45: =IF(H45>0,K45/H45,"") | M45: =IF(G45="买入",H45,0) | N45: =IF(G45="买入",K45,0) | O45: =IF(G45="卖出",H45,0) | P45: =IF(G45="卖出",K45,0) | Q45: =SUMIFS($H$2:H44,$A$2:A44,"流水",$D$2:D44,D45,$E$2:E44,E45,$G$2:G44,"买入") | R45: =SUMIFS($K$2:K44,$A$2:A44,"流水",$D$2:D44,D45,$E$2:E44,E45,$G$2:G44,"买入") | S45: =IF(Q45>0,R45/Q45,"") | T45: =IF(G45="卖出",IF(S45="","",(L45-S45)*H45),0) | U45: -535649.9 | V45: =IF(AND(J45>0,D45="深港"),K45/J45,"") | W45: =IF(G45="卖出","(L45-S45)×H45 = ("&TEXT(L45,"0.######")&"-"&TEXT(S45,"0.######")&")×"&H45,"") | X45: (L45-L15)×20000=(103.015950-129.798445)×20000=-535649.90 → -535649.9 | Y45: =IF(E45="","",IF(D45="深港",TEXT(--E45,"0000")&".HK",IF(--E45>=600000,TEXT(--E45,"000000")&".SH",TEXT(--E45,"000000")&".SZ"))) | Z45: =IF(Y45="","",IFERROR(INDEX('估值日行情'!$C$3:$C$61,MATCH(Y45,'估值日行情'!$A$3:$A$61,0)),"")) | AA45: =IF(D45="深港",IFERROR('FX_RATES_TO_CNY_HIST'!$B$3,""),1) | AB45: =IF(Z45<>"",Z45*AA45,"") | AC45: =SUMIFS($H$2:H45,$D$2:D45,D45,$E$2:E45,E45,$G$2:G45,"买入")-SUMIFS($H$2:H45,$D$2:D45,D45,$E$2:E45,E45,$G$2:G45,"卖出") | AD45: =IF(D45="深港",IF(Q45>0,SUMIFS($J$2:J44,$D$2:D44,D45,$E$2:E44,E45,$G$2:G44,"买入")/SUMIFS($H$2:H44,$D$2:D44,D45,$E$2:E44,E45,$G$2:G44,"买入"),""),S45) | AE45: =IF(AC45>0,AC45*Z45-AC45*AD45,0) | AF45: =IF(AC45>0,IF(D45="深港",AE45*AA45,AE45),0) | AG45: =SUMIFS($H$2:H44,$D$2:D44,D45,$E$2:E44,E45,$G$2:G44,"买入") | AH45: =SUMIFS($K$2:K44,$D$2:D44,D45,$E$2:E44,E45,$G$2:G44,"买入") | AI45: =IF(AG45>0,AH45/AG45,"") | AJ45: =IF(G45="卖出",IF(AI45="","",(L45-AI45)*H45),0) | AK45: =IF(G45="卖出",AJ45-T45,"") | AL45: =IF(G45="卖出","(L45-AI45)×H45 = ("&TEXT(L45,"0.######")&"-"&TEXT(AI45,"0.######")&")×"&H45,"")
A46: =IF('交易流水'!A6<>"","流水","") | B46: ='交易流水'!B6 | C46: ='交易流水'!X6 | D46: =IF(ISNUMBER(SEARCH("深港",C46)),"深港",IF(ISNUMBER(SEARCH("场内",C46)),"场内","其他")) | E46: ='交易流水'!F6 | F46: ='交易流水'!G6 | G46: ='交易流水'!H6 | H46: ='交易流水'!K6 | I46: ='交易流水'!P6 | J46: ='交易流水'!L6 | K46: ='交易流水'!AR6 | L46: =IF(H46>0,K46/H46,"") | M46: =IF(G46="买入",H46,0) | N46: =IF(G46="买入",K46,0) | O46: =IF(G46="卖出",H46,0) | P46: =IF(G46="卖出",K46,0) | Q46: =SUMIFS($H$2:H45,$A$2:A45,"流水",$D$2:D45,D46,$E$2:E45,E46,$G$2:G45,"买入") | R46: =SUMIFS($K$2:K45,$A$2:A45,"流水",$D$2:D45,D46,$E$2:E45,E46,$G$2:G45,"买入") | S46: =IF(Q46>0,R46/Q46,"") | T46: =IF(G46="卖出",IF(S46="","",(L46-S46)*H46),0) | U46: -308959.9 | V46: =IF(AND(J46>0,D46="深港"),K46/J46,"") | W46: =IF(G46="卖出","(L46-S46)×H46 = ("&TEXT(L46,"0.######")&"-"&TEXT(S46,"0.######")&")×"&H46,"") | X46: (L46-L11)×60000=(38.816667-43.965998)×60000=-308959.90 → -308959.9 | Y46: =IF(E46="","",IF(D46="深港",TEXT(--E46,"0000")&".HK",IF(--E46>=600000,TEXT(--E46,"000000")&".SH",TEXT(--E46,"000000")&".SZ"))) | Z46: =IF(Y46="","",IFERROR(INDEX('估值日行情'!$C$3:$C$61,MATCH(Y46,'估值日行情'!$A$3:$A$61,0)),"")) | AA46: =IF(D46="深港",IFERROR('FX_RATES_TO_CNY_HIST'!$B$3,""),1) | AB46: =IF(Z46<>"",Z46*AA46,"") | AC46: =SUMIFS($H$2:H46,$D$2:D46,D46,$E$2:E46,E46,$G$2:G46,"买入")-SUMIFS($H$2:H46,$D$2:D46,D46,$E$2:E46,E46,$G$2:G46,"卖出") | AD46: =IF(D46="深港",IF(Q46>0,SUMIFS($J$2:J45,$D$2:D45,D46,$E$2:E45,E46,$G$2:G45,"买入")/SUMIFS($H$2:H45,$D$2:D45,D46,$E$2:E45,E46,$G$2:G45,"买入"),""),S46) | AE46: =IF(AC46>0,AC46*Z46-AC46*AD46,0) | AF46: =IF(AC46>0,IF(D46="深港",AE46*AA46,AE46),0) | AG46: =SUMIFS($H$2:H45,$D$2:D45,D46,$E$2:E45,E46,$G$2:G45,"买入") | AH46: =SUMIFS($K$2:K45,$D$2:D45,D46,$E$2:E45,E46,$G$2:G45,"买入") | AI46: =IF(AG46>0,AH46/AG46,"") | AJ46: =IF(G46="卖出",IF(AI46="","",(L46-AI46)*H46),0) | AK46: =IF(G46="卖出",AJ46-T46,"") | AL46: =IF(G46="卖出","(L46-AI46)×H46 = ("&TEXT(L46,"0.######")&"-"&TEXT(AI46,"0.######")&")×"&H46,"")
A47: =IF('交易流水'!A7<>"","流水","") | B47: ='交易流水'!B7 | C47: ='交易流水'!X7 | D47: =IF(ISNUMBER(SEARCH("深港",C47)),"深港",IF(ISNUMBER(SEARCH("场内",C47)),"场内","其他")) | E47: ='交易流水'!F7 | F47: ='交易流水'!G7 | G47: ='交易流水'!H7 | H47: ='交易流水'!K7 | I47: ='交易流水'!P7 | J47: ='交易流水'!L7 | K47: ='交易流水'!AR7 | L47: =IF(H47>0,K47/H47,"") | M47: =IF(G47="买入",H47,0) | N47: =IF(G47="买入",K47,0) | O47: =IF(G47="卖出",H47,0) | P47: =IF(G47="卖出",K47,0) | Q47: =SUMIFS($H$2:H46,$A$2:A46,"流水",$D$2:D46,D47,$E$2:E46,E47,$G$2:G46,"买入") | R47: =SUMIFS($K$2:K46,$A$2:A46,"流水",$D$2:D46,D47,$E$2:E46,E47,$G$2:G46,"买入") | S47: =IF(Q47>0,R47/Q47,"") | T47: =IF(G47="卖出",IF(S47="","",(L47-S47)*H47),0) | U47: -418217.67 | V47: =IF(AND(J47>0,D47="深港"),K47/J47,"") | W47: =IF(G47="卖出","(L47-S47)×H47 = ("&TEXT(L47,"0.######")&"-"&TEXT(S47,"0.######")&")×"&H47,"") | X47: (L47-L12)×60000=(34.046300-41.016594)×60000=-418217.67 → -418217.67 | Y47: =IF(E47="","",IF(D47="深港",TEXT(--E47,"0000")&".HK",IF(--E47>=600000,TEXT(--E47,"000000")&".SH",TEXT(--E47,"000000")&".SZ"))) | Z47: =IF(Y47="","",IFERROR(INDEX('估值日行情'!$C$3:$C$61,MATCH(Y47,'估值日行情'!$A$3:$A$61,0)),"")) | AA47: =IF(D47="深港",IFERROR('FX_RATES_TO_CNY_HIST'!$B$3,""),1) | AB47: =IF(Z47<>"",Z47*AA47,"") | AC47: =SUMIFS($H$2:H47,$D$2:D47,D47,$E$2:E47,E47,$G$2:G47,"买入")-SUMIFS($H$2:H47,$D$2:D47,D47,$E$2:E47,E47,$G$2:G47,"卖出") | AD47: =IF(D47="深港",IF(Q47>0,SUMIFS($J$2:J46,$D$2:D46,D47,$E$2:E46,E47,$G$2:G46,"买入")/SUMIFS($H$2:H46,$D$2:D46,D47,$E$2:E46,E47,$G$2:G46,"买入"),""),S47) | AE47: =IF(AC47>0,AC47*Z47-AC47*AD47,0) | AF47: =IF(AC47>0,IF(D47="深港",AE47*AA47,AE47),0) | AG47: =SUMIFS($H$2:H46,$D$2:D46,D47,$E$2:E46,E47,$G$2:G46,"买入") | AH47: =SUMIFS($K$2:K46,$D$2:D46,D47,$E$2:E46,E47,$G$2:G46,"买入") | AI47: =IF(AG47>0,AH47/AG47,"") | AJ47: =IF(G47="卖出",IF(AI47="","",(L47-AI47)*H47),0) | AK47: =IF(G47="卖出",AJ47-T47,"") | AL47: =IF(G47="卖出","(L47-AI47)×H47 = ("&TEXT(L47,"0.######")&"-"&TEXT(AI47,"0.######")&")×"&H47,"")
A48: =IF('交易流水'!A8<>"","流水","") | B48: ='交易流水'!B8 | C48: ='交易流水'!X8 | D48: =IF(ISNUMBER(SEARCH("深港",C48)),"深港",IF(ISNUMBER(SEARCH("场内",C48)),"场内","其他")) | E48: ='交易流水'!F8 | F48: ='交易流水'!G8 | G48: ='交易流水'!H8 | H48: ='交易流水'!K8 | I48: ='交易流水'!P8 | J48: ='交易流水'!L8 | K48: ='交易流水'!AR8 | L48: =IF(H48>0,K48/H48,"") | M48: =IF(G48="买入",H48,0) | N48: =IF(G48="买入",K48,0) | O48: =IF(G48="卖出",H48,0) | P48: =IF(G48="卖出",K48,0) | Q48: =SUMIFS($H$2:H47,$A$2:A47,"流水",$D$2:D47,D48,$E$2:E47,E48,$G$2:G47,"买入") | R48: =SUMIFS($K$2:K47,$A$2:A47,"流水",$D$2:D47,D48,$E$2:E47,E48,$G$2:G47,"买入") | S48: =IF(Q48>0,R48/Q48,"") | T48: =IF(G48="卖出",IF(S48="","",(L48-S48)*H48),0) | U48: 0 | V48: =IF(AND(J48>0,D48="深港"),K48/J48,"") | W48: =IF(G48="卖出","(L48-S48)×H48 = ("&TEXT(L48,"0.######")&"-"&TEXT(S48,"0.######")&")×"&H48,"") | Y48: =IF(E48="","",IF(D48="深港",TEXT(--E48,"0000")&".HK",IF(--E48>=600000,TEXT(--E48,"000000")&".SH",TEXT(--E48,"000000")&".SZ"))) | Z48: =IF(Y48="","",IFERROR(INDEX('估值日行情'!$C$3:$C$61,MATCH(Y48,'估值日行情'!$A$3:$A$61,0)),"")) | AA48: =IF(D48="深港",IFERROR('FX_RATES_TO_CNY_HIST'!$B$3,""),1) | AB48: =IF(Z48<>"",Z48*AA48,"") | AC48: =SUMIFS($H$2:H48,$D$2:D48,D48,$E$2:E48,E48,$G$2:G48,"买入")-SUMIFS($H$2:H48,$D$2:D48,D48,$E$2:E48,E48,$G$2:G48,"卖出") | AD48: =IF(D48="深港",IF(Q48>0,SUMIFS($J$2:J47,$D$2:D47,D48,$E$2:E47,E48,$G$2:G47,"买入")/SUMIFS($H$2:H47,$D$2:D47,D48,$E$2:E47,E48,$G$2:G47,"买入"),""),S48) | AE48: =IF(AC48>0,AC48*Z48-AC48*AD48,0) | AF48: =IF(AC48>0,IF(D48="深港",AE48*AA48,AE48),0) | AG48: =SUMIFS($H$2:H47,$D$2:D47,D48,$E$2:E47,E48,$G$2:G47,"买入") | AH48: =SUMIFS($K$2:K47,$D$2:D47,D48,$E$2:E47,E48,$G$2:G47,"买入") | AI48: =IF(AG48>0,AH48/AG48,"") | AJ48: =IF(G48="卖出",IF(AI48="","",(L48-AI48)*H48),0) | AK48: =IF(G48="卖出",AJ48-T48,"") | AL48: =IF(G48="卖出","(L48-AI48)×H48 = ("&TEXT(L48,"0.######")&"-"&TEXT(AI48,"0.######")&")×"&H48,"")
A49: =IF('交易流水'!A9<>"","流水","") | B49: ='交易流水'!B9 | C49: ='交易流水'!X9 | D49: =IF(ISNUMBER(SEARCH("深港",C49)),"深港",IF(ISNUMBER(SEARCH("场内",C49)),"场内","其他")) | E49: ='交易流水'!F9 | F49: ='交易流水'!G9 | G49: ='交易流水'!H9 | H49: ='交易流水'!K9 | I49: ='交易流水'!P9 | J49: ='交易流水'!L9 | K49: ='交易流水'!AR9 | L49: =IF(H49>0,K49/H49,"") | M49: =IF(G49="买入",H49,0) | N49: =IF(G49="买入",K49,0) | O49: =IF(G49="卖出",H49,0) | P49: =IF(G49="卖出",K49,0) | Q49: =SUMIFS($H$2:H48,$A$2:A48,"流水",$D$2:D48,D49,$E$2:E48,E49,$G$2:G48,"买入") | R49: =SUMIFS($K$2:K48,$A$2:A48,"流水",$D$2:D48,D49,$E$2:E48,E49,$G$2:G48,"买入") | S49: =IF(Q49>0,R49/Q49,"") | T49: =IF(G49="卖出",IF(S49="","",(L49-S49)*H49),0) | U49: 0 | V49: =IF(AND(J49>0,D49="深港"),K49/J49,"") | W49: =IF(G49="卖出","(L49-S49)×H49 = ("&TEXT(L49,"0.######")&"-"&TEXT(S49,"0.######")&")×"&H49,"") | Y49: =IF(E49="","",IF(D49="深港",TEXT(--E49,"0000")&".HK",IF(--E49>=600000,TEXT(--E49,"000000")&".SH",TEXT(--E49,"000000")&".SZ"))) | Z49: =IF(Y49="","",IFERROR(INDEX('估值日行情'!$C$3:$C$61,MATCH(Y49,'估值日行情'!$A$3:$A$61,0)),"")) | AA49: =IF(D49="深港",IFERROR('FX_RATES_TO_CNY_HIST'!$B$3,""),1) | AB49: =IF(Z49<>"",Z49*AA49,"") | AC49: =SUMIFS($H$2:H49,$D$2:D49,D49,$E$2:E49,E49,$G$2:G49,"买入")-SUMIFS($H$2:H49,$D$2:D49,D49,$E$2:E49,E49,$G$2:G49,"卖出") | AD49: =IF(D49="深港",IF(Q49>0,SUMIFS($J$2:J48,$D$2:D48,D49,$E$2:E48,E49,$G$2:G48,"买入")/SUMIFS($H$2:H48,$D$2:D48,D49,$E$2:E48,E49,$G$2:G48,"买入"),""),S49) | AE49: =IF(AC49>0,AC49*Z49-AC49*AD49,0) | AF49: =IF(AC49>0,IF(D49="深港",AE49*AA49,AE49),0) | AG49: =SUMIFS($H$2:H48,$D$2:D48,D49,$E$2:E48,E49,$G$2:G48,"买入") | AH49: =SUMIFS($K$2:K48,$D$2:D48,D49,$E$2:E48,E49,$G$2:G48,"买入") | AI49: =IF(AG49>0,AH49/AG49,"") | AJ49: =IF(G49="卖出",IF(AI49="","",(L49-AI49)*H49),0) | AK49: =IF(G49="卖出",AJ49-T49,"") | AL49: =IF(G49="卖出","(L49-AI49)×H49 = ("&TEXT(L49,"0.######")&"-"&TEXT(AI49,"0.######")&")×"&H49,"")
A50: =IF('交易流水'!A10<>"","流水","") | B50: ='交易流水'!B10 | C50: ='交易流水'!X10 | D50: =IF(ISNUMBER(SEARCH("深港",C50)),"深港",IF(ISNUMBER(SEARCH("场内",C50)),"场内","其他")) | E50: ='交易流水'!F10 | F50: ='交易流水'!G10 | G50: ='交易流水'!H10 | H50: ='交易流水'!K10 | I50: ='交易流水'!P10 | J50: ='交易流水'!L10 | K50: ='交易流水'!AR10 | L50: =IF(H50>0,K50/H50,"") | M50: =IF(G50="买入",H50,0) | N50: =IF(G50="买入",K50,0) | O50: =IF(G50="卖出",H50,0) | P50: =IF(G50="卖出",K50,0) | Q50: =SUMIFS($H$2:H49,$A$2:A49,"流水",$D$2:D49,D50,$E$2:E49,E50,$G$2:G49,"买入") | R50: =SUMIFS($K$2:K49,$A$2:A49,"流水",$D$2:D49,D50,$E$2:E49,E50,$G$2:G49,"买入") | S50: =IF(Q50>0,R50/Q50,"") | T50: =IF(G50="卖出",IF(S50="","",(L50-S50)*H50),0) | U50: -13560.9 | V50: =IF(AND(J50>0,D50="深港"),K50/J50,"") | W50: =IF(G50="卖出","(L50-S50)×H50 = ("&TEXT(L50,"0.######")&"-"&TEXT(S50,"0.######")&")×"&H50,"") | X50: (L50-L3)×100=(1347.500000-1483.109000)×100=-13560.90 → -13560.9 | Y50: =IF(E50="","",IF(D50="深港",TEXT(--E50,"0000")&".HK",IF(--E50>=600000,TEXT(--E50,"000000")&".SH",TEXT(--E50,"000000")&".SZ"))) | Z50: =IF(Y50="","",IFERROR(INDEX('估值日行情'!$C$3:$C$61,MATCH(Y50,'估值日行情'!$A$3:$A$61,0)),"")) | AA50: =IF(D50="深港",IFERROR('FX_RATES_TO_CNY_HIST'!$B$3,""),1) | AB50: =IF(Z50<>"",Z50*AA50,"") | AC50: =SUMIFS($H$2:H50,$D$2:D50,D50,$E$2:E50,E50,$G$2:G50,"买入")-SUMIFS($H$2:H50,$D$2:D50,D50,$E$2:E50,E50,$G$2:G50,"卖出") | AD50: =IF(D50="深港",IF(Q50>0,SUMIFS($J$2:J49,$D$2:D49,D50,$E$2:E49,E50,$G$2:G49,"买入")/SUMIFS($H$2:H49,$D$2:D49,D50,$E$2:E49,E50,$G$2:G49,"买入"),""),S50) | AE50: =IF(AC50>0,AC50*Z50-AC50*AD50,0) | AF50: =IF(AC50>0,IF(D50="深港",AE50*AA50,AE50),0) | AG50: =SUMIFS($H$2:H49,$D$2:D49,D50,$E$2:E49,E50,$G$2:G49,"买入") | AH50: =SUMIFS($K$2:K49,$D$2:D49,D50,$E$2:E49,E50,$G$2:G49,"买入") | AI50: =IF(AG50>0,AH50/AG50,"") | AJ50: =IF(G50="卖出",IF(AI50="","",(L50-AI50)*H50),0) | AK50: =IF(G50="卖出",AJ50-T50,"") | AL50: =IF(G50="卖出","(L50-AI50)×H50 = ("&TEXT(L50,"0.######")&"-"&TEXT(AI50,"0.######")&")×"&H50,"")
A51: =IF('交易流水'!A11<>"","流水","") | B51: ='交易流水'!B11 | C51: ='交易流水'!X11 | D51: =IF(ISNUMBER(SEARCH("深港",C51)),"深港",IF(ISNUMBER(SEARCH("场内",C51)),"场内","其他")) | E51: ='交易流水'!F11 | F51: ='交易流水'!G11 | G51: ='交易流水'!H11 | H51: ='交易流水'!K11 | I51: ='交易流水'!P11 | J51: ='交易流水'!L11 | K51: ='交易流水'!AR11 | L51: =IF(H51>0,K51/H51,"") | M51: =IF(G51="买入",H51,0) | N51: =IF(G51="买入",K51,0) | O51: =IF(G51="卖出",H51,0) | P51: =IF(G51="卖出",K51,0) | Q51: =SUMIFS($H$2:H50,$A$2:A50,"流水",$D$2:D50,D51,$E$2:E50,E51,$G$2:G50,"买入") | R51: =SUMIFS($K$2:K50,$A$2:A50,"流水",$D$2:D50,D51,$E$2:E50,E51,$G$2:G50,"买入") | S51: =IF(Q51>0,R51/Q51,"") | T51: =IF(G51="卖出",IF(S51="","",(L51-S51)*H51),0) | U51: 0 | V51: =IF(AND(J51>0,D51="深港"),K51/J51,"") | W51: =IF(G51="卖出","(L51-S51)×H51 = ("&TEXT(L51,"0.######")&"-"&TEXT(S51,"0.######")&")×"&H51,"") | Y51: =IF(E51="","",IF(D51="深港",TEXT(--E51,"0000")&".HK",IF(--E51>=600000,TEXT(--E51,"000000")&".SH",TEXT(--E51,"000000")&".SZ"))) | Z51: =IF(Y51="","",IFERROR(INDEX('估值日行情'!$C$3:$C$61,MATCH(Y51,'估值日行情'!$A$3:$A$61,0)),"")) | AA51: =IF(D51="深港",IFERROR('FX_RATES_TO_CNY_HIST'!$B$3,""),1) | AB51: =IF(Z51<>"",Z51*AA51,"") | AC51: =SUMIFS($H$2:H51,$D$2:D51,D51,$E$2:E51,E51,$G$2:G51,"买入")-SUMIFS($H$2:H51,$D$2:D51,D51,$E$2:E51,E51,$G$2:G51,"卖出") | AD51: =IF(D51="深港",IF(Q51>0,SUMIFS($J$2:J50,$D$2:D50,D51,$E$2:E50,E51,$G$2:G50,"买入")/SUMIFS($H$2:H50,$D$2:D50,D51,$E$2:E50,E51,$G$2:G50,"买入"),""),S51) | AE51: =IF(AC51>0,AC51*Z51-AC51*AD51,0) | AF51: =IF(AC51>0,IF(D51="深港",AE51*AA51,AE51),0) | AG51: =SUMIFS($H$2:H50,$D$2:D50,D51,$E$2:E50,E51,$G$2:G50,"买入") | AH51: =SUMIFS($K$2:K50,$D$2:D50,D51,$E$2:E50,E51,$G$2:G50,"买入") | AI51: =IF(AG51>0,AH51/AG51,"") | AJ51: =IF(G51="卖出",IF(AI51="","",(L51-AI51)*H51),0) | AK51: =IF(G51="卖出",AJ51-T51,"") | AL51: =IF(G51="卖出","(L51-AI51)×H51 = ("&TEXT(L51,"0.######")&"-"&TEXT(AI51,"0.######")&")×"&H51,"")
A52: =IF('交易流水'!A12<>"","流水","") | B52: ='交易流水'!B12 | C52: ='交易流水'!X12 | D52: =IF(ISNUMBER(SEARCH("深港",C52)),"深港",IF(ISNUMBER(SEARCH("场内",C52)),"场内","其他")) | E52: ='交易流水'!F12 | F52: ='交易流水'!G12 | G52: ='交易流水'!H12 | H52: ='交易流水'!K12 | I52: ='交易流水'!P12 | J52: ='交易流水'!L12 | K52: ='交易流水'!AR12 | L52: =IF(H52>0,K52/H52,"") | M52: =IF(G52="买入",H52,0) | N52: =IF(G52="买入",K52,0) | O52: =IF(G52="卖出",H52,0) | P52: =IF(G52="卖出",K52,0) | Q52: =SUMIFS($H$2:H51,$A$2:A51,"流水",$D$2:D51,D52,$E$2:E51,E52,$G$2:G51,"买入") | R52: =SUMIFS($K$2:K51,$A$2:A51,"流水",$D$2:D51,D52,$E$2:E51,E52,$G$2:G51,"买入") | S52: =IF(Q52>0,R52/Q52,"") | T52: =IF(G52="卖出",IF(S52="","",(L52-S52)*H52),0) | U52: -76819.68 | V52: =IF(AND(J52>0,D52="深港"),K52/J52,"") | W52: =IF(G52="卖出","(L52-S52)×H52 = ("&TEXT(L52,"0.######")&"-"&TEXT(S52,"0.######")&")×"&H52,"") | X52: (L52-L36)×100000=(10.765721-11.533917)×100000=-76819.68 → -76819.68 | Y52: =IF(E52="","",IF(D52="深港",TEXT(--E52,"0000")&".HK",IF(--E52>=600000,TEXT(--E52,"000000")&".SH",TEXT(--E52,"000000")&".SZ"))) | Z52: =IF(Y52="","",IFERROR(INDEX('估值日行情'!$C$3:$C$61,MATCH(Y52,'估值日行情'!$A$3:$A$61,0)),"")) | AA52: =IF(D52="深港",IFERROR('FX_RATES_TO_CNY_HIST'!$B$3,""),1) | AB52: =IF(Z52<>"",Z52*AA52,"") | AC52: =SUMIFS($H$2:H52,$D$2:D52,D52,$E$2:E52,E52,$G$2:G52,"买入")-SUMIFS($H$2:H52,$D$2:D52,D52,$E$2:E52,E52,$G$2:G52,"卖出") | AD52: =IF(D52="深港",IF(Q52>0,SUMIFS($J$2:J51,$D$2:D51,D52,$E$2:E51,E52,$G$2:G51,"买入")/SUMIFS($H$2:H51,$D$2:D51,D52,$E$2:E51,E52,$G$2:G51,"买入"),""),S52) | AE52: =IF(AC52>0,AC52*Z52-AC52*AD52,0) | AF52: =IF(AC52>0,IF(D52="深港",AE52*AA52,AE52),0) | AG52: =SUMIFS($H$2:H51,$D$2:D51,D52,$E$2:E51,E52,$G$2:G51,"买入") | AH52: =SUMIFS($K$2:K51,$D$2:D51,D52,$E$2:E51,E52,$G$2:G51,"买入") | AI52: =IF(AG52>0,AH52/AG52,"") | AJ52: =IF(G52="卖出",IF(AI52="","",(L52-AI52)*H52),0) | AK52: =IF(G52="卖出",AJ52-T52,"") | AL52: =IF(G52="卖出","(L52-AI52)×H52 = ("&TEXT(L52,"0.######")&"-"&TEXT(AI52,"0.######")&")×"&H52,"")
A53: =IF('交易流水'!A13<>"","流水","") | B53: ='交易流水'!B13 | C53: ='交易流水'!X13 | D53: =IF(ISNUMBER(SEARCH("深港",C53)),"深港",IF(ISNUMBER(SEARCH("场内",C53)),"场内","其他")) | E53: ='交易流水'!F13 | F53: ='交易流水'!G13 | G53: ='交易流水'!H13 | H53: ='交易流水'!K13 | I53: ='交易流水'!P13 | J53: ='交易流水'!L13 | K53: ='交易流水'!AR13 | L53: =IF(H53>0,K53/H53,"") | M53: =IF(G53="买入",H53,0) | N53: =IF(G53="买入",K53,0) | O53: =IF(G53="卖出",H53,0) | P53: =IF(G53="卖出",K53,0) | Q53: =SUMIFS($H$2:H52,$A$2:A52,"流水",$D$2:D52,D53,$E$2:E52,E53,$G$2:G52,"买入") | R53: =SUMIFS($K$2:K52,$A$2:A52,"流水",$D$2:D52,D53,$E$2:E52,E53,$G$2:G52,"买入") | S53: =IF(Q53>0,R53/Q53,"") | T53: =IF(G53="卖出",IF(S53="","",(L53-S53)*H53),0) | U53: 190830.13 | V53: =IF(AND(J53>0,D53="深港"),K53/J53,"") | W53: =IF(G53="卖出","(L53-S53)×H53 = ("&TEXT(L53,"0.######")&"-"&TEXT(S53,"0.######")&")×"&H53,"") | X53: (L53-L34)×10000=(61.503400-42.420387)×10000=190830.13 → 190830.13 | Y53: =IF(E53="","",IF(D53="深港",TEXT(--E53,"0000")&".HK",IF(--E53>=600000,TEXT(--E53,"000000")&".SH",TEXT(--E53,"000000")&".SZ"))) | Z53: =IF(Y53="","",IFERROR(INDEX('估值日行情'!$C$3:$C$61,MATCH(Y53,'估值日行情'!$A$3:$A$61,0)),"")) | AA53: =IF(D53="深港",IFERROR('FX_RATES_TO_CNY_HIST'!$B$3,""),1) | AB53: =IF(Z53<>"",Z53*AA53,"") | AC53: =SUMIFS($H$2:H53,$D$2:D53,D53,$E$2:E53,E53,$G$2:G53,"买入")-SUMIFS($H$2:H53,$D$2:D53,D53,$E$2:E53,E53,$G$2:G53,"卖出") | AD53: =IF(D53="深港",IF(Q53>0,SUMIFS($J$2:J52,$D$2:D52,D53,$E$2:E52,E53,$G$2:G52,"买入")/SUMIFS($H$2:H52,$D$2:D52,D53,$E$2:E52,E53,$G$2:G52,"买入"),""),S53) | AE53: =IF(AC53>0,AC53*Z53-AC53*AD53,0) | AF53: =IF(AC53>0,IF(D53="深港",AE53*AA53,AE53),0) | AG53: =SUMIFS($H$2:H52,$D$2:D52,D53,$E$2:E52,E53,$G$2:G52,"买入") | AH53: =SUMIFS($K$2:K52,$D$2:D52,D53,$E$2:E52,E53,$G$2:G52,"买入") | AI53: =IF(AG53>0,AH53/AG53,"") | AJ53: =IF(G53="卖出",IF(AI53="","",(L53-AI53)*H53),0) | AK53: =IF(G53="卖出",AJ53-T53,"") | AL53: =IF(G53="卖出","(L53-AI53)×H53 = ("&TEXT(L53,"0.######")&"-"&TEXT(AI53,"0.######")&")×"&H53,"")
A54: =IF('交易流水'!A14<>"","流水","") | B54: ='交易流水'!B14 | C54: ='交易流水'!X14 | D54: =IF(ISNUMBER(SEARCH("深港",C54)),"深港",IF(ISNUMBER(SEARCH("场内",C54)),"场内","其他")) | E54: ='交易流水'!F14 | F54: ='交易流水'!G14 | G54: ='交易流水'!H14 | H54: ='交易流水'!K14 | I54: ='交易流水'!P14 | J54: ='交易流水'!L14 | K54: ='交易流水'!AR14 | L54: =IF(H54>0,K54/H54,"") | M54: =IF(G54="买入",H54,0) | N54: =IF(G54="买入",K54,0) | O54: =IF(G54="卖出",H54,0) | P54: =IF(G54="卖出",K54,0) | Q54: =SUMIFS($H$2:H53,$A$2:A53,"流水",$D$2:D53,D54,$E$2:E53,E54,$G$2:G53,"买入") | R54: =SUMIFS($K$2:K53,$A$2:A53,"流水",$D$2:D53,D54,$E$2:E53,E54,$G$2:G53,"买入") | S54: =IF(Q54>0,R54/Q54,"") | T54: =IF(G54="卖出",IF(S54="","",(L54-S54)*H54),0) | U54: 0 | V54: =IF(AND(J54>0,D54="深港"),K54/J54,"") | W54: =IF(G54="卖出","(L54-S54)×H54 = ("&TEXT(L54,"0.######")&"-"&TEXT(S54,"0.######")&")×"&H54,"") | Y54: =IF(E54="","",IF(D54="深港",TEXT(--E54,"0000")&".HK",IF(--E54>=600000,TEXT(--E54,"000000")&".SH",TEXT(--E54,"000000")&".SZ"))) | Z54: =IF(Y54="","",IFERROR(INDEX('估值日行情'!$C$3:$C$61,MATCH(Y54,'估值日行情'!$A$3:$A$61,0)),"")) | AA54: =IF(D54="深港",IFERROR('FX_RATES_TO_CNY_HIST'!$B$3,""),1) | AB54: =IF(Z54<>"",Z54*AA54,"") | AC54: =SUMIFS($H$2:H54,$D$2:D54,D54,$E$2:E54,E54,$G$2:G54,"买入")-SUMIFS($H$2:H54,$D$2:D54,D54,$E$2:E54,E54,$G$2:G54,"卖出") | AD54: =IF(D54="深港",IF(Q54>0,SUMIFS($J$2:J53,$D$2:D53,D54,$E$2:E53,E54,$G$2:G53,"买入")/SUMIFS($H$2:H53,$D$2:D53,D54,$E$2:E53,E54,$G$2:G53,"买入"),""),S54) | AE54: =IF(AC54>0,AC54*Z54-AC54*AD54,0) | AF54: =IF(AC54>0,IF(D54="深港",AE54*AA54,AE54),0) | AG54: =SUMIFS($H$2:H53,$D$2:D53,D54,$E$2:E53,E54,$G$2:G53,"买入") | AH54: =SUMIFS($K$2:K53,$D$2:D53,D54,$E$2:E53,E54,$G$2:G53,"买入") | AI54: =IF(AG54>0,AH54/AG54,"") | AJ54: =IF(G54="卖出",IF(AI54="","",(L54-AI54)*H54),0) | AK54: =IF(G54="卖出",AJ54-T54,"") | AL54: =IF(G54="卖出","(L54-AI54)×H54 = ("&TEXT(L54,"0.######")&"-"&TEXT(AI54,"0.######")&")×"&H54,"")
A55: =IF('交易流水'!A15<>"","流水","") | B55: ='交易流水'!B15 | C55: ='交易流水'!X15 | D55: =IF(ISNUMBER(SEARCH("深港",C55)),"深港",IF(ISNUMBER(SEARCH("场内",C55)),"场内","其他")) | E55: ='交易流水'!F15 | F55: ='交易流水'!G15 | G55: ='交易流水'!H15 | H55: ='交易流水'!K15 | I55: ='交易流水'!P15 | J55: ='交易流水'!L15 | K55: ='交易流水'!AR15 | L55: =IF(H55>0,K55/H55,"") | M55: =IF(G55="买入",H55,0) | N55: =IF(G55="买入",K55,0) | O55: =IF(G55="卖出",H55,0) | P55: =IF(G55="卖出",K55,0) | Q55: =SUMIFS($H$2:H54,$A$2:A54,"流水",$D$2:D54,D55,$E$2:E54,E55,$G$2:G54,"买入") | R55: =SUMIFS($K$2:K54,$A$2:A54,"流水",$D$2:D54,D55,$E$2:E54,E55,$G$2:G54,"买入") | S55: =IF(Q55>0,R55/Q55,"") | T55: =IF(G55="卖出",IF(S55="","",(L55-S55)*H55),0) | U55: 0 | V55: =IF(AND(J55>0,D55="深港"),K55/J55,"") | W55: =IF(G55="卖出","(L55-S55)×H55 = ("&TEXT(L55,"0.######")&"-"&TEXT(S55,"0.######")&")×"&H55,"") | Y55: =IF(E55="","",IF(D55="深港",TEXT(--E55,"0000")&".HK",IF(--E55>=600000,TEXT(--E55,"000000")&".SH",TEXT(--E55,"000000")&".SZ"))) | Z55: =IF(Y55="","",IFERROR(INDEX('估值日行情'!$C$3:$C$61,MATCH(Y55,'估值日行情'!$A$3:$A$61,0)),"")) | AA55: =IF(D55="深港",IFERROR('FX_RATES_TO_CNY_HIST'!$B$3,""),1) | AB55: =IF(Z55<>"",Z55*AA55,"") | AC55: =SUMIFS($H$2:H55,$D$2:D55,D55,$E$2:E55,E55,$G$2:G55,"买入")-SUMIFS($H$2:H55,$D$2:D55,D55,$E$2:E55,E55,$G$2:G55,"卖出") | AD55: =IF(D55="深港",IF(Q55>0,SUMIFS($J$2:J54,$D$2:D54,D55,$E$2:E54,E55,$G$2:G54,"买入")/SUMIFS($H$2:H54,$D$2:D54,D55,$E$2:E54,E55,$G$2:G54,"买入"),""),S55) | AE55: =IF(AC55>0,AC55*Z55-AC55*AD55,0) | AF55: =IF(AC55>0,IF(D55="深港",AE55*AA55,AE55),0) | AG55: =SUMIFS($H$2:H54,$D$2:D54,D55,$E$2:E54,E55,$G$2:G54,"买入") | AH55: =SUMIFS($K$2:K54,$D$2:D54,D55,$E$2:E54,E55,$G$2:G54,"买入") | AI55: =IF(AG55>0,AH55/AG55,"") | AJ55: =IF(G55="卖出",IF(AI55="","",(L55-AI55)*H55),0) | AK55: =IF(G55="卖出",AJ55-T55,"") | AL55: =IF(G55="卖出","(L55-AI55)×H55 = ("&TEXT(L55,"0.######")&"-"&TEXT(AI55,"0.######")&")×"&H55,"")
A56: =IF('交易流水'!A16<>"","流水","") | B56: ='交易流水'!B16 | C56: ='交易流水'!X16 | D56: =IF(ISNUMBER(SEARCH("深港",C56)),"深港",IF(ISNUMBER(SEARCH("场内",C56)),"场内","其他")) | E56: ='交易流水'!F16 | F56: ='交易流水'!G16 | G56: ='交易流水'!H16 | H56: ='交易流水'!K16 | I56: ='交易流水'!P16 | J56: ='交易流水'!L16 | K56: ='交易流水'!AR16 | L56: =IF(H56>0,K56/H56,"") | M56: =IF(G56="买入",H56,0) | N56: =IF(G56="买入",K56,0) | O56: =IF(G56="卖出",H56,0) | P56: =IF(G56="卖出",K56,0) | Q56: =SUMIFS($H$2:H55,$A$2:A55,"流水",$D$2:D55,D56,$E$2:E55,E56,$G$2:G55,"买入") | R56: =SUMIFS($K$2:K55,$A$2:A55,"流水",$D$2:D55,D56,$E$2:E55,E56,$G$2:G55,"买入") | S56: =IF(Q56>0,R56/Q56,"") | T56: =IF(G56="卖出",IF(S56="","",(L56-S56)*H56),0) | U56: 0 | V56: =IF(AND(J56>0,D56="深港"),K56/J56,"") | W56: =IF(G56="卖出","(L56-S56)×H56 = ("&TEXT(L56,"0.######")&"-"&TEXT(S56,"0.######")&")×"&H56,"") | Y56: =IF(E56="","",IF(D56="深港",TEXT(--E56,"0000")&".HK",IF(--E56>=600000,TEXT(--E56,"000000")&".SH",TEXT(--E56,"000000")&".SZ"))) | Z56: =IF(Y56="","",IFERROR(INDEX('估值日行情'!$C$3:$C$61,MATCH(Y56,'估值日行情'!$A$3:$A$61,0)),"")) | AA56: =IF(D56="深港",IFERROR('FX_RATES_TO_CNY_HIST'!$B$3,""),1) | AB56: =IF(Z56<>"",Z56*AA56,"") | AC56: =SUMIFS($H$2:H56,$D$2:D56,D56,$E$2:E56,E56,$G$2:G56,"买入")-SUMIFS($H$2:H56,$D$2:D56,D56,$E$2:E56,E56,$G$2:G56,"卖出") | AD56: =IF(D56="深港",IF(Q56>0,SUMIFS($J$2:J55,$D$2:D55,D56,$E$2:E55,E56,$G$2:G55,"买入")/SUMIFS($H$2:H55,$D$2:D55,D56,$E$2:E55,E56,$G$2:G55,"买入"),""),S56) | AE56: =IF(AC56>0,AC56*Z56-AC56*AD56,0) | AF56: =IF(AC56>0,IF(D56="深港",AE56*AA56,AE56),0) | AG56: =SUMIFS($H$2:H55,$D$2:D55,D56,$E$2:E55,E56,$G$2:G55,"买入") | AH56: =SUMIFS($K$2:K55,$D$2:D55,D56,$E$2:E55,E56,$G$2:G55,"买入") | AI56: =IF(AG56>0,AH56/AG56,"") | AJ56: =IF(G56="卖出",IF(AI56="","",(L56-AI56)*H56),0) | AK56: =IF(G56="卖出",AJ56-T56,"") | AL56: =IF(G56="卖出","(L56-AI56)×H56 = ("&TEXT(L56,"0.######")&"-"&TEXT(AI56,"0.######")&")×"&H56,"")
A57: =IF('交易流水'!A17<>"","流水","") | B57: ='交易流水'!B17 | C57: ='交易流水'!X17 | D57: =IF(ISNUMBER(SEARCH("深港",C57)),"深港",IF(ISNUMBER(SEARCH("场内",C57)),"场内","其他")) | E57: ='交易流水'!F17 | F57: ='交易流水'!G17 | G57: ='交易流水'!H17 | H57: ='交易流水'!K17 | I57: ='交易流水'!P17 | J57: ='交易流水'!L17 | K57: ='交易流水'!AR17 | L57: =IF(H57>0,K57/H57,"") | M57: =IF(G57="买入",H57,0) | N57: =IF(G57="买入",K57,0) | O57: =IF(G57="卖出",H57,0) | P57: =IF(G57="卖出",K57,0) | Q57: =SUMIFS($H$2:H56,$A$2:A56,"流水",$D$2:D56,D57,$E$2:E56,E57,$G$2:G56,"买入") | R57: =SUMIFS($K$2:K56,$A$2:A56,"流水",$D$2:D56,D57,$E$2:E56,E57,$G$2:G56,"买入") | S57: =IF(Q57>0,R57/Q57,"") | T57: =IF(G57="卖出",IF(S57="","",(L57-S57)*H57),0) | U57: 0 | V57: =IF(AND(J57>0,D57="深港"),K57/J57,"") | W57: =IF(G57="卖出","(L57-S57)×H57 = ("&TEXT(L57,"0.######")&"-"&TEXT(S57,"0.######")&")×"&H57,"") | Y57: =IF(E57="","",IF(D57="深港",TEXT(--E57,"0000")&".HK",IF(--E57>=600000,TEXT(--E57,"000000")&".SH",TEXT(--E57,"000000")&".SZ"))) | Z57: =IF(Y57="","",IFERROR(INDEX('估值日行情'!$C$3:$C$61,MATCH(Y57,'估值日行情'!$A$3:$A$61,0)),"")) | AA57: =IF(D57="深港",IFERROR('FX_RATES_TO_CNY_HIST'!$B$3,""),1) | AB57: =IF(Z57<>"",Z57*AA57,"") | AC57: =SUMIFS($H$2:H57,$D$2:D57,D57,$E$2:E57,E57,$G$2:G57,"买入")-SUMIFS($H$2:H57,$D$2:D57,D57,$E$2:E57,E57,$G$2:G57,"卖出") | AD57: =IF(D57="深港",IF(Q57>0,SUMIFS($J$2:J56,$D$2:D56,D57,$E$2:E56,E57,$G$2:G56,"买入")/SUMIFS($H$2:H56,$D$2:D56,D57,$E$2:E56,E57,$G$2:G56,"买入"),""),S57) | AE57: =IF(AC57>0,AC57*Z57-AC57*AD57,0) | AF57: =IF(AC57>0,IF(D57="深港",AE57*AA57,AE57),0) | AG57: =SUMIFS($H$2:H56,$D$2:D56,D57,$E$2:E56,E57,$G$2:G56,"买入") | AH57: =SUMIFS($K$2:K56,$D$2:D56,D57,$E$2:E56,E57,$G$2:G56,"买入") | AI57: =IF(AG57>0,AH57/AG57,"") | AJ57: =IF(G57="卖出",IF(AI57="","",(L57-AI57)*H57),0) | AK57: =IF(G57="卖出",AJ57-T57,"") | AL57: =IF(G57="卖出","(L57-AI57)×H57 = ("&TEXT(L57,"0.######")&"-"&TEXT(AI57,"0.######")&")×"&H57,"")
A58: =IF('交易流水'!A18<>"","流水","") | B58: ='交易流水'!B18 | C58: ='交易流水'!X18 | D58: =IF(ISNUMBER(SEARCH("深港",C58)),"深港",IF(ISNUMBER(SEARCH("场内",C58)),"场内","其他")) | E58: ='交易流水'!F18 | F58: ='交易流水'!G18 | G58: ='交易流水'!H18 | H58: ='交易流水'!K18 | I58: ='交易流水'!P18 | J58: ='交易流水'!L18 | K58: ='交易流水'!AR18 | L58: =IF(H58>0,K58/H58,"") | M58: =IF(G58="买入",H58,0) | N58: =IF(G58="买入",K58,0) | O58: =IF(G58="卖出",H58,0) | P58: =IF(G58="卖出",K58,0) | Q58: =SUMIFS($H$2:H57,$A$2:A57,"流水",$D$2:D57,D58,$E$2:E57,E58,$G$2:G57,"买入") | R58: =SUMIFS($K$2:K57,$A$2:A57,"流水",$D$2:D57,D58,$E$2:E57,E58,$G$2:G57,"买入") | S58: =IF(Q58>0,R58/Q58,"") | T58: =IF(G58="卖出",IF(S58="","",(L58-S58)*H58),0) | U58: 0 | V58: =IF(AND(J58>0,D58="深港"),K58/J58,"") | W58: =IF(G58="卖出","(L58-S58)×H58 = ("&TEXT(L58,"0.######")&"-"&TEXT(S58,"0.######")&")×"&H58,"") | Y58: =IF(E58="","",IF(D58="深港",TEXT(--E58,"0000")&".HK",IF(--E58>=600000,TEXT(--E58,"000000")&".SH",TEXT(--E58,"000000")&".SZ"))) | Z58: =IF(Y58="","",IFERROR(INDEX('估值日行情'!$C$3:$C$61,MATCH(Y58,'估值日行情'!$A$3:$A$61,0)),"")) | AA58: =IF(D58="深港",IFERROR('FX_RATES_TO_CNY_HIST'!$B$3,""),1) | AB58: =IF(Z58<>"",Z58*AA58,"") | AC58: =SUMIFS($H$2:H58,$D$2:D58,D58,$E$2:E58,E58,$G$2:G58,"买入")-SUMIFS($H$2:H58,$D$2:D58,D58,$E$2:E58,E58,$G$2:G58,"卖出") | AD58: =IF(D58="深港",IF(Q58>0,SUMIFS($J$2:J57,$D$2:D57,D58,$E$2:E57,E58,$G$2:G57,"买入")/SUMIFS($H$2:H57,$D$2:D57,D58,$E$2:E57,E58,$G$2:G57,"买入"),""),S58) | AE58: =IF(AC58>0,AC58*Z58-AC58*AD58,0) | AF58: =IF(AC58>0,IF(D58="深港",AE58*AA58,AE58),0) | AG58: =SUMIFS($H$2:H57,$D$2:D57,D58,$E$2:E57,E58,$G$2:G57,"买入") | AH58: =SUMIFS($K$2:K57,$D$2:D57,D58,$E$2:E57,E58,$G$2:G57,"买入") | AI58: =IF(AG58>0,AH58/AG58,"") | AJ58: =IF(G58="卖出",IF(AI58="","",(L58-AI58)*H58),0) | AK58: =IF(G58="卖出",AJ58-T58,"") | AL58: =IF(G58="卖出","(L58-AI58)×H58 = ("&TEXT(L58,"0.######")&"-"&TEXT(AI58,"0.######")&")×"&H58,"")
A59: =IF('交易流水'!A19<>"","流水","") | B59: ='交易流水'!B19 | C59: ='交易流水'!X19 | D59: =IF(ISNUMBER(SEARCH("深港",C59)),"深港",IF(ISNUMBER(SEARCH("场内",C59)),"场内","其他")) | E59: ='交易流水'!F19 | F59: ='交易流水'!G19 | G59: ='交易流水'!H19 | H59: ='交易流水'!K19 | I59: ='交易流水'!P19 | J59: ='交易流水'!L19 | K59: ='交易流水'!AR19 | L59: =IF(H59>0,K59/H59,"") | M59: =IF(G59="买入",H59,0) | N59: =IF(G59="买入",K59,0) | O59: =IF(G59="卖出",H59,0) | P59: =IF(G59="卖出",K59,0) | Q59: =SUMIFS($H$2:H58,$A$2:A58,"流水",$D$2:D58,D59,$E$2:E58,E59,$G$2:G58,"买入") | R59: =SUMIFS($K$2:K58,$A$2:A58,"流水",$D$2:D58,D59,$E$2:E58,E59,$G$2:G58,"买入") | S59: =IF(Q59>0,R59/Q59,"") | T59: =IF(G59="卖出",IF(S59="","",(L59-S59)*H59),0) | U59: 39709.55 | V59: =IF(AND(J59>0,D59="深港"),K59/J59,"") | W59: =IF(G59="卖出","(L59-S59)×H59 = ("&TEXT(L59,"0.######")&"-"&TEXT(S59,"0.######")&")×"&H59,"") | X59: (L59-L5)×300000=(11.240000-11.107635)×300000=39709.55 → 39709.55 | Y59: =IF(E59="","",IF(D59="深港",TEXT(--E59,"0000")&".HK",IF(--E59>=600000,TEXT(--E59,"000000")&".SH",TEXT(--E59,"000000")&".SZ"))) | Z59: =IF(Y59="","",IFERROR(INDEX('估值日行情'!$C$3:$C$61,MATCH(Y59,'估值日行情'!$A$3:$A$61,0)),"")) | AA59: =IF(D59="深港",IFERROR('FX_RATES_TO_CNY_HIST'!$B$3,""),1) | AB59: =IF(Z59<>"",Z59*AA59,"") | AC59: =SUMIFS($H$2:H59,$D$2:D59,D59,$E$2:E59,E59,$G$2:G59,"买入")-SUMIFS($H$2:H59,$D$2:D59,D59,$E$2:E59,E59,$G$2:G59,"卖出") | AD59: =IF(D59="深港",IF(Q59>0,SUMIFS($J$2:J58,$D$2:D58,D59,$E$2:E58,E59,$G$2:G58,"买入")/SUMIFS($H$2:H58,$D$2:D58,D59,$E$2:E58,E59,$G$2:G58,"买入"),""),S59) | AE59: =IF(AC59>0,AC59*Z59-AC59*AD59,0) | AF59: =IF(AC59>0,IF(D59="深港",AE59*AA59,AE59),0) | AG59: =SUMIFS($H$2:H58,$D$2:D58,D59,$E$2:E58,E59,$G$2:G58,"买入") | AH59: =SUMIFS($K$2:K58,$D$2:D58,D59,$E$2:E58,E59,$G$2:G58,"买入") | AI59: =IF(AG59>0,AH59/AG59,"") | AJ59: =IF(G59="卖出",IF(AI59="","",(L59-AI59)*H59),0) | AK59: =IF(G59="卖出",AJ59-T59,"") | AL59: =IF(G59="卖出","(L59-AI59)×H59 = ("&TEXT(L59,"0.######")&"-"&TEXT(AI59,"0.######")&")×"&H59,"")
A60: =IF('交易流水'!A20<>"","流水","") | B60: ='交易流水'!B20 | C60: ='交易流水'!X20 | D60: =IF(ISNUMBER(SEARCH("深港",C60)),"深港",IF(ISNUMBER(SEARCH("场内",C60)),"场内","其他")) | E60: ='交易流水'!F20 | F60: ='交易流水'!G20 | G60: ='交易流水'!H20 | H60: ='交易流水'!K20 | I60: ='交易流水'!P20 | J60: ='交易流水'!L20 | K60: ='交易流水'!AR20 | L60: =IF(H60>0,K60/H60,"") | M60: =IF(G60="买入",H60,0) | N60: =IF(G60="买入",K60,0) | O60: =IF(G60="卖出",H60,0) | P60: =IF(G60="卖出",K60,0) | Q60: =SUMIFS($H$2:H59,$A$2:A59,"流水",$D$2:D59,D60,$E$2:E59,E60,$G$2:G59,"买入") | R60: =SUMIFS($K$2:K59,$A$2:A59,"流水",$D$2:D59,D60,$E$2:E59,E60,$G$2:G59,"买入") | S60: =IF(Q60>0,R60/Q60,"") | T60: =IF(G60="卖出",IF(S60="","",(L60-S60)*H60),0) | U60: 0 | V60: =IF(AND(J60>0,D60="深港"),K60/J60,"") | W60: =IF(G60="卖出","(L60-S60)×H60 = ("&TEXT(L60,"0.######")&"-"&TEXT(S60,"0.######")&")×"&H60,"") | Y60: =IF(E60="","",IF(D60="深港",TEXT(--E60,"0000")&".HK",IF(--E60>=600000,TEXT(--E60,"000000")&".SH",TEXT(--E60,"000000")&".SZ"))) | Z60: =IF(Y60="","",IFERROR(INDEX('估值日行情'!$C$3:$C$61,MATCH(Y60,'估值日行情'!$A$3:$A$61,0)),"")) | AA60: =IF(D60="深港",IFERROR('FX_RATES_TO_CNY_HIST'!$B$3,""),1) | AB60: =IF(Z60<>"",Z60*AA60,"") | AC60: =SUMIFS($H$2:H60,$D$2:D60,D60,$E$2:E60,E60,$G$2:G60,"买入")-SUMIFS($H$2:H60,$D$2:D60,D60,$E$2:E60,E60,$G$2:G60,"卖出") | AD60: =IF(D60="深港",IF(Q60>0,SUMIFS($J$2:J59,$D$2:D59,D60,$E$2:E59,E60,$G$2:G59,"买入")/SUMIFS($H$2:H59,$D$2:D59,D60,$E$2:E59,E60,$G$2:G59,"买入"),""),S60) | AE60: =IF(AC60>0,AC60*Z60-AC60*AD60,0) | AF60: =IF(AC60>0,IF(D60="深港",AE60*AA60,AE60),0) | AG60: =SUMIFS($H$2:H59,$D$2:D59,D60,$E$2:E59,E60,$G$2:G59,"买入") | AH60: =SUMIFS($K$2:K59,$D$2:D59,D60,$E$2:E59,E60,$G$2:G59,"买入") | AI60: =IF(AG60>0,AH60/AG60,"") | AJ60: =IF(G60="卖出",IF(AI60="","",(L60-AI60)*H60),0) | AK60: =IF(G60="卖出",AJ60-T60,"") | AL60: =IF(G60="卖出","(L60-AI60)×H60 = ("&TEXT(L60,"0.######")&"-"&TEXT(AI60,"0.######")&")×"&H60,"")
A61: =IF('交易流水'!A21<>"","流水","") | B61: ='交易流水'!B21 | C61: ='交易流水'!X21 | D61: =IF(ISNUMBER(SEARCH("深港",C61)),"深港",IF(ISNUMBER(SEARCH("场内",C61)),"场内","其他")) | E61: ='交易流水'!F21 | F61: ='交易流水'!G21 | G61: ='交易流水'!H21 | H61: ='交易流水'!K21 | I61: ='交易流水'!P21 | J61: ='交易流水'!L21 | K61: ='交易流水'!AR21 | L61: =IF(H61>0,K61/H61,"") | M61: =IF(G61="买入",H61,0) | N61: =IF(G61="买入",K61,0) | O61: =IF(G61="卖出",H61,0) | P61: =IF(G61="卖出",K61,0) | Q61: =SUMIFS($H$2:H60,$A$2:A60,"流水",$D$2:D60,D61,$E$2:E60,E61,$G$2:G60,"买入") | R61: =SUMIFS($K$2:K60,$A$2:A60,"流水",$D$2:D60,D61,$E$2:E60,E61,$G$2:G60,"买入") | S61: =IF(Q61>0,R61/Q61,"") | T61: =IF(G61="卖出",IF(S61="","",(L61-S61)*H61),0) | U61: -11238.73 | V61: =IF(AND(J61>0,D61="深港"),K61/J61,"") | W61: =IF(G61="卖出","(L61-S61)×H61 = ("&TEXT(L61,"0.######")&"-"&TEXT(S61,"0.######")&")×"&H61,"") | X61: (L61-L35)×10000=(15.578677-16.702550)×10000=-11238.73 → -11238.73 | Y61: =IF(E61="","",IF(D61="深港",TEXT(--E61,"0000")&".HK",IF(--E61>=600000,TEXT(--E61,"000000")&".SH",TEXT(--E61,"000000")&".SZ"))) | Z61: =IF(Y61="","",IFERROR(INDEX('估值日行情'!$C$3:$C$61,MATCH(Y61,'估值日行情'!$A$3:$A$61,0)),"")) | AA61: =IF(D61="深港",IFERROR('FX_RATES_TO_CNY_HIST'!$B$3,""),1) | AB61: =IF(Z61<>"",Z61*AA61,"") | AC61: =SUMIFS($H$2:H61,$D$2:D61,D61,$E$2:E61,E61,$G$2:G61,"买入")-SUMIFS($H$2:H61,$D$2:D61,D61,$E$2:E61,E61,$G$2:G61,"卖出") | AD61: =IF(D61="深港",IF(Q61>0,SUMIFS($J$2:J60,$D$2:D60,D61,$E$2:E60,E61,$G$2:G60,"买入")/SUMIFS($H$2:H60,$D$2:D60,D61,$E$2:E60,E61,$G$2:G60,"买入"),""),S61) | AE61: =IF(AC61>0,AC61*Z61-AC61*AD61,0) | AF61: =IF(AC61>0,IF(D61="深港",AE61*AA61,AE61),0) | AG61: =SUMIFS($H$2:H60,$D$2:D60,D61,$E$2:E60,E61,$G$2:G60,"买入") | AH61: =SUMIFS($K$2:K60,$D$2:D60,D61,$E$2:E60,E61,$G$2:G60,"买入") | AI61: =IF(AG61>0,AH61/AG61,"") | AJ61: =IF(G61="卖出",IF(AI61="","",(L61-AI61)*H61),0) | AK61: =IF(G61="卖出",AJ61-T61,"") | AL61: =IF(G61="卖出","(L61-AI61)×H61 = ("&TEXT(L61,"0.######")&"-"&TEXT(AI61,"0.######")&")×"&H61,"")
A62: =IF('交易流水'!A22<>"","流水","") | B62: ='交易流水'!B22 | C62: ='交易流水'!X22 | D62: =IF(ISNUMBER(SEARCH("深港",C62)),"深港",IF(ISNUMBER(SEARCH("场内",C62)),"场内","其他")) | E62: ='交易流水'!F22 | F62: ='交易流水'!G22 | G62: ='交易流水'!H22 | H62: ='交易流水'!K22 | I62: ='交易流水'!P22 | J62: ='交易流水'!L22 | K62: ='交易流水'!AR22 | L62: =IF(H62>0,K62/H62,"") | M62: =IF(G62="买入",H62,0) | N62: =IF(G62="买入",K62,0) | O62: =IF(G62="卖出",H62,0) | P62: =IF(G62="卖出",K62,0) | Q62: =SUMIFS($H$2:H61,$A$2:A61,"流水",$D$2:D61,D62,$E$2:E61,E62,$G$2:G61,"买入") | R62: =SUMIFS($K$2:K61,$A$2:A61,"流水",$D$2:D61,D62,$E$2:E61,E62,$G$2:G61,"买入") | S62: =IF(Q62>0,R62/Q62,"") | T62: =IF(G62="卖出",IF(S62="","",(L62-S62)*H62),0) | U62: -8970.86 | V62: =IF(AND(J62>0,D62="深港"),K62/J62,"") | W62: =IF(G62="卖出","(L62-S62)×H62 = ("&TEXT(L62,"0.######")&"-"&TEXT(S62,"0.######")&")×"&H62,"") | X62: (L62-L39)×100000=(4.165564-4.255273)×100000=-8970.86 → -8970.86 | Y62: =IF(E62="","",IF(D62="深港",TEXT(--E62,"0000")&".HK",IF(--E62>=600000,TEXT(--E62,"000000")&".SH",TEXT(--E62,"000000")&".SZ"))) | Z62: =IF(Y62="","",IFERROR(INDEX('估值日行情'!$C$3:$C$61,MATCH(Y62,'估值日行情'!$A$3:$A$61,0)),"")) | AA62: =IF(D62="深港",IFERROR('FX_RATES_TO_CNY_HIST'!$B$3,""),1) | AB62: =IF(Z62<>"",Z62*AA62,"") | AC62: =SUMIFS($H$2:H62,$D$2:D62,D62,$E$2:E62,E62,$G$2:G62,"买入")-SUMIFS($H$2:H62,$D$2:D62,D62,$E$2:E62,E62,$G$2:G62,"卖出") | AD62: =IF(D62="深港",IF(Q62>0,SUMIFS($J$2:J61,$D$2:D61,D62,$E$2:E61,E62,$G$2:G61,"买入")/SUMIFS($H$2:H61,$D$2:D61,D62,$E$2:E61,E62,$G$2:G61,"买入"),""),S62) | AE62: =IF(AC62>0,AC62*Z62-AC62*AD62,0) | AF62: =IF(AC62>0,IF(D62="深港",AE62*AA62,AE62),0) | AG62: =SUMIFS($H$2:H61,$D$2:D61,D62,$E$2:E61,E62,$G$2:G61,"买入") | AH62: =SUMIFS($K$2:K61,$D$2:D61,D62,$E$2:E61,E62,$G$2:G61,"买入") | AI62: =IF(AG62>0,AH62/AG62,"") | AJ62: =IF(G62="卖出",IF(AI62="","",(L62-AI62)*H62),0) | AK62: =IF(G62="卖出",AJ62-T62,"") | AL62: =IF(G62="卖出","(L62-AI62)×H62 = ("&TEXT(L62,"0.######")&"-"&TEXT(AI62,"0.######")&")×"&H62,"")
A63: =IF('交易流水'!A23<>"","流水","") | B63: ='交易流水'!B23 | C63: ='交易流水'!X23 | D63: =IF(ISNUMBER(SEARCH("深港",C63)),"深港",IF(ISNUMBER(SEARCH("场内",C63)),"场内","其他")) | E63: ='交易流水'!F23 | F63: ='交易流水'!G23 | G63: ='交易流水'!H23 | H63: ='交易流水'!K23 | I63: ='交易流水'!P23 | J63: ='交易流水'!L23 | K63: ='交易流水'!AR23 | L63: =IF(H63>0,K63/H63,"") | M63: =IF(G63="买入",H63,0) | N63: =IF(G63="买入",K63,0) | O63: =IF(G63="卖出",H63,0) | P63: =IF(G63="卖出",K63,0) | Q63: =SUMIFS($H$2:H62,$A$2:A62,"流水",$D$2:D62,D63,$E$2:E62,E63,$G$2:G62,"买入") | R63: =SUMIFS($K$2:K62,$A$2:A62,"流水",$D$2:D62,D63,$E$2:E62,E63,$G$2:G62,"买入") | S63: =IF(Q63>0,R63/Q63,"") | T63: =IF(G63="卖出",IF(S63="","",(L63-S63)*H63),0) | U63: -81063.86 | V63: =IF(AND(J63>0,D63="深港"),K63/J63,"") | W63: =IF(G63="卖出","(L63-S63)×H63 = ("&TEXT(L63,"0.######")&"-"&TEXT(S63,"0.######")&")×"&H63,"") | X63: (L63-L4)×9000=(170.313333-179.320429)×9000=-81063.86 → -81063.86 | Y63: =IF(E63="","",IF(D63="深港",TEXT(--E63,"0000")&".HK",IF(--E63>=600000,TEXT(--E63,"000000")&".SH",TEXT(--E63,"000000")&".SZ"))) | Z63: =IF(Y63="","",IFERROR(INDEX('估值日行情'!$C$3:$C$61,MATCH(Y63,'估值日行情'!$A$3:$A$61,0)),"")) | AA63: =IF(D63="深港",IFERROR('FX_RATES_TO_CNY_HIST'!$B$3,""),1) | AB63: =IF(Z63<>"",Z63*AA63,"") | AC63: =SUMIFS($H$2:H63,$D$2:D63,D63,$E$2:E63,E63,$G$2:G63,"买入")-SUMIFS($H$2:H63,$D$2:D63,D63,$E$2:E63,E63,$G$2:G63,"卖出") | AD63: =IF(D63="深港",IF(Q63>0,SUMIFS($J$2:J62,$D$2:D62,D63,$E$2:E62,E63,$G$2:G62,"买入")/SUMIFS($H$2:H62,$D$2:D62,D63,$E$2:E62,E63,$G$2:G62,"买入"),""),S63) | AE63: =IF(AC63>0,AC63*Z63-AC63*AD63,0) | AF63: =IF(AC63>0,IF(D63="深港",AE63*AA63,AE63),0) | AG63: =SUMIFS($H$2:H62,$D$2:D62,D63,$E$2:E62,E63,$G$2:G62,"买入") | AH63: =SUMIFS($K$2:K62,$D$2:D62,D63,$E$2:E62,E63,$G$2:G62,"买入") | AI63: =IF(AG63>0,AH63/AG63,"") | AJ63: =IF(G63="卖出",IF(AI63="","",(L63-AI63)*H63),0) | AK63: =IF(G63="卖出",AJ63-T63,"") | AL63: =IF(G63="卖出","(L63-AI63)×H63 = ("&TEXT(L63,"0.######")&"-"&TEXT(AI63,"0.######")&")×"&H63,"")
A64: =IF('交易流水'!A24<>"","流水","") | B64: ='交易流水'!B24 | C64: ='交易流水'!X24 | D64: =IF(ISNUMBER(SEARCH("深港",C64)),"深港",IF(ISNUMBER(SEARCH("场内",C64)),"场内","其他")) | E64: ='交易流水'!F24 | F64: ='交易流水'!G24 | G64: ='交易流水'!H24 | H64: ='交易流水'!K24 | I64: ='交易流水'!P24 | J64: ='交易流水'!L24 | K64: ='交易流水'!AR24 | L64: =IF(H64>0,K64/H64,"") | M64: =IF(G64="买入",H64,0) | N64: =IF(G64="买入",K64,0) | O64: =IF(G64="卖出",H64,0) | P64: =IF(G64="卖出",K64,0) | Q64: =SUMIFS($H$2:H63,$A$2:A63,"流水",$D$2:D63,D64,$E$2:E63,E64,$G$2:G63,"买入") | R64: =SUMIFS($K$2:K63,$A$2:A63,"流水",$D$2:D63,D64,$E$2:E63,E64,$G$2:G63,"买入") | S64: =IF(Q64>0,R64/Q64,"") | T64: =IF(G64="卖出",IF(S64="","",(L64-S64)*H64),0) | U64: 0 | V64: =IF(AND(J64>0,D64="深港"),K64/J64,"") | W64: =IF(G64="卖出","(L64-S64)×H64 = ("&TEXT(L64,"0.######")&"-"&TEXT(S64,"0.######")&")×"&H64,"") | Y64: =IF(E64="","",IF(D64="深港",TEXT(--E64,"0000")&".HK",IF(--E64>=600000,TEXT(--E64,"000000")&".SH",TEXT(--E64,"000000")&".SZ"))) | Z64: =IF(Y64="","",IFERROR(INDEX('估值日行情'!$C$3:$C$61,MATCH(Y64,'估值日行情'!$A$3:$A$61,0)),"")) | AA64: =IF(D64="深港",IFERROR('FX_RATES_TO_CNY_HIST'!$B$3,""),1) | AB64: =IF(Z64<>"",Z64*AA64,"") | AC64: =SUMIFS($H$2:H64,$D$2:D64,D64,$E$2:E64,E64,$G$2:G64,"买入")-SUMIFS($H$2:H64,$D$2:D64,D64,$E$2:E64,E64,$G$2:G64,"卖出") | AD64: =IF(D64="深港",IF(Q64>0,SUMIFS($J$2:J63,$D$2:D63,D64,$E$2:E63,E64,$G$2:G63,"买入")/SUMIFS($H$2:H63,$D$2:D63,D64,$E$2:E63,E64,$G$2:G63,"买入"),""),S64) | AE64: =IF(AC64>0,AC64*Z64-AC64*AD64,0) | AF64: =IF(AC64>0,IF(D64="深港",AE64*AA64,AE64),0) | AG64: =SUMIFS($H$2:H63,$D$2:D63,D64,$E$2:E63,E64,$G$2:G63,"买入") | AH64: =SUMIFS($K$2:K63,$D$2:D63,D64,$E$2:E63,E64,$G$2:G63,"买入") | AI64: =IF(AG64>0,AH64/AG64,"") | AJ64: =IF(G64="卖出",IF(AI64="","",(L64-AI64)*H64),0) | AK64: =IF(G64="卖出",AJ64-T64,"") | AL64: =IF(G64="卖出","(L64-AI64)×H64 = ("&TEXT(L64,"0.######")&"-"&TEXT(AI64,"0.######")&")×"&H64,"")
A65: =IF('交易流水'!A25<>"","流水","") | B65: ='交易流水'!B25 | C65: ='交易流水'!X25 | D65: =IF(ISNUMBER(SEARCH("深港",C65)),"深港",IF(ISNUMBER(SEARCH("场内",C65)),"场内","其他")) | E65: ='交易流水'!F25 | F65: ='交易流水'!G25 | G65: ='交易流水'!H25 | H65: ='交易流水'!K25 | I65: ='交易流水'!P25 | J65: ='交易流水'!L25 | K65: ='交易流水'!AR25 | L65: =IF(H65>0,K65/H65,"") | M65: =IF(G65="买入",H65,0) | N65: =IF(G65="买入",K65,0) | O65: =IF(G65="卖出",H65,0) | P65: =IF(G65="卖出",K65,0) | Q65: =SUMIFS($H$2:H64,$A$2:A64,"流水",$D$2:D64,D65,$E$2:E64,E65,$G$2:G64,"买入") | R65: =SUMIFS($K$2:K64,$A$2:A64,"流水",$D$2:D64,D65,$E$2:E64,E65,$G$2:G64,"买入") | S65: =IF(Q65>0,R65/Q65,"") | T65: =IF(G65="卖出",IF(S65="","",(L65-S65)*H65),0) | U65: 0 | V65: =IF(AND(J65>0,D65="深港"),K65/J65,"") | W65: =IF(G65="卖出","(L65-S65)×H65 = ("&TEXT(L65,"0.######")&"-"&TEXT(S65,"0.######")&")×"&H65,"") | Y65: =IF(E65="","",IF(D65="深港",TEXT(--E65,"0000")&".HK",IF(--E65>=600000,TEXT(--E65,"000000")&".SH",TEXT(--E65,"000000")&".SZ"))) | Z65: =IF(Y65="","",IFERROR(INDEX('估值日行情'!$C$3:$C$61,MATCH(Y65,'估值日行情'!$A$3:$A$61,0)),"")) | AA65: =IF(D65="深港",IFERROR('FX_RATES_TO_CNY_HIST'!$B$3,""),1) | AB65: =IF(Z65<>"",Z65*AA65,"") | AC65: =SUMIFS($H$2:H65,$D$2:D65,D65,$E$2:E65,E65,$G$2:G65,"买入")-SUMIFS($H$2:H65,$D$2:D65,D65,$E$2:E65,E65,$G$2:G65,"卖出") | AD65: =IF(D65="深港",IF(Q65>0,SUMIFS($J$2:J64,$D$2:D64,D65,$E$2:E64,E65,$G$2:G64,"买入")/SUMIFS($H$2:H64,$D$2:D64,D65,$E$2:E64,E65,$G$2:G64,"买入"),""),S65) | AE65: =IF(AC65>0,AC65*Z65-AC65*AD65,0) | AF65: =IF(AC65>0,IF(D65="深港",AE65*AA65,AE65),0) | AG65: =SUMIFS($H$2:H64,$D$2:D64,D65,$E$2:E64,E65,$G$2:G64,"买入") | AH65: =SUMIFS($K$2:K64,$D$2:D64,D65,$E$2:E64,E65,$G$2:G64,"买入") | AI65: =IF(AG65>0,AH65/AG65,"") | AJ65: =IF(G65="卖出",IF(AI65="","",(L65-AI65)*H65),0) | AK65: =IF(G65="卖出",AJ65-T65,"") | AL65: =IF(G65="卖出","(L65-AI65)×H65 = ("&TEXT(L65,"0.######")&"-"&TEXT(AI65,"0.######")&")×"&H65,"")
A66: =IF('交易流水'!A26<>"","流水","") | B66: ='交易流水'!B26 | C66: ='交易流水'!X26 | D66: =IF(ISNUMBER(SEARCH("深港",C66)),"深港",IF(ISNUMBER(SEARCH("场内",C66)),"场内","其他")) | E66: ='交易流水'!F26 | F66: ='交易流水'!G26 | G66: ='交易流水'!H26 | H66: ='交易流水'!K26 | I66: ='交易流水'!P26 | J66: ='交易流水'!L26 | K66: ='交易流水'!AR26 | L66: =IF(H66>0,K66/H66,"") | M66: =IF(G66="买入",H66,0) | N66: =IF(G66="买入",K66,0) | O66: =IF(G66="卖出",H66,0) | P66: =IF(G66="卖出",K66,0) | Q66: =SUMIFS($H$2:H65,$A$2:A65,"流水",$D$2:D65,D66,$E$2:E65,E66,$G$2:G65,"买入") | R66: =SUMIFS($K$2:K65,$A$2:A65,"流水",$D$2:D65,D66,$E$2:E65,E66,$G$2:G65,"买入") | S66: =IF(Q66>0,R66/Q66,"") | T66: =IF(G66="卖出",IF(S66="","",(L66-S66)*H66),0) | U66: 0 | V66: =IF(AND(J66>0,D66="深港"),K66/J66,"") | W66: =IF(G66="卖出","(L66-S66)×H66 = ("&TEXT(L66,"0.######")&"-"&TEXT(S66,"0.######")&")×"&H66,"") | Y66: =IF(E66="","",IF(D66="深港",TEXT(--E66,"0000")&".HK",IF(--E66>=600000,TEXT(--E66,"000000")&".SH",TEXT(--E66,"000000")&".SZ"))) | Z66: =IF(Y66="","",IFERROR(INDEX('估值日行情'!$C$3:$C$61,MATCH(Y66,'估值日行情'!$A$3:$A$61,0)),"")) | AA66: =IF(D66="深港",IFERROR('FX_RATES_TO_CNY_HIST'!$B$3,""),1) | AB66: =IF(Z66<>"",Z66*AA66,"") | AC66: =SUMIFS($H$2:H66,$D$2:D66,D66,$E$2:E66,E66,$G$2:G66,"买入")-SUMIFS($H$2:H66,$D$2:D66,D66,$E$2:E66,E66,$G$2:G66,"卖出") | AD66: =IF(D66="深港",IF(Q66>0,SUMIFS($J$2:J65,$D$2:D65,D66,$E$2:E65,E66,$G$2:G65,"买入")/SUMIFS($H$2:H65,$D$2:D65,D66,$E$2:E65,E66,$G$2:G65,"买入"),""),S66) | AE66: =IF(AC66>0,AC66*Z66-AC66*AD66,0) | AF66: =IF(AC66>0,IF(D66="深港",AE66*AA66,AE66),0) | AG66: =SUMIFS($H$2:H65,$D$2:D65,D66,$E$2:E65,E66,$G$2:G65,"买入") | AH66: =SUMIFS($K$2:K65,$D$2:D65,D66,$E$2:E65,E66,$G$2:G65,"买入") | AI66: =IF(AG66>0,AH66/AG66,"") | AJ66: =IF(G66="卖出",IF(AI66="","",(L66-AI66)*H66),0) | AK66: =IF(G66="卖出",AJ66-T66,"") | AL66: =IF(G66="卖出","(L66-AI66)×H66 = ("&TEXT(L66,"0.######")&"-"&TEXT(AI66,"0.######")&")×"&H66,"")
A67: =IF('交易流水'!A27<>"","流水","") | B67: ='交易流水'!B27 | C67: ='交易流水'!X27 | D67: =IF(ISNUMBER(SEARCH("深港",C67)),"深港",IF(ISNUMBER(SEARCH("场内",C67)),"场内","其他")) | E67: ='交易流水'!F27 | F67: ='交易流水'!G27 | G67: ='交易流水'!H27 | H67: ='交易流水'!K27 | I67: ='交易流水'!P27 | J67: ='交易流水'!L27 | K67: ='交易流水'!AR27 | L67: =IF(H67>0,K67/H67,"") | M67: =IF(G67="买入",H67,0) | N67: =IF(G67="买入",K67,0) | O67: =IF(G67="卖出",H67,0) | P67: =IF(G67="卖出",K67,0) | Q67: =SUMIFS($H$2:H66,$A$2:A66,"流水",$D$2:D66,D67,$E$2:E66,E67,$G$2:G66,"买入") | R67: =SUMIFS($K$2:K66,$A$2:A66,"流水",$D$2:D66,D67,$E$2:E66,E67,$G$2:G66,"买入") | S67: =IF(Q67>0,R67/Q67,"") | T67: =IF(G67="卖出",IF(S67="","",(L67-S67)*H67),0) | U67: 0 | V67: =IF(AND(J67>0,D67="深港"),K67/J67,"") | W67: =IF(G67="卖出","(L67-S67)×H67 = ("&TEXT(L67,"0.######")&"-"&TEXT(S67,"0.######")&")×"&H67,"") | Y67: =IF(E67="","",IF(D67="深港",TEXT(--E67,"0000")&".HK",IF(--E67>=600000,TEXT(--E67,"000000")&".SH",TEXT(--E67,"000000")&".SZ"))) | Z67: =IF(Y67="","",IFERROR(INDEX('估值日行情'!$C$3:$C$61,MATCH(Y67,'估值日行情'!$A$3:$A$61,0)),"")) | AA67: =IF(D67="深港",IFERROR('FX_RATES_TO_CNY_HIST'!$B$3,""),1) | AB67: =IF(Z67<>"",Z67*AA67,"") | AC67: =SUMIFS($H$2:H67,$D$2:D67,D67,$E$2:E67,E67,$G$2:G67,"买入")-SUMIFS($H$2:H67,$D$2:D67,D67,$E$2:E67,E67,$G$2:G67,"卖出") | AD67: =IF(D67="深港",IF(Q67>0,SUMIFS($J$2:J66,$D$2:D66,D67,$E$2:E66,E67,$G$2:G66,"买入")/SUMIFS($H$2:H66,$D$2:D66,D67,$E$2:E66,E67,$G$2:G66,"买入"),""),S67) | AE67: =IF(AC67>0,AC67*Z67-AC67*AD67,0) | AF67: =IF(AC67>0,IF(D67="深港",AE67*AA67,AE67),0) | AG67: =SUMIFS($H$2:H66,$D$2:D66,D67,$E$2:E66,E67,$G$2:G66,"买入") | AH67: =SUMIFS($K$2:K66,$D$2:D66,D67,$E$2:E66,E67,$G$2:G66,"买入") | AI67: =IF(AG67>0,AH67/AG67,"") | AJ67: =IF(G67="卖出",IF(AI67="","",(L67-AI67)*H67),0) | AK67: =IF(G67="卖出",AJ67-T67,"") | AL67: =IF(G67="卖出","(L67-AI67)×H67 = ("&TEXT(L67,"0.######")&"-"&TEXT(AI67,"0.######")&")×"&H67,"")
A68: =IF('交易流水'!A28<>"","流水","") | B68: ='交易流水'!B28 | C68: ='交易流水'!X28 | D68: =IF(ISNUMBER(SEARCH("深港",C68)),"深港",IF(ISNUMBER(SEARCH("场内",C68)),"场内","其他")) | E68: ='交易流水'!F28 | F68: ='交易流水'!G28 | G68: ='交易流水'!H28 | H68: ='交易流水'!K28 | I68: ='交易流水'!P28 | J68: ='交易流水'!L28 | K68: ='交易流水'!AR28 | L68: =IF(H68>0,K68/H68,"") | M68: =IF(G68="买入",H68,0) | N68: =IF(G68="买入",K68,0) | O68: =IF(G68="卖出",H68,0) | P68: =IF(G68="卖出",K68,0) | Q68: =SUMIFS($H$2:H67,$A$2:A67,"流水",$D$2:D67,D68,$E$2:E67,E68,$G$2:G67,"买入") | R68: =SUMIFS($K$2:K67,$A$2:A67,"流水",$D$2:D67,D68,$E$2:E67,E68,$G$2:G67,"买入") | S68: =IF(Q68>0,R68/Q68,"") | T68: =IF(G68="卖出",IF(S68="","",(L68-S68)*H68),0) | U68: -56542.96 | V68: =IF(AND(J68>0,D68="深港"),K68/J68,"") | W68: =IF(G68="卖出","(L68-S68)×H68 = ("&TEXT(L68,"0.######")&"-"&TEXT(S68,"0.######")&")×"&H68,"") | X68: (L68-L14)×15000=(117.954267-121.723797)×15000=-56542.96 → -56542.96 | Y68: =IF(E68="","",IF(D68="深港",TEXT(--E68,"0000")&".HK",IF(--E68>=600000,TEXT(--E68,"000000")&".SH",TEXT(--E68,"000000")&".SZ"))) | Z68: =IF(Y68="","",IFERROR(INDEX('估值日行情'!$C$3:$C$61,MATCH(Y68,'估值日行情'!$A$3:$A$61,0)),"")) | AA68: =IF(D68="深港",IFERROR('FX_RATES_TO_CNY_HIST'!$B$3,""),1) | AB68: =IF(Z68<>"",Z68*AA68,"") | AC68: =SUMIFS($H$2:H68,$D$2:D68,D68,$E$2:E68,E68,$G$2:G68,"买入")-SUMIFS($H$2:H68,$D$2:D68,D68,$E$2:E68,E68,$G$2:G68,"卖出") | AD68: =IF(D68="深港",IF(Q68>0,SUMIFS($J$2:J67,$D$2:D67,D68,$E$2:E67,E68,$G$2:G67,"买入")/SUMIFS($H$2:H67,$D$2:D67,D68,$E$2:E67,E68,$G$2:G67,"买入"),""),S68) | AE68: =IF(AC68>0,AC68*Z68-AC68*AD68,0) | AF68: =IF(AC68>0,IF(D68="深港",AE68*AA68,AE68),0) | AG68: =SUMIFS($H$2:H67,$D$2:D67,D68,$E$2:E67,E68,$G$2:G67,"买入") | AH68: =SUMIFS($K$2:K67,$D$2:D67,D68,$E$2:E67,E68,$G$2:G67,"买入") | AI68: =IF(AG68>0,AH68/AG68,"") | AJ68: =IF(G68="卖出",IF(AI68="","",(L68-AI68)*H68),0) | AK68: =IF(G68="卖出",AJ68-T68,"") | AL68: =IF(G68="卖出","(L68-AI68)×H68 = ("&TEXT(L68,"0.######")&"-"&TEXT(AI68,"0.######")&")×"&H68,"")
A69: =IF('交易流水'!A29<>"","流水","") | B69: ='交易流水'!B29 | C69: ='交易流水'!X29 | D69: =IF(ISNUMBER(SEARCH("深港",C69)),"深港",IF(ISNUMBER(SEARCH("场内",C69)),"场内","其他")) | E69: ='交易流水'!F29 | F69: ='交易流水'!G29 | G69: ='交易流水'!H29 | H69: ='交易流水'!K29 | I69: ='交易流水'!P29 | J69: ='交易流水'!L29 | K69: ='交易流水'!AR29 | L69: =IF(H69>0,K69/H69,"") | M69: =IF(G69="买入",H69,0) | N69: =IF(G69="买入",K69,0) | O69: =IF(G69="卖出",H69,0) | P69: =IF(G69="卖出",K69,0) | Q69: =SUMIFS($H$2:H68,$A$2:A68,"流水",$D$2:D68,D69,$E$2:E68,E69,$G$2:G68,"买入") | R69: =SUMIFS($K$2:K68,$A$2:A68,"流水",$D$2:D68,D69,$E$2:E68,E69,$G$2:G68,"买入") | S69: =IF(Q69>0,R69/Q69,"") | T69: =IF(G69="卖出",IF(S69="","",(L69-S69)*H69),0) | U69: 0 | V69: =IF(AND(J69>0,D69="深港"),K69/J69,"") | W69: =IF(G69="卖出","(L69-S69)×H69 = ("&TEXT(L69,"0.######")&"-"&TEXT(S69,"0.######")&")×"&H69,"") | Y69: =IF(E69="","",IF(D69="深港",TEXT(--E69,"0000")&".HK",IF(--E69>=600000,TEXT(--E69,"000000")&".SH",TEXT(--E69,"000000")&".SZ"))) | Z69: =IF(Y69="","",IFERROR(INDEX('估值日行情'!$C$3:$C$61,MATCH(Y69,'估值日行情'!$A$3:$A$61,0)),"")) | AA69: =IF(D69="深港",IFERROR('FX_RATES_TO_CNY_HIST'!$B$3,""),1) | AB69: =IF(Z69<>"",Z69*AA69,"") | AC69: =SUMIFS($H$2:H69,$D$2:D69,D69,$E$2:E69,E69,$G$2:G69,"买入")-SUMIFS($H$2:H69,$D$2:D69,D69,$E$2:E69,E69,$G$2:G69,"卖出") | AD69: =IF(D69="深港",IF(Q69>0,SUMIFS($J$2:J68,$D$2:D68,D69,$E$2:E68,E69,$G$2:G68,"买入")/SUMIFS($H$2:H68,$D$2:D68,D69,$E$2:E68,E69,$G$2:G68,"买入"),""),S69) | AE69: =IF(AC69>0,AC69*Z69-AC69*AD69,0) | AF69: =IF(AC69>0,IF(D69="深港",AE69*AA69,AE69),0) | AG69: =SUMIFS($H$2:H68,$D$2:D68,D69,$E$2:E68,E69,$G$2:G68,"买入") | AH69: =SUMIFS($K$2:K68,$D$2:D68,D69,$E$2:E68,E69,$G$2:G68,"买入") | AI69: =IF(AG69>0,AH69/AG69,"") | AJ69: =IF(G69="卖出",IF(AI69="","",(L69-AI69)*H69),0) | AK69: =IF(G69="卖出",AJ69-T69,"") | AL69: =IF(G69="卖出","(L69-AI69)×H69 = ("&TEXT(L69,"0.######")&"-"&TEXT(AI69,"0.######")&")×"&H69,"")
A70: =IF('交易流水'!A30<>"","流水","") | B70: ='交易流水'!B30 | C70: ='交易流水'!X30 | D70: =IF(ISNUMBER(SEARCH("深港",C70)),"深港",IF(ISNUMBER(SEARCH("场内",C70)),"场内","其他")) | E70: ='交易流水'!F30 | F70: ='交易流水'!G30 | G70: ='交易流水'!H30 | H70: ='交易流水'!K30 | I70: ='交易流水'!P30 | J70: ='交易流水'!L30 | K70: ='交易流水'!AR30 | L70: =IF(H70>0,K70/H70,"") | M70: =IF(G70="买入",H70,0) | N70: =IF(G70="买入",K70,0) | O70: =IF(G70="卖出",H70,0) | P70: =IF(G70="卖出",K70,0) | Q70: =SUMIFS($H$2:H69,$A$2:A69,"流水",$D$2:D69,D70,$E$2:E69,E70,$G$2:G69,"买入") | R70: =SUMIFS($K$2:K69,$A$2:A69,"流水",$D$2:D69,D70,$E$2:E69,E70,$G$2:G69,"买入") | S70: =IF(Q70>0,R70/Q70,"") | T70: =IF(G70="卖出",IF(S70="","",(L70-S70)*H70),0) | U70: -77423.01 | V70: =IF(AND(J70>0,D70="深港"),K70/J70,"") | W70: =IF(G70="卖出","(L70-S70)×H70 = ("&TEXT(L70,"0.######")&"-"&TEXT(S70,"0.######")&")×"&H70,"") | X70: (L70-L4)×7000=(168.260000-179.320429)×7000=-77423.01 → -77423.01 | Y70: =IF(E70="","",IF(D70="深港",TEXT(--E70,"0000")&".HK",IF(--E70>=600000,TEXT(--E70,"000000")&".SH",TEXT(--E70,"000000")&".SZ"))) | Z70: =IF(Y70="","",IFERROR(INDEX('估值日行情'!$C$3:$C$61,MATCH(Y70,'估值日行情'!$A$3:$A$61,0)),"")) | AA70: =IF(D70="深港",IFERROR('FX_RATES_TO_CNY_HIST'!$B$3,""),1) | AB70: =IF(Z70<>"",Z70*AA70,"") | AC70: =SUMIFS($H$2:H70,$D$2:D70,D70,$E$2:E70,E70,$G$2:G70,"买入")-SUMIFS($H$2:H70,$D$2:D70,D70,$E$2:E70,E70,$G$2:G70,"卖出") | AD70: =IF(D70="深港",IF(Q70>0,SUMIFS($J$2:J69,$D$2:D69,D70,$E$2:E69,E70,$G$2:G69,"买入")/SUMIFS($H$2:H69,$D$2:D69,D70,$E$2:E69,E70,$G$2:G69,"买入"),""),S70) | AE70: =IF(AC70>0,AC70*Z70-AC70*AD70,0) | AF70: =IF(AC70>0,IF(D70="深港",AE70*AA70,AE70),0) | AG70: =SUMIFS($H$2:H69,$D$2:D69,D70,$E$2:E69,E70,$G$2:G69,"买入") | AH70: =SUMIFS($K$2:K69,$D$2:D69,D70,$E$2:E69,E70,$G$2:G69,"买入") | AI70: =IF(AG70>0,AH70/AG70,"") | AJ70: =IF(G70="卖出",IF(AI70="","",(L70-AI70)*H70),0) | AK70: =IF(G70="卖出",AJ70-T70,"") | AL70: =IF(G70="卖出","(L70-AI70)×H70 = ("&TEXT(L70,"0.######")&"-"&TEXT(AI70,"0.######")&")×"&H70,"")
A71: =IF('交易流水'!A31<>"","流水","") | B71: ='交易流水'!B31 | C71: ='交易流水'!X31 | D71: =IF(ISNUMBER(SEARCH("深港",C71)),"深港",IF(ISNUMBER(SEARCH("场内",C71)),"场内","其他")) | E71: ='交易流水'!F31 | F71: ='交易流水'!G31 | G71: ='交易流水'!H31 | H71: ='交易流水'!K31 | I71: ='交易流水'!P31 | J71: ='交易流水'!L31 | K71: ='交易流水'!AR31 | L71: =IF(H71>0,K71/H71,"") | M71: =IF(G71="买入",H71,0) | N71: =IF(G71="买入",K71,0) | O71: =IF(G71="卖出",H71,0) | P71: =IF(G71="卖出",K71,0) | Q71: =SUMIFS($H$2:H70,$A$2:A70,"流水",$D$2:D70,D71,$E$2:E70,E71,$G$2:G70,"买入") | R71: =SUMIFS($K$2:K70,$A$2:A70,"流水",$D$2:D70,D71,$E$2:E70,E71,$G$2:G70,"买入") | S71: =IF(Q71>0,R71/Q71,"") | T71: =IF(G71="卖出",IF(S71="","",(L71-S71)*H71),0) | U71: -45937.97 | V71: =IF(AND(J71>0,D71="深港"),K71/J71,"") | W71: =IF(G71="卖出","(L71-S71)×H71 = ("&TEXT(L71,"0.######")&"-"&TEXT(S71,"0.######")&")×"&H71,"") | X71: (L71-L14)×10000=(117.130000-121.723797)×10000=-45937.97 → -45937.97 | Y71: =IF(E71="","",IF(D71="深港",TEXT(--E71,"0000")&".HK",IF(--E71>=600000,TEXT(--E71,"000000")&".SH",TEXT(--E71,"000000")&".SZ"))) | Z71: =IF(Y71="","",IFERROR(INDEX('估值日行情'!$C$3:$C$61,MATCH(Y71,'估值日行情'!$A$3:$A$61,0)),"")) | AA71: =IF(D71="深港",IFERROR('FX_RATES_TO_CNY_HIST'!$B$3,""),1) | AB71: =IF(Z71<>"",Z71*AA71,"") | AC71: =SUMIFS($H$2:H71,$D$2:D71,D71,$E$2:E71,E71,$G$2:G71,"买入")-SUMIFS($H$2:H71,$D$2:D71,D71,$E$2:E71,E71,$G$2:G71,"卖出") | AD71: =IF(D71="深港",IF(Q71>0,SUMIFS($J$2:J70,$D$2:D70,D71,$E$2:E70,E71,$G$2:G70,"买入")/SUMIFS($H$2:H70,$D$2:D70,D71,$E$2:E70,E71,$G$2:G70,"买入"),""),S71) | AE71: =IF(AC71>0,AC71*Z71-AC71*AD71,0) | AF71: =IF(AC71>0,IF(D71="深港",AE71*AA71,AE71),0) | AG71: =SUMIFS($H$2:H70,$D$2:D70,D71,$E$2:E70,E71,$G$2:G70,"买入") | AH71: =SUMIFS($K$2:K70,$D$2:D70,D71,$E$2:E70,E71,$G$2:G70,"买入") | AI71: =IF(AG71>0,AH71/AG71,"") | AJ71: =IF(G71="卖出",IF(AI71="","",(L71-AI71)*H71),0) | AK71: =IF(G71="卖出",AJ71-T71,"") | AL71: =IF(G71="卖出","(L71-AI71)×H71 = ("&TEXT(L71,"0.######")&"-"&TEXT(AI71,"0.######")&")×"&H71,"")
A72: =IF('交易流水'!A32<>"","流水","") | B72: ='交易流水'!B32 | C72: ='交易流水'!X32 | D72: =IF(ISNUMBER(SEARCH("深港",C72)),"深港",IF(ISNUMBER(SEARCH("场内",C72)),"场内","其他")) | E72: ='交易流水'!F32 | F72: ='交易流水'!G32 | G72: ='交易流水'!H32 | H72: ='交易流水'!K32 | I72: ='交易流水'!P32 | J72: ='交易流水'!L32 | K72: ='交易流水'!AR32 | L72: =IF(H72>0,K72/H72,"") | M72: =IF(G72="买入",H72,0) | N72: =IF(G72="买入",K72,0) | O72: =IF(G72="卖出",H72,0) | P72: =IF(G72="卖出",K72,0) | Q72: =SUMIFS($H$2:H71,$A$2:A71,"流水",$D$2:D71,D72,$E$2:E71,E72,$G$2:G71,"买入") | R72: =SUMIFS($K$2:K71,$A$2:A71,"流水",$D$2:D71,D72,$E$2:E71,E72,$G$2:G71,"买入") | S72: =IF(Q72>0,R72/Q72,"") | T72: =IF(G72="卖出",IF(S72="","",(L72-S72)*H72),0) | U72: 0 | V72: =IF(AND(J72>0,D72="深港"),K72/J72,"") | W72: =IF(G72="卖出","(L72-S72)×H72 = ("&TEXT(L72,"0.######")&"-"&TEXT(S72,"0.######")&")×"&H72,"") | Y72: =IF(E72="","",IF(D72="深港",TEXT(--E72,"0000")&".HK",IF(--E72>=600000,TEXT(--E72,"000000")&".SH",TEXT(--E72,"000000")&".SZ"))) | Z72: =IF(Y72="","",IFERROR(INDEX('估值日行情'!$C$3:$C$61,MATCH(Y72,'估值日行情'!$A$3:$A$61,0)),"")) | AA72: =IF(D72="深港",IFERROR('FX_RATES_TO_CNY_HIST'!$B$3,""),1) | AB72: =IF(Z72<>"",Z72*AA72,"") | AC72: =SUMIFS($H$2:H72,$D$2:D72,D72,$E$2:E72,E72,$G$2:G72,"买入")-SUMIFS($H$2:H72,$D$2:D72,D72,$E$2:E72,E72,$G$2:G72,"卖出") | AD72: =IF(D72="深港",IF(Q72>0,SUMIFS($J$2:J71,$D$2:D71,D72,$E$2:E71,E72,$G$2:G71,"买入")/SUMIFS($H$2:H71,$D$2:D71,D72,$E$2:E71,E72,$G$2:G71,"买入"),""),S72) | AE72: =IF(AC72>0,AC72*Z72-AC72*AD72,0) | AF72: =IF(AC72>0,IF(D72="深港",AE72*AA72,AE72),0) | AG72: =SUMIFS($H$2:H71,$D$2:D71,D72,$E$2:E71,E72,$G$2:G71,"买入") | AH72: =SUMIFS($K$2:K71,$D$2:D71,D72,$E$2:E71,E72,$G$2:G71,"买入") | AI72: =IF(AG72>0,AH72/AG72,"") | AJ72: =IF(G72="卖出",IF(AI72="","",(L72-AI72)*H72),0) | AK72: =IF(G72="卖出",AJ72-T72,"") | AL72: =IF(G72="卖出","(L72-AI72)×H72 = ("&TEXT(L72,"0.######")&"-"&TEXT(AI72,"0.######")&")×"&H72,"")
A73: =IF('交易流水'!A33<>"","流水","") | B73: ='交易流水'!B33 | C73: ='交易流水'!X33 | D73: =IF(ISNUMBER(SEARCH("深港",C73)),"深港",IF(ISNUMBER(SEARCH("场内",C73)),"场内","其他")) | E73: ='交易流水'!F33 | F73: ='交易流水'!G33 | G73: ='交易流水'!H33 | H73: ='交易流水'!K33 | I73: ='交易流水'!P33 | J73: ='交易流水'!L33 | K73: ='交易流水'!AR33 | L73: =IF(H73>0,K73/H73,"") | M73: =IF(G73="买入",H73,0) | N73: =IF(G73="买入",K73,0) | O73: =IF(G73="卖出",H73,0) | P73: =IF(G73="卖出",K73,0) | Q73: =SUMIFS($H$2:H72,$A$2:A72,"流水",$D$2:D72,D73,$E$2:E72,E73,$G$2:G72,"买入") | R73: =SUMIFS($K$2:K72,$A$2:A72,"流水",$D$2:D72,D73,$E$2:E72,E73,$G$2:G72,"买入") | S73: =IF(Q73>0,R73/Q73,"") | T73: =IF(G73="卖出",IF(S73="","",(L73-S73)*H73),0) | U73: 0 | V73: =IF(AND(J73>0,D73="深港"),K73/J73,"") | W73: =IF(G73="卖出","(L73-S73)×H73 = ("&TEXT(L73,"0.######")&"-"&TEXT(S73,"0.######")&")×"&H73,"") | Y73: =IF(E73="","",IF(D73="深港",TEXT(--E73,"0000")&".HK",IF(--E73>=600000,TEXT(--E73,"000000")&".SH",TEXT(--E73,"000000")&".SZ"))) | Z73: =IF(Y73="","",IFERROR(INDEX('估值日行情'!$C$3:$C$61,MATCH(Y73,'估值日行情'!$A$3:$A$61,0)),"")) | AA73: =IF(D73="深港",IFERROR('FX_RATES_TO_CNY_HIST'!$B$3,""),1) | AB73: =IF(Z73<>"",Z73*AA73,"") | AC73: =SUMIFS($H$2:H73,$D$2:D73,D73,$E$2:E73,E73,$G$2:G73,"买入")-SUMIFS($H$2:H73,$D$2:D73,D73,$E$2:E73,E73,$G$2:G73,"卖出") | AD73: =IF(D73="深港",IF(Q73>0,SUMIFS($J$2:J72,$D$2:D72,D73,$E$2:E72,E73,$G$2:G72,"买入")/SUMIFS($H$2:H72,$D$2:D72,D73,$E$2:E72,E73,$G$2:G72,"买入"),""),S73) | AE73: =IF(AC73>0,AC73*Z73-AC73*AD73,0) | AF73: =IF(AC73>0,IF(D73="深港",AE73*AA73,AE73),0) | AG73: =SUMIFS($H$2:H72,$D$2:D72,D73,$E$2:E72,E73,$G$2:G72,"买入") | AH73: =SUMIFS($K$2:K72,$D$2:D72,D73,$E$2:E72,E73,$G$2:G72,"买入") | AI73: =IF(AG73>0,AH73/AG73,"") | AJ73: =IF(G73="卖出",IF(AI73="","",(L73-AI73)*H73),0) | AK73: =IF(G73="卖出",AJ73-T73,"") | AL73: =IF(G73="卖出","(L73-AI73)×H73 = ("&TEXT(L73,"0.######")&"-"&TEXT(AI73,"0.######")&")×"&H73,"")
A74: =IF('交易流水'!A34<>"","流水","") | B74: ='交易流水'!B34 | C74: ='交易流水'!X34 | D74: =IF(ISNUMBER(SEARCH("深港",C74)),"深港",IF(ISNUMBER(SEARCH("场内",C74)),"场内","其他")) | E74: ='交易流水'!F34 | F74: ='交易流水'!G34 | G74: ='交易流水'!H34 | H74: ='交易流水'!K34 | I74: ='交易流水'!P34 | J74: ='交易流水'!L34 | K74: ='交易流水'!AR34 | L74: =IF(H74>0,K74/H74,"") | M74: =IF(G74="买入",H74,0) | N74: =IF(G74="买入",K74,0) | O74: =IF(G74="卖出",H74,0) | P74: =IF(G74="卖出",K74,0) | Q74: =SUMIFS($H$2:H73,$A$2:A73,"流水",$D$2:D73,D74,$E$2:E73,E74,$G$2:G73,"买入") | R74: =SUMIFS($K$2:K73,$A$2:A73,"流水",$D$2:D73,D74,$E$2:E73,E74,$G$2:G73,"买入") | S74: =IF(Q74>0,R74/Q74,"") | T74: =IF(G74="卖出",IF(S74="","",(L74-S74)*H74),0) | U74: 0 | V74: =IF(AND(J74>0,D74="深港"),K74/J74,"") | W74: =IF(G74="卖出","(L74-S74)×H74 = ("&TEXT(L74,"0.######")&"-"&TEXT(S74,"0.######")&")×"&H74,"") | Y74: =IF(E74="","",IF(D74="深港",TEXT(--E74,"0000")&".HK",IF(--E74>=600000,TEXT(--E74,"000000")&".SH",TEXT(--E74,"000000")&".SZ"))) | Z74: =IF(Y74="","",IFERROR(INDEX('估值日行情'!$C$3:$C$61,MATCH(Y74,'估值日行情'!$A$3:$A$61,0)),"")) | AA74: =IF(D74="深港",IFERROR('FX_RATES_TO_CNY_HIST'!$B$3,""),1) | AB74: =IF(Z74<>"",Z74*AA74,"") | AC74: =SUMIFS($H$2:H74,$D$2:D74,D74,$E$2:E74,E74,$G$2:G74,"买入")-SUMIFS($H$2:H74,$D$2:D74,D74,$E$2:E74,E74,$G$2:G74,"卖出") | AD74: =IF(D74="深港",IF(Q74>0,SUMIFS($J$2:J73,$D$2:D73,D74,$E$2:E73,E74,$G$2:G73,"买入")/SUMIFS($H$2:H73,$D$2:D73,D74,$E$2:E73,E74,$G$2:G73,"买入"),""),S74) | AE74: =IF(AC74>0,AC74*Z74-AC74*AD74,0) | AF74: =IF(AC74>0,IF(D74="深港",AE74*AA74,AE74),0) | AG74: =SUMIFS($H$2:H73,$D$2:D73,D74,$E$2:E73,E74,$G$2:G73,"买入") | AH74: =SUMIFS($K$2:K73,$D$2:D73,D74,$E$2:E73,E74,$G$2:G73,"买入") | AI74: =IF(AG74>0,AH74/AG74,"") | AJ74: =IF(G74="卖出",IF(AI74="","",(L74-AI74)*H74),0) | AK74: =IF(G74="卖出",AJ74-T74,"") | AL74: =IF(G74="卖出","(L74-AI74)×H74 = ("&TEXT(L74,"0.######")&"-"&TEXT(AI74,"0.######")&")×"&H74,"")
A75: =IF('交易流水'!A35<>"","流水","") | B75: ='交易流水'!B35 | C75: ='交易流水'!X35 | D75: =IF(ISNUMBER(SEARCH("深港",C75)),"深港",IF(ISNUMBER(SEARCH("场内",C75)),"场内","其他")) | E75: ='交易流水'!F35 | F75: ='交易流水'!G35 | G75: ='交易流水'!H35 | H75: ='交易流水'!K35 | I75: ='交易流水'!P35 | J75: ='交易流水'!L35 | K75: ='交易流水'!AR35 | L75: =IF(H75>0,K75/H75,"") | M75: =IF(G75="买入",H75,0) | N75: =IF(G75="买入",K75,0) | O75: =IF(G75="卖出",H75,0) | P75: =IF(G75="卖出",K75,0) | Q75: =SUMIFS($H$2:H74,$A$2:A74,"流水",$D$2:D74,D75,$E$2:E74,E75,$G$2:G74,"买入") | R75: =SUMIFS($K$2:K74,$A$2:A74,"流水",$D$2:D74,D75,$E$2:E74,E75,$G$2:G74,"买入") | S75: =IF(Q75>0,R75/Q75,"") | T75: =IF(G75="卖出",IF(S75="","",(L75-S75)*H75),0) | U75: 592730.77 | V75: =IF(AND(J75>0,D75="深港"),K75/J75,"") | W75: =IF(G75="卖出","(L75-S75)×H75 = ("&TEXT(L75,"0.######")&"-"&TEXT(S75,"0.######")&")×"&H75,"") | X75: (L75-L17)×50000=(81.193164-69.338549)×50000=592730.77 → 592730.77 | Y75: =IF(E75="","",IF(D75="深港",TEXT(--E75,"0000")&".HK",IF(--E75>=600000,TEXT(--E75,"000000")&".SH",TEXT(--E75,"000000")&".SZ"))) | Z75: =IF(Y75="","",IFERROR(INDEX('估值日行情'!$C$3:$C$61,MATCH(Y75,'估值日行情'!$A$3:$A$61,0)),"")) | AA75: =IF(D75="深港",IFERROR('FX_RATES_TO_CNY_HIST'!$B$3,""),1) | AB75: =IF(Z75<>"",Z75*AA75,"") | AC75: =SUMIFS($H$2:H75,$D$2:D75,D75,$E$2:E75,E75,$G$2:G75,"买入")-SUMIFS($H$2:H75,$D$2:D75,D75,$E$2:E75,E75,$G$2:G75,"卖出") | AD75: =IF(D75="深港",IF(Q75>0,SUMIFS($J$2:J74,$D$2:D74,D75,$E$2:E74,E75,$G$2:G74,"买入")/SUMIFS($H$2:H74,$D$2:D74,D75,$E$2:E74,E75,$G$2:G74,"买入"),""),S75) | AE75: =IF(AC75>0,AC75*Z75-AC75*AD75,0) | AF75: =IF(AC75>0,IF(D75="深港",AE75*AA75,AE75),0) | AG75: =SUMIFS($H$2:H74,$D$2:D74,D75,$E$2:E74,E75,$G$2:G74,"买入") | AH75: =SUMIFS($K$2:K74,$D$2:D74,D75,$E$2:E74,E75,$G$2:G74,"买入") | AI75: =IF(AG75>0,AH75/AG75,"") | AJ75: =IF(G75="卖出",IF(AI75="","",(L75-AI75)*H75),0) | AK75: =IF(G75="卖出",AJ75-T75,"") | AL75: =IF(G75="卖出","(L75-AI75)×H75 = ("&TEXT(L75,"0.######")&"-"&TEXT(AI75,"0.######")&")×"&H75,"")
A76: =IF('交易流水'!A36<>"","流水","") | B76: ='交易流水'!B36 | C76: ='交易流水'!X36 | D76: =IF(ISNUMBER(SEARCH("深港",C76)),"深港",IF(ISNUMBER(SEARCH("场内",C76)),"场内","其他")) | E76: ='交易流水'!F36 | F76: ='交易流水'!G36 | G76: ='交易流水'!H36 | H76: ='交易流水'!K36 | I76: ='交易流水'!P36 | J76: ='交易流水'!L36 | K76: ='交易流水'!AR36 | L76: =IF(H76>0,K76/H76,"") | M76: =IF(G76="买入",H76,0) | N76: =IF(G76="买入",K76,0) | O76: =IF(G76="卖出",H76,0) | P76: =IF(G76="卖出",K76,0) | Q76: =SUMIFS($H$2:H75,$A$2:A75,"流水",$D$2:D75,D76,$E$2:E75,E76,$G$2:G75,"买入") | R76: =SUMIFS($K$2:K75,$A$2:A75,"流水",$D$2:D75,D76,$E$2:E75,E76,$G$2:G75,"买入") | S76: =IF(Q76>0,R76/Q76,"") | T76: =IF(G76="卖出",IF(S76="","",(L76-S76)*H76),0) | U76: 0 | V76: =IF(AND(J76>0,D76="深港"),K76/J76,"") | W76: =IF(G76="卖出","(L76-S76)×H76 = ("&TEXT(L76,"0.######")&"-"&TEXT(S76,"0.######")&")×"&H76,"") | Y76: =IF(E76="","",IF(D76="深港",TEXT(--E76,"0000")&".HK",IF(--E76>=600000,TEXT(--E76,"000000")&".SH",TEXT(--E76,"000000")&".SZ"))) | Z76: =IF(Y76="","",IFERROR(INDEX('估值日行情'!$C$3:$C$61,MATCH(Y76,'估值日行情'!$A$3:$A$61,0)),"")) | AA76: =IF(D76="深港",IFERROR('FX_RATES_TO_CNY_HIST'!$B$3,""),1) | AB76: =IF(Z76<>"",Z76*AA76,"") | AC76: =SUMIFS($H$2:H76,$D$2:D76,D76,$E$2:E76,E76,$G$2:G76,"买入")-SUMIFS($H$2:H76,$D$2:D76,D76,$E$2:E76,E76,$G$2:G76,"卖出") | AD76: =IF(D76="深港",IF(Q76>0,SUMIFS($J$2:J75,$D$2:D75,D76,$E$2:E75,E76,$G$2:G75,"买入")/SUMIFS($H$2:H75,$D$2:D75,D76,$E$2:E75,E76,$G$2:G75,"买入"),""),S76) | AE76: =IF(AC76>0,AC76*Z76-AC76*AD76,0) | AF76: =IF(AC76>0,IF(D76="深港",AE76*AA76,AE76),0) | AG76: =SUMIFS($H$2:H75,$D$2:D75,D76,$E$2:E75,E76,$G$2:G75,"买入") | AH76: =SUMIFS($K$2:K75,$D$2:D75,D76,$E$2:E75,E76,$G$2:G75,"买入") | AI76: =IF(AG76>0,AH76/AG76,"") | AJ76: =IF(G76="卖出",IF(AI76="","",(L76-AI76)*H76),0) | AK76: =IF(G76="卖出",AJ76-T76,"") | AL76: =IF(G76="卖出","(L76-AI76)×H76 = ("&TEXT(L76,"0.######")&"-"&TEXT(AI76,"0.######")&")×"&H76,"")
A77: =IF('交易流水'!A37<>"","流水","") | B77: ='交易流水'!B37 | C77: ='交易流水'!X37 | D77: =IF(ISNUMBER(SEARCH("深港",C77)),"深港",IF(ISNUMBER(SEARCH("场内",C77)),"场内","其他")) | E77: ='交易流水'!F37 | F77: ='交易流水'!G37 | G77: ='交易流水'!H37 | H77: ='交易流水'!K37 | I77: ='交易流水'!P37 | J77: ='交易流水'!L37 | K77: ='交易流水'!AR37 | L77: =IF(H77>0,K77/H77,"") | M77: =IF(G77="买入",H77,0) | N77: =IF(G77="买入",K77,0) | O77: =IF(G77="卖出",H77,0) | P77: =IF(G77="卖出",K77,0) | Q77: =SUMIFS($H$2:H76,$A$2:A76,"流水",$D$2:D76,D77,$E$2:E76,E77,$G$2:G76,"买入") | R77: =SUMIFS($K$2:K76,$A$2:A76,"流水",$D$2:D76,D77,$E$2:E76,E77,$G$2:G76,"买入") | S77: =IF(Q77>0,R77/Q77,"") | T77: =IF(G77="卖出",IF(S77="","",(L77-S77)*H77),0) | U77: -149358.35 | V77: =IF(AND(J77>0,D77="深港"),K77/J77,"") | W77: =IF(G77="卖出","(L77-S77)×H77 = ("&TEXT(L77,"0.######")&"-"&TEXT(S77,"0.######")&")×"&H77,"") | X77: (L77-L25)×200000=(15.950670-16.697462)×200000=-149358.35 → -149358.35 | Y77: =IF(E77="","",IF(D77="深港",TEXT(--E77,"0000")&".HK",IF(--E77>=600000,TEXT(--E77,"000000")&".SH",TEXT(--E77,"000000")&".SZ"))) | Z77: =IF(Y77="","",IFERROR(INDEX('估值日行情'!$C$3:$C$61,MATCH(Y77,'估值日行情'!$A$3:$A$61,0)),"")) | AA77: =IF(D77="深港",IFERROR('FX_RATES_TO_CNY_HIST'!$B$3,""),1) | AB77: =IF(Z77<>"",Z77*AA77,"") | AC77: =SUMIFS($H$2:H77,$D$2:D77,D77,$E$2:E77,E77,$G$2:G77,"买入")-SUMIFS($H$2:H77,$D$2:D77,D77,$E$2:E77,E77,$G$2:G77,"卖出") | AD77: =IF(D77="深港",IF(Q77>0,SUMIFS($J$2:J76,$D$2:D76,D77,$E$2:E76,E77,$G$2:G76,"买入")/SUMIFS($H$2:H76,$D$2:D76,D77,$E$2:E76,E77,$G$2:G76,"买入"),""),S77) | AE77: =IF(AC77>0,AC77*Z77-AC77*AD77,0) | AF77: =IF(AC77>0,IF(D77="深港",AE77*AA77,AE77),0) | AG77: =SUMIFS($H$2:H76,$D$2:D76,D77,$E$2:E76,E77,$G$2:G76,"买入") | AH77: =SUMIFS($K$2:K76,$D$2:D76,D77,$E$2:E76,E77,$G$2:G76,"买入") | AI77: =IF(AG77>0,AH77/AG77,"") | AJ77: =IF(G77="卖出",IF(AI77="","",(L77-AI77)*H77),0) | AK77: =IF(G77="卖出",AJ77-T77,"") | AL77: =IF(G77="卖出","(L77-AI77)×H77 = ("&TEXT(L77,"0.######")&"-"&TEXT(AI77,"0.######")&")×"&H77,"")
A78: =IF('交易流水'!A38<>"","流水","") | B78: ='交易流水'!B38 | C78: ='交易流水'!X38 | D78: =IF(ISNUMBER(SEARCH("深港",C78)),"深港",IF(ISNUMBER(SEARCH("场内",C78)),"场内","其他")) | E78: ='交易流水'!F38 | F78: ='交易流水'!G38 | G78: ='交易流水'!H38 | H78: ='交易流水'!K38 | I78: ='交易流水'!P38 | J78: ='交易流水'!L38 | K78: ='交易流水'!AR38 | L78: =IF(H78>0,K78/H78,"") | M78: =IF(G78="买入",H78,0) | N78: =IF(G78="买入",K78,0) | O78: =IF(G78="卖出",H78,0) | P78: =IF(G78="卖出",K78,0) | Q78: =SUMIFS($H$2:H77,$A$2:A77,"流水",$D$2:D77,D78,$E$2:E77,E78,$G$2:G77,"买入") | R78: =SUMIFS($K$2:K77,$A$2:A77,"流水",$D$2:D77,D78,$E$2:E77,E78,$G$2:G77,"买入") | S78: =IF(Q78>0,R78/Q78,"") | T78: =IF(G78="卖出",IF(S78="","",(L78-S78)*H78),0) | U78: 0 | V78: =IF(AND(J78>0,D78="深港"),K78/J78,"") | W78: =IF(G78="卖出","(L78-S78)×H78 = ("&TEXT(L78,"0.######")&"-"&TEXT(S78,"0.######")&")×"&H78,"") | Y78: =IF(E78="","",IF(D78="深港",TEXT(--E78,"0000")&".HK",IF(--E78>=600000,TEXT(--E78,"000000")&".SH",TEXT(--E78,"000000")&".SZ"))) | Z78: =IF(Y78="","",IFERROR(INDEX('估值日行情'!$C$3:$C$61,MATCH(Y78,'估值日行情'!$A$3:$A$61,0)),"")) | AA78: =IF(D78="深港",IFERROR('FX_RATES_TO_CNY_HIST'!$B$3,""),1) | AB78: =IF(Z78<>"",Z78*AA78,"") | AC78: =SUMIFS($H$2:H78,$D$2:D78,D78,$E$2:E78,E78,$G$2:G78,"买入")-SUMIFS($H$2:H78,$D$2:D78,D78,$E$2:E78,E78,$G$2:G78,"卖出") | AD78: =IF(D78="深港",IF(Q78>0,SUMIFS($J$2:J77,$D$2:D77,D78,$E$2:E77,E78,$G$2:G77,"买入")/SUMIFS($H$2:H77,$D$2:D77,D78,$E$2:E77,E78,$G$2:G77,"买入"),""),S78) | AE78: =IF(AC78>0,AC78*Z78-AC78*AD78,0) | AF78: =IF(AC78>0,IF(D78="深港",AE78*AA78,AE78),0) | AG78: =SUMIFS($H$2:H77,$D$2:D77,D78,$E$2:E77,E78,$G$2:G77,"买入") | AH78: =SUMIFS($K$2:K77,$D$2:D77,D78,$E$2:E77,E78,$G$2:G77,"买入") | AI78: =IF(AG78>0,AH78/AG78,"") | AJ78: =IF(G78="卖出",IF(AI78="","",(L78-AI78)*H78),0) | AK78: =IF(G78="卖出",AJ78-T78,"") | AL78: =IF(G78="卖出","(L78-AI78)×H78 = ("&TEXT(L78,"0.######")&"-"&TEXT(AI78,"0.######")&")×"&H78,"")
A79: =IF('交易流水'!A39<>"","流水","") | B79: ='交易流水'!B39 | C79: ='交易流水'!X39 | D79: =IF(ISNUMBER(SEARCH("深港",C79)),"深港",IF(ISNUMBER(SEARCH("场内",C79)),"场内","其他")) | E79: ='交易流水'!F39 | F79: ='交易流水'!G39 | G79: ='交易流水'!H39 | H79: ='交易流水'!K39 | I79: ='交易流水'!P39 | J79: ='交易流水'!L39 | K79: ='交易流水'!AR39 | L79: =IF(H79>0,K79/H79,"") | M79: =IF(G79="买入",H79,0) | N79: =IF(G79="买入",K79,0) | O79: =IF(G79="卖出",H79,0) | P79: =IF(G79="卖出",K79,0) | Q79: =SUMIFS($H$2:H78,$A$2:A78,"流水",$D$2:D78,D79,$E$2:E78,E79,$G$2:G78,"买入") | R79: =SUMIFS($K$2:K78,$A$2:A78,"流水",$D$2:D78,D79,$E$2:E78,E79,$G$2:G78,"买入") | S79: =IF(Q79>0,R79/Q79,"") | T79: =IF(G79="卖出",IF(S79="","",(L79-S79)*H79),0) | U79: 0 | V79: =IF(AND(J79>0,D79="深港"),K79/J79,"") | W79: =IF(G79="卖出","(L79-S79)×H79 = ("&TEXT(L79,"0.######")&"-"&TEXT(S79,"0.######")&")×"&H79,"") | Y79: =IF(E79="","",IF(D79="深港",TEXT(--E79,"0000")&".HK",IF(--E79>=600000,TEXT(--E79,"000000")&".SH",TEXT(--E79,"000000")&".SZ"))) | Z79: =IF(Y79="","",IFERROR(INDEX('估值日行情'!$C$3:$C$61,MATCH(Y79,'估值日行情'!$A$3:$A$61,0)),"")) | AA79: =IF(D79="深港",IFERROR('FX_RATES_TO_CNY_HIST'!$B$3,""),1) | AB79: =IF(Z79<>"",Z79*AA79,"") | AC79: =SUMIFS($H$2:H79,$D$2:D79,D79,$E$2:E79,E79,$G$2:G79,"买入")-SUMIFS($H$2:H79,$D$2:D79,D79,$E$2:E79,E79,$G$2:G79,"卖出") | AD79: =IF(D79="深港",IF(Q79>0,SUMIFS($J$2:J78,$D$2:D78,D79,$E$2:E78,E79,$G$2:G78,"买入")/SUMIFS($H$2:H78,$D$2:D78,D79,$E$2:E78,E79,$G$2:G78,"买入"),""),S79) | AE79: =IF(AC79>0,AC79*Z79-AC79*AD79,0) | AF79: =IF(AC79>0,IF(D79="深港",AE79*AA79,AE79),0) | AG79: =SUMIFS($H$2:H78,$D$2:D78,D79,$E$2:E78,E79,$G$2:G78,"买入") | AH79: =SUMIFS($K$2:K78,$D$2:D78,D79,$E$2:E78,E79,$G$2:G78,"买入") | AI79: =IF(AG79>0,AH79/AG79,"") | AJ79: =IF(G79="卖出",IF(AI79="","",(L79-AI79)*H79),0) | AK79: =IF(G79="卖出",AJ79-T79,"") | AL79: =IF(G79="卖出","(L79-AI79)×H79 = ("&TEXT(L79,"0.######")&"-"&TEXT(AI79,"0.######")&")×"&H79,"")
A80: =IF('交易流水'!A40<>"","流水","") | B80: ='交易流水'!B40 | C80: ='交易流水'!X40 | D80: =IF(ISNUMBER(SEARCH("深港",C80)),"深港",IF(ISNUMBER(SEARCH("场内",C80)),"场内","其他")) | E80: ='交易流水'!F40 | F80: ='交易流水'!G40 | G80: ='交易流水'!H40 | H80: ='交易流水'!K40 | I80: ='交易流水'!P40 | J80: ='交易流水'!L40 | K80: ='交易流水'!AR40 | L80: =IF(H80>0,K80/H80,"") | M80: =IF(G80="买入",H80,0) | N80: =IF(G80="买入",K80,0) | O80: =IF(G80="卖出",H80,0) | P80: =IF(G80="卖出",K80,0) | Q80: =SUMIFS($H$2:H79,$A$2:A79,"流水",$D$2:D79,D80,$E$2:E79,E80,$G$2:G79,"买入") | R80: =SUMIFS($K$2:K79,$A$2:A79,"流水",$D$2:D79,D80,$E$2:E79,E80,$G$2:G79,"买入") | S80: =IF(Q80>0,R80/Q80,"") | T80: =IF(G80="卖出",IF(S80="","",(L80-S80)*H80),0) | U80: -512420.91 | V80: =IF(AND(J80>0,D80="深港"),K80/J80,"") | W80: =IF(G80="卖出","(L80-S80)×H80 = ("&TEXT(L80,"0.######")&"-"&TEXT(S80,"0.######")&")×"&H80,"") | X80: (L80-L30)×1500000=(3.710005-4.051619)×1500000=-512420.91 → -512420.91 | Y80: =IF(E80="","",IF(D80="深港",TEXT(--E80,"0000")&".HK",IF(--E80>=600000,TEXT(--E80,"000000")&".SH",TEXT(--E80,"000000")&".SZ"))) | Z80: =IF(Y80="","",IFERROR(INDEX('估值日行情'!$C$3:$C$61,MATCH(Y80,'估值日行情'!$A$3:$A$61,0)),"")) | AA80: =IF(D80="深港",IFERROR('FX_RATES_TO_CNY_HIST'!$B$3,""),1) | AB80: =IF(Z80<>"",Z80*AA80,"") | AC80: =SUMIFS($H$2:H80,$D$2:D80,D80,$E$2:E80,E80,$G$2:G80,"买入")-SUMIFS($H$2:H80,$D$2:D80,D80,$E$2:E80,E80,$G$2:G80,"卖出") | AD80: =IF(D80="深港",IF(Q80>0,SUMIFS($J$2:J79,$D$2:D79,D80,$E$2:E79,E80,$G$2:G79,"买入")/SUMIFS($H$2:H79,$D$2:D79,D80,$E$2:E79,E80,$G$2:G79,"买入"),""),S80) | AE80: =IF(AC80>0,AC80*Z80-AC80*AD80,0) | AF80: =IF(AC80>0,IF(D80="深港",AE80*AA80,AE80),0) | AG80: =SUMIFS($H$2:H79,$D$2:D79,D80,$E$2:E79,E80,$G$2:G79,"买入") | AH80: =SUMIFS($K$2:K79,$D$2:D79,D80,$E$2:E79,E80,$G$2:G79,"买入") | AI80: =IF(AG80>0,AH80/AG80,"") | AJ80: =IF(G80="卖出",IF(AI80="","",(L80-AI80)*H80),0) | AK80: =IF(G80="卖出",AJ80-T80,"") | AL80: =IF(G80="卖出","(L80-AI80)×H80 = ("&TEXT(L80,"0.######")&"-"&TEXT(AI80,"0.######")&")×"&H80,"")
A81: =IF('交易流水'!A41<>"","流水","") | B81: ='交易流水'!B41 | C81: ='交易流水'!X41 | D81: =IF(ISNUMBER(SEARCH("深港",C81)),"深港",IF(ISNUMBER(SEARCH("场内",C81)),"场内","其他")) | E81: ='交易流水'!F41 | F81: ='交易流水'!G41 | G81: ='交易流水'!H41 | H81: ='交易流水'!K41 | I81: ='交易流水'!P41 | J81: ='交易流水'!L41 | K81: ='交易流水'!AR41 | L81: =IF(H81>0,K81/H81,"") | M81: =IF(G81="买入",H81,0) | N81: =IF(G81="买入",K81,0) | O81: =IF(G81="卖出",H81,0) | P81: =IF(G81="卖出",K81,0) | Q81: =SUMIFS($H$2:H80,$A$2:A80,"流水",$D$2:D80,D81,$E$2:E80,E81,$G$2:G80,"买入") | R81: =SUMIFS($K$2:K80,$A$2:A80,"流水",$D$2:D80,D81,$E$2:E80,E81,$G$2:G80,"买入") | S81: =IF(Q81>0,R81/Q81,"") | T81: =IF(G81="卖出",IF(S81="","",(L81-S81)*H81),0) | U81: 0 | V81: =IF(AND(J81>0,D81="深港"),K81/J81,"") | W81: =IF(G81="卖出","(L81-S81)×H81 = ("&TEXT(L81,"0.######")&"-"&TEXT(S81,"0.######")&")×"&H81,"") | Y81: =IF(E81="","",IF(D81="深港",TEXT(--E81,"0000")&".HK",IF(--E81>=600000,TEXT(--E81,"000000")&".SH",TEXT(--E81,"000000")&".SZ"))) | Z81: =IF(Y81="","",IFERROR(INDEX('估值日行情'!$C$3:$C$61,MATCH(Y81,'估值日行情'!$A$3:$A$61,0)),"")) | AA81: =IF(D81="深港",IFERROR('FX_RATES_TO_CNY_HIST'!$B$3,""),1) | AB81: =IF(Z81<>"",Z81*AA81,"") | AC81: =SUMIFS($H$2:H81,$D$2:D81,D81,$E$2:E81,E81,$G$2:G81,"买入")-SUMIFS($H$2:H81,$D$2:D81,D81,$E$2:E81,E81,$G$2:G81,"卖出") | AD81: =IF(D81="深港",IF(Q81>0,SUMIFS($J$2:J80,$D$2:D80,D81,$E$2:E80,E81,$G$2:G80,"买入")/SUMIFS($H$2:H80,$D$2:D80,D81,$E$2:E80,E81,$G$2:G80,"买入"),""),S81) | AE81: =IF(AC81>0,AC81*Z81-AC81*AD81,0) | AF81: =IF(AC81>0,IF(D81="深港",AE81*AA81,AE81),0) | AG81: =SUMIFS($H$2:H80,$D$2:D80,D81,$E$2:E80,E81,$G$2:G80,"买入") | AH81: =SUMIFS($K$2:K80,$D$2:D80,D81,$E$2:E80,E81,$G$2:G80,"买入") | AI81: =IF(AG81>0,AH81/AG81,"") | AJ81: =IF(G81="卖出",IF(AI81="","",(L81-AI81)*H81),0) | AK81: =IF(G81="卖出",AJ81-T81,"") | AL81: =IF(G81="卖出","(L81-AI81)×H81 = ("&TEXT(L81,"0.######")&"-"&TEXT(AI81,"0.######")&")×"&H81,"")
A82: =IF('交易流水'!A42<>"","流水","") | B82: ='交易流水'!B42 | C82: ='交易流水'!X42 | D82: =IF(ISNUMBER(SEARCH("深港",C82)),"深港",IF(ISNUMBER(SEARCH("场内",C82)),"场内","其他")) | E82: ='交易流水'!F42 | F82: ='交易流水'!G42 | G82: ='交易流水'!H42 | H82: ='交易流水'!K42 | I82: ='交易流水'!P42 | J82: ='交易流水'!L42 | K82: ='交易流水'!AR42 | L82: =IF(H82>0,K82/H82,"") | M82: =IF(G82="买入",H82,0) | N82: =IF(G82="买入",K82,0) | O82: =IF(G82="卖出",H82,0) | P82: =IF(G82="卖出",K82,0) | Q82: =SUMIFS($H$2:H81,$A$2:A81,"流水",$D$2:D81,D82,$E$2:E81,E82,$G$2:G81,"买入") | R82: =SUMIFS($K$2:K81,$A$2:A81,"流水",$D$2:D81,D82,$E$2:E81,E82,$G$2:G81,"买入") | S82: =IF(Q82>0,R82/Q82,"") | T82: =IF(G82="卖出",IF(S82="","",(L82-S82)*H82),0) | U82: 0 | V82: =IF(AND(J82>0,D82="深港"),K82/J82,"") | W82: =IF(G82="卖出","(L82-S82)×H82 = ("&TEXT(L82,"0.######")&"-"&TEXT(S82,"0.######")&")×"&H82,"") | Y82: =IF(E82="","",IF(D82="深港",TEXT(--E82,"0000")&".HK",IF(--E82>=600000,TEXT(--E82,"000000")&".SH",TEXT(--E82,"000000")&".SZ"))) | Z82: =IF(Y82="","",IFERROR(INDEX('估值日行情'!$C$3:$C$61,MATCH(Y82,'估值日行情'!$A$3:$A$61,0)),"")) | AA82: =IF(D82="深港",IFERROR('FX_RATES_TO_CNY_HIST'!$B$3,""),1) | AB82: =IF(Z82<>"",Z82*AA82,"") | AC82: =SUMIFS($H$2:H82,$D$2:D82,D82,$E$2:E82,E82,$G$2:G82,"买入")-SUMIFS($H$2:H82,$D$2:D82,D82,$E$2:E82,E82,$G$2:G82,"卖出") | AD82: =IF(D82="深港",IF(Q82>0,SUMIFS($J$2:J81,$D$2:D81,D82,$E$2:E81,E82,$G$2:G81,"买入")/SUMIFS($H$2:H81,$D$2:D81,D82,$E$2:E81,E82,$G$2:G81,"买入"),""),S82) | AE82: =IF(AC82>0,AC82*Z82-AC82*AD82,0) | AF82: =IF(AC82>0,IF(D82="深港",AE82*AA82,AE82),0) | AG82: =SUMIFS($H$2:H81,$D$2:D81,D82,$E$2:E81,E82,$G$2:G81,"买入") | AH82: =SUMIFS($K$2:K81,$D$2:D81,D82,$E$2:E81,E82,$G$2:G81,"买入") | AI82: =IF(AG82>0,AH82/AG82,"") | AJ82: =IF(G82="卖出",IF(AI82="","",(L82-AI82)*H82),0) | AK82: =IF(G82="卖出",AJ82-T82,"") | AL82: =IF(G82="卖出","(L82-AI82)×H82 = ("&TEXT(L82,"0.######")&"-"&TEXT(AI82,"0.######")&")×"&H82,"")
A83: =IF('交易流水'!A43<>"","流水","") | B83: ='交易流水'!B43 | C83: ='交易流水'!X43 | D83: =IF(ISNUMBER(SEARCH("深港",C83)),"深港",IF(ISNUMBER(SEARCH("场内",C83)),"场内","其他")) | E83: ='交易流水'!F43 | F83: ='交易流水'!G43 | G83: ='交易流水'!H43 | H83: ='交易流水'!K43 | I83: ='交易流水'!P43 | J83: ='交易流水'!L43 | K83: ='交易流水'!AR43 | L83: =IF(H83>0,K83/H83,"") | M83: =IF(G83="买入",H83,0) | N83: =IF(G83="买入",K83,0) | O83: =IF(G83="卖出",H83,0) | P83: =IF(G83="卖出",K83,0) | Q83: =SUMIFS($H$2:H82,$A$2:A82,"流水",$D$2:D82,D83,$E$2:E82,E83,$G$2:G82,"买入") | R83: =SUMIFS($K$2:K82,$A$2:A82,"流水",$D$2:D82,D83,$E$2:E82,E83,$G$2:G82,"买入") | S83: =IF(Q83>0,R83/Q83,"") | T83: =IF(G83="卖出",IF(S83="","",(L83-S83)*H83),0) | U83: 610170.04 | V83: =IF(AND(J83>0,D83="深港"),K83/J83,"") | W83: =IF(G83="卖出","(L83-S83)×H83 = ("&TEXT(L83,"0.######")&"-"&TEXT(S83,"0.######")&")×"&H83,"") | X83: (L83-L17)×50000=(81.541950-69.338549)×50000=610170.04 → 610170.04 | Y83: =IF(E83="","",IF(D83="深港",TEXT(--E83,"0000")&".HK",IF(--E83>=600000,TEXT(--E83,"000000")&".SH",TEXT(--E83,"000000")&".SZ"))) | Z83: =IF(Y83="","",IFERROR(INDEX('估值日行情'!$C$3:$C$61,MATCH(Y83,'估值日行情'!$A$3:$A$61,0)),"")) | AA83: =IF(D83="深港",IFERROR('FX_RATES_TO_CNY_HIST'!$B$3,""),1) | AB83: =IF(Z83<>"",Z83*AA83,"") | AC83: =SUMIFS($H$2:H83,$D$2:D83,D83,$E$2:E83,E83,$G$2:G83,"买入")-SUMIFS($H$2:H83,$D$2:D83,D83,$E$2:E83,E83,$G$2:G83,"卖出") | AD83: =IF(D83="深港",IF(Q83>0,SUMIFS($J$2:J82,$D$2:D82,D83,$E$2:E82,E83,$G$2:G82,"买入")/SUMIFS($H$2:H82,$D$2:D82,D83,$E$2:E82,E83,$G$2:G82,"买入"),""),S83) | AE83: =IF(AC83>0,AC83*Z83-AC83*AD83,0) | AF83: =IF(AC83>0,IF(D83="深港",AE83*AA83,AE83),0) | AG83: =SUMIFS($H$2:H82,$D$2:D82,D83,$E$2:E82,E83,$G$2:G82,"买入") | AH83: =SUMIFS($K$2:K82,$D$2:D82,D83,$E$2:E82,E83,$G$2:G82,"买入") | AI83: =IF(AG83>0,AH83/AG83,"") | AJ83: =IF(G83="卖出",IF(AI83="","",(L83-AI83)*H83),0) | AK83: =IF(G83="卖出",AJ83-T83,"") | AL83: =IF(G83="卖出","(L83-AI83)×H83 = ("&TEXT(L83,"0.######")&"-"&TEXT(AI83,"0.######")&")×"&H83,"")
A84: =IF('交易流水'!A44<>"","流水","") | B84: ='交易流水'!B44 | C84: ='交易流水'!X44 | D84: =IF(ISNUMBER(SEARCH("深港",C84)),"深港",IF(ISNUMBER(SEARCH("场内",C84)),"场内","其他")) | E84: ='交易流水'!F44 | F84: ='交易流水'!G44 | G84: ='交易流水'!H44 | H84: ='交易流水'!K44 | I84: ='交易流水'!P44 | J84: ='交易流水'!L44 | K84: ='交易流水'!AR44 | L84: =IF(H84>0,K84/H84,"") | M84: =IF(G84="买入",H84,0) | N84: =IF(G84="买入",K84,0) | O84: =IF(G84="卖出",H84,0) | P84: =IF(G84="卖出",K84,0) | Q84: =SUMIFS($H$2:H83,$A$2:A83,"流水",$D$2:D83,D84,$E$2:E83,E84,$G$2:G83,"买入") | R84: =SUMIFS($K$2:K83,$A$2:A83,"流水",$D$2:D83,D84,$E$2:E83,E84,$G$2:G83,"买入") | S84: =IF(Q84>0,R84/Q84,"") | T84: =IF(G84="卖出",IF(S84="","",(L84-S84)*H84),0) | U84: 0 | V84: =IF(AND(J84>0,D84="深港"),K84/J84,"") | W84: =IF(G84="卖出","(L84-S84)×H84 = ("&TEXT(L84,"0.######")&"-"&TEXT(S84,"0.######")&")×"&H84,"") | Y84: =IF(E84="","",IF(D84="深港",TEXT(--E84,"0000")&".HK",IF(--E84>=600000,TEXT(--E84,"000000")&".SH",TEXT(--E84,"000000")&".SZ"))) | Z84: =IF(Y84="","",IFERROR(INDEX('估值日行情'!$C$3:$C$61,MATCH(Y84,'估值日行情'!$A$3:$A$61,0)),"")) | AA84: =IF(D84="深港",IFERROR('FX_RATES_TO_CNY_HIST'!$B$3,""),1) | AB84: =IF(Z84<>"",Z84*AA84,"") | AC84: =SUMIFS($H$2:H84,$D$2:D84,D84,$E$2:E84,E84,$G$2:G84,"买入")-SUMIFS($H$2:H84,$D$2:D84,D84,$E$2:E84,E84,$G$2:G84,"卖出") | AD84: =IF(D84="深港",IF(Q84>0,SUMIFS($J$2:J83,$D$2:D83,D84,$E$2:E83,E84,$G$2:G83,"买入")/SUMIFS($H$2:H83,$D$2:D83,D84,$E$2:E83,E84,$G$2:G83,"买入"),""),S84) | AE84: =IF(AC84>0,AC84*Z84-AC84*AD84,0) | AF84: =IF(AC84>0,IF(D84="深港",AE84*AA84,AE84),0) | AG84: =SUMIFS($H$2:H83,$D$2:D83,D84,$E$2:E83,E84,$G$2:G83,"买入") | AH84: =SUMIFS($K$2:K83,$D$2:D83,D84,$E$2:E83,E84,$G$2:G83,"买入") | AI84: =IF(AG84>0,AH84/AG84,"") | AJ84: =IF(G84="卖出",IF(AI84="","",(L84-AI84)*H84),0) | AK84: =IF(G84="卖出",AJ84-T84,"") | AL84: =IF(G84="卖出","(L84-AI84)×H84 = ("&TEXT(L84,"0.######")&"-"&TEXT(AI84,"0.######")&")×"&H84,"")
